Workbook

Sheet README
A1: CRITICAL SUPPLIER PERFORMANCE REVIEW — REVAMPED WORKBOOK
A2: Remediation & Restructuring Q1 2026 → Template Reusable untuk Q2 2026
A4: 1. APA YANG BERUBAH DARI FILE ASLI
A5: • 18 sheet per-supplier (ITSEC, IPROTEKSI, dst) dengan angka HARDCODE dikonsolidasikan menjadi 1 sheet SCORE CALC — semua nilai sekarang formula, ditarik LANGSUNG dari RAW DATA, tidak ada lagi copy-paste manual.
A6: • Sheet CONFIG baru ditambahkan: berisi mapping kolom (Quality/Timeline/Relationship) per supplier ke RAW DATA. Ini yang membuat file REUSABLE — untuk Q2, cukup update kolom 'Raw Sheet Name' di CONFIG dan tempel data baru, seluruh perhitungan otomatis mengikuti.
A7: • Sheet RESULT dirombak: Total Score, Status, Remarks, dan DD Result (by User) sekarang 100% formula (live link ke raw data). Kolom 'Assessment Result (by SRM)' dan 'Repetition of Below Expectation' tetap manual input (kuning) karena butuh judgement SRM, bukan hasil kalkulasi.
A8: • Sheet SUMMARY diperbaiki: '% Vendor Dievaluasi' sebelumnya menampilkan angka mentah (1) alih-alih persentase — sekarang benar (0%-100%) dan berbasis formula, bukan hitung manual.
A9: • Sheet HISTORICAL: kolom skor Q1 2026 sekarang live-link ke RESULT (bukan angka mati), dan status (Meet/Exceed/dst) memakai formula ambang batas yang SAMA dengan kolom tahun-tahun sebelumnya (sebelumnya kolom Q1 2026 di-ketik manual, tidak konsisten dengan formula tahun lalu).
A10: • Sheet 'Sheet1' (draft yang tidak terpakai, cuma 1 baris) dihapus.
A12: 2. BUG YANG DITEMUKAN & DIPERBAIKI (PENTING)
A13: Saat formula lama diganti dengan link otomatis ke raw data, ditemukan 3 kesalahan formula di file asli:
A14: a) Satria Antaran Prima – Mailing Room: formula Timeline ("=AVERAGE(I3:P3)*35%") salah rentang — ikut merata-ratakan kolom Quality & hasil weighted Quality (M3) alih-alih hanya kolom Timeline (N:P). Total Score resmi 3.063272 → seharusnya 3.404167. Status TETAP 'Meet Expectation', tidak berubah.
... A58: 5) Untuk detail jawaban per pertanyaan suatu vendor, buka sheet 'Q2 [nama vendor]' (contoh: 'Q2 ITSEC').

Sheet DASHBOARD
A1: DASHBOARD — CRITICAL SUPPLIER PERFORMANCE REVIEW
A3: 🔍 Cari Vendor: | C3: ITSEC ASIA - PENETRATION TEST | J3: MatchRow
A4: (pilih dari dropdown, atau ketik sebagian nama) | J4: =IFERROR(MATCH($C$3,HISTORICAL!$R$4:$R$25,0)+3,"") -> 22
A6: Vendor | B6: Service | C6: PIC Saat Ini | D6: Skor Q2 2026 | E6: Status Q2 2026 | F6: Skor Q1 2026 | G6: Tren vs Q1
A7: =IF($J$4="","",INDEX(HISTORICAL!B:B,$J$4)) -> ITSEC ASIA | B7: =IF($J$4="","",INDEX(HISTORICAL!C:C,$J$4)) -> PENETRATION TEST | C7: =IF($J$4="","",INDEX(HISTORICAL!O:O,$J$4)) -> Fauzi ARYANTO | D7: =IF($J$4="","",INDEX(HISTORICAL!M:M,$J$4)) -> 3 | E7: =IF($J$4="","",INDEX(HISTORICAL!N:N,$J$4)) -> Meet Expectation | F7: =IF($J$4="","",INDEX(HISTORICAL!L:L,$J$4)) -> 3 | G7: =IF($J$4="","",IF(OR(F7="",D7=""),"n/a",IF(D7>F7,"▲ Naik "&TEXT(D7-F7,"0.00"),IF(D7<F7,"▼ Turun "&TEXT(F7-D7,"0.00"),"— Stabil")))) -> — Stabil
A10: TREN SKOR PER KUARTAL
A11: 2024 Q1 | B11: 2024 Q2 | C11: 2024 Q3 | D11: 2024 Q4 | E11: 2025 Q1 | F11: 2025 Q2 | G11: 2025 Q3 | H11: 2025 Q4 | I11: 2026 Q1 | J11: 2026 Q2
A12: =IF($J$4="","",IF(OR(INDEX(HISTORICAL!D:D,$J$4)="N/A",INDEX(HISTORICAL!D:D,$J$4)=0),"-",INDEX(HISTORICAL!D:D,$J$4))) -> - | B12: =IF($J$4="","",IF(OR(INDEX(HISTORICAL!E:E,$J$4)="N/A",INDEX(HISTORICAL!E:E,$J$4)=0),"-",INDEX(HISTORICAL!E:E,$J$4))) -> - | C12: =IF($J$4="","",IF(OR(INDEX(HISTORICAL!F:F,$J$4)="N/A",INDEX(HISTORICAL!F:F,$J$4)=0),"-",INDEX(HISTORICAL!F:F,$J$4))) -> - | D12: =IF($J$4="","",IF(OR(INDEX(HISTORICAL!G:G,$J$4)="N/A",INDEX(HISTORICAL!G:G,$J$4)=0),"-",INDEX(HISTORICAL!G:G,$J$4))) -> - | E12: =IF($J$4="","",IF(OR(INDEX(HISTORICAL!H:H,$J$4)="N/A",INDEX(HISTORICAL!H:H,$J$4)=0),"-",INDEX(HISTORICAL!H:H,$J$4))) -> - | F12: =IF($J$4="","",IF(OR(INDEX(HISTORICAL!I:I,$J$4)="N/A",INDEX(HISTORICAL!I:I,$J$4)=0),"-",INDEX(HISTORICAL!I:I,$J$4))) -> - | G12: =IF($J$4="","",IF(OR(INDEX(HISTORICAL!J:J,$J$4)="N/A",INDEX(HISTORICAL!J:J,$J$4)=0),"-",INDEX(HISTORICAL!J:J,$J$4))) -> - | H12: =IF($J$4="","",IF(OR(INDEX(HISTORICAL!K:K,$J$4)="N/A",INDEX(HISTORICAL!K:K,$J$4)=0),"-",INDEX(HISTORICAL!K:K,$J$4))) -> - | I12: =IF($J$4="","",IF(OR(INDEX(HISTORICAL!L:L,$J$4)="N/A",INDEX(HISTORICAL!L:L,$J$4)=0),"-",INDEX(HISTORICAL!L:L,$J$4))) -> 3 | J12: =IF($J$4="","",IF(OR(INDEX(HISTORICAL!M:M,$J$4)="N/A",INDEX(HISTORICAL!M:M,$J$4)=0),"-",INDEX(HISTORICAL!M:M,$J$4))) -> 3
A19: (data pendukung grafik)
A20: 2024 Q1 | B20: =IFERROR(IF(A12="-",NA(),VALUE(A12)),NA()) -> #N/A
A21: 2024 Q2 | B21: =IFERROR(IF(B12="-",NA(),VALUE(B12)),NA()) -> #N/A
A22: 2024 Q3 | B22: =IFERROR(IF(C12="-",NA(),VALUE(C12)),NA()) -> #N/A
A23: 2024 Q4 | B23: =IFERROR(IF(D12="-",NA(),VALUE(D12)),NA()) -> #N/A
A24: 2025 Q1 | B24: =IFERROR(IF(E12="-",NA(),VALUE(E12)),NA()) -> #N/A
A25: 2025 Q2 | B25: =IFERROR(IF(F12="-",NA(),VALUE(F12)),NA()) -> #N/A
A26: 2025 Q3 | B26: =IFERROR(IF(G12="-",NA(),VALUE(G12)),NA()) -> #N/A
A27: 2025 Q4 | B27: =IFERROR(IF(H12="-",NA(),VALUE(H12)),NA()) -> #N/A
A28: REMARKS / FEEDBACK
A29: Q1 2026: | B29: =IF($J$4="","",INDEX(HISTORICAL!P:P,$J$4)) -> Currently no need improvement
A30: Q2 2026: | B30: =IF($J$4="","",INDEX(HISTORICAL!Q:Q,$J$4)) -> -
A33: RINGKASAN SEMUA VENDOR (Q2 2026)
A34: No | B34: Vendor | C34: Service | D34: Skor Q1 2026 | E34: Skor Q2 2026 | F34: Status Terkini | G34: Tren
A35: 1 | B35: =HISTORICAL!B4 -> INDOSAT | C35: =HISTORICAL!C4 -> LAYANAN PBX BERBASISKAN CLOUD DENGAN TEKNOLOGI SIP TRUNK | D35: =IF(HISTORICAL!L4="N/A","-",HISTORICAL!L4) -> 3.3184211 | E35: =IF(HISTORICAL!M4="N/A","-",HISTORICAL!M4) -> 3.4394737 | F35: =HISTORICAL!N4 -> Meet Expectation | G35: =IF(OR(NOT(ISNUMBER(D35)),NOT(ISNUMBER(E35))),"-",IF(E35>D35,"▲",IF(E35<D35,"▼","—"))) -> ▲
A36: 2 | B36: =HISTORICAL!B5 -> INFORMASI TEKNOLOGI INDONESIA | C36: =HISTORICAL!C5 -> PENYEDIAAN JASA SMS BROADCAST DAN JASA SMS PULL; CONNECTIVITY PRIMARY LINK | D36: =IF(HISTORICAL!L5="N/A","-",HISTORICAL!L5) -> 3 | E36: =IF(HISTORICAL!M5="N/A","-",HISTORICAL!M5) -> 3 | F36: =HISTORICAL!N5 -> Meet Expectation | G36: =IF(OR(NOT(ISNUMBER(D36)),NOT(ISNUMBER(E36))),"-",IF(E36>D36,"▲",IF(E36<D36,"▼","—"))) -> —
A37: 3 | B37: =HISTORICAL!B6 -> MITRA INTEGRASI INFORMATIKA | C37: =HISTORICAL!C6 -> SFDC MAINTENANCE | D37: =IF(HISTORICAL!L6="N/A","-",HISTORICAL!L6) -> 4.8294872 | E37: =IF(HISTORICAL!M6="N/A","-",HISTORICAL!M6) -> 4.7487179 | F37: =HISTORICAL!N6 -> Exceed Expectation | G37: =IF(OR(NOT(ISNUMBER(D37)),NOT(ISNUMBER(E37))),"-",IF(E37>D37,"▲",IF(E37<D37,"▼","—"))) -> ▼
A38: 4 | B38: =HISTORICAL!B7 -> MULTIFILING MITRA INDONESIA | C38: =HISTORICAL!C7 -> RECORD MANAGEMENT SERVICE | D38: =IF(HISTORICAL!L7="N/A","-",HISTORICAL!L7) -> 3.0318182 | E38: =IF(HISTORICAL!M7="N/A","-",HISTORICAL!M7) -> 3 | F38: =HISTORICAL!N7 -> Meet Expectation | G38: =IF(OR(NOT(ISNUMBER(D38)),NOT(ISNUMBER(E38))),"-",IF(E38>D38,"▲",IF(E38<D38,"▼","—"))) -> ▼
A39: 5 | B39: =HISTORICAL!B8 -> CIPTADRA SOFTINDO | C39: =HISTORICAL!C8 -> PEMELIHARAAN PERANGKAT LUNAK AXITS DAN PERANGKAT LUNAK DMTM | D39: =IF(HISTORICAL!L8="N/A","-",HISTORICAL!L8) -> 4 | E39: =IF(HISTORICAL!M8="N/A","-",HISTORICAL!M8) -> 4.3 | F39: =HISTORICAL!N8 -> Exceed Expectation | G39: =IF(OR(NOT(ISNUMBER(D39)),NOT(ISNUMBER(E39))),"-",IF(E39>D39,"▲",IF(E39<D39,"▼","—"))) -> ▲
A40: 6 | B40: =HISTORICAL!B9 -> INMOTION INOVASI TEKNOLOGI | C40: =HISTORICAL!C9 -> JASA APLIKASI CHATBOT DAN LIVE CHAT | D40: =IF(HISTORICAL!L9="N/A","-",HISTORICAL!L9) -> 4 | E40: =IF(HISTORICAL!M9="N/A","-",HISTORICAL!M9) -> 4 | F40: =HISTORICAL!N9 -> Exceed Expectation | G40: =IF(OR(NOT(ISNUMBER(D40)),NOT(ISNUMBER(E40))),"-",IF(E40>D40,"▲",IF(E40<D40,"▼","—"))) -> —
A41: 7 | B41: =HISTORICAL!B10 -> SATRIA ANTARAN PRIMA TBK | C41: =HISTORICAL!C10 -> PENGIRIMAN POLIS DOKUMEN DAN PAKET DALAM NEGERI | D41: =IF(HISTORICAL!L10="N/A","-",HISTORICAL!L10) -> 3 | E41: =IF(HISTORICAL!M10="N/A","-",HISTORICAL!M10) -> 3.2383333 | F41: =HISTORICAL!N10 -> Meet Expectation | G41: =IF(OR(NOT(ISNUMBER(D41)),NOT(ISNUMBER(E41))),"-",IF(E41>D41,"▲",IF(E41<D41,"▼","—"))) -> ▲
A42: 8 | B42: =HISTORICAL!B11 -> SATRIA ANTARAN PRIMA TBK | C42: =HISTORICAL!C11 -> MAILING ROOM | D42: =IF(HISTORICAL!L11="N/A","-",HISTORICAL!L11) -> 3.4041667 | E42: =IF(HISTORICAL!M11="N/A","-",HISTORICAL!M11) -> 3.04375 | F42: =HISTORICAL!N11 -> Meet Expectation | G42: =IF(OR(NOT(ISNUMBER(D42)),NOT(ISNUMBER(E42))),"-",IF(E42>D42,"▲",IF(E42<D42,"▼","—"))) -> ▼
A43: 9 | B43: =HISTORICAL!B12 -> TARGET SUKSES SINERGI | C43: =HISTORICAL!C12 -> PENGIRIMAN EMAIL MARKETING AUTOMATION | D43: =IF(HISTORICAL!L12="N/A","-",HISTORICAL!L12) -> 3.9 | E43: =IF(HISTORICAL!M12="N/A","-",HISTORICAL!M12) -> 2.9416667 | F43: =HISTORICAL!N12 -> Below Expectation | G43: =IF(OR(NOT(ISNUMBER(D43)),NOT(ISNUMBER(E43))),"-",IF(E43>D43,"▲",IF(E43<D43,"▼","—"))) -> ▼
A44: 10 | B44: =HISTORICAL!B13 -> WIZ TECHNOLOGY INDONESIA | C44: =HISTORICAL!C13 -> VOICE BOT REMINDER CALL | D44: =IF(HISTORICAL!L13="N/A","-",HISTORICAL!L13) -> - | E44: =IF(HISTORICAL!M13="N/A","-",HISTORICAL!M13) -> 3.0875 | F44: =HISTORICAL!N13 -> Meet Expectation | G44: =IF(OR(NOT(ISNUMBER(D44)),NOT(ISNUMBER(E44))),"-",IF(E44>D44,"▲",IF(E44<D44,"▼","—"))) -> -
A45: 11 | B45: =HISTORICAL!B14 -> KARYAPUTRA SURYAGEMILANG | C45: =HISTORICAL!C14 -> TELEMARKETING REVAMP PROJECT | D45: =IF(HISTORICAL!L14="N/A","-",HISTORICAL!L14) -> 3.0318182 | E45: =IF(HISTORICAL!M14="N/A","-",HISTORICAL!M14) -> 3.5393939 | F45: =HISTORICAL!N14 -> Meet Expectation | G45: =IF(OR(NOT(ISNUMBER(D45)),NOT(ISNUMBER(E45))),"-",IF(E45>D45,"▲",IF(E45<D45,"▼","—"))) -> ▲
A46: 12 | B46: =HISTORICAL!B15 -> ARAH SEJAHTERA ABADI | C46: =HISTORICAL!C15 -> PERJANJIAN SEWA MENYEWA | D46: =IF(HISTORICAL!L15="N/A","-",HISTORICAL!L15) -> 2.9611111 | E46: =IF(HISTORICAL!M15="N/A","-",HISTORICAL!M15) -> - | F46: =HISTORICAL!N15 -> Below Expectation | G46: =IF(OR(NOT(ISNUMBER(D46)),NOT(ISNUMBER(E46))),"-",IF(E46>D46,"▲",IF(E46<D46,"▼","—"))) -> -
... A56: 22 | B56: =HISTORICAL!B25 -> ESHAEL Indonesia | C56: =HISTORICAL!C25 -> Talent Assesment | D56: =IF(HISTORICAL!L25="N/A","-",HISTORICAL!L25) -> - | E56: =IF(HISTORICAL!M25="N/A","-",HISTORICAL!M25) -> 4.6083333 | F56: =HISTORICAL!N25 -> Exceed Expectation | G56: =IF(OR(NOT(ISNUMBER(D56)),NOT(ISNUMBER(E56))),"-",IF(E56>D56,"▲",IF(E56<D56,"▼","—"))) -> -

Sheet HISTORICAL
A1: HISTORICAL PERFORMANCE — TREN SKOR PER VENDOR
A3: No | B3: Vendor | C3: Service Scope | D3: 2024 Q1 | E3: 2024 Q2 | F3: 2024 Q3 | G3: 2024 Q4 | H3: 2025 Q1 | I3: 2025 Q2 | J3: 2025 Q3 | K3: 2025 Q4 | L3: 2026 Q1 | M3: 2026 Q2 | N3: Status Terkini | O3: PIC Q2 2026 | P3: Remarks Q1 2026 | Q3: Remarks Q2 2026 | R3: Search Key
A4: 1 | B4: INDOSAT | C4: LAYANAN PBX BERBASISKAN CLOUD DENGAN TEKNOLOGI SIP TRUNK | D4: 3 | E4: 3 | F4: 2.95 | G4: 3 | H4: 2.345 | I4: 1.99 | J4: 2.72 | K4: 2.9825 | L4: =RESULT!E9 -> 3.3184211 | M4: =IFERROR(VALUE('RESULT Q2'!E9),"N/A") -> 3.4394737 | N4: =IF(ISNUMBER(M4),IF(M4>4.99,"Exceptional",IF(M4>3.99,"Exceed Expectation",IF(M4>=2.99,"Meet Expectation",IF(M4>1.9,"Below Expectation","Unsatisfactory")))),IF(ISNUMBER(L4),IF(L4>4.99,"Exceptional",IF(L4>3.99,"Exceed Expectation",IF(L4>=2.99,"Meet Expectation",IF(L4>1.9,"Below Expectation","Unsatisfactory")))),"N/A")) -> Meet Expectation | O4: =IFERROR('RESULT Q2'!D9,"-") -> Nuril HUDHA | P4: =IFERROR(RESULT!G9,"-") -> The performance is getting better, please keep improve the performance. | Q4: =IFERROR('RESULT Q2'!G9,"-") -> Vendor performance is generally acceptable and aligns with the expected level of service. While the engagement has been positive overall, improvements are needed in feature enhancement, dashboard capabilities, and the regularity of report updates. Better preparation in deployment and timely reporting would help increase the overall value and effectiveness of the service. | R4: =B4&" - "&C4 -> INDOSAT - LAYANAN PBX BERBASISKAN CLOUD DENGAN TEKNOLOGI SIP TRUNK
A5: 2 | B5: INFORMASI TEKNOLOGI INDONESIA | C5: PENYEDIAAN JASA SMS BROADCAST DAN JASA SMS PULL; CONNECTIVITY PRIMARY LINK | D5: 3.78 | E5: 4.21 | F5: 3 | G5: 3 | H5: 3 | I5: 3 | J5: 3 | K5: 3.0818182 | L5: =RESULT!E6 -> 3 | M5: =IFERROR(VALUE('RESULT Q2'!E6),"N/A") -> 3 | N5: =IF(ISNUMBER(M5),IF(M5>4.99,"Exceptional",IF(M5>3.99,"Exceed Expectation",IF(M5>=2.99,"Meet Expectation",IF(M5>1.9,"Below Expectation","Unsatisfactory")))),IF(ISNUMBER(L5),IF(L5>4.99,"Exceptional",IF(L5>3.99,"Exceed Expectation",IF(L5>=2.99,"Meet Expectation",IF(L5>1.9,"Below Expectation","Unsatisfactory")))),"N/A")) -> Meet Expectation | O5: =IFERROR('RESULT Q2'!D6,"-") -> Fifin SARINURLITA | P5: =IFERROR(RESULT!G6,"-") -> Jatis has provided good service throughout this year | Q5: =IFERROR('RESULT Q2'!G6,"-") -> So far, Jatis Vendor has provided good service. Their response time is fast, and they are able to provide effective solutions whenever issues arise | R5: =B5&" - "&C5 -> INFORMASI TEKNOLOGI INDONESIA - PENYEDIAAN JASA SMS BROADCAST DAN JASA SMS PULL; CONNECTIVITY PRIMARY LINK
A6: 3 | B6: MITRA INTEGRASI INFORMATIKA | C6: SFDC MAINTENANCE | D6: 3 | E6: 3 | F6: 3.96 | G6: 3.65 | H6: 3 | I6: 4.4166667 | J6: 4.3538462 | K6: 4.2730769 | L6: =RESULT!E13 -> 4.8294872 | M6: =IFERROR(VALUE('RESULT Q2'!E13),"N/A") -> 4.7487179 | N6: =IF(ISNUMBER(M6),IF(M6>4.99,"Exceptional",IF(M6>3.99,"Exceed Expectation",IF(M6>=2.99,"Meet Expectation",IF(M6>1.9,"Below Expectation","Unsatisfactory")))),IF(ISNUMBER(L6),IF(L6>4.99,"Exceptional",IF(L6>3.99,"Exceed Expectation",IF(L6>=2.99,"Meet Expectation",IF(L6>1.9,"Below Expectation","Unsatisfactory")))),"N/A")) -> Exceed Expectation | O6: =IFERROR('RESULT Q2'!D13,"-") -> Chandra Nugraha PUTRA | P6: =IFERROR(RESULT!G13,"-") -> verall, the level of support has been satisfactory. The improvements carried out were highly effective, and several demands were consistent with the initial assessment and expectations. | Q6: =IFERROR('RESULT Q2'!G13,"-") -> Respons terhadap issue maupun kebutuhan sudah cukup baik dan cepat. Support on-site juga sangat membantu dan responsif. Ke depannya, mungkin dapat lebih rutin memberikan update terkait progress kendala atau perbaikan yang sedang dilakukan, sehingga pihak terkait dapat mengetahui status terbaru dan lebih cepat menentukan langkah selanjutnya. | R6: =B6&" - "&C6 -> MITRA INTEGRASI INFORMATIKA - SFDC MAINTENANCE
A7: 4 | B7: MULTIFILING MITRA INDONESIA | C7: RECORD MANAGEMENT SERVICE | D7: 3 | E7: 4 | F7: 4 | G7: 3.65 | H7: 3 | I7: 3 | J7: 3.9125 | K7: 3.0693182 | L7: =RESULT!E8 -> 3.0318182 | M7: =IFERROR(VALUE('RESULT Q2'!E8),"N/A") -> 3 | N7: =IF(ISNUMBER(M7),IF(M7>4.99,"Exceptional",IF(M7>3.99,"Exceed Expectation",IF(M7>=2.99,"Meet Expectation",IF(M7>1.9,"Below Expectation","Unsatisfactory")))),IF(ISNUMBER(L7),IF(L7>4.99,"Exceptional",IF(L7>3.99,"Exceed Expectation",IF(L7>=2.99,"Meet Expectation",IF(L7>1.9,"Below Expectation","Unsatisfactory")))),"N/A")) -> Meet Expectation | O7: =IFERROR('RESULT Q2'!D8,"-") -> Ibnu KUMALA | P7: =IFERROR(RESULT!G8,"-") -> impprove innovation dan simplyfy process | Q7: =IFERROR('RESULT Q2'!G8,"-") -> .. | R7: =B7&" - "&C7 -> MULTIFILING MITRA INDONESIA - RECORD MANAGEMENT SERVICE
A8: 5 | B8: CIPTADRA SOFTINDO | C8: PEMELIHARAAN PERANGKAT LUNAK AXITS DAN PERANGKAT LUNAK DMTM | D8: 4.9 | E8: 4.73 | F8: 3.38 | G8: 3 | H8: 3.975 | I8: 3.675 | J8: 3.75 | K8: 4.2 | L8: =RESULT!E10 -> 4 | M8: =IFERROR(VALUE('RESULT Q2'!E10),"N/A") -> 4.3 | N8: =IF(ISNUMBER(M8),IF(M8>4.99,"Exceptional",IF(M8>3.99,"Exceed Expectation",IF(M8>=2.99,"Meet Expectation",IF(M8>1.9,"Below Expectation","Unsatisfactory")))),IF(ISNUMBER(L8),IF(L8>4.99,"Exceptional",IF(L8>3.99,"Exceed Expectation",IF(L8>=2.99,"Meet Expectation",IF(L8>1.9,"Below Expectation","Unsatisfactory")))),"N/A")) -> Exceed Expectation | O8: =IFERROR('RESULT Q2'!D10,"-") -> Raninta MAHARDI | P8: =IFERROR(RESULT!G10,"-") -> Performance is Good | Q8: =IFERROR('RESULT Q2'!G10,"-") -> Ciptadra selalu fast response ketika ada incident yang terjadi di DMTM | R8: =B8&" - "&C8 -> CIPTADRA SOFTINDO - PEMELIHARAAN PERANGKAT LUNAK AXITS DAN PERANGKAT LUNAK DMTM
A9: 6 | B9: INMOTION INOVASI TEKNOLOGI | C9: JASA APLIKASI CHATBOT DAN LIVE CHAT | D9: 3 | E9: 3 | F9: 3.09 | G9: 3 | H9: 2.121875 | I9: 2.9890625 | J9: 3 | K9: 3.65 | L9: =RESULT!E12 -> 4 | M9: =IFERROR(VALUE('RESULT Q2'!E12),"N/A") -> 4 | N9: =IF(ISNUMBER(M9),IF(M9>4.99,"Exceptional",IF(M9>3.99,"Exceed Expectation",IF(M9>=2.99,"Meet Expectation",IF(M9>1.9,"Below Expectation","Unsatisfactory")))),IF(ISNUMBER(L9),IF(L9>4.99,"Exceptional",IF(L9>3.99,"Exceed Expectation",IF(L9>=2.99,"Meet Expectation",IF(L9>1.9,"Below Expectation","Unsatisfactory")))),"N/A")) -> Exceed Expectation | O9: =IFERROR('RESULT Q2'!D12,"-") -> Djoko DJOKO | P9: =IFERROR(RESULT!G12,"-") -> continue performing thorough and frequent periodic checks to ensure that during service hours, there are no issues that could disrupt operations and resolve the remaining unresolved 401 issue Berikan umpan balik Anda tentang BizChat | Q9: =IFERROR('RESULT Q2'!G12,"-") -> Tetap up to date dan helpful | R9: =B9&" - "&C9 -> INMOTION INOVASI TEKNOLOGI - JASA APLIKASI CHATBOT DAN LIVE CHAT
A10: 7 | B10: SATRIA ANTARAN PRIMA TBK | C10: PENGIRIMAN POLIS DOKUMEN DAN PAKET DALAM NEGERI | D10: 3.75 | E10: 3.83 | F10: 2.74 | G10: 2.725 | H10: 2.86 | I10: 2.6166667 | J10: 2.5 | K10: 2.9611111 | L10: =RESULT!E7 -> 3 | M10: =IFERROR(VALUE('RESULT Q2'!E7),"N/A") -> 3.2383333 | N10: =IF(ISNUMBER(M10),IF(M10>4.99,"Exceptional",IF(M10>3.99,"Exceed Expectation",IF(M10>=2.99,"Meet Expectation",IF(M10>1.9,"Below Expectation","Unsatisfactory")))),IF(ISNUMBER(L10),IF(L10>4.99,"Exceptional",IF(L10>3.99,"Exceed Expectation",IF(L10>=2.99,"Meet Expectation",IF(L10>1.9,"Below Expectation","Unsatisfactory")))),"N/A")) -> Meet Expectation | O10: =IFERROR('RESULT Q2'!D7,"-") -> Fifin SARINURLITA, Novia Laras SANTI | P10: =IFERROR(RESULT!G7,"-") -> SAP has provided excellent service throughout this year | Q10: =IFERROR('RESULT Q2'!G7,"-") -> SAP has shown improvement in terms of reporting and provides a fast response whenever issues arise. | 1. untuk detail status pengiriman dokumen/barang harus diberikan keterangan penerima dengan lengkap dan jelas; 2. Maks. SLA pengiriman harus memenuhi sesuai dengan yang ditetapkan yaitu <5% not meet SLA; 3. Invoice biaya pengiriman dikirimkan ke user yang sesuai dan dikirimkan tidak melebihi periode yang ditetapkan. 4. Report Stock sesuai dengan real stock di warehouse. | R10: =B10&" - "&C10 -> SATRIA ANTARAN PRIMA TBK - PENGIRIMAN POLIS DOKUMEN DAN PAKET DALAM NEGERI
A11: 8 | B11: SATRIA ANTARAN PRIMA TBK | C11: MAILING ROOM | H11: 3 | J11: 3.9125 | K11: 3.05 | L11: =RESULT!E5 -> 3.4041667 | M11: =IFERROR(VALUE('RESULT Q2'!E5),"N/A") -> 3.04375 | N11: =IF(ISNUMBER(M11),IF(M11>4.99,"Exceptional",IF(M11>3.99,"Exceed Expectation",IF(M11>=2.99,"Meet Expectation",IF(M11>1.9,"Below Expectation","Unsatisfactory")))),IF(ISNUMBER(L11),IF(L11>4.99,"Exceptional",IF(L11>3.99,"Exceed Expectation",IF(L11>=2.99,"Meet Expectation",IF(L11>1.9,"Below Expectation","Unsatisfactory")))),"N/A")) -> Meet Expectation | O11: =IFERROR('RESULT Q2'!D5,"-") -> Ibnu KUMALA | P11: =IFERROR(RESULT!G5,"-") -> Over all mailing ok, please improve coordinated with Headoffice team for reduce complain/misscomm (ex case overseas shipment ) | Q11: =IFERROR('RESULT Q2'!G5,"-") -> improve inisiatsis | R11: =B11&" - "&C11 -> SATRIA ANTARAN PRIMA TBK - MAILING ROOM
A12: 9 | B12: TARGET SUKSES SINERGI | C12: PENGIRIMAN EMAIL MARKETING AUTOMATION | D12: 2.85 | E12: 3.28 | F12: 4 | G12: 3.3125 | H12: 3.7444444 | I12: 4 | J12: 3 | K12: 3.65 | L12: =RESULT!E11 -> 3.9 | M12: =IFERROR(VALUE('RESULT Q2'!E11),"N/A") -> 2.9416667 | N12: =IF(ISNUMBER(M12),IF(M12>4.99,"Exceptional",IF(M12>3.99,"Exceed Expectation",IF(M12>=2.99,"Meet Expectation",IF(M12>1.9,"Below Expectation","Unsatisfactory")))),IF(ISNUMBER(L12),IF(L12>4.99,"Exceptional",IF(L12>3.99,"Exceed Expectation",IF(L12>=2.99,"Meet Expectation",IF(L12>1.9,"Below Expectation","Unsatisfactory")))),"N/A")) -> Below Expectation | O12: =IFERROR('RESULT Q2'!D11,"-") -> Bella Friska DEPARI | P12: =IFERROR(RESULT!G11,"-") -> Harganya buat next contrac please murahin ya | Q12: =IFERROR('RESULT Q2'!G11,"-") -> Secara keseluruhan, MTarget telah memberikan dukungan yang baik dalam operasional email campaign dan responsif dalam menangani kebutuhan maupun isu yang muncul. Namun, insiden kesalahan pengiriman email yang terjadi menunjukkan perlunya penguatan pada proses deployment, pengujian, serta validasi sebelum implementasi ke production. Ke depannya, kami berharap MTarget dapat memperkuat proses change management, quality assurance, dan kontrol terhadap segmentasi serta pengiriman email untuk meminimalkan risiko terjadinya insiden serupa. | R12: =B12&" - "&C12 -> TARGET SUKSES SINERGI - PENGIRIMAN EMAIL MARKETING AUTOMATION
A13: 10 | B13: WIZ TECHNOLOGY INDONESIA | C13: VOICE BOT REMINDER CALL | D13: 3 | E13: 3.61 | F13: 3.4 | G13: 3.0875 | H13: 3.0388889 | I13: 3.5444444 | J13: 3 | K13: 3.46875 | L13: N/A | M13: =IFERROR(VALUE('RESULT Q2'!E19),"N/A") -> 3.0875 | N13: =IF(ISNUMBER(M13),IF(M13>4.99,"Exceptional",IF(M13>3.99,"Exceed Expectation",IF(M13>=2.99,"Meet Expectation",IF(M13>1.9,"Below Expectation","Unsatisfactory")))),IF(ISNUMBER(L13),IF(L13>4.99,"Exceptional",IF(L13>3.99,"Exceed Expectation",IF(L13>=2.99,"Meet Expectation",IF(L13>1.9,"Below Expectation","Unsatisfactory")))),"N/A")) -> Meet Expectation | O13: =IFERROR('RESULT Q2'!D19,"-") -> Ravika OKTAVIANI | P13: - | Q13: =IFERROR('RESULT Q2'!G19,"-") -> To ensure a smooth process, we need to move faster and maintain effective communication | R13: =B13&" - "&C13 -> WIZ TECHNOLOGY INDONESIA - VOICE BOT REMINDER CALL
A14: 11 | B14: KARYAPUTRA SURYAGEMILANG | C14: TELEMARKETING REVAMP PROJECT | D14: 3.46 | E14: 3.46 | F14: 3.86 | G14: 3 | H14: 3.1807692 | I14: 2.9371795 | J14: 2.4272727 | K14: 3.5181818 | L14: =RESULT!E19 -> 3.0318182 | M14: =IFERROR(VALUE('RESULT Q2'!E18),"N/A") -> 3.5393939 | N14: =IF(ISNUMBER(M14),IF(M14>4.99,"Exceptional",IF(M14>3.99,"Exceed Expectation",IF(M14>=2.99,"Meet Expectation",IF(M14>1.9,"Below Expectation","Unsatisfactory")))),IF(ISNUMBER(L14),IF(L14>4.99,"Exceptional",IF(L14>3.99,"Exceed Expectation",IF(L14>=2.99,"Meet Expectation",IF(L14>1.9,"Below Expectation","Unsatisfactory")))),"N/A")) -> Meet Expectation | O14: =IFERROR('RESULT Q2'!D18,"-") -> Nuril HUDHA | P14: =IFERROR(RESULT!G19,"-") -> Diharapkan untuk tim project yang diassign apabila CR sudah di signoff agar availibility dari resource ready | Q14: =IFERROR('RESULT Q2'!G18,"-") -> 1. For AI Implementation, KPSG need to improve the delivery time, quality and PIC availability and backup PIC support 2. Another enhancement need to speed up with dedicated team | R14: =B14&" - "&C14 -> KARYAPUTRA SURYAGEMILANG - TELEMARKETING REVAMP PROJECT
A15: 12 | B15: ARAH SEJAHTERA ABADI | C15: PERJANJIAN SEWA MENYEWA | E15: 3 | F15: 3 | G15: 3.35 | H15: 2.8409091 | I15: 2.7727273 | J15: 2 | K15: 2.9611111 | L15: =RESULT!E16 -> 2.9611111 | M15: =IFERROR(VALUE('RESULT Q2'!E23),"N/A") -> N/A | N15: =IF(ISNUMBER(M15),IF(M15>4.99,"Exceptional",IF(M15>3.99,"Exceed Expectation",IF(M15>=2.99,"Meet Expectation",IF(M15>1.9,"Below Expectation","Unsatisfactory")))),IF(ISNUMBER(L15),IF(L15>4.99,"Exceptional",IF(L15>3.99,"Exceed Expectation",IF(L15>=2.99,"Meet Expectation",IF(L15>1.9,"Below Expectation","Unsatisfactory")))),"N/A")) -> Below Expectation | O15: =IFERROR('RESULT Q2'!D23,"-") -> ibnu.kumala@axa-mandiri.co.id | P15: =IFERROR(RESULT!G16,"-") -> Improve quality service, specially for leakage, | Q15: =IFERROR('RESULT Q2'!G23,"-") -> - | R15: =B15&" - "&C15 -> ARAH SEJAHTERA ABADI - PERJANJIAN SEWA MENYEWA
A16: 13 | B16: DELOITTE CONSULTING | C16: DATA PRIVACY TOOLS & PELATIHAN PERSONAL DATA PROTECTION (PDP) | G16: 3.2333333 | H16: 2.9708333 | I16: 2.8833333 | J16: 3.1 | K16: 3.1166667 | L16: =RESULT!E17 -> 3.1636364 | M16: =IFERROR(VALUE('RESULT Q2'!E16),"N/A") -> 4.0636364 | N16: =IF(ISNUMBER(M16),IF(M16>4.99,"Exceptional",IF(M16>3.99,"Exceed Expectation",IF(M16>=2.99,"Meet Expectation",IF(M16>1.9,"Below Expectation","Unsatisfactory")))),IF(ISNUMBER(L16),IF(L16>4.99,"Exceptional",IF(L16>3.99,"Exceed Expectation",IF(L16>=2.99,"Meet Expectation",IF(L16>1.9,"Below Expectation","Unsatisfactory")))),"N/A")) -> Exceed Expectation | O16: =IFERROR('RESULT Q2'!D16,"-") -> M. Andrian Patria Shaleh RIZAL | P16: =IFERROR(RESULT!G17,"-") -> Need more improvement regarding initiative to take mitigation/preventive action to prevent the problem from recurring/current issue. | Q16: =IFERROR('RESULT Q2'!G16,"-") -> In dealing with Security AI-related issues, Deloitte is occasionally unable to provide a resolution and therefore redirects the matter to the Security AI team. Furthermore, several system features are restricted, and these limitations were not clearly communicated at the outset. Consequently, this has created challenges in implementing system enhancements and aligning the system with the business requirements of Security AI users. | R16: =B16&" - "&C16 -> DELOITTE CONSULTING - DATA PRIVACY TOOLS & PELATIHAN PERSONAL DATA PROTECTION (PDP)
A17: 14 | B17: SUTRA MANAGEMENT CONSULTANCIES | C17: IMPLEMENTASI SAS IFRS17 | H17: 3.1866667 | I17: 3.6733333 | J17: 3.5166667 | K17: 3.8666667 | L17: =RESULT!E14 -> 3.6833333 | M17: =IFERROR(VALUE('RESULT Q2'!E14),"N/A") -> 3.3333333 | N17: =IF(ISNUMBER(M17),IF(M17>4.99,"Exceptional",IF(M17>3.99,"Exceed Expectation",IF(M17>=2.99,"Meet Expectation",IF(M17>1.9,"Below Expectation","Unsatisfactory")))),IF(ISNUMBER(L17),IF(L17>4.99,"Exceptional",IF(L17>3.99,"Exceed Expectation",IF(L17>=2.99,"Meet Expectation",IF(L17>1.9,"Below Expectation","Unsatisfactory")))),"N/A")) -> Meet Expectation | O17: =IFERROR('RESULT Q2'!D14,"-") -> Tatang SUTIAMAN | P17: =IFERROR(RESULT!G14,"-") -> Local vendor Sutra is affiliated with SAS Technology which is known as more expensive system compared to other vendors during the Vendor Bidding Process. However, SAS Technology System has been used in few well-known insurance companies in Indonesia, so it is easier to get the review and information; mostly positive. | Q17: =IFERROR('RESULT Q2'!G14,"-") -> no feedback | R17: =B17&" - "&C17 -> SUTRA MANAGEMENT CONSULTANCIES - IMPLEMENTASI SAS IFRS17
A18: 15 | B18: TMF INDONESIA | C18: PAYROLL | L18: =RESULT!E18 -> 3 | M18: =IFERROR(VALUE('RESULT Q2'!E17),"N/A") -> 3 | N18: =IF(ISNUMBER(M18),IF(M18>4.99,"Exceptional",IF(M18>3.99,"Exceed Expectation",IF(M18>=2.99,"Meet Expectation",IF(M18>1.9,"Below Expectation","Unsatisfactory")))),IF(ISNUMBER(L18),IF(L18>4.99,"Exceptional",IF(L18>3.99,"Exceed Expectation",IF(L18>=2.99,"Meet Expectation",IF(L18>1.9,"Below Expectation","Unsatisfactory")))),"N/A")) -> Meet Expectation | O18: =IFERROR('RESULT Q2'!D17,"-") -> Enung HARYATI | P18: =IFERROR(RESULT!G18,"-") -> Always check and recheck the task in internal PIC TMF before send the report to AMFS PIC | Q18: =IFERROR('RESULT Q2'!G17,"-") -> - | R18: =B18&" - "&C18 -> TMF INDONESIA - PAYROLL
A19: 16 | B19: REYCOM DOCUMENT SOLUTION | C19: PRINTING & DMC | L19: =RESULT!E15 -> 4.7666667 | M19: =IFERROR(VALUE('RESULT Q2'!E15),"N/A") -> 4.3 | N19: =IF(ISNUMBER(M19),IF(M19>4.99,"Exceptional",IF(M19>3.99,"Exceed Expectation",IF(M19>=2.99,"Meet Expectation",IF(M19>1.9,"Below Expectation","Unsatisfactory")))),IF(ISNUMBER(L19),IF(L19>4.99,"Exceptional",IF(L19>3.99,"Exceed Expectation",IF(L19>=2.99,"Meet Expectation",IF(L19>1.9,"Below Expectation","Unsatisfactory")))),"N/A")) -> Exceed Expectation | O19: =IFERROR('RESULT Q2'!D15,"-") -> Yulia KURNIATI | P19: =IFERROR(RESULT!G15,"-") -> More inovation for 2026 | Q19: =IFERROR('RESULT Q2'!G15,"-") -> Improvements to their latest Technology to support process at AXA | R19: =B19&" - "&C19 -> REYCOM DOCUMENT SOLUTION - PRINTING & DMC
A20: 17 | B20: FPT METRODATA INDONESIA | C20: PENETRATION TEST | L20: =RESULT!E4 -> 3 | M20: =IFERROR(VALUE('RESULT Q2'!E4),"N/A") -> 4 | N20: =IF(ISNUMBER(M20),IF(M20>4.99,"Exceptional",IF(M20>3.99,"Exceed Expectation",IF(M20>=2.99,"Meet Expectation",IF(M20>1.9,"Below Expectation","Unsatisfactory")))),IF(ISNUMBER(L20),IF(L20>4.99,"Exceptional",IF(L20>3.99,"Exceed Expectation",IF(L20>=2.99,"Meet Expectation",IF(L20>1.9,"Below Expectation","Unsatisfactory")))),"N/A")) -> Exceed Expectation | O20: =IFERROR('RESULT Q2'!D4,"-") -> Fauzi ARYANTO | P20: =IFERROR(RESULT!G4,"-") -> No need improvement | Q20: =IFERROR('RESULT Q2'!G4,"-") -> - | R20: =B20&" - "&C20 -> FPT METRODATA INDONESIA - PENETRATION TEST
A21: 18 | B21: IPROTEKSI TELEMATIKA | C21: PENETRATION TEST | L21: =RESULT!E3 -> 4 | M21: =IFERROR(VALUE('RESULT Q2'!E3),"N/A") -> 4 | N21: =IF(ISNUMBER(M21),IF(M21>4.99,"Exceptional",IF(M21>3.99,"Exceed Expectation",IF(M21>=2.99,"Meet Expectation",IF(M21>1.9,"Below Expectation","Unsatisfactory")))),IF(ISNUMBER(L21),IF(L21>4.99,"Exceptional",IF(L21>3.99,"Exceed Expectation",IF(L21>=2.99,"Meet Expectation",IF(L21>1.9,"Below Expectation","Unsatisfactory")))),"N/A")) -> Exceed Expectation | O21: =IFERROR('RESULT Q2'!D3,"-") -> Fauzi ARYANTO | P21: =IFERROR(RESULT!G3,"-") -> no need improvement | Q21: =IFERROR('RESULT Q2'!G3,"-") -> - | R21: =B21&" - "&C21 -> IPROTEKSI TELEMATIKA - PENETRATION TEST
A22: 19 | B22: ITSEC ASIA | C22: PENETRATION TEST | L22: =RESULT!E2 -> 3 | M22: =IFERROR(VALUE('RESULT Q2'!E2),"N/A") -> 3 | N22: =IF(ISNUMBER(M22),IF(M22>4.99,"Exceptional",IF(M22>3.99,"Exceed Expectation",IF(M22>=2.99,"Meet Expectation",IF(M22>1.9,"Below Expectation","Unsatisfactory")))),IF(ISNUMBER(L22),IF(L22>4.99,"Exceptional",IF(L22>3.99,"Exceed Expectation",IF(L22>=2.99,"Meet Expectation",IF(L22>1.9,"Below Expectation","Unsatisfactory")))),"N/A")) -> Meet Expectation | O22: =IFERROR('RESULT Q2'!D2,"-") -> Fauzi ARYANTO | P22: =IFERROR(RESULT!G2,"-") -> Currently no need improvement | Q22: =IFERROR('RESULT Q2'!G2,"-") -> - | R22: =B22&" - "&C22 -> ITSEC ASIA - PENETRATION TEST
A23: 20 | B23: Karyaputra Suryagemilang | C23: Purecloud Decommisioning | D23: N/A | E23: N/A | F23: N/A | G23: N/A | H23: N/A | I23: N/A | J23: N/A | K23: N/A | L23: N/A | M23: =IFERROR(VALUE('RESULT Q2'!E20),"N/A") -> 3.4458333 | N23: =IF(ISNUMBER(M23),IF(M23>4.99,"Exceptional",IF(M23>3.99,"Exceed Expectation",IF(M23>=2.99,"Meet Expectation",IF(M23>1.9,"Below Expectation","Unsatisfactory")))),"N/A") -> Meet Expectation | O23: =IFERROR('RESULT Q2'!D20,"-") -> Noviani MARBUN | P23: - | Q23: =IFERROR('RESULT Q2'!G20,"-") -> 1. KPSG-ARSI Perspective (The approach applied is still limited to best practices without considering the scenarios occurring in AMFS). 2. Requirement Gap (There is a significant requirement gap due to missed requirements, caused by insufficient exploration of user needs and requirements) 3. Frequent Manpower (MP) and PIC Changes (Manpower changes occur quite frequently, while the implementation team is no longer on-site. The PIC from KPSG also changes often. It is requested that a dedicated PIC be provided for IT Support as well as a dedicated Project Manager) 4. Deployment Issues (Each deployment consistently results in new issues that impact areas outside the deployment scope. This indicates a lack of proper health checks after deployment). 5. Deployment Communication (Communication regarding deployment plans is still lacking, particularly in obtaining approval from business users. This matter has already been communicated by AMFS to the KPSG team). 6. Contact Center Experience (The team’s experience in contact center operations, especially inbound, remains limited). 7. Change Requests (CR) and Production Issues (Many CRs and production issues are delivered based on targets determined unilaterally by KPSG). 8. User Guide and Feature Socialization. (The User Guide is not well maintained. When new features are introduced, documentation should be updated immediately, socialized to users, and the latest User Guide shared to ensure optimal usage) | R23: =B23&" - "&C23 -> Karyaputra Suryagemilang - Purecloud Decommisioning
A24: 21 | B24: Mitra Integrasi Informatika | C24: Purecloud Decommisioning | D24: N/A | E24: N/A | F24: N/A | G24: N/A | H24: N/A | I24: N/A | J24: N/A | K24: N/A | L24: N/A | M24: =IFERROR(VALUE('RESULT Q2'!E21),"N/A") -> 3.8833333 | N24: =IF(ISNUMBER(M24),IF(M24>4.99,"Exceptional",IF(M24>3.99,"Exceed Expectation",IF(M24>=2.99,"Meet Expectation",IF(M24>1.9,"Below Expectation","Unsatisfactory")))),"N/A") -> Meet Expectation | O24: =IFERROR('RESULT Q2'!D21,"-") -> Noviani MARBUN | P24: - | Q24: =IFERROR('RESULT Q2'!G21,"-") -> 1) Training Process During the training sessions, it is expected that explanations are delivered in detail and step by step. When participants are conducting hands-on activities, they should be properly provided with guidance and direct support. This is important to avoid unnecessary questions that could otherwise be answered clearly, ensuring that participants can immediately understand the changes and new features introduced. 2) “Baby Sitting” Phase In the “baby sitting” phase, the MII team was expected to be present full day on-site at AMFS for two weeks. However, in practice, the team did not consistently attend and only joined full day after being specifically requested. As a result, the actual presence was only around five days instead of the full two weeks as originally required. | R24: =B24&" - "&C24 -> Mitra Integrasi Informatika - Purecloud Decommisioning
A25: 22 | B25: ESHAEL Indonesia | C25: Talent Assesment | D25: N/A | E25: N/A | F25: N/A | G25: N/A | H25: N/A | I25: N/A | J25: N/A | K25: N/A | L25: N/A | M25: =IFERROR(VALUE('RESULT Q2'!E22),"N/A") -> 4.6083333 | N25: =IF(ISNUMBER(M25),IF(M25>4.99,"Exceptional",IF(M25>3.99,"Exceed Expectation",IF(M25>=2.99,"Meet Expectation",IF(M25>1.9,"Below Expectation","Unsatisfactory")))),"N/A") -> Exceed Expectation | O25: =IFERROR('RESULT Q2'!D22,"-") -> I Gusti Ayu Mira SETYAWARDHANIE | P25: - | Q25: =IFERROR('RESULT Q2'!G22,"-") -> N/A | R25: =B25&" - "&C25 -> ESHAEL Indonesia - Talent Assesment

Sheet RESULT Q2
A1: No | B1: Vendor | C1: Service | D1: PIC (User) | E1: Total Score | F1: Status | G1: Remarks | H1: Catatan Data
A2: 1 | B2: Itsec Asia | C2: Penetration Testing | D2: Fauzi ARYANTO | E2: ='Q2 ITSEC'!B20 -> 3 | F2: ='Q2 ITSEC'!B21 -> Meet Expectation | G2: ='Q2 ITSEC'!B32 -> -
A3: 2 | B3: Iproteksi Telematika | C3: Penetration Testing | D3: Fauzi ARYANTO | E3: ='Q2 IPROTEKSI'!B20 -> 4 | F3: ='Q2 IPROTEKSI'!B21 -> Exceed Expectation | G3: ='Q2 IPROTEKSI'!B32 -> -
A4: 3 | B4: FPT Metrodata | C4: Penetration Testing | D4: Fauzi ARYANTO | E4: ='Q2 FPT'!B20 -> 4 | F4: ='Q2 FPT'!B21 -> Exceed Expectation | G4: ='Q2 FPT'!B32 -> -
A5: 4 | B5: Satria Antaran Prima | C5: Mailing Room | D5: Ibnu KUMALA | E5: ='Q2 SAP-Mailing'!B25 -> 3.04375 | F5: ='Q2 SAP-Mailing'!B26 -> Meet Expectation | G5: ='Q2 SAP-Mailing'!B37 -> improve inisiatsis
A6: 5 | B6: Informasi Teknologi Indonesia | C6: SMS Broadcast | D6: Fifin SARINURLITA | E6: ='Q2 JATIS'!B29 -> 3 | F6: ='Q2 JATIS'!B30 -> Meet Expectation | G6: ='Q2 JATIS'!B41 -> So far, Jatis Vendor has provided good service. Their response time is fast, and they are able to provide effective solutions whenever issues arise
A7: 6 | B7: Satria Antaran Prima | C7: Courier Service | D7: Fifin SARINURLITA, Novia Laras SANTI | E7: ='Q2 SAP-Courier'!B33 -> 3.2383333 | F7: ='Q2 SAP-Courier'!B34 -> Meet Expectation | G7: ='Q2 SAP-Courier'!B47&" | "&'Q2 SAP-Courier'!B48 -> SAP has shown improvement in terms of reporting and provides a fast response whenever issues arise. | 1. untuk detail status pengiriman dokumen/barang harus diberikan keterangan penerima dengan lengkap dan jelas; 2. Maks. SLA pengiriman harus memenuhi sesuai dengan yang ditetapkan yaitu <5% not meet SLA; 3. Invoice biaya pengiriman dikirimkan ke user yang sesuai dan dikirimkan tidak melebihi periode yang ditetapkan. 4. Report Stock sesuai dengan real stock di warehouse. | H7: Skor rata-rata 2 business user; JAWABAN COMPLIANCE BERBEDA antar user — cek sheet detail.
A8: 7 | B8: Multifiling Mitra Indonesia | C8: Record Management Service | D8: Ibnu KUMALA | E8: ='Q2 MMI'!B29 -> 3 | F8: ='Q2 MMI'!B30 -> Meet Expectation | G8: ='Q2 MMI'!B41 -> ..
A9: 8 | B9: Indosat | C9: Layanan PBX berbasiskan cloud dengan Teknologi SIP Trunk | D9: Nuril HUDHA | E9: ='Q2 INDOSAT'!B36 -> 3.4394737 | F9: ='Q2 INDOSAT'!B37 -> Meet Expectation | G9: ='Q2 INDOSAT'!B48 -> Vendor performance is generally acceptable and aligns with the expected level of service. While the engagement has been positive overall, improvements are needed in feature enhancement, dashboard capabilities, and the regularity of report updates. Better preparation in deployment and timely reporting would help increase the overall value and effectiveness of the service.
A10: 9 | B10: Ciptadra Softindo | C10: Pemeliharaan Axits & DMTM | D10: Raninta MAHARDI | E10: ='Q2 CIPTADRA'!B32 -> 4.3 | F10: ='Q2 CIPTADRA'!B33 -> Exceed Expectation | G10: ='Q2 CIPTADRA'!B44 -> Ciptadra selalu fast response ketika ada incident yang terjadi di DMTM
A11: 10 | B11: Target Sukses Sinergi | C11: Email Marketing Automation | D11: Bella Friska DEPARI | E11: ='Q2 MTARGET'!B23 -> 2.9416667 | F11: ='Q2 MTARGET'!B24 -> Below Expectation | G11: ='Q2 MTARGET'!B35 -> Secara keseluruhan, MTarget telah memberikan dukungan yang baik dalam operasional email campaign dan responsif dalam menangani kebutuhan maupun isu yang muncul. Namun, insiden kesalahan pengiriman email yang terjadi menunjukkan perlunya penguatan pada proses deployment, pengujian, serta validasi sebelum implementasi ke production. Ke depannya, kami berharap MTarget dapat memperkuat proses change management, quality assurance, dan kontrol terhadap segmentasi serta pengiriman email untuk meminimalkan risiko terjadinya insiden serupa.
A12: 11 | B12: Inmotion Inovasi Teknologi | C12: Jasa Aplikasi Chatbot dan Live Chat | D12: Djoko DJOKO | E12: ='Q2 INMOTION'!B54 -> 4 | F12: ='Q2 INMOTION'!B55 -> Exceed Expectation | G12: ='Q2 INMOTION'!B66 -> Tetap up to date dan helpful
A13: 12 | B13: Mitra Integrasi Informatika | C13: SFDC Maintenance | D13: Chandra Nugraha PUTRA | E13: ='Q2 MII-SFDC'!B30 -> 4.7487179 | F13: ='Q2 MII-SFDC'!B31 -> Exceed Expectation | G13: ='Q2 MII-SFDC'!B42 -> Respons terhadap issue maupun kebutuhan sudah cukup baik dan cepat. Support on-site juga sangat membantu dan responsif. Ke depannya, mungkin dapat lebih rutin memberikan update terkait progress kendala atau perbaikan yang sedang dilakukan, sehingga pihak terkait dapat mengetahui status terbaru dan lebih cepat menentukan langkah selanjutnya.
A14: 13 | B14: Sutra Management Consultancies | C14: Implementasi SAS IFRS17 | D14: Tatang SUTIAMAN | E14: ='Q2 SUTRA'!B38 -> 3.3333333 | F14: ='Q2 SUTRA'!B39 -> Meet Expectation | G14: ='Q2 SUTRA'!B50 -> no feedback
A15: 14 | B15: Reycom Document Solution | C15: Printing & Data Management Center | D15: Yulia KURNIATI | E15: ='Q2 RDS-Printing'!B33 -> 4.3 | F15: ='Q2 RDS-Printing'!B34 -> Exceed Expectation | G15: ='Q2 RDS-Printing'!B45 -> Improvements to their latest Technology to support process at AXA | H15: Vendor submit 2x; menggunakan submission terakhir (lebih lengkap).
A16: 15 | B16: Deloitte Consulting | C16: Data Privacy & Pelatihan Personal Data Protection (PDP) | D16: M. Andrian Patria Shaleh RIZAL | E16: ='Q2 DELOITTE'!B28 -> 4.0636364 | F16: ='Q2 DELOITTE'!B29 -> Exceed Expectation | G16: ='Q2 DELOITTE'!B40 -> In dealing with Security AI-related issues, Deloitte is occasionally unable to provide a resolution and therefore redirects the matter to the Security AI team. Furthermore, several system features are restricted, and these limitations were not clearly communicated at the outset. Consequently, this has created challenges in implementing system enhancements and aligning the system with the business requirements of Security AI users.
A17: 16 | B17: TMF Indonesia | C17: Payroll | D17: Enung HARYATI | E17: ='Q2 TMF'!B23 -> 3 | F17: ='Q2 TMF'!B24 -> Meet Expectation | G17: ='Q2 TMF'!B35 -> -
A18: 17 | B18: Karya Putra Surya Gemilang | C18: Telemarketing Revamp Project | D18: Nuril HUDHA | E18: ='Q2 KPSG-TM'!B28 -> 3.5393939 | F18: ='Q2 KPSG-TM'!B29 -> Meet Expectation | G18: ='Q2 KPSG-TM'!B40 -> 1. For AI Implementation, KPSG need to improve the delivery time, quality and PIC availability and backup PIC support 2. Another enhancement need to speed up with dedicated team
A19: 18 | B19: Wiz Technology | C19: Voice Bot Reminder Call | D19: Ravika OKTAVIANI | E19: ='Q2 WIZ'!B25 -> 3.0875 | F19: ='Q2 WIZ'!B26 -> Meet Expectation | G19: ='Q2 WIZ'!B37 -> To ensure a smooth process, we need to move faster and maintain effective communication
A20: 19 | B20: Karyaputra Suryagemilang | C20: Purecloud Decommisioning | D20: Noviani MARBUN | E20: ='Q2 KPSG-ARSI'!B34 -> 3.4458333 | F20: ='Q2 KPSG-ARSI'!B35 -> Meet Expectation | G20: ='Q2 KPSG-ARSI'!B46 -> 1. KPSG-ARSI Perspective (The approach applied is still limited to best practices without considering the scenarios occurring in AMFS). 2. Requirement Gap (There is a significant requirement gap due to missed requirements, caused by insufficient exploration of user needs and requirements) 3. Frequent Manpower (MP) and PIC Changes (Manpower changes occur quite frequently, while the implementation team is no longer on-site. The PIC from KPSG also changes often. It is requested that a dedicated PIC be provided for IT Support as well as a dedicated Project Manager) 4. Deployment Issues (Each deployment consistently results in new issues that impact areas outside the deployment scope. This indicates a lack of proper health checks after deployment). 5. Deployment Communication (Communication regarding deployment plans is still lacking, particularly in obtaining approval from business users. This matter has already been communicated by AMFS to the KPSG team). 6. Contact Center Experience (The team’s experience in contact center operations, especially inbound, remains limited). 7. Change Requests (CR) and Production Issues (Many CRs and production issues are delivered based on targets determined unilaterally by KPSG). 8. User Guide and Feature Socialization. (The User Guide is not well maintained. When new features are introduced, documentation should be updated immediately, socialized to users, and the latest User Guide shared to ensure optimal usage) | H20: Vendor/proyek baru; belum ada histori kuartal sebelumnya. Klasifikasi Quality/Timeline pada pertanyaan custom memakai heuristik kata kunci — mohon di-review SRM.
A21: 20 | B21: Mitra Integrasi Informatika | C21: Purecloud Decommisioning | D21: Noviani MARBUN | E21: ='Q2 MII-Purecloud'!B30 -> 3.8833333 | F21: ='Q2 MII-Purecloud'!B31 -> Meet Expectation | G21: ='Q2 MII-Purecloud'!B42 -> 1) Training Process During the training sessions, it is expected that explanations are delivered in detail and step by step. When participants are conducting hands-on activities, they should be properly provided with guidance and direct support. This is important to avoid unnecessary questions that could otherwise be answered clearly, ensuring that participants can immediately understand the changes and new features introduced. 2) “Baby Sitting” Phase In the “baby sitting” phase, the MII team was expected to be present full day on-site at AMFS for two weeks. However, in practice, the team did not consistently attend and only joined full day after being specifically requested. As a result, the actual presence was only around five days instead of the full two weeks as originally required. | H21: Vendor/proyek baru; belum ada histori kuartal sebelumnya. Klasifikasi Quality/Timeline pada pertanyaan custom memakai heuristik kata kunci — mohon di-review SRM.
A22: 21 | B22: ESHAEL Indonesia | C22: Talent Assesment | D22: I Gusti Ayu Mira SETYAWARDHANIE | E22: ='Q2 ESHAEL'!B29 -> 4.6083333 | F22: ='Q2 ESHAEL'!B30 -> Exceed Expectation | G22: ='Q2 ESHAEL'!B41 -> N/A | H22: Vendor/proyek baru; belum ada histori kuartal sebelumnya. Klasifikasi Quality/Timeline pada pertanyaan custom memakai heuristik kata kunci — mohon di-review SRM.
A23: 22 | B23: Arah Sejahtera Abadi | C23: Perjanjian Sewa Menyewa | D23: ibnu.kumala@axa-mandiri.co.id | E23: N/A | F23: Tidak Dievaluasi Q2 | G23: - | H23: Vendor tidak mengisi assessment pada periode Q2 2026.

Sheet Q2 ITSEC
A1: HASIL REVIEW VENDOR — Q2 2026
A2: Vendor | B2: Itsec Asia
A3: Service | B3: Penetration Testing
A4: PIC (Business User) | B4: Fauzi ARYANTO
A6: No | B6: Dimensi | C6: Pertanyaan | D6: Skor
A7: 1 | B7: Quality | C7: ='RAW DATA Q2 - 1'!ER$1 -> How would you rate the Technical services that is used to penetrate the application which includes: 1. Technical Specification Design. 2. Hardware and capacity sizing for concurrent requests 3. Functi2 | D7: ='RAW DATA Q2 - 1'!ER10 -> 3
A8: 2 | B8: Quality | C8: ='RAW DATA Q2 - 1'!ES$1 -> How would you rate the after sales support capability and methodology?2 | D8: ='RAW DATA Q2 - 1'!ES10 -> 3
A9: 3 | B9: Quality | C9: ='RAW DATA Q2 - 1'!ET$1 -> How would you rate the availability of documentation for product (user manual, troubleshoot document, setup document, etc)?1 | D9: ='RAW DATA Q2 - 1'!ET10 -> 3
A10: 4 | B10: Timeline | C10: ='RAW DATA Q2 - 1'!EU$1 -> How would you rate the supplier's timeliness in delivering goods/services compared to the agreed-upon timeline? | D10: ='RAW DATA Q2 - 1'!EU10 -> 3
A11: 5 | B11: Timeline | C11: ='RAW DATA Q2 - 1'!EV$1 -> How would you rate the supplier's timeliness in sending reports to you? | D11: ='RAW DATA Q2 - 1'!EV10 -> 3
A12: 6 | B12: Timeline | C12: ='RAW DATA Q2 - 1'!EW$1 -> How would you rate the supplier's speed ​​of administrative completion, including completion of contracts draft? | D12: ='RAW DATA Q2 - 1'!EW10 -> 3
A13: 7 | B13: Relationship | C13: ='RAW DATA Q2 - 1'!FM$1 -> How would you rate the supplier's communication with you? | D13: ='RAW DATA Q2 - 1'!FM10 -> 3
A14: 8 | B14: Relationship | C14: ='RAW DATA Q2 - 1'!FN$1 -> How would you rate the supplier's PIC's availability to be contacted when needed? | D14: ='RAW DATA Q2 - 1'!FN10 -> 3
A15: 9 | B15: Relationship | C15: ='RAW DATA Q2 - 1'!FO$1 -> How would you rate the supplier's response speed to you when there are issues? | D15: ='RAW DATA Q2 - 1'!FO10 -> 3
A17: Quality Avg (35%) | B17: =AVERAGEIF(B7:B15,"Quality",D7:D15) -> 3
A18: Timeline Avg (35%) | B18: =AVERAGEIF(B7:B15,"Timeline",D7:D15) -> 3
A19: Relationship Avg (30%) | B19: =AVERAGEIF(B7:B15,"Relationship",D7:D15) -> 3
A20: TOTAL SCORE | B20: =B17*0.35+B18*0.35+B19*0.3 -> 3
A21: STATUS | B21: =IF(B20>4.99,"Exceptional",IF(B20>3.99,"Exceed Expectation",IF(B20>=2.99,"Meet Expectation",IF(B20>1.9,"Below Expectation","Unsatisfactory")))) -> Meet Expectation
A23: DUE DILIGENCE / COMPLIANCE
A24: Financial Assessment | B24: ='RAW DATA Q2 - 1'!FP10 -> Yes
A25: Reputational Assessment | B25: ='RAW DATA Q2 - 1'!FQ10 -> Yes
A26: DPIA | B26: ='RAW DATA Q2 - 1'!FR10 -> Yes, DPIA completed and there are actions to be done by Project Owner
A27: DPSQ | B27: ='RAW DATA Q2 - 1'!FS10 -> No Implementation
A28: VSDDT | B28: ='RAW DATA Q2 - 1'!FT10 -> Yes, VSDDT completed and there are actions to be done by supplier
A29: Action Plan
A31: REMARKS / FEEDBACK
B32: ='RAW DATA Q2 - 1'!FU10 -> -

Sheet Q2 IPROTEKSI
A1: HASIL REVIEW VENDOR — Q2 2026
A2: Vendor | B2: Iproteksi Telematika
A3: Service | B3: Penetration Testing
A4: PIC (Business User) | B4: Fauzi ARYANTO
A6: No | B6: Dimensi | C6: Pertanyaan | D6: Skor
A7: 1 | B7: Quality | C7: ='RAW DATA Q2 - 1'!EO$1 -> How would you rate the Technical services that is used to penetrate the application which includes: 1. Technical Specification Design. 2. Hardware and capacity sizing for concurrent requests 3. Functi1 | D7: ='RAW DATA Q2 - 1'!EO9 -> 4
A8: 2 | B8: Quality | C8: ='RAW DATA Q2 - 1'!EP$1 -> How would you rate the after sales support capability and methodology?1 | D8: ='RAW DATA Q2 - 1'!EP9 -> 4
A9: 3 | B9: Quality | C9: ='RAW DATA Q2 - 1'!EQ$1 -> How would you rate the availability of documentation for product (user manual, troubleshoot document, setup document, etc)? | D9: ='RAW DATA Q2 - 1'!EQ9 -> 4
A10: 4 | B10: Timeline | C10: ='RAW DATA Q2 - 1'!EU$1 -> How would you rate the supplier's timeliness in delivering goods/services compared to the agreed-upon timeline? | D10: ='RAW DATA Q2 - 1'!EU9 -> 4
A11: 5 | B11: Timeline | C11: ='RAW DATA Q2 - 1'!EV$1 -> How would you rate the supplier's timeliness in sending reports to you? | D11: ='RAW DATA Q2 - 1'!EV9 -> 4
A12: 6 | B12: Timeline | C12: ='RAW DATA Q2 - 1'!EW$1 -> How would you rate the supplier's speed ​​of administrative completion, including completion of contracts draft? | D12: ='RAW DATA Q2 - 1'!EW9 -> 4
A13: 7 | B13: Relationship | C13: ='RAW DATA Q2 - 1'!FM$1 -> How would you rate the supplier's communication with you? | D13: ='RAW DATA Q2 - 1'!FM9 -> 4
A14: 8 | B14: Relationship | C14: ='RAW DATA Q2 - 1'!FN$1 -> How would you rate the supplier's PIC's availability to be contacted when needed? | D14: ='RAW DATA Q2 - 1'!FN9 -> 4
A15: 9 | B15: Relationship | C15: ='RAW DATA Q2 - 1'!FO$1 -> How would you rate the supplier's response speed to you when there are issues? | D15: ='RAW DATA Q2 - 1'!FO9 -> 4
A17: Quality Avg (35%) | B17: =AVERAGEIF(B7:B15,"Quality",D7:D15) -> 4
A18: Timeline Avg (35%) | B18: =AVERAGEIF(B7:B15,"Timeline",D7:D15) -> 4
A19: Relationship Avg (30%) | B19: =AVERAGEIF(B7:B15,"Relationship",D7:D15) -> 4
A20: TOTAL SCORE | B20: =B17*0.35+B18*0.35+B19*0.3 -> 4
A21: STATUS | B21: =IF(B20>4.99,"Exceptional",IF(B20>3.99,"Exceed Expectation",IF(B20>=2.99,"Meet Expectation",IF(B20>1.9,"Below Expectation","Unsatisfactory")))) -> Exceed Expectation
A23: DUE DILIGENCE / COMPLIANCE
A24: Financial Assessment | B24: ='RAW DATA Q2 - 1'!FP9 -> Yes
A25: Reputational Assessment | B25: ='RAW DATA Q2 - 1'!FQ9 -> Yes
A26: DPIA | B26: ='RAW DATA Q2 - 1'!FR9 -> Yes, DPIA completed and there are actions to be done by Project Owner
A27: DPSQ | B27: ='RAW DATA Q2 - 1'!FS9 -> No Implementation
A28: VSDDT | B28: ='RAW DATA Q2 - 1'!FT9 -> Yes, VSDDT completed and there are actions to be done by supplier
A29: Action Plan
A31: REMARKS / FEEDBACK
B32: ='RAW DATA Q2 - 1'!FU9 -> -

Sheet Q2 FPT
A1: HASIL REVIEW VENDOR — Q2 2026
A2: Vendor | B2: FPT Metrodata
A3: Service | B3: Penetration Testing
A4: PIC (Business User) | B4: Fauzi ARYANTO
A6: No | B6: Dimensi | C6: Pertanyaan | D6: Skor
A7: 1 | B7: Quality | C7: ='RAW DATA Q2 - 1'!EL$1 -> How would you rate the Technical services that is used to penetrate the application which includes: 1. Technical Specification Design. 2. Hardware and capacity sizing for concurrent requests 3. Functi | D7: ='RAW DATA Q2 - 1'!EL8 -> 4
A8: 2 | B8: Quality | C8: ='RAW DATA Q2 - 1'!EM$1 -> How would you rate the after sales support capability and methodology? | D8: ='RAW DATA Q2 - 1'!EM8 -> 4
A9: 3 | B9: Quality | C9: ='RAW DATA Q2 - 1'!EN$1 -> How would you rate the availability of documentation for service (user manual, troubleshoot document, setup document, etc)? | D9: ='RAW DATA Q2 - 1'!EN8 -> 4
A10: 4 | B10: Timeline | C10: ='RAW DATA Q2 - 1'!EU$1 -> How would you rate the supplier's timeliness in delivering goods/services compared to the agreed-upon timeline? | D10: ='RAW DATA Q2 - 1'!EU8 -> 4
A11: 5 | B11: Timeline | C11: ='RAW DATA Q2 - 1'!EV$1 -> How would you rate the supplier's timeliness in sending reports to you? | D11: ='RAW DATA Q2 - 1'!EV8 -> 4
A12: 6 | B12: Timeline | C12: ='RAW DATA Q2 - 1'!EW$1 -> How would you rate the supplier's speed ​​of administrative completion, including completion of contracts draft? | D12: ='RAW DATA Q2 - 1'!EW8 -> 4
A13: 7 | B13: Relationship | C13: ='RAW DATA Q2 - 1'!FM$1 -> How would you rate the supplier's communication with you? | D13: ='RAW DATA Q2 - 1'!FM8 -> 4
A14: 8 | B14: Relationship | C14: ='RAW DATA Q2 - 1'!FN$1 -> How would you rate the supplier's PIC's availability to be contacted when needed? | D14: ='RAW DATA Q2 - 1'!FN8 -> 4
A15: 9 | B15: Relationship | C15: ='RAW DATA Q2 - 1'!FO$1 -> How would you rate the supplier's response speed to you when there are issues? | D15: ='RAW DATA Q2 - 1'!FO8 -> 4
A17: Quality Avg (35%) | B17: =AVERAGEIF(B7:B15,"Quality",D7:D15) -> 4
A18: Timeline Avg (35%) | B18: =AVERAGEIF(B7:B15,"Timeline",D7:D15) -> 4
A19: Relationship Avg (30%) | B19: =AVERAGEIF(B7:B15,"Relationship",D7:D15) -> 4
A20: TOTAL SCORE | B20: =B17*0.35+B18*0.35+B19*0.3 -> 4
A21: STATUS | B21: =IF(B20>4.99,"Exceptional",IF(B20>3.99,"Exceed Expectation",IF(B20>=2.99,"Meet Expectation",IF(B20>1.9,"Below Expectation","Unsatisfactory")))) -> Exceed Expectation
A23: DUE DILIGENCE / COMPLIANCE
A24: Financial Assessment | B24: ='RAW DATA Q2 - 1'!FP8 -> Yes
A25: Reputational Assessment | B25: ='RAW DATA Q2 - 1'!FQ8 -> Yes
A26: DPIA | B26: ='RAW DATA Q2 - 1'!FR8 -> Yes, DPIA completed and there are actions to be done by Project Owner
A27: DPSQ | B27: ='RAW DATA Q2 - 1'!FS8 -> No Implementation
A28: VSDDT | B28: ='RAW DATA Q2 - 1'!FT8 -> Yes, VSDDT completed and there are actions to be done by supplier
A29: Action Plan
A31: REMARKS / FEEDBACK
B32: ='RAW DATA Q2 - 1'!FU8 -> -

Sheet Q2 SAP-Mailing
A1: HASIL REVIEW VENDOR — Q2 2026
A2: Vendor | B2: Satria Antaran Prima
A3: Service | B3: Mailing Room
A4: PIC (Business User) | B4: Ibnu KUMALA
A6: No | B6: Dimensi | C6: Pertanyaan | D6: Skor
A7: 1 | B7: Quality | C7: ='RAW DATA Q2 - 1'!DX$1 -> How would you rate the goods/services provided by the Supplier against the agreed standards?1 | D7: ='RAW DATA Q2 - 1'!DX11 -> 3
A8: 2 | B8: Quality | C8: ='RAW DATA Q2 - 1'!DY$1 -> How would you rate the accuracy of the data in the Supplier's reports?6 | D8: ='RAW DATA Q2 - 1'!DY11 -> 4
A9: 3 | B9: Quality | C9: ='RAW DATA Q2 - 1'!DZ$1 -> How would you rate overall quality of the work reports provided by the Supplier?6 | D9: ='RAW DATA Q2 - 1'!DZ11 -> 3
A10: 4 | B10: Quality | C10: ='RAW DATA Q2 - 1'!EA$1 -> How would you rate the solutions provided when there is trouble?6 | D10: ='RAW DATA Q2 - 1'!EA11 -> 3
A11: 5 | B11: Quality | C11: ='RAW DATA Q2 - 1'!EB$1 -> How would you rate the resolution to the problem that occurred?6 | D11: ='RAW DATA Q2 - 1'!EB11 -> 3
A12: 6 | B12: Quality | C12: ='RAW DATA Q2 - 1'!EC$1 -> How would you rate the supplier initiative to take mitigation/preventive action to prevent the problem from recurring?7 | D12: ='RAW DATA Q2 - 1'!EC11 -> 3
A13: 7 | B13: Quality | C13: ='RAW DATA Q2 - 1'!ED$1 -> How would you rate the service provided? | D13: ='RAW DATA Q2 - 1'!ED11 -> 3
A14: 8 | B14: Quality | C14: ='RAW DATA Q2 - 1'!EE$1 -> How would you rate the Complaint Handling? | D14: ='RAW DATA Q2 - 1'!EE11 -> 3
A15: 9 | B15: Timeline | C15: ='RAW DATA Q2 - 1'!EU$1 -> How would you rate the supplier's timeliness in delivering goods/services compared to the agreed-upon timeline? | D15: ='RAW DATA Q2 - 1'!EU11 -> 3
A16: 10 | B16: Timeline | C16: ='RAW DATA Q2 - 1'!EV$1 -> How would you rate the supplier's timeliness in sending reports to you? | D16: ='RAW DATA Q2 - 1'!EV11 -> 3
A17: 11 | B17: Timeline | C17: ='RAW DATA Q2 - 1'!EW$1 -> How would you rate the supplier's speed ​​of administrative completion, including completion of contracts draft? | D17: ='RAW DATA Q2 - 1'!EW11 -> 3
A18: 12 | B18: Relationship | C18: ='RAW DATA Q2 - 1'!FM$1 -> How would you rate the supplier's communication with you? | D18: ='RAW DATA Q2 - 1'!FM11 -> 3
A19: 13 | B19: Relationship | C19: ='RAW DATA Q2 - 1'!FN$1 -> How would you rate the supplier's PIC's availability to be contacted when needed? | D19: ='RAW DATA Q2 - 1'!FN11 -> 3
A20: 14 | B20: Relationship | C20: ='RAW DATA Q2 - 1'!FO$1 -> How would you rate the supplier's response speed to you when there are issues? | D20: ='RAW DATA Q2 - 1'!FO11 -> 3
A22: Quality Avg (35%) | B22: =AVERAGEIF(B7:B20,"Quality",D7:D20) -> 3.125
A23: Timeline Avg (35%) | B23: =AVERAGEIF(B7:B20,"Timeline",D7:D20) -> 3
A24: Relationship Avg (30%) | B24: =AVERAGEIF(B7:B20,"Relationship",D7:D20) -> 3
A25: TOTAL SCORE | B25: =B22*0.35+B23*0.35+B24*0.3 -> 3.04375
A26: STATUS | B26: =IF(B25>4.99,"Exceptional",IF(B25>3.99,"Exceed Expectation",IF(B25>=2.99,"Meet Expectation",IF(B25>1.9,"Below Expectation","Unsatisfactory")))) -> Meet Expectation
A28: DUE DILIGENCE / COMPLIANCE
A29: Financial Assessment | B29: ='RAW DATA Q2 - 1'!FP11 -> Yes
A30: Reputational Assessment | B30: ='RAW DATA Q2 - 1'!FQ11 -> Yes
A31: DPIA | B31: ='RAW DATA Q2 - 1'!FR11 -> Yes, DPIA completed and there are actions to be done by Project Owner
A32: DPSQ | B32: ='RAW DATA Q2 - 1'!FS11 -> No Implementation
A33: VSDDT | B33: ='RAW DATA Q2 - 1'!FT11 -> Yes, VSDDT completed and there are actions to be done by supplier
A34: Action Plan
A36: REMARKS / FEEDBACK
B37: ='RAW DATA Q2 - 1'!FU11 -> improve inisiatsis

Sheet Q2 JATIS
A1: HASIL REVIEW VENDOR — Q2 2026
A2: Vendor | B2: Informasi Teknologi Indonesia - SMS Broadcast
A3: Service
A4: PIC (Business User) | B4: Fifin SARINURLITA
A6: No | B6: Dimensi | C6: Pertanyaan | D6: Skor
A7: 1 | B7: Quality | C7: ='RAW DATA Q2 - 1'!AA$1 -> How would you rate Supplier's ability to understand and meet your needs?1 | D7: ='RAW DATA Q2 - 1'!AA5 -> 3
A8: 2 | B8: Quality | C8: ='RAW DATA Q2 - 1'!AB$1 -> How would you rate the goods/services provided by the Supplier against the agreed standards? | D8: ='RAW DATA Q2 - 1'!AB5 -> 3
A9: 3 | B9: Quality | C9: ='RAW DATA Q2 - 1'!AC$1 -> How would you rate the accuracy of the data in the Supplier's reports? | D9: ='RAW DATA Q2 - 1'!AC5 -> 3
A10: 4 | B10: Quality | C10: ='RAW DATA Q2 - 1'!AD$1 -> How would you rate overall quality of the work reports provided by the Supplier? | D10: ='RAW DATA Q2 - 1'!AD5 -> 3
A11: 5 | B11: Quality | C11: ='RAW DATA Q2 - 1'!AE$1 -> How would you rate the solutions provided when there is trouble? | D11: ='RAW DATA Q2 - 1'!AE5 -> 3
A12: 6 | B12: Quality | C12: ='RAW DATA Q2 - 1'!AF$1 -> How would you rate the resolution to the problem that occurred? | D12: ='RAW DATA Q2 - 1'!AF5 -> 3
A13: 7 | B13: Quality | C13: ='RAW DATA Q2 - 1'!AG$1 -> How would you rate the speed of resolution given to problems that occur? | D13: ='RAW DATA Q2 - 1'!AG5 -> 3
A14: 8 | B14: Quality | C14: ='RAW DATA Q2 - 1'!AH$1 -> How would you rate the supplier initiative to take mitigation/preventive action to prevent the problem from recurring? | D14: ='RAW DATA Q2 - 1'!AH5 -> 3
A15: 9 | B15: Quality | C15: ='RAW DATA Q2 - 1'!AI$1 -> How would you rate supplier compliance with administrative processes, including completion of draft cooperation contract?1 | D15: ='RAW DATA Q2 - 1'!AI5 -> 3
A16: 10 | B16: Quality | C16: ='RAW DATA Q2 - 1'!AJ$1 -> How would you rate the Implementation of UAT? | D16: ='RAW DATA Q2 - 1'!AJ5 -> 3
A17: 11 | B17: Quality | C17: ='RAW DATA Q2 - 1'!AK$1 -> How would you rate the maintenance includes bug fixing and support for system problems that occur in the JATIS MOBILE application/service? | D17: ='RAW DATA Q2 - 1'!AK5 -> 3
A18: 12 | B18: Timeline | C18: ='RAW DATA Q2 - 1'!EX$1 -> How would you rate the supplier's timeliness in delivering goods/services compared to the agreed-upon timeline?1 | D18: ='RAW DATA Q2 - 1'!EX5 -> 3
A19: 13 | B19: Timeline | C19: ='RAW DATA Q2 - 1'!EY$1 -> How would you rate the supplier's timeliness in sending reports to you? | D19: ='RAW DATA Q2 - 1'!EY5 -> 3
A20: 14 | B20: Timeline | C20: ='RAW DATA Q2 - 1'!EZ$1 -> How would you rate the supplier's Traffic Confirmation SLA Fulfillment? | D20: ='RAW DATA Q2 - 1'!EZ5 -> 3
A21: 15 | B21: Timeline | C21: ='RAW DATA Q2 - 1'!FA$1 -> How would you rate the supplier's speed ​​of administrative completion, including completion of contracts draft? | D21: ='RAW DATA Q2 - 1'!FA5 -> 3
A22: 16 | B22: Relationship | C22: ='RAW DATA Q2 - 1'!FM$1 -> How would you rate the supplier's communication with you? | D22: ='RAW DATA Q2 - 1'!FM5 -> 3
A23: 17 | B23: Relationship | C23: ='RAW DATA Q2 - 1'!FN$1 -> How would you rate the supplier's PIC's availability to be contacted when needed? | D23: ='RAW DATA Q2 - 1'!FN5 -> 3
A24: 18 | B24: Relationship | C24: ='RAW DATA Q2 - 1'!FO$1 -> How would you rate the supplier's response speed to you when there are issues? | D24: ='RAW DATA Q2 - 1'!FO5 -> 3
A26: Quality Avg (35%) | B26: =AVERAGEIF(B7:B24,"Quality",D7:D24) -> 3
A27: Timeline Avg (35%) | B27: =AVERAGEIF(B7:B24,"Timeline",D7:D24) -> 3
A28: Relationship Avg (30%) | B28: =AVERAGEIF(B7:B24,"Relationship",D7:D24) -> 3
A29: TOTAL SCORE | B29: =B26*0.35+B27*0.35+B28*0.3 -> 3
A30: STATUS | B30: =IF(B29>4.99,"Exceptional",IF(B29>3.99,"Exceed Expectation",IF(B29>=2.99,"Meet Expectation",IF(B29>1.9,"Below Expectation","Unsatisfactory")))) -> Meet Expectation
A32: DUE DILIGENCE / COMPLIANCE
A33: Financial Assessment | B33: ='RAW DATA Q2 - 1'!FP5 -> Yes
A34: Reputational Assessment | B34: ='RAW DATA Q2 - 1'!FQ5 -> Yes
A35: DPIA | B35: ='RAW DATA Q2 - 1'!FR5 -> Yes, DPIA completed and there are actions to be done by Project Owner
A36: DPSQ | B36: ='RAW DATA Q2 - 1'!FS5 -> Yes, DPSQ completed
A37: VSDDT | B37: ='RAW DATA Q2 - 1'!FT5 -> Yes, VSDDT completed and there are actions to be done by supplier
A38: Action Plan
A40: REMARKS / FEEDBACK
B41: ='RAW DATA Q2 - 1'!FU5 -> So far, Jatis Vendor has provided good service. Their response time is fast, and they are able to provide effective solutions whenever issues arise

Sheet Q2 SAP-Courier
A1: HASIL REVIEW VENDOR — Q2 2026
A2: Vendor | B2: Satria Antaran Prima
A3: Service | B3: Courier Service
A4: PIC (Business User) | B4: Fifin SARINURLITA, Novia Laras SANTI
A5: Catatan | B5: Skor merupakan RATA-RATA dari 2 business user yang menilai vendor/service yang sama pada periode ini.
A7: No | B7: Dimensi | C7: Pertanyaan | D7: Skor
A8: 1 | B8: Quality | C8: ='RAW DATA Q2 - 1'!DI$1 -> How would you rate the goods/services provided by the Supplier against the agreed standards3 | D8: =AVERAGE('RAW DATA Q2 - 1'!DI6,'RAW DATA Q2 - 1'!DI7) -> 3.5
A9: 2 | B9: Quality | C9: ='RAW DATA Q2 - 1'!DJ$1 -> How would you rate the accuracy of the data in the Supplier's reports?5 | D9: =AVERAGE('RAW DATA Q2 - 1'!DJ6,'RAW DATA Q2 - 1'!DJ7) -> 2.5
A10: 3 | B10: Quality | C10: ='RAW DATA Q2 - 1'!DK$1 -> How would you rate overall quality of the work reports provided by the Supplier?5 | D10: =AVERAGE('RAW DATA Q2 - 1'!DK6,'RAW DATA Q2 - 1'!DK7) -> 3
A11: 4 | B11: Quality | C11: ='RAW DATA Q2 - 1'!DL$1 -> How would you rate the solutions provided when there is trouble?5 | D11: =AVERAGE('RAW DATA Q2 - 1'!DL6,'RAW DATA Q2 - 1'!DL7) -> 3
A12: 5 | B12: Quality | C12: ='RAW DATA Q2 - 1'!DM$1 -> How would you rate the resolution to the problem that occurred?5 | D12: =AVERAGE('RAW DATA Q2 - 1'!DM6,'RAW DATA Q2 - 1'!DM7) -> 2.5
A13: 6 | B13: Quality | C13: ='RAW DATA Q2 - 1'!DN$1 -> How would you rate the speed of resolution given to problems that occur | D13: =AVERAGE('RAW DATA Q2 - 1'!DN6,'RAW DATA Q2 - 1'!DN7) -> 3.5
A14: 7 | B14: Quality | C14: ='RAW DATA Q2 - 1'!DO$1 -> How would you rate the supplier initiative to take mitigation/preventive action to prevent the problem from recurring?6 | D14: =AVERAGE('RAW DATA Q2 - 1'!DO6,'RAW DATA Q2 - 1'!DO7) -> 3
A15: 8 | B15: Quality | C15: ='RAW DATA Q2 - 1'!DP$1 -> How would you rate supplier compliance with administrative processes, including completion of draft cooperation contract?6 | D15: =AVERAGE('RAW DATA Q2 - 1'!DP6,'RAW DATA Q2 - 1'!DP7) -> 3
A16: 9 | B16: Quality | C16: ='RAW DATA Q2 - 1'!DQ$1 -> How would you rate the shipping target achievement? | D16: =AVERAGE('RAW DATA Q2 - 1'!DQ6,'RAW DATA Q2 - 1'!DQ7) -> 2.5
A17: 10 | B17: Quality | C17: ='RAW DATA Q2 - 1'!DR$1 -> How would you rate the delivery times? Based on SLA, the delivery time are Monday to Saturday, service levels will remain the same from Monday to Friday. | D17: =AVERAGE('RAW DATA Q2 - 1'!DR6,'RAW DATA Q2 - 1'!DR7) -> 2.5
A18: 11 | B18: Quality | C18: ='RAW DATA Q2 - 1'!DS$1 -> How would you rate the Receipt retention period? | D18: =AVERAGE('RAW DATA Q2 - 1'!DS6,'RAW DATA Q2 - 1'!DS7) -> 2.5
A19: 12 | B19: Quality | C19: ='RAW DATA Q2 - 1'!DT$1 -> How would you rate the Airway Bill Storage: | D19: =AVERAGE('RAW DATA Q2 - 1'!DT6,'RAW DATA Q2 - 1'!DT7) -> 3.5
A20: 13 | B20: Quality | C20: ='RAW DATA Q2 - 1'!DU$1 -> How would you rate the Handling of Policies/Documents and/or delivery process? | D20: =AVERAGE('RAW DATA Q2 - 1'!DU6,'RAW DATA Q2 - 1'!DU7) -> 3
A21: 14 | B21: Quality | C21: ='RAW DATA Q2 - 1'!DV$1 -> How would you rate the response to complaints/investigations of the delivery process? | D21: =AVERAGE('RAW DATA Q2 - 1'!DV6,'RAW DATA Q2 - 1'!DV7) -> 3.5
A22: 15 | B22: Quality | C22: ='RAW DATA Q2 - 1'!DW$1 -> How would you rate the response taken when a delivery failure occurs? | D22: =AVERAGE('RAW DATA Q2 - 1'!DW6,'RAW DATA Q2 - 1'!DW7) -> 3
A23: 16 | B23: Timeline | C23: ='RAW DATA Q2 - 1'!FJ$1 -> How would you rate the supplier's timeliness in delivering goods/services compared to the agreed-upon timeline?4 | D23: =AVERAGE('RAW DATA Q2 - 1'!FJ6,'RAW DATA Q2 - 1'!FJ7) -> 2.5
A24: 17 | B24: Timeline | C24: ='RAW DATA Q2 - 1'!FK$1 -> How would you rate the supplier's timeliness in sending reports to you?1 | D24: =AVERAGE('RAW DATA Q2 - 1'!FK6,'RAW DATA Q2 - 1'!FK7) -> 3.5
A25: 18 | B25: Timeline | C25: ='RAW DATA Q2 - 1'!FL$1 -> How would you rate the supplier's speed ​​of administrative completion, including completion of contracts draft?2 | D25: =AVERAGE('RAW DATA Q2 - 1'!FL6,'RAW DATA Q2 - 1'!FL7) -> 3
A26: 19 | B26: Relationship | C26: ='RAW DATA Q2 - 1'!FM$1 -> How would you rate the supplier's communication with you? | D26: =AVERAGE('RAW DATA Q2 - 1'!FM6,'RAW DATA Q2 - 1'!FM7) -> 4
A27: 20 | B27: Relationship | C27: ='RAW DATA Q2 - 1'!FN$1 -> How would you rate the supplier's PIC's availability to be contacted when needed? | D27: =AVERAGE('RAW DATA Q2 - 1'!FN6,'RAW DATA Q2 - 1'!FN7) -> 4
A28: 21 | B28: Relationship | C28: ='RAW DATA Q2 - 1'!FO$1 -> How would you rate the supplier's response speed to you when there are issues? | D28: =AVERAGE('RAW DATA Q2 - 1'!FO6,'RAW DATA Q2 - 1'!FO7) -> 3.5
A30: Quality Avg (35%) | B30: =AVERAGEIF(B8:B28,"Quality",D8:D28) -> 2.9666667
A31: Timeline Avg (35%) | B31: =AVERAGEIF(B8:B28,"Timeline",D8:D28) -> 3
A32: Relationship Avg (30%) | B32: =AVERAGEIF(B8:B28,"Relationship",D8:D28) -> 3.8333333
A33: TOTAL SCORE | B33: =B30*0.35+B31*0.35+B32*0.3 -> 3.2383333
A34: STATUS | B34: =IF(B33>4.99,"Exceptional",IF(B33>3.99,"Exceed Expectation",IF(B33>=2.99,"Meet Expectation",IF(B33>1.9,"Below Expectation","Unsatisfactory")))) -> Meet Expectation
A36: DUE DILIGENCE / COMPLIANCE
B37: Fifin SARINURLITA | C37: Novia Laras SANTI
A38: Financial Assessment | B38: ='RAW DATA Q2 - 1'!FP6 -> Yes | C38: ='RAW DATA Q2 - 1'!FP7 -> No
A39: Reputational Assessment | B39: ='RAW DATA Q2 - 1'!FQ6 -> Yes | C39: ='RAW DATA Q2 - 1'!FQ7 -> Yes
A40: DPIA | B40: ='RAW DATA Q2 - 1'!FR6 -> Yes, DPIA completed and there are actions to be done by Project Owner | C40: ='RAW DATA Q2 - 1'!FR7 -> No Implementation
A41: DPSQ | B41: ='RAW DATA Q2 - 1'!FS6 -> Yes, DPSQ completed | C41: ='RAW DATA Q2 - 1'!FS7 -> No Implementation
A42: VSDDT | B42: ='RAW DATA Q2 - 1'!FT6 -> Yes, VSDDT completed and there are actions to be done by supplier | C42: ='RAW DATA Q2 - 1'!FT7 -> No Implementation
A43: Action Plan
A44: ⚠ Catatan | B44: Jawaban compliance dari 2 user BERBEDA — mohon konfirmasi dengan SRM/PIC terkait mana yang valid.
A46: REMARKS / FEEDBACK
A47: Fifin SARINURLITA: | B47: ='RAW DATA Q2 - 1'!FU6 -> SAP has shown improvement in terms of reporting and provides a fast response whenever issues arise.
A48: Novia Laras SANTI: | B48: ='RAW DATA Q2 - 1'!FU7 -> 1. untuk detail status pengiriman dokumen/barang harus diberikan keterangan penerima dengan lengkap dan jelas; 2. Maks. SLA pengiriman harus memenuhi sesuai dengan yang ditetapkan yaitu <5% not meet SLA; 3. Invoice biaya pengiriman dikirimkan ke user yang sesuai dan dikirimkan tidak melebihi periode yang ditetapkan. 4. Report Stock sesuai dengan real stock di warehouse.

Sheet Q2 MMI
A1: HASIL REVIEW VENDOR — Q2 2026
A2: Vendor | B2: Multifiling Mitra Indonesia
A3: Service | B3: Record Management Service
A4: PIC (Business User) | B4: Ibnu KUMALA
A6: No | B6: Dimensi | C6: Pertanyaan | D6: Skor
A7: 1 | B7: Quality | C7: ='RAW DATA Q2 - 1'!AY$1 -> How would you rate The goods/services provided by the Supplier against the agreed standards | D7: ='RAW DATA Q2 - 1'!AY12 -> 3
A8: 2 | B8: Quality | C8: ='RAW DATA Q2 - 1'!AZ$1 -> How would you rate the supplier's services? | D8: ='RAW DATA Q2 - 1'!AZ12 -> 3
A9: 3 | B9: Quality | C9: ='RAW DATA Q2 - 1'!BA$1 -> How would you rate the supplier's service in providing a guarantee of administrative services for archive management, computer data collection for all AXA cartons, and ease of access for AXA to the ar | D9: ='RAW DATA Q2 - 1'!BA12 -> 3
A10: 4 | B10: Quality | C10: ='RAW DATA Q2 - 1'!BB$1 -> How would you rate the supplier's service in providing the required number of empty cartons? | D10: ='RAW DATA Q2 - 1'!BB12 -> 3
A11: 5 | B11: Quality | C11: ='RAW DATA Q2 - 1'!BC$1 -> How would you rate overall quality of the work reports provided by the Supplier?2 | D11: ='RAW DATA Q2 - 1'!BC12 -> 3
A12: 6 | B12: Quality | C12: ='RAW DATA Q2 - 1'!BD$1 -> How would you rate the completeness report containing the number of AXA cartons deposited in the supplier's warehouse, a list of cartons that are being borrowed (retrieval) and have not been returned | D12: ='RAW DATA Q2 - 1'!BD12 -> 3
A13: 7 | B13: Quality | C13: ='RAW DATA Q2 - 1'!BE$1 -> How would you rate the solutions provided when there is trouble?2 | D13: ='RAW DATA Q2 - 1'!BE12 -> 3
A14: 8 | B14: Quality | C14: ='RAW DATA Q2 - 1'!BF$1 -> How would you rate the resolution to the problem that occurred?2 | D14: ='RAW DATA Q2 - 1'!BF12 -> 3
A15: 9 | B15: Quality | C15: ='RAW DATA Q2 - 1'!BG$1 -> How would you rate the speed of resolution given to problems that occur?2 | D15: ='RAW DATA Q2 - 1'!BG12 -> 3
A16: 10 | B16: Quality | C16: ='RAW DATA Q2 - 1'!BH$1 -> How would you rate the supplier initiative to take mitigation/preventive action to prevent the problem from recurring?2 | D16: ='RAW DATA Q2 - 1'!BH12 -> 3
A17: 11 | B17: Quality | C17: ='RAW DATA Q2 - 1'!BI$1 -> How would you rate supplier compliance with administrative processes, including completion of draft cooperation contract?3 | D17: ='RAW DATA Q2 - 1'!BI12 -> 3
A18: 12 | B18: Timeline | C18: ='RAW DATA Q2 - 1'!FB$1 -> How would you rate the supplier's timeliness in delivering goods/services compared to the agreed-upon timeline?2 | D18: ='RAW DATA Q2 - 1'!FB12 -> 3
A19: 13 | B19: Timeline | C19: ='RAW DATA Q2 - 1'!FC$1 -> How would you rate the supplier's timeliness in sending reports to you? Based on SLA, suppliers must provide reports on the 10th of each month. | D19: ='RAW DATA Q2 - 1'!FC12 -> 3
A20: 14 | B20: Timeline | C20: ='RAW DATA Q2 - 1'!FD$1 -> How would you rate the supplier's speed ​​of administrative completion, including completion of contracts draft? 1 | D20: ='RAW DATA Q2 - 1'!FD12 -> 3
A21: 15 | B21: Timeline | C21: ='RAW DATA Q2 - 1'!FE$1 -> How would you rate the supplier's SLA Fulfillment? | D21: ='RAW DATA Q2 - 1'!FE12 -> 3
A22: 16 | B22: Relationship | C22: ='RAW DATA Q2 - 1'!FM$1 -> How would you rate the supplier's communication with you? | D22: ='RAW DATA Q2 - 1'!FM12 -> 3
A23: 17 | B23: Relationship | C23: ='RAW DATA Q2 - 1'!FN$1 -> How would you rate the supplier's PIC's availability to be contacted when needed? | D23: ='RAW DATA Q2 - 1'!FN12 -> 3
A24: 18 | B24: Relationship | C24: ='RAW DATA Q2 - 1'!FO$1 -> How would you rate the supplier's response speed to you when there are issues? | D24: ='RAW DATA Q2 - 1'!FO12 -> 3
A26: Quality Avg (35%) | B26: =AVERAGEIF(B7:B24,"Quality",D7:D24) -> 3
A27: Timeline Avg (35%) | B27: =AVERAGEIF(B7:B24,"Timeline",D7:D24) -> 3
A28: Relationship Avg (30%) | B28: =AVERAGEIF(B7:B24,"Relationship",D7:D24) -> 3
A29: TOTAL SCORE | B29: =B26*0.35+B27*0.35+B28*0.3 -> 3
A30: STATUS | B30: =IF(B29>4.99,"Exceptional",IF(B29>3.99,"Exceed Expectation",IF(B29>=2.99,"Meet Expectation",IF(B29>1.9,"Below Expectation","Unsatisfactory")))) -> Meet Expectation
A32: DUE DILIGENCE / COMPLIANCE
A33: Financial Assessment | B33: ='RAW DATA Q2 - 1'!FP12 -> Yes
A34: Reputational Assessment | B34: ='RAW DATA Q2 - 1'!FQ12 -> Yes
A35: DPIA | B35: ='RAW DATA Q2 - 1'!FR12 -> Yes, DPIA completed and there are actions to be done by Project Owner
A36: DPSQ | B36: ='RAW DATA Q2 - 1'!FS12 -> Yes, DPSQ completed
A37: VSDDT | B37: ='RAW DATA Q2 - 1'!FT12 -> Yes, VSDDT completed and there are actions to be done by supplier
A38: Action Plan
A40: REMARKS / FEEDBACK
B41: ='RAW DATA Q2 - 1'!FU12 -> ..

Sheet Q2 INDOSAT
A1: HASIL REVIEW VENDOR — Q2 2026
A2: Vendor | B2: Indosat
A3: Service | B3: Layanan PBX berbasiskan cloud dengan Teknologi SIP Trunk
A4: PIC (Business User) | B4: Nuril HUDHA
A6: No | B6: Dimensi | C6: Pertanyaan | D6: Skor
A7: 1 | B7: Quality | C7: ='RAW DATA Q2 - 1'!H$1 -> How would you rate Supplier's ability to understand and meet your needs? | D7: ='RAW DATA Q2 - 1'!H3 -> 3
A8: 2 | B8: Quality | C8: ='RAW DATA Q2 - 1'!I$1 -> How would you rate the Quality of fulfillment of specifications required by Perfect Assistant? | D8: ='RAW DATA Q2 - 1'!I3 -> 3
A9: 3 | B9: Quality | C9: ='RAW DATA Q2 - 1'!J$1 -> How would you rate the data model of source of leads on customer level, which contains Existing Customers, Potential Customers, and Hot Leads? | D9: ='RAW DATA Q2 - 1'!J3 -> 4
A10: 4 | B10: Quality | C10: ='RAW DATA Q2 - 1'!K$1 -> How would you rate the Leads activity evidence and result details, such as Call, Appointment, Visit, and Closing result evidence? | D10: ='RAW DATA Q2 - 1'!K3 -> 4
A11: 5 | B11: Quality | C11: ='RAW DATA Q2 - 1'!L$1 -> How would you rate the Sales Activity Management process, as tracked by the Sales Leader and sorted by time range? | D11: ='RAW DATA Q2 - 1'!L3 -> 4
A12: 6 | B12: Quality | C12: ='RAW DATA Q2 - 1'!M$1 -> How would you rate the Notification to Sales Team which consist of: | D12: ='RAW DATA Q2 - 1'!M3 -> 4
A13: 7 | B13: Quality | C13: ='RAW DATA Q2 - 1'!N$1 -> How would you rate the telephony features which enable to mask either/both Customers’ and Agents’ personal phone number for better customer service and better protection of Customers’ privacy? | D13: ='RAW DATA Q2 - 1'!N3 -> 4
A14: 8 | B14: Quality | C14: ='RAW DATA Q2 - 1'!O$1 -> How would you rate the assignment features which enable leaders to re-assign the leads to other FA (e.g. FA resigned or move to other branch then the Leads will be assigned to existing FA)? | D14: ='RAW DATA Q2 - 1'!O3 -> 3
A15: 9 | B15: Quality | C15: ='RAW DATA Q2 - 1'!P$1 -> How would you rate the System Availability, Redundancy, and Overload Protection? | D15: ='RAW DATA Q2 - 1'!P3 -> 3
A16: 10 | B16: Quality | C16: ='RAW DATA Q2 - 1'!Q$1 -> How would you rate the Security Access? | D16: ='RAW DATA Q2 - 1'!Q3 -> 4
A17: 11 | B17: Quality | C17: ='RAW DATA Q2 - 1'!R$1 -> How would you rate the Audit Trail? | D17: ='RAW DATA Q2 - 1'!R3 -> 4
A18: 12 | B18: Quality | C18: ='RAW DATA Q2 - 1'!S$1 -> How would you rate the Overall Supplier's reports including Report of Leads activity record and tracking? | D18: ='RAW DATA Q2 - 1'!S3 -> 4
A19: 13 | B19: Quality | C19: ='RAW DATA Q2 - 1'!T$1 -> How would you rate the Resources / Authorized Personel Commitment and Qualification? | D19: ='RAW DATA Q2 - 1'!T3 -> 4
A20: 14 | B20: Quality | C20: ='RAW DATA Q2 - 1'!U$1 -> How would you rate supplier initiative to take mitigation/preventive action to prevent recurring problem? | D20: ='RAW DATA Q2 - 1'!U3 -> 4
A21: 15 | B21: Quality | C21: ='RAW DATA Q2 - 1'!V$1 -> How would you rate supplier compliance with administrative processes, including completion of draft cooperation contract? | D21: ='RAW DATA Q2 - 1'!V3 -> 4
A22: 16 | B22: Quality | C22: ='RAW DATA Q2 - 1'!W$1 -> How would you rate the Integration with Perfect Assistant? | D22: ='RAW DATA Q2 - 1'!W3 -> 4
A23: 17 | B23: Quality | C23: ='RAW DATA Q2 - 1'!X$1 -> How would you rate the use of channels to avoid customer data leaks? | D23: ='RAW DATA Q2 - 1'!X3 -> 4
A24: 18 | B24: Quality | C24: ='RAW DATA Q2 - 1'!Y$1 -> How would you rate the Access to the recording dashboard? | D24: ='RAW DATA Q2 - 1'!Y3 -> 3
A25: 19 | B25: Quality | C25: ='RAW DATA Q2 - 1'!Z$1 -> How would you rate the Security compare to its standard? | D25: ='RAW DATA Q2 - 1'!Z3 -> 3
A26: 20 | B26: Timeline | C26: ='RAW DATA Q2 - 1'!EU$1 -> How would you rate the supplier's timeliness in delivering goods/services compared to the agreed-upon timeline? | D26: ='RAW DATA Q2 - 1'!EU3 -> 3
A27: 21 | B27: Timeline | C27: ='RAW DATA Q2 - 1'!EV$1 -> How would you rate the supplier's timeliness in sending reports to you? | D27: ='RAW DATA Q2 - 1'!EV3 -> 3
A28: 22 | B28: Timeline | C28: ='RAW DATA Q2 - 1'!EW$1 -> How would you rate the supplier's speed ​​of administrative completion, including completion of contracts draft? | D28: ='RAW DATA Q2 - 1'!EW3 -> 3
A29: 23 | B29: Relationship | C29: ='RAW DATA Q2 - 1'!FM$1 -> How would you rate the supplier's communication with you? | D29: ='RAW DATA Q2 - 1'!FM3 -> 4
A30: 24 | B30: Relationship | C30: ='RAW DATA Q2 - 1'!FN$1 -> How would you rate the supplier's PIC's availability to be contacted when needed? | D30: ='RAW DATA Q2 - 1'!FN3 -> 4
A31: 25 | B31: Relationship | C31: ='RAW DATA Q2 - 1'!FO$1 -> How would you rate the supplier's response speed to you when there are issues? | D31: ='RAW DATA Q2 - 1'!FO3 -> 3
A33: Quality Avg (35%) | B33: =AVERAGEIF(B7:B31,"Quality",D7:D31) -> 3.6842105
A34: Timeline Avg (35%) | B34: =AVERAGEIF(B7:B31,"Timeline",D7:D31) -> 3
A35: Relationship Avg (30%) | B35: =AVERAGEIF(B7:B31,"Relationship",D7:D31) -> 3.6666667
A36: TOTAL SCORE | B36: =B33*0.35+B34*0.35+B35*0.3 -> 3.4394737
A37: STATUS | B37: =IF(B36>4.99,"Exceptional",IF(B36>3.99,"Exceed Expectation",IF(B36>=2.99,"Meet Expectation",IF(B36>1.9,"Below Expectation","Unsatisfactory")))) -> Meet Expectation
A39: DUE DILIGENCE / COMPLIANCE
A40: Financial Assessment | B40: ='RAW DATA Q2 - 1'!FP3 -> Yes
A41: Reputational Assessment | B41: ='RAW DATA Q2 - 1'!FQ3 -> Yes
A42: DPIA | B42: ='RAW DATA Q2 - 1'!FR3 -> No Implementation
A43: DPSQ | B43: ='RAW DATA Q2 - 1'!FS3 -> DPSQ not completed yet
A44: VSDDT | B44: ='RAW DATA Q2 - 1'!FT3 -> No Implementation
A45: Action Plan
A47: REMARKS / FEEDBACK
B48: ='RAW DATA Q2 - 1'!FU3 -> Vendor performance is generally acceptable and aligns with the expected level of service. While the engagement has been positive overall, improvements are needed in feature enhancement, dashboard capabilities, and the regularity of report updates. Better preparation in deployment and timely reporting would help increase the overall value and effectiveness of the service.

Sheet Q2 CIPTADRA
A1: HASIL REVIEW VENDOR — Q2 2026
A2: Vendor | B2: Ciptadra Softindo
A3: Service | B3: Pemeliharaan Axits & DMTM
A4: PIC (Business User) | B4: Raninta MAHARDI
A6: No | B6: Dimensi | C6: Pertanyaan | D6: Skor
A7: 1 | B7: Quality | C7: ='RAW DATA Q2 - 1'!BJ$1 -> How would you rate the goods/services provided by the Supplier against the agreed standards1 | D7: ='RAW DATA Q2 - 1'!BJ13 -> 4
A8: 2 | B8: Quality | C8: ='RAW DATA Q2 - 1'!BK$1 -> How would you rate overall quality of the work reports provided by the Supplier?3 | D8: ='RAW DATA Q2 - 1'!BK13 -> 4
A9: 3 | B9: Quality | C9: ='RAW DATA Q2 - 1'!BL$1 -> How would you rate the solutions provided when there is trouble?3 | D9: ='RAW DATA Q2 - 1'!BL13 -> 4
A10: 4 | B10: Quality | C10: ='RAW DATA Q2 - 1'!BM$1 -> How would you rate the resolution to the problem that occurred?3 | D10: ='RAW DATA Q2 - 1'!BM13 -> 4
A11: 5 | B11: Quality | C11: ='RAW DATA Q2 - 1'!BN$1 -> How would you rate the supplier initiative to take mitigation/preventive action to prevent the problem from recurring?3 | D11: ='RAW DATA Q2 - 1'!BN13 -> 4
A12: 6 | B12: Quality | C12: ='RAW DATA Q2 - 1'!BO$1 -> How would you rate the accuracy of the data in the Supplier's reports?2 | D12: ='RAW DATA Q2 - 1'!BO13 -> 4
A13: 7 | B13: Quality | C13: ='RAW DATA Q2 - 1'!BP$1 -> How would you rate the overall quality of the work reports provided by the Supplier? | D13: ='RAW DATA Q2 - 1'!BP13 -> 4
A14: 8 | B14: Quality | C14: ='RAW DATA Q2 - 1'!BQ$1 -> How would you rate the competence of people provided by the supplier to provide support (understand AXITS and/or DMTM software)? | D14: ='RAW DATA Q2 - 1'!BQ13 -> 4
A15: 9 | B15: Quality | C15: ='RAW DATA Q2 - 1'!BR$1 -> How would you rate the supplier support in providing the form of consultation, offsite and onsite support if there is a disruption to application operations? | D15: ='RAW DATA Q2 - 1'!BR13 -> 4
A16: 10 | B16: Quality | C16: ='RAW DATA Q2 - 1'!BS$1 -> How would you rate the supplier support in doing periodic checks once every 3 months to maintain application quality, including application performance checks (profiling) and error log checks? | D16: ='RAW DATA Q2 - 1'!BS13 -> 4
A17: 11 | B17: Quality | C17: ='RAW DATA Q2 - 1'!BT$1 -> How would you rate the supplier support for updating versions of components, frameworks and libraries issued by third parties with prior written approval from AXA if this is possible? | D17: ='RAW DATA Q2 - 1'!BT13 -> 4
A18: 12 | B18: Quality | C18: ='RAW DATA Q2 - 1'!BU$1 -> How would you rate the suppliers support in compliance to security? | D18: ='RAW DATA Q2 - 1'!BU13 -> 4
A19: 13 | B19: Quality | C19: ='RAW DATA Q2 - 1'!BV$1 -> How would you rate the supplier initiative to take mitigation/preventive action to prevent the problem from recurring?4 | D19: ='RAW DATA Q2 - 1'!BV13 -> 4
A20: 14 | B20: Quality | C20: ='RAW DATA Q2 - 1'!BW$1 -> How would you rate supplier compliance with administrative processes, including completion of draft cooperation contract?4 | D20: ='RAW DATA Q2 - 1'!BW13 -> 4
A21: 15 | B21: Timeline | C21: ='RAW DATA Q2 - 1'!FF$1 -> How would you rate the Supplier's timeliness in delivering goods/services compared to the agreed-upon timeline?3 | D21: ='RAW DATA Q2 - 1'!FF13 -> 4
A22: 16 | B22: Timeline | C22: ='RAW DATA Q2 - 1'!FG$1 -> How would you rate the supplier's timeliness in sending reports to you? Based on SLA, support reports should be sent every 3 months on the 10th | D22: ='RAW DATA Q2 - 1'!FG13 -> 4
A23: 17 | B23: Timeline | C23: ='RAW DATA Q2 - 1'!FH$1 -> How would you rate the supplier's speed ​​of administrative completion, including completion of contracts draft?1 | D23: ='RAW DATA Q2 - 1'!FH13 -> 4
A24: 18 | B24: Timeline | C24: ='RAW DATA Q2 - 1'!FI$1 -> How would you rate the supplier's resolution time? | D24: ='RAW DATA Q2 - 1'!FI13 -> 4
A25: 19 | B25: Relationship | C25: ='RAW DATA Q2 - 1'!FM$1 -> How would you rate the supplier's communication with you? | D25: ='RAW DATA Q2 - 1'!FM13 -> 5
A26: 20 | B26: Relationship | C26: ='RAW DATA Q2 - 1'!FN$1 -> How would you rate the supplier's PIC's availability to be contacted when needed? | D26: ='RAW DATA Q2 - 1'!FN13 -> 5
A27: 21 | B27: Relationship | C27: ='RAW DATA Q2 - 1'!FO$1 -> How would you rate the supplier's response speed to you when there are issues? | D27: ='RAW DATA Q2 - 1'!FO13 -> 5
A29: Quality Avg (35%) | B29: =AVERAGEIF(B7:B27,"Quality",D7:D27) -> 4
A30: Timeline Avg (35%) | B30: =AVERAGEIF(B7:B27,"Timeline",D7:D27) -> 4
A31: Relationship Avg (30%) | B31: =AVERAGEIF(B7:B27,"Relationship",D7:D27) -> 5
A32: TOTAL SCORE | B32: =B29*0.35+B30*0.35+B31*0.3 -> 4.3
A33: STATUS | B33: =IF(B32>4.99,"Exceptional",IF(B32>3.99,"Exceed Expectation",IF(B32>=2.99,"Meet Expectation",IF(B32>1.9,"Below Expectation","Unsatisfactory")))) -> Exceed Expectation
A35: DUE DILIGENCE / COMPLIANCE
A36: Financial Assessment | B36: ='RAW DATA Q2 - 1'!FP13 -> Yes
A37: Reputational Assessment | B37: ='RAW DATA Q2 - 1'!FQ13 -> Yes
A38: DPIA | B38: ='RAW DATA Q2 - 1'!FR13 -> Yes, DPIA completed and there are actions to be done by Project Owner
A39: DPSQ | B39: ='RAW DATA Q2 - 1'!FS13 -> No Implementation
A40: VSDDT | B40: ='RAW DATA Q2 - 1'!FT13 -> Yes, VSDDT completed and there are actions to be done by supplier
A41: Action Plan
A43: REMARKS / FEEDBACK
B44: ='RAW DATA Q2 - 1'!FU13 -> Ciptadra selalu fast response ketika ada incident yang terjadi di DMTM

Sheet Q2 MTARGET
A1: HASIL REVIEW VENDOR — Q2 2026
A2: Vendor | B2: Target Sukses Sinergi
A3: Service | B3: Email Marketing Automation
A4: PIC (Business User) | B4: Bella Friska DEPARI
A6: No | B6: Dimensi | C6: Pertanyaan | D6: Skor
A7: 1 | B7: Quality | C7: ='RAW DATA Q2 - 1'!EF$1 -> How would you rate the service provided?1 | D7: ='RAW DATA Q2 - 1'!EF4 -> 3
A8: 2 | B8: Quality | C8: ='RAW DATA Q2 - 1'!EG$1 -> How would you rate the accuracy of the data in the Supplier's reports?7 | D8: ='RAW DATA Q2 - 1'!EG4 -> 3
A9: 3 | B9: Quality | C9: ='RAW DATA Q2 - 1'!EH$1 -> How would you rate overall quality of the work reports provided by the Supplier?7 | D9: ='RAW DATA Q2 - 1'!EH4 -> 3
A10: 4 | B10: Quality | C10: ='RAW DATA Q2 - 1'!EI$1 -> How would you rate the resolution to the problem that occurred?7 | D10: ='RAW DATA Q2 - 1'!EI4 -> 3
A11: 5 | B11: Quality | C11: ='RAW DATA Q2 - 1'!EJ$1 -> How would you rate the supplier initiative to take mitigation/preventive action to prevent the problem from recurring?8 | D11: ='RAW DATA Q2 - 1'!EJ4 -> 2
A12: 6 | B12: Quality | C12: ='RAW DATA Q2 - 1'!EK$1 -> How would you rate supplier compliance with administrative processes, including completion of draft cooperation contract?7 | D12: ='RAW DATA Q2 - 1'!EK4 -> 3
A13: 7 | B13: Timeline | C13: ='RAW DATA Q2 - 1'!EU$1 -> How would you rate the supplier's timeliness in delivering goods/services compared to the agreed-upon timeline? | D13: ='RAW DATA Q2 - 1'!EU4 -> 3
A14: 8 | B14: Timeline | C14: ='RAW DATA Q2 - 1'!EV$1 -> How would you rate the supplier's timeliness in sending reports to you? | D14: ='RAW DATA Q2 - 1'!EV4 -> 3
A15: 9 | B15: Timeline | C15: ='RAW DATA Q2 - 1'!EW$1 -> How would you rate the supplier's speed ​​of administrative completion, including completion of contracts draft? | D15: ='RAW DATA Q2 - 1'!EW4 -> 3
A16: 10 | B16: Relationship | C16: ='RAW DATA Q2 - 1'!FM$1 -> How would you rate the supplier's communication with you? | D16: ='RAW DATA Q2 - 1'!FM4 -> 3
A17: 11 | B17: Relationship | C17: ='RAW DATA Q2 - 1'!FN$1 -> How would you rate the supplier's PIC's availability to be contacted when needed? | D17: ='RAW DATA Q2 - 1'!FN4 -> 3
A18: 12 | B18: Relationship | C18: ='RAW DATA Q2 - 1'!FO$1 -> How would you rate the supplier's response speed to you when there are issues? | D18: ='RAW DATA Q2 - 1'!FO4 -> 3
A20: Quality Avg (35%) | B20: =AVERAGEIF(B7:B18,"Quality",D7:D18) -> 2.8333333
A21: Timeline Avg (35%) | B21: =AVERAGEIF(B7:B18,"Timeline",D7:D18) -> 3
A22: Relationship Avg (30%) | B22: =AVERAGEIF(B7:B18,"Relationship",D7:D18) -> 3
A23: TOTAL SCORE | B23: =B20*0.35+B21*0.35+B22*0.3 -> 2.9416667
A24: STATUS | B24: =IF(B23>4.99,"Exceptional",IF(B23>3.99,"Exceed Expectation",IF(B23>=2.99,"Meet Expectation",IF(B23>1.9,"Below Expectation","Unsatisfactory")))) -> Below Expectation
A26: DUE DILIGENCE / COMPLIANCE
A27: Financial Assessment | B27: ='RAW DATA Q2 - 1'!FP4 -> Yes
A28: Reputational Assessment | B28: ='RAW DATA Q2 - 1'!FQ4 -> Yes
A29: DPIA | B29: ='RAW DATA Q2 - 1'!FR4 -> Yes, DPIA completed and there are actions to be done by Project Owner
A30: DPSQ | B30: ='RAW DATA Q2 - 1'!FS4 -> No Implementation
A31: VSDDT | B31: ='RAW DATA Q2 - 1'!FT4 -> Yes, VSDDT completed and there are actions to be done by supplier
A32: Action Plan
A34: REMARKS / FEEDBACK
B35: ='RAW DATA Q2 - 1'!FU4 -> Secara keseluruhan, MTarget telah memberikan dukungan yang baik dalam operasional email campaign dan responsif dalam menangani kebutuhan maupun isu yang muncul. Namun, insiden kesalahan pengiriman email yang terjadi menunjukkan perlunya penguatan pada proses deployment, pengujian, serta validasi sebelum implementasi ke production. Ke depannya, kami berharap MTarget dapat memperkuat proses change management, quality assurance, dan kontrol terhadap segmentasi serta pengiriman email untuk meminimalkan risiko terjadinya insiden serupa.

Sheet Q2 INMOTION
A1: HASIL REVIEW VENDOR — Q2 2026
A2: Vendor | B2: Inmotion Inovasi Teknologi
A3: Service | B3: Jasa Aplikasi Chatbot dan Live Chat
A4: PIC (Business User) | B4: Djoko DJOKO
A6: No | B6: Dimensi | C6: Pertanyaan | D6: Skor
A7: 1 | B7: Quality | C7: ='RAW DATA Q2 - 1'!BX$1 -> How would you rate the goods/services provided by the Supplier against the agreed standards2 | D7: ='RAW DATA Q2 - 1'!BX2 -> 4
A8: 2 | B8: Quality | C8: ='RAW DATA Q2 - 1'!BY$1 -> How would you rate the Customer Interaction Requirement which includes: | D8: ='RAW DATA Q2 - 1'!BY2 -> 4
A9: 3 | B9: Quality | C9: ='RAW DATA Q2 - 1'!BZ$1 -> How would you rate the Case Management which includes: | D9: ='RAW DATA Q2 - 1'!BZ2 -> 4
A10: 4 | B10: Quality | C10: ='RAW DATA Q2 - 1'!CA$1 -> How would you rate the Integration process which includes: | D10: ='RAW DATA Q2 - 1'!CA2 -> 4
A11: 5 | B11: Quality | C11: ='RAW DATA Q2 - 1'!CB$1 -> How would you rate the Architectural Requirement? | D11: ='RAW DATA Q2 - 1'!CB2 -> 4
A12: 6 | B12: Quality | C12: ='RAW DATA Q2 - 1'!CC$1 -> How would you rate the Security Requirement? | D12: ='RAW DATA Q2 - 1'!CC2 -> 4
A13: 7 | B13: Quality | C13: ='RAW DATA Q2 - 1'!CD$1 -> How would you rate the Backup and Restore, Capacity and Performance Requirements? | D13: ='RAW DATA Q2 - 1'!CD2 -> 4
A14: 8 | B14: Quality | C14: ='RAW DATA Q2 - 1'!CE$1 -> How would you rate the Operational and Configuration Management? | D14: ='RAW DATA Q2 - 1'!CE2 -> 4
A15: 9 | B15: Quality | C15: ='RAW DATA Q2 - 1'!CF$1 -> How would you rate the accuracy of the data in the Supplier's reports?3 | D15: ='RAW DATA Q2 - 1'!CF2 -> 4
A16: 10 | B16: Quality | C16: ='RAW DATA Q2 - 1'!CG$1 -> How would you rate overall quality of the work reports provided by the Supplier?4 | D16: ='RAW DATA Q2 - 1'!CG2 -> 4
A17: 11 | B17: Quality | C17: ='RAW DATA Q2 - 1'!CH$1 -> How would you rate the solutions provided when there is trouble?4 | D17: ='RAW DATA Q2 - 1'!CH2 -> 4
A18: 12 | B18: Quality | C18: ='RAW DATA Q2 - 1'!CI$1 -> How would you rate the resolution to the problem that occurred?4 | D18: ='RAW DATA Q2 - 1'!CI2 -> 4
A19: 13 | B19: Quality | C19: ='RAW DATA Q2 - 1'!CJ$1 -> How would you rate the speed of resolution given to problems that occur?3 | D19: ='RAW DATA Q2 - 1'!CJ2 -> 4
A20: 14 | B20: Quality | C20: ='RAW DATA Q2 - 1'!CK$1 -> How would you rate the supplier initiative to take mitigation/preventive action to prevent the problem from recurring?5 | D20: ='RAW DATA Q2 - 1'!CK2 -> 4
A21: 15 | B21: Quality | C21: ='RAW DATA Q2 - 1'!CL$1 -> How would you rate supplier compliance with administrative processes, including completion of draft cooperation contract?5 | D21: ='RAW DATA Q2 - 1'!CL2 -> 4
A22: 16 | B22: Quality | C22: ='RAW DATA Q2 - 1'!CM$1 -> How would you rate the accuracy of the data in the Supplier's reports?4 | D22: ='RAW DATA Q2 - 1'!CM2 -> 4
A23: 17 | B23: Quality | C23: ='RAW DATA Q2 - 1'!CN$1 -> How would you rate the overall quality of the work reports provided by the Supplier?1 | D23: ='RAW DATA Q2 - 1'!CN2 -> 4
A24: 18 | B24: Quality | C24: ='RAW DATA Q2 - 1'!CO$1 -> How would you rate the performing installation, setup and configuration of 3Dolphins? | D24: ='RAW DATA Q2 - 1'!CO2 -> 4
A25: 19 | B25: Quality | C25: ='RAW DATA Q2 - 1'!CP$1 -> How would you rate the integration of 3Dolphins with SalesForce? | D25: ='RAW DATA Q2 - 1'!CP2 -> 4
A26: 20 | B26: Quality | C26: ='RAW DATA Q2 - 1'!CQ$1 -> How would you rate the Chatbot Corpus with data provided by AXA? | D26: ='RAW DATA Q2 - 1'!CQ2 -> 4
A27: 21 | B27: Quality | C27: ='RAW DATA Q2 - 1'!CR$1 -> How would you rate the supplier's services in providing 3Dolphins Solutions as stated in the Functional Specification Document (FSD) and Technical Specification Document (TSD)? | D27: ='RAW DATA Q2 - 1'!CR2 -> 4
A28: 22 | B28: Quality | C28: ='RAW DATA Q2 - 1'!CS$1 -> How would you rate the supplier's services in conducting System Integration Test (SIT) with AXA IT testing team and IT Project Team? | D28: ='RAW DATA Q2 - 1'!CS2 -> 4
A29: 23 | B29: Quality | C29: ='RAW DATA Q2 - 1'!CT$1 -> How would you rate the supplier's services in conducting User Acceptance Test (UAT) with AXA Business Team and Project IT Team? | D29: ='RAW DATA Q2 - 1'!CT2 -> 4
A30: 24 | B30: Quality | C30: ='RAW DATA Q2 - 1'!CU$1 -> How would you rate the supplier's services in migrating to production server or Go Live and providing support after Go Live? | D30: ='RAW DATA Q2 - 1'!CU2 -> 4
A31: 25 | B31: Quality | C31: ='RAW DATA Q2 - 1'!CV$1 -> How would you rate the supplier's services in providing the human resources needed in the project and timeline according to the agreed scope? | D31: ='RAW DATA Q2 - 1'!CV2 -> 4
A32: 26 | B32: Quality | C32: ='RAW DATA Q2 - 1'!CW$1 -> How would you rate the supplier's services in assigning a Project Manager to coordinate with the AXA team? | D32: ='RAW DATA Q2 - 1'!CW2 -> 4
A33: 27 | B33: Quality | C33: ='RAW DATA Q2 - 1'!CX$1 -> How would you rate the supplier's project documentation as follows: | D33: ='RAW DATA Q2 - 1'!CX2 -> 4
A34: 28 | B34: Quality | C34: ='RAW DATA Q2 - 1'!CY$1 -> How would you rate the supplier support in providing the perform maintenance on all software related to 3Dolphins, which is installed in the AXA data center? | D34: ='RAW DATA Q2 - 1'!CY2 -> 4
A35: 29 | B35: Quality | C35: ='RAW DATA Q2 - 1'!CZ$1 -> How would you rate the supplier support in providing 3Dolphins application maintenance service time, namely 24 hours x 7 days a week, 365 days/year? | D35: ='RAW DATA Q2 - 1'!CZ2 -> 4
A36: 30 | B36: Quality | C36: ='RAW DATA Q2 - 1'!DA$1 -> How would you rate the supplier support in preparing at least 2 people who understand and are experts in chatbots owned by AXA and can also provide support for services that often occur (eg. New custo | D36: ='RAW DATA Q2 - 1'!DA2 -> 4
A37: 31 | B37: Quality | C37: ='RAW DATA Q2 - 1'!DB$1 -> How would you rate the supplier support in providing support center that can be visited during AXA business hours to respond to any questions and issues that arise? | D37: ='RAW DATA Q2 - 1'!DB2 -> 4
A38: 32 | B38: Quality | C38: ='RAW DATA Q2 - 1'!DC$1 -> How would you rate the supplier support in providing SLA reports to AXA? | D38: ='RAW DATA Q2 - 1'!DC2 -> 4
A39: 33 | B39: Quality | C39: ='RAW DATA Q2 - 1'!DD$1 -> How would you rate the supplier support in providing testing and updates the Chatbot Solution if there is a new software version/release/patch according to the required conditions? | D39: ='RAW DATA Q2 - 1'!DD2 -> 4
A40: 34 | B40: Quality | C40: ='RAW DATA Q2 - 1'!DE$1 -> How would you rate the supplier support in reinstall the 3Dolphins application a maximum of 1 time per year if AXA will upgrade the hardware? | D40: ='RAW DATA Q2 - 1'!DE2 -> 4
A41: 35 | B41: Quality | C41: ='RAW DATA Q2 - 1'!DF$1 -> How would you rate the supplier support in providing a checklist to monitor daily activities? | D41: ='RAW DATA Q2 - 1'!DF2 -> 4
A42: 36 | B42: Quality | C42: ='RAW DATA Q2 - 1'!DG$1 -> How would you rate the supplier support in providing a testing configuration and event logging? | D42: ='RAW DATA Q2 - 1'!DG2 -> 4
A43: 37 | B43: Quality | C43: ='RAW DATA Q2 - 1'!DH$1 -> How would you rate the supplier support in providing a backup for short and long term? | D43: ='RAW DATA Q2 - 1'!DH2 -> 4
A44: 38 | B44: Timeline | C44: ='RAW DATA Q2 - 1'!EU$1 -> How would you rate the supplier's timeliness in delivering goods/services compared to the agreed-upon timeline? | D44: ='RAW DATA Q2 - 1'!EU2 -> 4
A45: 39 | B45: Timeline | C45: ='RAW DATA Q2 - 1'!EV$1 -> How would you rate the supplier's timeliness in sending reports to you? | D45: ='RAW DATA Q2 - 1'!EV2 -> 4
A46: 40 | B46: Timeline | C46: ='RAW DATA Q2 - 1'!EW$1 -> How would you rate the supplier's speed ​​of administrative completion, including completion of contracts draft? | D46: ='RAW DATA Q2 - 1'!EW2 -> 4
A47: 41 | B47: Relationship | C47: ='RAW DATA Q2 - 1'!FM$1 -> How would you rate the supplier's communication with you? | D47: ='RAW DATA Q2 - 1'!FM2 -> 4
A48: 42 | B48: Relationship | C48: ='RAW DATA Q2 - 1'!FN$1 -> How would you rate the supplier's PIC's availability to be contacted when needed? | D48: ='RAW DATA Q2 - 1'!FN2 -> 4
A49: 43 | B49: Relationship | C49: ='RAW DATA Q2 - 1'!FO$1 -> How would you rate the supplier's response speed to you when there are issues? | D49: ='RAW DATA Q2 - 1'!FO2 -> 4
A51: Quality Avg (35%) | B51: =AVERAGEIF(B7:B49,"Quality",D7:D49) -> 4
A52: Timeline Avg (35%) | B52: =AVERAGEIF(B7:B49,"Timeline",D7:D49) -> 4
A53: Relationship Avg (30%) | B53: =AVERAGEIF(B7:B49,"Relationship",D7:D49) -> 4
A54: TOTAL SCORE | B54: =B51*0.35+B52*0.35+B53*0.3 -> 4
A55: STATUS | B55: =IF(B54>4.99,"Exceptional",IF(B54>3.99,"Exceed Expectation",IF(B54>=2.99,"Meet Expectation",IF(B54>1.9,"Below Expectation","Unsatisfactory")))) -> Exceed Expectation
A57: DUE DILIGENCE / COMPLIANCE
A58: Financial Assessment | B58: ='RAW DATA Q2 - 1'!FP2 -> Yes
A59: Reputational Assessment | B59: ='RAW DATA Q2 - 1'!FQ2 -> Yes
A60: DPIA | B60: ='RAW DATA Q2 - 1'!FR2 -> Yes, DPIA completed and there are actions to be done by Project Owner
A61: DPSQ | B61: ='RAW DATA Q2 - 1'!FS2 -> DPSQ not completed yet
A62: VSDDT | B62: ='RAW DATA Q2 - 1'!FT2 -> Yes, VSDDT completed and there are actions to be done by supplier
A63: Action Plan
A65: REMARKS / FEEDBACK
B66: ='RAW DATA Q2 - 1'!FU2 -> Tetap up to date dan helpful

Sheet Q2 MII-SFDC
A1: HASIL REVIEW VENDOR — Q2 2026
A2: Vendor | B2: Mitra Integrasi Informatika
A3: Service | B3: SFDC Maintenance
A4: PIC (Business User) | B4: Chandra Nugraha PUTRA
A6: No | B6: Dimensi | C6: Pertanyaan | D6: Skor
A7: 1 | B7: Quality | C7: ='RAW DATA Q2 - 1'!AL$1 -> How would you rate Supplier's ability to understand and meet your needs?2 | D7: ='RAW DATA Q2 - 1'!AL14 -> 4
A8: 2 | B8: Quality | C8: ='RAW DATA Q2 - 1'!AM$1 -> How would you rate the The goods/services provided by the Supplier against the agreed standards? | D8: ='RAW DATA Q2 - 1'!AM14 -> 5
A9: 3 | B9: Quality | C9: ='RAW DATA Q2 - 1'!AN$1 -> How would you rate the General support and maintenance requirement? | D9: ='RAW DATA Q2 - 1'!AN14 -> 5
A10: 4 | B10: Quality | C10: ='RAW DATA Q2 - 1'!AO$1 -> How would you rate the Performance Management Requirement which includes to support low latency, documentation, performance monitoring, and any major or minor updates? | D10: ='RAW DATA Q2 - 1'!AO14 -> 5
A11: 5 | B11: Quality | C11: ='RAW DATA Q2 - 1'!AP$1 -> How would you rate the Security Management Requirement? | D11: ='RAW DATA Q2 - 1'!AP14 -> 5
A12: 6 | B12: Quality | C12: ='RAW DATA Q2 - 1'!AQ$1 -> How would you rate the Supporting Model which includes onsite support from dedicated engineers and its service level agreement (SLA)? | D12: ='RAW DATA Q2 - 1'!AQ14 -> 4
A13: 7 | B13: Quality | C13: ='RAW DATA Q2 - 1'!AR$1 -> How would you rate the accuracy of the data in the Supplier's reports?1 | D13: ='RAW DATA Q2 - 1'!AR14 -> 5
A14: 8 | B14: Quality | C14: ='RAW DATA Q2 - 1'!AS$1 -> How would you rate overall quality of the work reports provided by the Supplier?1 | D14: ='RAW DATA Q2 - 1'!AS14 -> 4
A15: 9 | B15: Quality | C15: ='RAW DATA Q2 - 1'!AT$1 -> How would you rate the solutions provided when there is trouble?1 | D15: ='RAW DATA Q2 - 1'!AT14 -> 5
A16: 10 | B16: Quality | C16: ='RAW DATA Q2 - 1'!AU$1 -> How would you rate the resolution to the problem that occurred?1 | D16: ='RAW DATA Q2 - 1'!AU14 -> 4
A17: 11 | B17: Quality | C17: ='RAW DATA Q2 - 1'!AV$1 -> How would you rate the speed of resolution given to problems that occur?1 | D17: ='RAW DATA Q2 - 1'!AV14 -> 5
A18: 12 | B18: Quality | C18: ='RAW DATA Q2 - 1'!AW$1 -> How would you rate the supplier initiative to take mitigation/preventive action to prevent the problem from recurring?1 | D18: ='RAW DATA Q2 - 1'!AW14 -> 4
A19: 13 | B19: Quality | C19: ='RAW DATA Q2 - 1'!AX$1 -> How would you rate supplier compliance with administrative processes, including completion of draft cooperation contract?2 | D19: ='RAW DATA Q2 - 1'!AX14 -> 5
A20: 14 | B20: Timeline | C20: ='RAW DATA Q2 - 1'!EU$1 -> How would you rate the supplier's timeliness in delivering goods/services compared to the agreed-upon timeline? | D20: ='RAW DATA Q2 - 1'!EU14 -> 4
A21: 15 | B21: Timeline | C21: ='RAW DATA Q2 - 1'!EV$1 -> How would you rate the supplier's timeliness in sending reports to you? | D21: ='RAW DATA Q2 - 1'!EV14 -> 5
A22: 16 | B22: Timeline | C22: ='RAW DATA Q2 - 1'!EW$1 -> How would you rate the supplier's speed ​​of administrative completion, including completion of contracts draft? | D22: ='RAW DATA Q2 - 1'!EW14 -> 5
A23: 17 | B23: Relationship | C23: ='RAW DATA Q2 - 1'!FM$1 -> How would you rate the supplier's communication with you? | D23: ='RAW DATA Q2 - 1'!FM14 -> 5
A24: 18 | B24: Relationship | C24: ='RAW DATA Q2 - 1'!FN$1 -> How would you rate the supplier's PIC's availability to be contacted when needed? | D24: ='RAW DATA Q2 - 1'!FN14 -> 5
A25: 19 | B25: Relationship | C25: ='RAW DATA Q2 - 1'!FO$1 -> How would you rate the supplier's response speed to you when there are issues? | D25: ='RAW DATA Q2 - 1'!FO14 -> 5
A27: Quality Avg (35%) | B27: =AVERAGEIF(B7:B25,"Quality",D7:D25) -> 4.6153846
A28: Timeline Avg (35%) | B28: =AVERAGEIF(B7:B25,"Timeline",D7:D25) -> 4.6666667
A29: Relationship Avg (30%) | B29: =AVERAGEIF(B7:B25,"Relationship",D7:D25) -> 5
A30: TOTAL SCORE | B30: =B27*0.35+B28*0.35+B29*0.3 -> 4.7487179
A31: STATUS | B31: =IF(B30>4.99,"Exceptional",IF(B30>3.99,"Exceed Expectation",IF(B30>=2.99,"Meet Expectation",IF(B30>1.9,"Below Expectation","Unsatisfactory")))) -> Exceed Expectation
A33: DUE DILIGENCE / COMPLIANCE
A34: Financial Assessment | B34: ='RAW DATA Q2 - 1'!FP14 -> Yes
A35: Reputational Assessment | B35: ='RAW DATA Q2 - 1'!FQ14 -> Yes
A36: DPIA | B36: ='RAW DATA Q2 - 1'!FR14 -> Yes, DPIA completed and there are actions to be done by Project Owner
A37: DPSQ | B37: ='RAW DATA Q2 - 1'!FS14 -> No Implementation
A38: VSDDT | B38: ='RAW DATA Q2 - 1'!FT14 -> Yes, VSDDT completed and there are actions to be done by supplier
A39: Action Plan
A41: REMARKS / FEEDBACK
B42: ='RAW DATA Q2 - 1'!FU14 -> Respons terhadap issue maupun kebutuhan sudah cukup baik dan cepat. Support on-site juga sangat membantu dan responsif. Ke depannya, mungkin dapat lebih rutin memberikan update terkait progress kendala atau perbaikan yang sedang dilakukan, sehingga pihak terkait dapat mengetahui status terbaru dan lebih cepat menentukan langkah selanjutnya.

Sheet Q2 SUTRA
A1: HASIL REVIEW VENDOR — Q2 2026
A2: Vendor | B2: Sutra Management Consultancies
A3: Service | B3: Implementasi SAS IFRS17
A4: PIC (Business User) | B4: Tatang SUTIAMAN
A6: No | B6: Dimensi | C6: Pertanyaan | D6: Skor
A7: 1 | B7: Quality | C7: ='RAW DATA Q2 - 2'!AU$1 -> How would you rate the goods/services provided by the Supplier against the agreed standards1 | D7: ='RAW DATA Q2 - 2'!AU10 -> 4
A8: 2 | B8: Quality | C8: ='RAW DATA Q2 - 2'!AV$1 -> How would you rate the accuracy of the data in the Supplier's reports?2 | D8: ='RAW DATA Q2 - 2'!AV10 -> 3
A9: 3 | B9: Quality | C9: ='RAW DATA Q2 - 2'!AW$1 -> How would you rate the Vendor initiative to take mitigation/preventive action to prevent the problem from recurring?3 | D9: ='RAW DATA Q2 - 2'!AW10 -> 4
A10: 4 | B10: Quality | C10: ='RAW DATA Q2 - 2'!AX$1 -> How would you rate supplier compliance with administrative processes, including completion of draft cooperation contract?4 | D10: ='RAW DATA Q2 - 2'!AX10 -> 3
A11: 5 | B11: Quality | C11: ='RAW DATA Q2 - 2'!AY$1 -> How would you rate the Installation of SAS IFRS17 solution on AXA infrastructure? | D11: ='RAW DATA Q2 - 2'!AY10 -> 3
A12: 6 | B12: Quality | C12: ='RAW DATA Q2 - 2'!AZ$1 -> How would you rate the workshops and finalize functional specification documents that summarize requirements which conducted by the supplier? | D12: ='RAW DATA Q2 - 2'!AZ10 -> 3
A13: 7 | B13: Quality | C13: ='RAW DATA Q2 - 2'!BA$1 -> How would you rate the implementation of an end-to-end solution flow design for SAS IFRS17? | D13: ='RAW DATA Q2 - 2'!BA10 -> 3
A14: 8 | B14: Quality | C14: ='RAW DATA Q2 - 2'!BB$1 -> How would you rate the Implementation of SAS IFRS17solution? | D14: ='RAW DATA Q2 - 2'!BB10 -> 3
A15: 9 | B15: Quality | C15: ='RAW DATA Q2 - 2'!BC$1 -> How would you rate the End-to-End Calculation Functions which includes: | D15: ='RAW DATA Q2 - 2'!BC10 -> 3
A16: 10 | B16: Quality | C16: ='RAW DATA Q2 - 2'!BD$1 -> How would you rate the PSAK74 Contract Grouping using Data Input and Predefine Rule which generates: | D16: ='RAW DATA Q2 - 2'!BD10 -> 3
A17: 11 | B17: Quality | C17: ='RAW DATA Q2 - 2'!BE$1 -> How would you rate PSAK74 System implementation on its standard and configurable rule which includes: | D17: ='RAW DATA Q2 - 2'!BE10 -> 3
A18: 12 | B18: Quality | C18: ='RAW DATA Q2 - 2'!BF$1 -> How would you rate the currencies and interest rate facilitation? | D18: ='RAW DATA Q2 - 2'!BF10 -> 3
A19: 13 | B19: Quality | C19: ='RAW DATA Q2 - 2'!BG$1 -> How would you rate the capability to estimate the Initial Recognition? | D19: ='RAW DATA Q2 - 2'!BG10 -> 3
A20: 14 | B20: Quality | C20: ='RAW DATA Q2 - 2'!BH$1 -> How would you rate the capability to estimate GMM/PAA/VFA Approach both direct and reinsurance: | D20: ='RAW DATA Q2 - 2'!BH10 -> 3
A21: 15 | B21: Quality | C21: ='RAW DATA Q2 - 2'!BI$1 -> How would you rate the capability to do the Allocation on Actual Cash Flow (CF): | D21: ='RAW DATA Q2 - 2'!BI10 -> 3
A22: 16 | B22: Quality | C22: ='RAW DATA Q2 - 2'!BJ$1 -> How would you rate the capability to generate PSAK74 Disclosure in monthly base: | D22: ='RAW DATA Q2 - 2'!BJ10 -> 3
A23: 17 | B23: Quality | C23: ='RAW DATA Q2 - 2'!BK$1 -> How would you rate the System Availability, Redundancy, and Overload Protection? | D23: ='RAW DATA Q2 - 2'!BK10 -> 3
A24: 18 | B24: Quality | C24: ='RAW DATA Q2 - 2'!BL$1 -> How would you rate the Common Security Access? | D24: ='RAW DATA Q2 - 2'!BL10 -> 3
A25: 19 | B25: Quality | C25: ='RAW DATA Q2 - 2'!BM$1 -> How would you rate the Audit Trail? | D25: ='RAW DATA Q2 - 2'!BM10 -> 3
A26: 20 | B26: Quality | C26: ='RAW DATA Q2 - 2'!BN$1 -> How would you rate the supplier's service in providing one month warranty support after go-live? | D26: ='RAW DATA Q2 - 2'!BN10 -> 3
A27: 21 | B27: Quality | C27: ='RAW DATA Q2 - 2'!BO$1 -> How would you rate the supplier's services in conducting three-day user training for SAS IFRS17 solution and conducted one-day system administration training for users? | D27: ='RAW DATA Q2 - 2'!BO10 -> 3
A28: 22 | B28: Timeline | C28: ='RAW DATA Q2 - 2'!DO$1 -> How would you rate the supplier's timeliness in delivering goods/services compared to the agreed-upon timeline? | D28: ='RAW DATA Q2 - 2'!DO10 -> 3
A29: 23 | B29: Timeline | C29: ='RAW DATA Q2 - 2'!DP$1 -> How would you rate the supplier's timeliness in sending reports to you? | D29: ='RAW DATA Q2 - 2'!DP10 -> 3
A30: 24 | B30: Timeline | C30: ='RAW DATA Q2 - 2'!DQ$1 -> How would you rate the supplier's speed ​​of administrative completion, including completion of contracts draft? | D30: ='RAW DATA Q2 - 2'!DQ10 -> 3
A31: 25 | B31: Relationship | C31: ='RAW DATA Q2 - 2'!FM$1 -> How would you rate the supplier's communication with you? | D31: ='RAW DATA Q2 - 2'!FM10 -> 4
A32: 26 | B32: Relationship | C32: ='RAW DATA Q2 - 2'!FN$1 -> How would you rate the supplier's PIC's availability to be contacted when needed? | D32: ='RAW DATA Q2 - 2'!FN10 -> 4
A33: 27 | B33: Relationship | C33: ='RAW DATA Q2 - 2'!FO$1 -> How would you rate the supplier's response speed to you when there are issues? | D33: ='RAW DATA Q2 - 2'!FO10 -> 4
A35: Quality Avg (35%) | B35: =AVERAGEIF(B7:B33,"Quality",D7:D33) -> 3.0952381
A36: Timeline Avg (35%) | B36: =AVERAGEIF(B7:B33,"Timeline",D7:D33) -> 3
A37: Relationship Avg (30%) | B37: =AVERAGEIF(B7:B33,"Relationship",D7:D33) -> 4
A38: TOTAL SCORE | B38: =B35*0.35+B36*0.35+B37*0.3 -> 3.3333333
A39: STATUS | B39: =IF(B38>4.99,"Exceptional",IF(B38>3.99,"Exceed Expectation",IF(B38>=2.99,"Meet Expectation",IF(B38>1.9,"Below Expectation","Unsatisfactory")))) -> Meet Expectation
A41: DUE DILIGENCE / COMPLIANCE
A42: Financial Assessment | B42: ='RAW DATA Q2 - 2'!FP10 -> Yes
A43: Reputational Assessment | B43: ='RAW DATA Q2 - 2'!FQ10 -> Yes
A44: DPIA | B44: ='RAW DATA Q2 - 2'!FR10 -> No Implementation
A45: DPSQ | B45: ='RAW DATA Q2 - 2'!FS10 -> No Implementation
A46: VSDDT | B46: ='RAW DATA Q2 - 2'!FT10 -> No Implementation
A47: Action Plan | B47: ='RAW DATA Q2 - 2'!FU10 -> No – No action items were required
A49: REMARKS / FEEDBACK
B50: ='RAW DATA Q2 - 2'!FV10 -> no feedback

Sheet Q2 RDS-Printing
A1: HASIL REVIEW VENDOR — Q2 2026
A2: Vendor | B2: Reycom Document Solution
A3: Service | B3: Printing & Data Management Center
A4: PIC (Business User) | B4: Yulia KURNIATI
A5: Catatan | B5: Vendor submit assessment 2x pada periode ini; sheet ini menggunakan submission TERAKHIR (paling lengkap).
A7: No | B7: Dimensi | C7: Pertanyaan | D7: Skor
A8: 1 | B8: Quality | C8: ='RAW DATA Q2 - 2'!BV$1 -> How would you rate the Supplier’s ability to deliver Policy Printing Services SLA? | D8: ='RAW DATA Q2 - 2'!BV9 -> 4
A9: 2 | B9: Quality | C9: ='RAW DATA Q2 - 2'!BW$1 -> Printed policy documents met the agreed material specifications for each policy type? | D9: ='RAW DATA Q2 - 2'!BW9 -> 4
A10: 3 | B10: Quality | C10: ='RAW DATA Q2 - 2'!BX$1 -> How would you rate overall quality of Letter Printing services which includes: | D10: ='RAW DATA Q2 - 2'!BX9 -> 4
A11: 4 | B11: Quality | C11: ='RAW DATA Q2 - 2'!BY$1 -> How would you rate the overall quality of Training Material Printing service which includes: | D11: ='RAW DATA Q2 - 2'!BY9 -> 4
A12: 5 | B12: Quality | C12: ='RAW DATA Q2 - 2'!BZ$1 -> How would you rate the Data Capture quality control which should be performed at 100% volume (not random/sample check) for all required QC fields | D12: ='RAW DATA Q2 - 2'!BZ9 -> 4
A13: 6 | B13: Quality | C13: ='RAW DATA Q2 - 2'!CA$1 -> How would you rate the Data Capture quality control which should be performed at 100% volume (not random/sample check) for all required QC fields? | D13: ='RAW DATA Q2 - 2'!CA9 -> 4
A14: 7 | B14: Timeline | C14: ='RAW DATA Q2 - 2'!CB$1 -> Daily and monthly operational reports were submitted completely, accurately, and on time. | D14: ='RAW DATA Q2 - 2'!CB9 -> 4
A15: 8 | B15: Quality | C15: ='RAW DATA Q2 - 2'!CC$1 -> How would you rate the Data Maintenance, Data Security, and Access Control which includes: | D15: ='RAW DATA Q2 - 2'!CC9 -> 4
A16: 9 | B16: Quality | C16: ='RAW DATA Q2 - 2'!CD$1 -> How would you rate the Recovery Process in the Event of Hardware/Software Failure which includes: | D16: ='RAW DATA Q2 - 2'!CD9 -> 4
A17: 10 | B17: Quality | C17: ='RAW DATA Q2 - 2'!CE$1 -> How would you rate overall Document Management Center service? | D17: ='RAW DATA Q2 - 2'!CE9 -> 4
A18: 11 | B18: Timeline | C18: ='RAW DATA Q2 - 2'!DR$1 -> Policy printing was completed within the agreed H0 → H1 → H3 delivery timeline | D18: ='RAW DATA Q2 - 2'!DR9 -> 4
A19: 12 | B19: Timeline | C19: ='RAW DATA Q2 - 2'!DS$1 -> Letter printing (Cetak Surat) was completed within H+2 from AMFS approval of the print data file. | D19: ='RAW DATA Q2 - 2'!DS9 -> 4
A20: 13 | B20: Timeline | C20: ='RAW DATA Q2 - 2'!DT$1 -> Training material printing (Cetak Dokumen Materi Training) was completed within all three agreed SLA phases | D20: ='RAW DATA Q2 - 2'!DT9 -> 4
A21: 14 | B21: Timeline | C21: ='RAW DATA Q2 - 2'!DU$1 -> New Business data was uploaded to RLS within the agreed daily cut-off schedule | D21: ='RAW DATA Q2 - 2'!DU9 -> 4
A22: 15 | B22: Timeline | C22: ='RAW DATA Q2 - 2'!DV$1 -> POS and Claim documents were scanned, indexed, and uploaded on the same day within the agreed scanning SLA window | D22: ='RAW DATA Q2 - 2'!DV9 -> 4
A23: 16 | B23: Timeline | C23: ='RAW DATA Q2 - 2'!DW$1 -> Physical document retrieval requests from AMFS were fulfilled within 2 working days | D23: ='RAW DATA Q2 - 2'!DW9 -> 4
A24: 17 | B24: Timeline | C24: ='RAW DATA Q2 - 2'!DX$1 -> The supplier consistently met late delivery penalty thresholds and did not trigger the escalated penalty clause for policy printing | D24: ='RAW DATA Q2 - 2'!DX9 -> 4
A25: 18 | B25: Timeline | C25: ='RAW DATA Q2 - 2'!DY$1 -> The supplier proactively communicated whenever daily SLA targets or processing volumes were at risk of not being met. | D25: ='RAW DATA Q2 - 2'!DY9 -> 4
A26: 19 | B26: Relationship | C26: ='RAW DATA Q2 - 2'!FM$1 -> How would you rate the supplier's communication with you? | D26: ='RAW DATA Q2 - 2'!FM9 -> 5
A27: 20 | B27: Relationship | C27: ='RAW DATA Q2 - 2'!FN$1 -> How would you rate the supplier's PIC's availability to be contacted when needed? | D27: ='RAW DATA Q2 - 2'!FN9 -> 5
A28: 21 | B28: Relationship | C28: ='RAW DATA Q2 - 2'!FO$1 -> How would you rate the supplier's response speed to you when there are issues? | D28: ='RAW DATA Q2 - 2'!FO9 -> 5
A30: Quality Avg (35%) | B30: =AVERAGEIF(B8:B28,"Quality",D8:D28) -> 4
A31: Timeline Avg (35%) | B31: =AVERAGEIF(B8:B28,"Timeline",D8:D28) -> 4
A32: Relationship Avg (30%) | B32: =AVERAGEIF(B8:B28,"Relationship",D8:D28) -> 5
A33: TOTAL SCORE | B33: =B30*0.35+B31*0.35+B32*0.3 -> 4.3
A34: STATUS | B34: =IF(B33>4.99,"Exceptional",IF(B33>3.99,"Exceed Expectation",IF(B33>=2.99,"Meet Expectation",IF(B33>1.9,"Below Expectation","Unsatisfactory")))) -> Exceed Expectation
A36: DUE DILIGENCE / COMPLIANCE
A37: Financial Assessment | B37: ='RAW DATA Q2 - 2'!FP9 -> Yes
A38: Reputational Assessment | B38: ='RAW DATA Q2 - 2'!FQ9 -> Yes
A39: DPIA | B39: ='RAW DATA Q2 - 2'!FR9 -> Yes, DPIA completed and there are actions to be done by Project Owner
A40: DPSQ | B40: ='RAW DATA Q2 - 2'!FS9 -> Yes, DPSQ completed
A41: VSDDT | B41: ='RAW DATA Q2 - 2'!FT9 -> Yes, VSDDT completed and there are actions to be done by supplier
A42: Action Plan | B42: ='RAW DATA Q2 - 2'!FU9 -> Yes – All action items have been completed and coordinated with relevant SME
A44: REMARKS / FEEDBACK
B45: ='RAW DATA Q2 - 2'!FV9 -> Improvements to their latest Technology to support process at AXA

Sheet Q2 DELOITTE
A1: HASIL REVIEW VENDOR — Q2 2026
A2: Vendor | B2: Deloitte Consulting
A3: Service | B3: Data Privacy & Pelatihan Personal Data Protection (PDP)
A4: PIC (Business User) | B4: M. Andrian Patria Shaleh RIZAL
A6: No | B6: Dimensi | C6: Pertanyaan | D6: Skor
A7: 1 | B7: Quality | C7: ='RAW DATA Q2 - 2'!AJ$1 -> How would you rate the services provided by the Supplier against the agreed standards | D7: ='RAW DATA Q2 - 2'!AJ11 -> 5
A8: 2 | B8: Quality | C8: ='RAW DATA Q2 - 2'!AK$1 -> How would you rate the accuracy of the data in the Supplier's reports?1 | D8: ='RAW DATA Q2 - 2'!AK11 -> 5
A9: 3 | B9: Quality | C9: ='RAW DATA Q2 - 2'!AL$1 -> How would you rate overall quality of the work reports provided by the Supplier?1 | D9: ='RAW DATA Q2 - 2'!AL11 -> 4
A10: 4 | B10: Quality | C10: ='RAW DATA Q2 - 2'!AM$1 -> How would you rate the solutions provided when there is trouble?2 | D10: ='RAW DATA Q2 - 2'!AM11 -> 3
A11: 5 | B11: Quality | C11: ='RAW DATA Q2 - 2'!AN$1 -> How would you rate the vendor initiative to take mitigation/preventive action to prevent the problem from recurring?2 | D11: ='RAW DATA Q2 - 2'!AN11 -> 3
A12: 6 | B12: Quality | C12: ='RAW DATA Q2 - 2'!AO$1 -> How would you rate supplier compliance with administrative processes, including completion of draft cooperation contract?3 | D12: ='RAW DATA Q2 - 2'!AO11 -> 5
A13: 7 | B13: Quality | C13: ='RAW DATA Q2 - 2'!AP$1 -> How would you rate the supplier's service in providing training materials in accordance with: | D13: ='RAW DATA Q2 - 2'!AP11 -> 5
A14: 8 | B14: Quality | C14: ='RAW DATA Q2 - 2'!AQ$1 -> How would you rate the supplier's service in creating a discussion session that covers current conditions, understanding objectives, and discussions using specific cases from the training material wit | D14: ='RAW DATA Q2 - 2'!AQ11 -> 3
A15: 9 | B15: Quality | C15: ='RAW DATA Q2 - 2'!AR$1 -> How would you rate the supplier's service in conducting 1 (one) session of Data Privacy and Protection awareness training sessions for AXA and its related business units, along with a post-test. | D15: ='RAW DATA Q2 - 2'!AR11 -> 5
A16: 10 | B16: Quality | C16: ='RAW DATA Q2 - 2'!AS$1 -> How would you rate the supplier's response time for service issues? | D16: ='RAW DATA Q2 - 2'!AS11 -> 4
A17: 11 | B17: Quality | C17: ='RAW DATA Q2 - 2'!AT$1 -> How would you rate the supplier's project management & management report? | D17: ='RAW DATA Q2 - 2'!AT11 -> 4
A18: 12 | B18: Timeline | C18: ='RAW DATA Q2 - 2'!DO$1 -> How would you rate the supplier's timeliness in delivering goods/services compared to the agreed-upon timeline? | D18: ='RAW DATA Q2 - 2'!DO11 -> 4
A19: 13 | B19: Timeline | C19: ='RAW DATA Q2 - 2'!DP$1 -> How would you rate the supplier's timeliness in sending reports to you? | D19: ='RAW DATA Q2 - 2'!DP11 -> 4
A20: 14 | B20: Timeline | C20: ='RAW DATA Q2 - 2'!DQ$1 -> How would you rate the supplier's speed ​​of administrative completion, including completion of contracts draft? | D20: ='RAW DATA Q2 - 2'!DQ11 -> 4
A21: 15 | B21: Relationship | C21: ='RAW DATA Q2 - 2'!FM$1 -> How would you rate the supplier's communication with you? | D21: ='RAW DATA Q2 - 2'!FM11 -> 4
A22: 16 | B22: Relationship | C22: ='RAW DATA Q2 - 2'!FN$1 -> How would you rate the supplier's PIC's availability to be contacted when needed? | D22: ='RAW DATA Q2 - 2'!FN11 -> 4
A23: 17 | B23: Relationship | C23: ='RAW DATA Q2 - 2'!FO$1 -> How would you rate the supplier's response speed to you when there are issues? | D23: ='RAW DATA Q2 - 2'!FO11 -> 4
A25: Quality Avg (35%) | B25: =AVERAGEIF(B7:B23,"Quality",D7:D23) -> 4.1818182
A26: Timeline Avg (35%) | B26: =AVERAGEIF(B7:B23,"Timeline",D7:D23) -> 4
A27: Relationship Avg (30%) | B27: =AVERAGEIF(B7:B23,"Relationship",D7:D23) -> 4
A28: TOTAL SCORE | B28: =B25*0.35+B26*0.35+B27*0.3 -> 4.0636364
A29: STATUS | B29: =IF(B28>4.99,"Exceptional",IF(B28>3.99,"Exceed Expectation",IF(B28>=2.99,"Meet Expectation",IF(B28>1.9,"Below Expectation","Unsatisfactory")))) -> Exceed Expectation
A31: DUE DILIGENCE / COMPLIANCE
A32: Financial Assessment | B32: ='RAW DATA Q2 - 2'!FP11 -> Yes
A33: Reputational Assessment | B33: ='RAW DATA Q2 - 2'!FQ11 -> Yes
A34: DPIA | B34: ='RAW DATA Q2 - 2'!FR11 -> Yes, DPIA completed and there are actions to be done by Project Owner
A35: DPSQ | B35: ='RAW DATA Q2 - 2'!FS11 -> No Implementation
A36: VSDDT | B36: ='RAW DATA Q2 - 2'!FT11 -> Yes, VSDDT completed and there are actions to be done by supplier
A37: Action Plan | B37: ='RAW DATA Q2 - 2'!FU11 -> Yes – Action items identified, but follow‑up and coordination with relevant SME is still required
A39: REMARKS / FEEDBACK
B40: ='RAW DATA Q2 - 2'!FV11 -> In dealing with Security AI-related issues, Deloitte is occasionally unable to provide a resolution and therefore redirects the matter to the Security AI team. Furthermore, several system features are restricted, and these limitations were not clearly communicated at the outset. Consequently, this has created challenges in implementing system enhancements and aligning the system with the business requirements of Security AI users.

Sheet Q2 TMF
A1: HASIL REVIEW VENDOR — Q2 2026
A2: Vendor | B2: TMF Indonesia
A3: Service | B3: Payroll
A4: PIC (Business User) | B4: Enung HARYATI
A6: No | B6: Dimensi | C6: Pertanyaan | D6: Skor
A7: 1 | B7: Quality | C7: ='RAW DATA Q2 - 2'!BP$1 -> How would you rate the Supplier’s ability to deliver monthly Payroll Services? | D7: ='RAW DATA Q2 - 2'!BP2 -> 3
A8: 2 | B8: Quality | C8: ='RAW DATA Q2 - 2'!BQ$1 -> How would you rate the Supplier’s ability to deliver Cash Management Services, including the following aspects: | D8: ='RAW DATA Q2 - 2'!BQ2 -> 3
A9: 3 | B9: Quality | C9: ='RAW DATA Q2 - 2'!BR$1 -> How would you rate the Supplier’s ability to deliver Compliance Services, including the following aspects: | D9: ='RAW DATA Q2 - 2'!BR2 -> 3
A10: 4 | B10: Quality | C10: ='RAW DATA Q2 - 2'!BS$1 -> How would you rate the Supplier’s ability to deliver BPJS Kesehatan Services? | D10: ='RAW DATA Q2 - 2'!BS2 -> 3
A11: 5 | B11: Quality | C11: ='RAW DATA Q2 - 2'!BT$1 -> How would you rate the Supplier’s ability to comply with penalty provisions for payroll processing? | D11: ='RAW DATA Q2 - 2'!BT2 -> 3
A12: 6 | B12: Quality | C12: ='RAW DATA Q2 - 2'!BU$1 -> How would you rate the Supplier’s ability to execute the Special Project for BPJS Kesehatan? | D12: ='RAW DATA Q2 - 2'!BU2 -> 3
A13: 7 | B13: Timeline | C13: ='RAW DATA Q2 - 2'!DZ$1 -> How would you rate the Supplier’s ability to meet payroll disbursement timelines? | D13: ='RAW DATA Q2 - 2'!DZ2 -> 3
A14: 8 | B14: Timeline | C14: ='RAW DATA Q2 - 2'!EA$1 -> How would you rate the Supplier’s ability to meet the timelines for report and form submissions, including the following aspects: | D14: ='RAW DATA Q2 - 2'!EA2 -> 3
A15: 9 | B15: Timeline | C15: ='RAW DATA Q2 - 2'!EB$1 -> How would you rate the Supplier’s ability to meet the required timelines for payment processing? | D15: ='RAW DATA Q2 - 2'!EB2 -> 3
A16: 10 | B16: Relationship | C16: ='RAW DATA Q2 - 2'!FM$1 -> How would you rate the supplier's communication with you? | D16: ='RAW DATA Q2 - 2'!FM2 -> 3
A17: 11 | B17: Relationship | C17: ='RAW DATA Q2 - 2'!FN$1 -> How would you rate the supplier's PIC's availability to be contacted when needed? | D17: ='RAW DATA Q2 - 2'!FN2 -> 3
A18: 12 | B18: Relationship | C18: ='RAW DATA Q2 - 2'!FO$1 -> How would you rate the supplier's response speed to you when there are issues? | D18: ='RAW DATA Q2 - 2'!FO2 -> 3
A20: Quality Avg (35%) | B20: =AVERAGEIF(B7:B18,"Quality",D7:D18) -> 3
A21: Timeline Avg (35%) | B21: =AVERAGEIF(B7:B18,"Timeline",D7:D18) -> 3
A22: Relationship Avg (30%) | B22: =AVERAGEIF(B7:B18,"Relationship",D7:D18) -> 3
A23: TOTAL SCORE | B23: =B20*0.35+B21*0.35+B22*0.3 -> 3
A24: STATUS | B24: =IF(B23>4.99,"Exceptional",IF(B23>3.99,"Exceed Expectation",IF(B23>=2.99,"Meet Expectation",IF(B23>1.9,"Below Expectation","Unsatisfactory")))) -> Meet Expectation
A26: DUE DILIGENCE / COMPLIANCE
A27: Financial Assessment | B27: ='RAW DATA Q2 - 2'!FP2 -> Yes
A28: Reputational Assessment | B28: ='RAW DATA Q2 - 2'!FQ2 -> Yes
A29: DPIA | B29: ='RAW DATA Q2 - 2'!FR2 -> Yes, DPIA completed and there are actions to be done by Project Owner
A30: DPSQ | B30: ='RAW DATA Q2 - 2'!FS2 -> Yes, DPSQ completed
A31: VSDDT | B31: ='RAW DATA Q2 - 2'!FT2 -> Yes, VSDDT completed and there are actions to be done by supplier
A32: Action Plan | B32: ='RAW DATA Q2 - 2'!FU2 -> Yes – All action items have been completed and coordinated with relevant SME
A34: REMARKS / FEEDBACK
B35: ='RAW DATA Q2 - 2'!FV2 -> -

Sheet Q2 KPSG-TM
A1: HASIL REVIEW VENDOR — Q2 2026
A2: Vendor | B2: Karya Putra Surya Gemilang
A3: Service | B3: Telemarketing Revamp Project
A4: PIC (Business User) | B4: Nuril HUDHA
A6: No | B6: Dimensi | C6: Pertanyaan | D6: Skor
A7: 1 | B7: Quality | C7: ='RAW DATA Q2 - 2'!P$1 -> How would you rate the goods/services provided by the Supplier against the agreed standards | D7: ='RAW DATA Q2 - 2'!P5 -> 3
A8: 2 | B8: Quality | C8: ='RAW DATA Q2 - 2'!Q$1 -> How would you rate the accuracy of the data in the Supplier's reports? | D8: ='RAW DATA Q2 - 2'!Q5 -> 4
A9: 3 | B9: Quality | C9: ='RAW DATA Q2 - 2'!R$1 -> How would you rate overall quality of the work reports provided by the Supplier? | D9: ='RAW DATA Q2 - 2'!R5 -> 4
A10: 4 | B10: Quality | C10: ='RAW DATA Q2 - 2'!S$1 -> How would you rate the solutions provided when there is trouble? | D10: ='RAW DATA Q2 - 2'!S5 -> 3
A11: 5 | B11: Quality | C11: ='RAW DATA Q2 - 2'!T$1 -> How would you rate the Vendor initiative to take mitigation/preventive action to prevent the problem from recurring? | D11: ='RAW DATA Q2 - 2'!T5 -> 3
A12: 6 | B12: Quality | C12: ='RAW DATA Q2 - 2'!U$1 -> How would you rate supplier compliance with administrative processes, including completion of draft cooperation contract?1 | D12: ='RAW DATA Q2 - 2'!U5 -> 4
A13: 7 | B13: Quality | C13: ='RAW DATA Q2 - 2'!V$1 -> How would you rate the supplier implementation on a Project Management Approach, which includes: | D13: ='RAW DATA Q2 - 2'!V5 -> 3
A14: 8 | B14: Quality | C14: ='RAW DATA Q2 - 2'!W$1 -> How would you rate the supplier support in providing 1 (one) Technical Support personnel who is specifically assigned? Based on SLA, this technical support will be assigned at Menara Global and Graha | D14: ='RAW DATA Q2 - 2'!W5 -> 4
A15: 9 | B15: Quality | C15: ='RAW DATA Q2 - 2'!X$1 -> How would you rate the supplier support in providing technical support personnel who will perform several activities such as: | D15: ='RAW DATA Q2 - 2'!X5 -> 4
A16: 10 | B16: Quality | C16: ='RAW DATA Q2 - 2'!Y$1 -> How would you rate the supplier support in maintaining 99% SLA for System Availability in providing the Services to AMFS (SLA calculation does not include service downtime triggered by deliverables no | D16: ='RAW DATA Q2 - 2'!Y5 -> 4
A17: 11 | B17: Quality | C17: ='RAW DATA Q2 - 2'!Z$1 -> How would you rate the supplier support in providing Annual Support such as: | D17: ='RAW DATA Q2 - 2'!Z5 -> 4
A18: 12 | B18: Timeline | C18: ='RAW DATA Q2 - 2'!DO$1 -> How would you rate the supplier's timeliness in delivering goods/services compared to the agreed-upon timeline? | D18: ='RAW DATA Q2 - 2'!DO5 -> 3
A19: 13 | B19: Timeline | C19: ='RAW DATA Q2 - 2'!DP$1 -> How would you rate the supplier's timeliness in sending reports to you? | D19: ='RAW DATA Q2 - 2'!DP5 -> 4
A20: 14 | B20: Timeline | C20: ='RAW DATA Q2 - 2'!DQ$1 -> How would you rate the supplier's speed ​​of administrative completion, including completion of contracts draft? | D20: ='RAW DATA Q2 - 2'!DQ5 -> 3
A21: 15 | B21: Relationship | C21: ='RAW DATA Q2 - 2'!FM$1 -> How would you rate the supplier's communication with you? | D21: ='RAW DATA Q2 - 2'!FM5 -> 4
A22: 16 | B22: Relationship | C22: ='RAW DATA Q2 - 2'!FN$1 -> How would you rate the supplier's PIC's availability to be contacted when needed? | D22: ='RAW DATA Q2 - 2'!FN5 -> 3
A23: 17 | B23: Relationship | C23: ='RAW DATA Q2 - 2'!FO$1 -> How would you rate the supplier's response speed to you when there are issues? | D23: ='RAW DATA Q2 - 2'!FO5 -> 4
A25: Quality Avg (35%) | B25: =AVERAGEIF(B7:B23,"Quality",D7:D23) -> 3.6363636
A26: Timeline Avg (35%) | B26: =AVERAGEIF(B7:B23,"Timeline",D7:D23) -> 3.3333333
A27: Relationship Avg (30%) | B27: =AVERAGEIF(B7:B23,"Relationship",D7:D23) -> 3.6666667
A28: TOTAL SCORE | B28: =B25*0.35+B26*0.35+B27*0.3 -> 3.5393939
A29: STATUS | B29: =IF(B28>4.99,"Exceptional",IF(B28>3.99,"Exceed Expectation",IF(B28>=2.99,"Meet Expectation",IF(B28>1.9,"Below Expectation","Unsatisfactory")))) -> Meet Expectation
A31: DUE DILIGENCE / COMPLIANCE
A32: Financial Assessment | B32: ='RAW DATA Q2 - 2'!FP5 -> Yes
A33: Reputational Assessment | B33: ='RAW DATA Q2 - 2'!FQ5 -> Yes
A34: DPIA | B34: ='RAW DATA Q2 - 2'!FR5 -> Yes, DPIA completed and there are actions to be done by Project Owner
A35: DPSQ | B35: ='RAW DATA Q2 - 2'!FS5 -> Yes, DPSQ not completed yet
A36: VSDDT | B36: ='RAW DATA Q2 - 2'!FT5 -> Yes, VSDDT completed and there are actions to be done by supplier
A37: Action Plan | B37: ='RAW DATA Q2 - 2'!FU5 -> Yes – Action items identified, but follow‑up and coordination with relevant SME is still required
A39: REMARKS / FEEDBACK
B40: ='RAW DATA Q2 - 2'!FV5 -> 1. For AI Implementation, KPSG need to improve the delivery time, quality and PIC availability and backup PIC support 2. Another enhancement need to speed up with dedicated team

Sheet Q2 WIZ
A1: HASIL REVIEW VENDOR — Q2 2026
A2: Vendor | B2: Wiz Technology
A3: Service | B3: Voice Bot Reminder Call
A4: PIC (Business User) | B4: Ravika OKTAVIANI
A6: No | B6: Dimensi | C6: Pertanyaan | D6: Skor
A7: 1 | B7: Quality | C7: ='RAW DATA Q2 - 2'!H$1 -> How would you rate the services provided by the supplier? | D7: ='RAW DATA Q2 - 2'!H7 -> 4
A8: 2 | B8: Quality | C8: ='RAW DATA Q2 - 2'!I$1 -> How would you rate the accuracy of the data in the Supplier's reports? | D8: ='RAW DATA Q2 - 2'!I7 -> 4
A9: 3 | B9: Quality | C9: ='RAW DATA Q2 - 2'!J$1 -> How would you rate overall quality of the work reports provided by the Supplier | D9: ='RAW DATA Q2 - 2'!J7 -> 3
A10: 4 | B10: Quality | C10: ='RAW DATA Q2 - 2'!K$1 -> How would you rate the solutions provided by the supplier when there is trouble? | D10: ='RAW DATA Q2 - 2'!K7 -> 3
A11: 5 | B11: Quality | C11: ='RAW DATA Q2 - 2'!L$1 -> How would you rate the resolution to the problem that occurred? | D11: ='RAW DATA Q2 - 2'!L7 -> 3
A12: 6 | B12: Quality | C12: ='RAW DATA Q2 - 2'!M$1 -> How would you rate the speed of resolution given to problems that occur? | D12: ='RAW DATA Q2 - 2'!M7 -> 3
A13: 7 | B13: Quality | C13: ='RAW DATA Q2 - 2'!N$1 -> How would you rate supplier initiative to take mitigation/preventive action to prevent recurring problem? | D13: ='RAW DATA Q2 - 2'!N7 -> 3
A14: 8 | B14: Quality | C14: ='RAW DATA Q2 - 2'!O$1 -> How would you rate supplier compliance with administrative processes, including completion of draft cooperation contract? | D14: ='RAW DATA Q2 - 2'!O7 -> 3
A15: 9 | B15: Timeline | C15: ='RAW DATA Q2 - 2'!DO$1 -> How would you rate the supplier's timeliness in delivering goods/services compared to the agreed-upon timeline? | D15: ='RAW DATA Q2 - 2'!DO7 -> 3
A16: 10 | B16: Timeline | C16: ='RAW DATA Q2 - 2'!DP$1 -> How would you rate the supplier's timeliness in sending reports to you? | D16: ='RAW DATA Q2 - 2'!DP7 -> 3
A17: 11 | B17: Timeline | C17: ='RAW DATA Q2 - 2'!DQ$1 -> How would you rate the supplier's speed ​​of administrative completion, including completion of contracts draft? | D17: ='RAW DATA Q2 - 2'!DQ7 -> 3
A18: 12 | B18: Relationship | C18: ='RAW DATA Q2 - 2'!FM$1 -> How would you rate the supplier's communication with you? | D18: ='RAW DATA Q2 - 2'!FM7 -> 3
A19: 13 | B19: Relationship | C19: ='RAW DATA Q2 - 2'!FN$1 -> How would you rate the supplier's PIC's availability to be contacted when needed? | D19: ='RAW DATA Q2 - 2'!FN7 -> 3
A20: 14 | B20: Relationship | C20: ='RAW DATA Q2 - 2'!FO$1 -> How would you rate the supplier's response speed to you when there are issues? | D20: ='RAW DATA Q2 - 2'!FO7 -> 3
A22: Quality Avg (35%) | B22: =AVERAGEIF(B7:B20,"Quality",D7:D20) -> 3.25
A23: Timeline Avg (35%) | B23: =AVERAGEIF(B7:B20,"Timeline",D7:D20) -> 3
A24: Relationship Avg (30%) | B24: =AVERAGEIF(B7:B20,"Relationship",D7:D20) -> 3
A25: TOTAL SCORE | B25: =B22*0.35+B23*0.35+B24*0.3 -> 3.0875
A26: STATUS | B26: =IF(B25>4.99,"Exceptional",IF(B25>3.99,"Exceed Expectation",IF(B25>=2.99,"Meet Expectation",IF(B25>1.9,"Below Expectation","Unsatisfactory")))) -> Meet Expectation
A28: DUE DILIGENCE / COMPLIANCE
A29: Financial Assessment | B29: ='RAW DATA Q2 - 2'!FP7 -> Yes
A30: Reputational Assessment | B30: ='RAW DATA Q2 - 2'!FQ7 -> Yes
A31: DPIA | B31: ='RAW DATA Q2 - 2'!FR7 -> Yes, DPIA completed and there are actions to be done by Project Owner
A32: DPSQ | B32: ='RAW DATA Q2 - 2'!FS7 -> Yes, DPSQ completed
A33: VSDDT | B33: ='RAW DATA Q2 - 2'!FT7 -> Yes, VSDDT completed and there are actions to be done by supplier
A34: Action Plan | B34: ='RAW DATA Q2 - 2'!FU7 -> No – No action items were required
A36: REMARKS / FEEDBACK
B37: ='RAW DATA Q2 - 2'!FV7 -> To ensure a smooth process, we need to move faster and maintain effective communication

Sheet Q2 KPSG-ARSI
A1: HASIL REVIEW VENDOR — Q2 2026
A2: Vendor | B2: Karyaputra Suryagemilang
A3: Service | B3: Purecloud Decommisioning
A4: PIC (Business User) | B4: Noviani MARBUN
A6: No | B6: Dimensi | C6: Pertanyaan | D6: Skor
A7: 1 | B7: Quality | C7: ='RAW DATA Q2 - 2'!CF$1 -> The ARSI system (Inbound & Outbound) works properly and is ready to use as promised | D7: ='RAW DATA Q2 - 2'!CF3 -> 4
A8: 2 | B8: Quality | C8: ='RAW DATA Q2 - 2'!CG$1 -> The work delivered by KPSG reflects a high level of professionalism and expertise | D8: ='RAW DATA Q2 - 2'!CG3 -> 3
A9: 3 | B9: Quality | C9: ='RAW DATA Q2 - 2'!CH$1 -> The integration with our other systems runs smoothly | D9: ='RAW DATA Q2 - 2'!CH3 -> 2
A10: 4 | B10: Quality | C10: ='RAW DATA Q2 - 2'!CI$1 -> The features provided work as expected | D10: ='RAW DATA Q2 - 2'!CI3 -> 3
A11: 5 | B11: Quality | C11: ='RAW DATA Q2 - 2'!CJ$1 -> Bugs or errors in the system are rare, and when they occur, they are fixed properly | D11: ='RAW DATA Q2 - 2'!CJ3 -> 3
A12: 6 | B12: Quality | C12: ='RAW DATA Q2 - 2'!CK$1 -> Project documents are complete and clear | D12: ='RAW DATA Q2 - 2'!CK3 -> 3
A13: 7 | B13: Quality | C13: ='RAW DATA Q2 - 2'!CL$1 -> Regular reports provided by KPSG are accurate and easy to understand | D13: ='RAW DATA Q2 - 2'!CL3 -> 4
A14: 8 | B14: Quality | C14: ='RAW DATA Q2 - 2'!CM$1 -> KPSG responds well and cooperatively when we raise complaints or request improvements | D14: ='RAW DATA Q2 - 2'!CM3 -> 4
A15: 9 | B15: Quality | C15: ='RAW DATA Q2 - 2'!CN$1 -> Our data and information are kept secure while using KPSG's system | D15: ='RAW DATA Q2 - 2'!CN3 -> 4
A16: 10 | B16: Quality | C16: ='RAW DATA Q2 - 2'!CO$1 -> Overall, the quality of KPSG's service meets our expectations | D16: ='RAW DATA Q2 - 2'!CO3 -> 3
A17: 11 | B17: Timeline | C17: ='RAW DATA Q2 - 2'!EC$1 -> KPSG's support team is available during agreed service hours (Mon–Fri, 09:00–18:00), with on-call support outside these hours when needed | D17: ='RAW DATA Q2 - 2'!EC3 -> 4
A18: 12 | B18: Quality | C18: ='RAW DATA Q2 - 2'!ED$1 -> The system is available at least 99% of the time, with minimal downtime | D18: ='RAW DATA Q2 - 2'!ED3 -> 4
A19: 13 | B19: Timeline | C19: ='RAW DATA Q2 - 2'!EE$1 -> KPSG responds to our service requests within 1 hour during normal working hours | D19: ='RAW DATA Q2 - 2'!EE3 -> 3
A20: 14 | B20: Timeline | C20: ='RAW DATA Q2 - 2'!EF$1 -> Issues are resolved within the agreed timeframe based on impact level | D20: ='RAW DATA Q2 - 2'!EF3 -> 2
A21: 15 | B21: Quality | C21: ='RAW DATA Q2 - 2'!EG$1 -> How would you rate the Data Back Up processing | D21: ='RAW DATA Q2 - 2'!EG3 -> 4
A22: 16 | B22: Timeline | C22: ='RAW DATA Q2 - 2'!EH$1 -> Project milestones are completed on the agreed dates | D22: ='RAW DATA Q2 - 2'!EH3 -> 2
A23: 17 | B23: Timeline | C23: ='RAW DATA Q2 - 2'!EI$1 -> KPSG gives us early warning if there's a risk of delay in any deliverable | D23: ='RAW DATA Q2 - 2'!EI3 -> 3
A24: 18 | B24: Timeline | C24: ='RAW DATA Q2 - 2'!EJ$1 -> Monthly and weekly reports are submitted on time | D24: ='RAW DATA Q2 - 2'!EJ3 -> 4
A25: 19 | B25: Timeline | C25: ='RAW DATA Q2 - 2'!EK$1 -> Any cybersecurity incidents are reported to us within 4 hours of detection | D25: ='RAW DATA Q2 - 2'!EK3 -> 3
A26: 20 | B26: Timeline | C26: ='RAW DATA Q2 - 2'!EL$1 -> Requests for system changes are followed up and completed within the agreed timeline | D26: ='RAW DATA Q2 - 2'!EL3 -> 3
A27: 21 | B27: Relationship | C27: ='RAW DATA Q2 - 2'!FM$1 -> How would you rate the supplier's communication with you? | D27: ='RAW DATA Q2 - 2'!FM3 -> 4
A28: 22 | B28: Relationship | C28: ='RAW DATA Q2 - 2'!FN$1 -> How would you rate the supplier's PIC's availability to be contacted when needed? | D28: ='RAW DATA Q2 - 2'!FN3 -> 4
A29: 23 | B29: Relationship | C29: ='RAW DATA Q2 - 2'!FO$1 -> How would you rate the supplier's response speed to you when there are issues? | D29: ='RAW DATA Q2 - 2'!FO3 -> 4
A31: Quality Avg (35%) | B31: =AVERAGEIF(B7:B29,"Quality",D7:D29) -> 3.4166667
A32: Timeline Avg (35%) | B32: =AVERAGEIF(B7:B29,"Timeline",D7:D29) -> 3
A33: Relationship Avg (30%) | B33: =AVERAGEIF(B7:B29,"Relationship",D7:D29) -> 4
A34: TOTAL SCORE | B34: =B31*0.35+B32*0.35+B33*0.3 -> 3.4458333
A35: STATUS | B35: =IF(B34>4.99,"Exceptional",IF(B34>3.99,"Exceed Expectation",IF(B34>=2.99,"Meet Expectation",IF(B34>1.9,"Below Expectation","Unsatisfactory")))) -> Meet Expectation
A37: DUE DILIGENCE / COMPLIANCE
A38: Financial Assessment | B38: ='RAW DATA Q2 - 2'!FP3 -> Yes
A39: Reputational Assessment | B39: ='RAW DATA Q2 - 2'!FQ3 -> Yes
A40: DPIA | B40: ='RAW DATA Q2 - 2'!FR3 -> Yes, DPIA completed and there are actions to be done by Project Owner
A41: DPSQ | B41: ='RAW DATA Q2 - 2'!FS3 -> Yes, DPSQ not completed yet
A42: VSDDT | B42: ='RAW DATA Q2 - 2'!FT3 -> Yes, VSDDT completed and there are actions to be done by supplier
A43: Action Plan | B43: ='RAW DATA Q2 - 2'!FU3 -> Yes – Action items identified, but follow‑up and coordination with relevant SME is still required
A45: REMARKS / FEEDBACK
B46: ='RAW DATA Q2 - 2'!FV3 -> 1. KPSG-ARSI Perspective (The approach applied is still limited to best practices without considering the scenarios occurring in AMFS). 2. Requirement Gap (There is a significant requirement gap due to missed requirements, caused by insufficient exploration of user needs and requirements) 3. Frequent Manpower (MP) and PIC Changes (Manpower changes occur quite frequently, while the implementation team is no longer on-site. The PIC from KPSG also changes often. It is requested that a dedicated PIC be provided for IT Support as well as a dedicated Project Manager) 4. Deployment Issues (Each deployment consistently results in new issues that impact areas outside the deployment scope. This indicates a lack of proper health checks after deployment). 5. Deployment Communication (Communication regarding deployment plans is still lacking, particularly in obtaining approval from business users. This matter has already been communicated by AMFS to the KPSG team). 6. Contact Center Experience (The team’s experience in contact center operations, especially inbound, remains limited). 7. Change Requests (CR) and Production Issues (Many CRs and production issues are delivered based on targets determined unilaterally by KPSG). 8. User Guide and Feature Socialization. (The User Guide is not well maintained. When new features are introduced, documentation should be updated immediately, socialized to users, and the latest User Guide shared to ensure optimal usage)

Sheet Q2 MII-Purecloud
A1: HASIL REVIEW VENDOR — Q2 2026
A2: Vendor | B2: Mitra Integrasi Informatika
A3: Service | B3: Purecloud Decommisioning
A4: PIC (Business User) | B4: Noviani MARBUN
A6: No | B6: Dimensi | C6: Pertanyaan | D6: Skor
A7: 1 | B7: Quality | C7: ='RAW DATA Q2 - 2'!CZ$1 -> The delivered solution met all agreed functional requirements | D7: ='RAW DATA Q2 - 2'!CZ4 -> 4
A8: 2 | B8: Quality | C8: ='RAW DATA Q2 - 2'!DA$1 -> The system passed User Acceptance Testing (UAT) with minimal critical issues or rework needed | D8: ='RAW DATA Q2 - 2'!DA4 -> 4
A9: 3 | B9: Timeline | C9: ='RAW DATA Q2 - 2'!DB$1 -> Call recordings were accessible and properly linked within the agreed retention period | D9: ='RAW DATA Q2 - 2'!DB4 -> 4
A10: 4 | B10: Quality | C10: ='RAW DATA Q2 - 2'!DC$1 -> Reports and dashboards were accurate and matched AXA’s required format | D10: ='RAW DATA Q2 - 2'!DC4 -> 4
A11: 5 | B11: Quality | C11: ='RAW DATA Q2 - 2'!DD$1 -> Defects or bugs found during the warranty period were minimal and resolved promptly at no extra cost | D11: ='RAW DATA Q2 - 2'!DD4 -> 4
A12: 6 | B12: Timeline | C12: ='RAW DATA Q2 - 2'!DE$1 -> Project documentation was complete, accurate, and submitted on time | D12: ='RAW DATA Q2 - 2'!DE4 -> 4
A13: 7 | B13: Quality | C13: ='RAW DATA Q2 - 2'!DF$1 -> Training provided was clear and sufficient for AXA’s team to operate independently | D13: ='RAW DATA Q2 - 2'!DF4 -> 2
A14: 8 | B14: Quality | C14: ='RAW DATA Q2 - 2'!DG$1 -> Overall, the quality of supplier work on the purecloud decommisioning project meets our expectations | D14: ='RAW DATA Q2 - 2'!DG4 -> 4
A15: 9 | B15: Timeline | C15: ='RAW DATA Q2 - 2'!EW$1 -> The Planning & Architecture phase was completed on schedule | D15: ='RAW DATA Q2 - 2'!EW4 -> 4
A16: 10 | B16: Timeline | C16: ='RAW DATA Q2 - 2'!EX$1 -> The Build/Construction phase was completed on schedule | D16: ='RAW DATA Q2 - 2'!EX4 -> 4
A17: 11 | B17: Timeline | C17: ='RAW DATA Q2 - 2'!EY$1 -> The Validation/UAT phase was completed on schedule | D17: ='RAW DATA Q2 - 2'!EY4 -> 4
A18: 12 | B18: Timeline | C18: ='RAW DATA Q2 - 2'!EZ$1 -> The Deployment & Go-Live phase was completed on schedule | D18: ='RAW DATA Q2 - 2'!EZ4 -> 4
A19: 13 | B19: Timeline | C19: ='RAW DATA Q2 - 2'!FA$1 -> The supplier responded to reported issues within the agreed response time | D19: ='RAW DATA Q2 - 2'!FA4 -> 4
A20: 14 | B20: Timeline | C20: ='RAW DATA Q2 - 2'!FB$1 -> The supplier resolved reported issues within the agreed resolution time | D20: ='RAW DATA Q2 - 2'!FB4 -> 4
A21: 15 | B21: Timeline | C21: ='RAW DATA Q2 - 2'!FC$1 -> The project was completed without delays requiring AXA to invoke late penalties | D21: ='RAW DATA Q2 - 2'!FC4 -> 4
A22: 16 | B22: Timeline | C22: ='RAW DATA Q2 - 2'!FD$1 -> The supplier proactively communicated whenever a milestone was at risk of delay | D22: ='RAW DATA Q2 - 2'!FD4 -> 4
A23: 17 | B23: Relationship | C23: ='RAW DATA Q2 - 2'!FM$1 -> How would you rate the supplier's communication with you? | D23: ='RAW DATA Q2 - 2'!FM4 -> 4
A24: 18 | B24: Relationship | C24: ='RAW DATA Q2 - 2'!FN$1 -> How would you rate the supplier's PIC's availability to be contacted when needed? | D24: ='RAW DATA Q2 - 2'!FN4 -> 4
A25: 19 | B25: Relationship | C25: ='RAW DATA Q2 - 2'!FO$1 -> How would you rate the supplier's response speed to you when there are issues? | D25: ='RAW DATA Q2 - 2'!FO4 -> 4
A27: Quality Avg (35%) | B27: =AVERAGEIF(B7:B25,"Quality",D7:D25) -> 3.6666667
A28: Timeline Avg (35%) | B28: =AVERAGEIF(B7:B25,"Timeline",D7:D25) -> 4
A29: Relationship Avg (30%) | B29: =AVERAGEIF(B7:B25,"Relationship",D7:D25) -> 4
A30: TOTAL SCORE | B30: =B27*0.35+B28*0.35+B29*0.3 -> 3.8833333
A31: STATUS | B31: =IF(B30>4.99,"Exceptional",IF(B30>3.99,"Exceed Expectation",IF(B30>=2.99,"Meet Expectation",IF(B30>1.9,"Below Expectation","Unsatisfactory")))) -> Meet Expectation
A33: DUE DILIGENCE / COMPLIANCE
A34: Financial Assessment | B34: ='RAW DATA Q2 - 2'!FP4 -> Yes
A35: Reputational Assessment | B35: ='RAW DATA Q2 - 2'!FQ4 -> Yes
A36: DPIA | B36: ='RAW DATA Q2 - 2'!FR4 -> Yes, DPIA completed and there are actions to be done by Project Owner
A37: DPSQ | B37: ='RAW DATA Q2 - 2'!FS4 -> No Implementation
A38: VSDDT | B38: ='RAW DATA Q2 - 2'!FT4 -> Yes, VSDDT completed and there are actions to be done by supplier
A39: Action Plan | B39: ='RAW DATA Q2 - 2'!FU4 -> Yes – Action items identified, but follow‑up and coordination with relevant SME is still required
A41: REMARKS / FEEDBACK
B42: ='RAW DATA Q2 - 2'!FV4 -> 1) Training Process During the training sessions, it is expected that explanations are delivered in detail and step by step. When participants are conducting hands-on activities, they should be properly provided with guidance and direct support. This is important to avoid unnecessary questions that could otherwise be answered clearly, ensuring that participants can immediately understand the changes and new features introduced. 2) “Baby Sitting” Phase In the “baby sitting” phase, the MII team was expected to be present full day on-site at AMFS for two weeks. However, in practice, the team did not consistently attend and only joined full day after being specifically requested. As a result, the actual presence was only around five days instead of the full two weeks as originally required.

Sheet Q2 ESHAEL
A1: HASIL REVIEW VENDOR — Q2 2026
A2: Vendor | B2: ESHAEL Indonesia
A3: Service | B3: Talent Assesment
A4: PIC (Business User) | B4: I Gusti Ayu Mira SETYAWARDHANIE
A6: No | B6: Dimensi | C6: Pertanyaan | D6: Skor
A7: 1 | B7: Quality | C7: ='RAW DATA Q2 - 2'!DH$1 -> How would you rate the assessment tools & results (Group Report & Individual Report) for Talent Acquisition/Talent Management needs | D7: ='RAW DATA Q2 - 2'!DH6 -> 4
A8: 2 | B8: Quality | C8: ='RAW DATA Q2 - 2'!DI$1 -> Assessment tools (Psychometric Test, Verbal/Numerical/Abstract Reasoning, Personality Questionnaire, Competency Based Interview, etc.) are relevant and appropriate to participants’ level/grade | D8: ='RAW DATA Q2 - 2'!DI6 -> 4
A9: 3 | B9: Timeline | C9: ='RAW DATA Q2 - 2'!DJ$1 -> Assessment sessions (online and offline) are conducted in an orderly, professional manner and according to the agreed schedule | D9: ='RAW DATA Q2 - 2'!DJ6 -> 5
A10: 4 | B10: Quality | C10: ='RAW DATA Q2 - 2'!DK$1 -> SHL maintains the confidentiality and security of assessment participants’ Personal Data in accordance with the privacy provisions in the Agreement | D10: ='RAW DATA Q2 - 2'!DK6 -> 5
A11: 5 | B11: Quality | C11: ='RAW DATA Q2 - 2'!DL$1 -> There are no administrative errors (participant data, grade, test type) throughout the process from Booking Form submission to report delivery | D11: ='RAW DATA Q2 - 2'!DL6 -> 4
A12: 6 | B12: Quality | C12: ='RAW DATA Q2 - 2'!DM$1 -> SHL proactively coordinates when there is a potential dispute or issue before it impacts participants/AXA | D12: ='RAW DATA Q2 - 2'!DM6 -> 4
A13: 7 | B13: Quality | C13: ='RAW DATA Q2 - 2'!DN$1 -> Overall, the quality of supplier work on the talent assesment project meets our expectations | D13: ='RAW DATA Q2 - 2'!DN6 -> 4
A14: 8 | B14: Timeline | C14: ='RAW DATA Q2 - 2'!FE$1 -> Booking Forms for Talent Acquisition assessments are processed on the same Business Day if received before 16.30 WIB | D14: ='RAW DATA Q2 - 2'!FE6 -> 5
A15: 9 | B15: Timeline | C15: ='RAW DATA Q2 - 2'!FF$1 -> Booking Forms for Talent Management assessments are responded to on the same Business Day for further scheduling | D15: ='RAW DATA Q2 - 2'!FF6 -> 5
A16: 10 | B16: Timeline | C16: ='RAW DATA Q2 - 2'!FG$1 -> Individual Reports for Talent Acquisition assessments are delivered within H+1 Business Day after the assessment is completed | D16: ='RAW DATA Q2 - 2'!FG6 -> 5
A17: 11 | B17: Timeline | C17: ='RAW DATA Q2 - 2'!FH$1 -> Recap Reports for Talent Acquisition assessments are delivered within H+3 Business Days after the assessment is completed | D17: ='RAW DATA Q2 - 2'!FH6 -> 5
A18: 12 | B18: Timeline | C18: ='RAW DATA Q2 - 2'!FI$1 -> Recap Reports for Talent Management assessments are delivered within H+5 Business Days after the assessment is completed | D18: ='RAW DATA Q2 - 2'!FI6 -> 5
A19: 13 | B19: Timeline | C19: ='RAW DATA Q2 - 2'!FJ$1 -> Individual Reports for Talent Management assessments are delivered within H+10 Business Days after the assessment is completed | D19: ='RAW DATA Q2 - 2'!FJ6 -> 5
A20: 14 | B20: Timeline | C20: ='RAW DATA Q2 - 2'!FK$1 -> SHL's helpdesk operates and is reachable within the committed service hours (Monday–Friday, 08.00–17.00 WIB). | D20: ='RAW DATA Q2 - 2'!FK6 -> 5
A21: 15 | B21: Timeline | C21: ='RAW DATA Q2 - 2'!FL$1 -> Overall, SHL is consistent in meeting all the time commitments agreed under this Agreement | D21: ='RAW DATA Q2 - 2'!FL6 -> 5
A22: 16 | B22: Relationship | C22: ='RAW DATA Q2 - 2'!FM$1 -> How would you rate the supplier's communication with you? | D22: ='RAW DATA Q2 - 2'!FM6 -> 5
A23: 17 | B23: Relationship | C23: ='RAW DATA Q2 - 2'!FN$1 -> How would you rate the supplier's PIC's availability to be contacted when needed? | D23: ='RAW DATA Q2 - 2'!FN6 -> 5
A24: 18 | B24: Relationship | C24: ='RAW DATA Q2 - 2'!FO$1 -> How would you rate the supplier's response speed to you when there are issues? | D24: ='RAW DATA Q2 - 2'!FO6 -> 4
A26: Quality Avg (35%) | B26: =AVERAGEIF(B7:B24,"Quality",D7:D24) -> 4.1666667
A27: Timeline Avg (35%) | B27: =AVERAGEIF(B7:B24,"Timeline",D7:D24) -> 5
A28: Relationship Avg (30%) | B28: =AVERAGEIF(B7:B24,"Relationship",D7:D24) -> 4.6666667
A29: TOTAL SCORE | B29: =B26*0.35+B27*0.35+B28*0.3 -> 4.6083333
A30: STATUS | B30: =IF(B29>4.99,"Exceptional",IF(B29>3.99,"Exceed Expectation",IF(B29>=2.99,"Meet Expectation",IF(B29>1.9,"Below Expectation","Unsatisfactory")))) -> Exceed Expectation
A32: DUE DILIGENCE / COMPLIANCE
A33: Financial Assessment | B33: ='RAW DATA Q2 - 2'!FP6 -> Yes
A34: Reputational Assessment | B34: ='RAW DATA Q2 - 2'!FQ6 -> Yes
A35: DPIA | B35: ='RAW DATA Q2 - 2'!FR6 -> Yes, DPIA completed and there are actions to be done by Project Owner
A36: DPSQ | B36: ='RAW DATA Q2 - 2'!FS6 -> No Implementation
A37: VSDDT | B37: ='RAW DATA Q2 - 2'!FT6 -> No Implementation
A38: Action Plan | B38: ='RAW DATA Q2 - 2'!FU6 -> No – No action items were required
A40: REMARKS / FEEDBACK
B41: ='RAW DATA Q2 - 2'!FV6 -> N/A

Sheet SUMMARY Q1 2026
A1: CRITICAL SUPPLIER PERFORMANCE REVIEW - SUMMARY
A2: Periode Review | B2: Q1 2026
A3: Jumlah Vendor Dievaluasi (dari RESULT) | B3: =COUNTA(RESULT!B2:B19) -> 18
A4: Total Vendor Kritis (Master List) - Input Manual | B4: 19
A5: % Vendor Dievaluasi | B5: =B3/B4 -> 0.94736842
A6: Jumlah "Meet / Exceed Expectation" | B6: =SUMPRODUCT(--(RESULT!F2:F19<>"Below Expectation"))-SUMPRODUCT(--(RESULT!F2:F19="Unsatisfactory")) -> 17
A7: Jumlah "Under Performance" (Below Expectation) | B7: =COUNTIF(RESULT!F2:F19,"Below Expectation")+COUNTIF(RESULT!F2:F19,"Unsatisfactory") -> 1
A8: Vendor Critical Below Expectation | B8: =_xlfn.TEXTJOIN(", ",TRUE(),RESULT!K2:K19) -> Arah Sejahtera Abadi - Perjanjian Sewa Menyewa

Sheet CONFIG
A1: No | B1: Supplier & Service (Key) | C1: PIC Email | D1: Raw Sheet Name (Quarter Aktif) | E1: Quality Col Start | F1: Quality Col End | G1: Timeline Col Start | H1: Timeline Col End | I1: Relationship Col Start | J1: Relationship Col End | K1: Remarks Col | L1: Financial Assessment Col | M1: Reputational Col | N1: DPIA Required Col | O1: DPSQ Required Col | P1: VSDDT Required Col | Q1: Action Plan Col
A2: 1 | B2: Itsec Asia - Penetration Testing | C2: fauzi.aryanto@axa-mandiri.co.id | D2: RAW DATA Q1 - 1 | E2: FJ | F2: FL | G2: FN | H2: FP | I2: GH | J2: GJ | K2: GS | L2: GK | M2: GL | N2: GM | O2: GN | P2: GO | Q2: GQ
A3: 2 | B3: Iproteksi Telematika - Penetration Testing | C3: fauzi.aryanto@axa-mandiri.co.id | D3: RAW DATA Q1 - 1 | E3: FG | F3: FI | G3: FN | H3: FP | I3: GH | J3: GJ | K3: GS | L3: GK | M3: GL | N3: GM | O3: GN | P3: GO | Q3: GQ
A4: 3 | B4: FPT Metrodata - Penetration Testing | C4: fauzi.aryanto@axa-mandiri.co.id | D4: RAW DATA Q1 - 1 | E4: FD | F4: FF | G4: FN | H4: FP | I4: GH | J4: GJ | K4: GS | L4: GK | M4: GL | N4: GM | O4: GN | P4: GO | Q4: GQ
A5: 4 | B5: Satria Antaran Prima - Mailing Room | C5: ibnu.kumala@axa-mandiri.co.id | D5: RAW DATA Q1 - 1 | E5: DX | F5: EE | G5: FN | H5: FP | I5: GH | J5: GJ | K5: GS | L5: GK | M5: GL | N5: GM | O5: GN | P5: GO | Q5: GQ
A6: 5 | B6: Informasi Teknologi Indonesia - SMS Broadcast | C6: fifin.sarinurlita@axa-mandiri.co.id | D6: RAW DATA Q1 - 1 | E6: AA | F6: AK | G6: FO | H6: FS | I6: GH | J6: GJ | K6: GS | L6: GK | M6: GL | N6: GM | O6: GN | P6: GO | Q6: GQ
A7: 6 | B7: Satria Antaran Prima - Courier Service | C7: fifin.sarinurlita@axa-mandiri.co.id | D7: RAW DATA Q1 - 1 | E7: DI | F7: DW | G7: GE | H7: GG | I7: GH | J7: GJ | K7: GS | L7: GK | M7: GL | N7: GM | O7: GN | P7: GO | Q7: GQ
A8: 7 | B8: Multifiling Mitra Indonesia - Record Management Service | C8: ibnu.kumala@axa-mandiri.co.id | D8: RAW DATA Q1 - 1 | E8: AY | F8: BI | G8: FU | H8: FX | I8: GH | J8: GJ | K8: GS | L8: GK | M8: GL | N8: GM | O8: GN | P8: GO | Q8: GQ
A9: 8 | B9: Indosat - Layanan PBX berbasiskan cloud dengan Teknologi SIP Trunk | C9: nuril.hudha@axa-mandiri.co.id | D9: RAW DATA Q1 - 1 | E9: G | F9: Z | G9: FN | H9: FP | I9: GH | J9: GJ | K9: GS | L9: GK | M9: GL | N9: GM | O9: GN | P9: GO | Q9: GQ
A10: 9 | B10: Ciptadra Softindo - Pemeliharaan Axits & DMTM | C10: raninta.mahardi@axa-mandiri.co.id | D10: RAW DATA Q1 - 1 | E10: BJ | F10: BW | G10: FY | H10: GD | I10: GH | J10: GJ | K10: GS | L10: GK | M10: GL | N10: GM | O10: GN | P10: GO | Q10: GQ
A11: 10 | B11: Target Sukses Sinergi - Email Marketing Automation | C11: bella.depari@axa-mandiri.co.id | D11: RAW DATA Q1 - 1 | E11: EF | F11: EL | G11: FN | H11: FP | I11: GH | J11: GJ | K11: GS | L11: GK | M11: GL | N11: GM | O11: GN | P11: GO | Q11: GQ
A12: 11 | B12: Inmotion Inovasi Teknologi - Jasa Aplikasi Chatbot dan Live Chat | C12: djoko.djoko@axa-mandiri.co.id | D12: RAW DATA Q1 - 1 | E12: BX | F12: DH | G12: FN | H12: FP | I12: GH | J12: GJ | K12: GS | L12: GK | M12: GL | N12: GM | O12: GN | P12: GO | Q12: GQ
A13: 12 | B13: Mitra Integrasi Informatika - SFDC Maintenance | C13: chandra.putra@axa-mandiri.co.id | D13: RAW DATA Q1 - 1 | E13: AL | F13: AX | G13: FN | H13: FP | I13: GH | J13: GJ | K13: GS | L13: GK | M13: GL | N13: GM | O13: GN | P13: GO | Q13: GQ
... A19: 18 | B19: Karya Putra Surya Gemilang - Telemarketing Revamp Project | C19: reza.resdilana@axa-mandiri.co.id | D19: RAW DATA Q1 - 2 | E19: O | F19: Y | G19: CJ | H19: CL | I19: CS | J19: CU | K19: DF | L19: CV | M19: CW | N19: CX | O19: CZ | P19: DB | Q19: DD

Sheet SCORE CALC
A1: No | B1: Supplier & Service | C1: Match Row (helper) | D1: Quality Avg (35%) | E1: Timeline Avg (35%) | F1: Relationship Avg (30%) | G1: TOTAL SCORE | H1: STATUS
A2: =CONFIG!A2 -> 1 | B2: =CONFIG!B2 -> Itsec Asia - Penetration Testing | C2: =MATCH($B2,INDIRECT("'"&CONFIG!D2&"'!$F:$F"),0) -> 2 | D2: =AVERAGE(INDIRECT("'"&CONFIG!D2&"'!"&CONFIG!E2&$C2&":"&CONFIG!F2&$C2)) -> 3 | E2: =AVERAGE(INDIRECT("'"&CONFIG!D2&"'!"&CONFIG!G2&$C2&":"&CONFIG!H2&$C2)) -> 3 | F2: =AVERAGE(INDIRECT("'"&CONFIG!D2&"'!"&CONFIG!I2&$C2&":"&CONFIG!J2&$C2)) -> 3 | G2: =D2*0.35+E2*0.35+F2*0.3 -> 3 | H2: =IF(G2>4.99,"Exceptional",IF(G2>3.99,"Exceed Expectation",IF(G2>=2.99,"Meet Expectation",IF(G2>1.9,"Below Expectation","Unsatisfactory")))) -> Meet Expectation
A3: =CONFIG!A3 -> 2 | B3: =CONFIG!B3 -> Iproteksi Telematika - Penetration Testing | C3: =MATCH($B3,INDIRECT("'"&CONFIG!D3&"'!$F:$F"),0) -> 3 | D3: =AVERAGE(INDIRECT("'"&CONFIG!D3&"'!"&CONFIG!E3&$C3&":"&CONFIG!F3&$C3)) -> 4 | E3: =AVERAGE(INDIRECT("'"&CONFIG!D3&"'!"&CONFIG!G3&$C3&":"&CONFIG!H3&$C3)) -> 4 | F3: =AVERAGE(INDIRECT("'"&CONFIG!D3&"'!"&CONFIG!I3&$C3&":"&CONFIG!J3&$C3)) -> 4 | G3: =D3*0.35+E3*0.35+F3*0.3 -> 4 | H3: =IF(G3>4.99,"Exceptional",IF(G3>3.99,"Exceed Expectation",IF(G3>=2.99,"Meet Expectation",IF(G3>1.9,"Below Expectation","Unsatisfactory")))) -> Exceed Expectation
A4: =CONFIG!A4 -> 3 | B4: =CONFIG!B4 -> FPT Metrodata - Penetration Testing | C4: =MATCH($B4,INDIRECT("'"&CONFIG!D4&"'!$F:$F"),0) -> 4 | D4: =AVERAGE(INDIRECT("'"&CONFIG!D4&"'!"&CONFIG!E4&$C4&":"&CONFIG!F4&$C4)) -> 3 | E4: =AVERAGE(INDIRECT("'"&CONFIG!D4&"'!"&CONFIG!G4&$C4&":"&CONFIG!H4&$C4)) -> 3 | F4: =AVERAGE(INDIRECT("'"&CONFIG!D4&"'!"&CONFIG!I4&$C4&":"&CONFIG!J4&$C4)) -> 3 | G4: =D4*0.35+E4*0.35+F4*0.3 -> 3 | H4: =IF(G4>4.99,"Exceptional",IF(G4>3.99,"Exceed Expectation",IF(G4>=2.99,"Meet Expectation",IF(G4>1.9,"Below Expectation","Unsatisfactory")))) -> Meet Expectation
A5: =CONFIG!A5 -> 4 | B5: =CONFIG!B5 -> Satria Antaran Prima - Mailing Room | C5: =MATCH($B5,INDIRECT("'"&CONFIG!D5&"'!$F:$F"),0) -> 5 | D5: =AVERAGE(INDIRECT("'"&CONFIG!D5&"'!"&CONFIG!E5&$C5&":"&CONFIG!F5&$C5)) -> 3.25 | E5: =AVERAGE(INDIRECT("'"&CONFIG!D5&"'!"&CONFIG!G5&$C5&":"&CONFIG!H5&$C5)) -> 3.3333333 | F5: =AVERAGE(INDIRECT("'"&CONFIG!D5&"'!"&CONFIG!I5&$C5&":"&CONFIG!J5&$C5)) -> 3.6666667 | G5: =D5*0.35+E5*0.35+F5*0.3 -> 3.4041667 | H5: =IF(G5>4.99,"Exceptional",IF(G5>3.99,"Exceed Expectation",IF(G5>=2.99,"Meet Expectation",IF(G5>1.9,"Below Expectation","Unsatisfactory")))) -> Meet Expectation
A6: =CONFIG!A6 -> 5 | B6: =CONFIG!B6 -> Informasi Teknologi Indonesia - SMS Broadcast | C6: =MATCH($B6,INDIRECT("'"&CONFIG!D6&"'!$F:$F"),0) -> 6 | D6: =AVERAGE(INDIRECT("'"&CONFIG!D6&"'!"&CONFIG!E6&$C6&":"&CONFIG!F6&$C6)) -> 3 | E6: =AVERAGE(INDIRECT("'"&CONFIG!D6&"'!"&CONFIG!G6&$C6&":"&CONFIG!H6&$C6)) -> 3 | F6: =AVERAGE(INDIRECT("'"&CONFIG!D6&"'!"&CONFIG!I6&$C6&":"&CONFIG!J6&$C6)) -> 3 | G6: =D6*0.35+E6*0.35+F6*0.3 -> 3 | H6: =IF(G6>4.99,"Exceptional",IF(G6>3.99,"Exceed Expectation",IF(G6>=2.99,"Meet Expectation",IF(G6>1.9,"Below Expectation","Unsatisfactory")))) -> Meet Expectation
A7: =CONFIG!A7 -> 6 | B7: =CONFIG!B7 -> Satria Antaran Prima - Courier Service | C7: =MATCH($B7,INDIRECT("'"&CONFIG!D7&"'!$F:$F"),0) -> 7 | D7: =AVERAGE(INDIRECT("'"&CONFIG!D7&"'!"&CONFIG!E7&$C7&":"&CONFIG!F7&$C7)) -> 3 | E7: =AVERAGE(INDIRECT("'"&CONFIG!D7&"'!"&CONFIG!G7&$C7&":"&CONFIG!H7&$C7)) -> 3 | F7: =AVERAGE(INDIRECT("'"&CONFIG!D7&"'!"&CONFIG!I7&$C7&":"&CONFIG!J7&$C7)) -> 3 | G7: =D7*0.35+E7*0.35+F7*0.3 -> 3 | H7: =IF(G7>4.99,"Exceptional",IF(G7>3.99,"Exceed Expectation",IF(G7>=2.99,"Meet Expectation",IF(G7>1.9,"Below Expectation","Unsatisfactory")))) -> Meet Expectation
A8: =CONFIG!A8 -> 7 | B8: =CONFIG!B8 -> Multifiling Mitra Indonesia - Record Management Service | C8: =MATCH($B8,INDIRECT("'"&CONFIG!D8&"'!$F:$F"),0) -> 8 | D8: =AVERAGE(INDIRECT("'"&CONFIG!D8&"'!"&CONFIG!E8&$C8&":"&CONFIG!F8&$C8)) -> 3.0909091 | E8: =AVERAGE(INDIRECT("'"&CONFIG!D8&"'!"&CONFIG!G8&$C8&":"&CONFIG!H8&$C8)) -> 3 | F8: =AVERAGE(INDIRECT("'"&CONFIG!D8&"'!"&CONFIG!I8&$C8&":"&CONFIG!J8&$C8)) -> 3 | G8: =D8*0.35+E8*0.35+F8*0.3 -> 3.0318182 | H8: =IF(G8>4.99,"Exceptional",IF(G8>3.99,"Exceed Expectation",IF(G8>=2.99,"Meet Expectation",IF(G8>1.9,"Below Expectation","Unsatisfactory")))) -> Meet Expectation
A9: =CONFIG!A9 -> 8 | B9: =CONFIG!B9 -> Indosat - Layanan PBX berbasiskan cloud dengan Teknologi SIP Trunk | C9: =MATCH($B9,INDIRECT("'"&CONFIG!D9&"'!$F:$F"),0) -> 9 | D9: =AVERAGE(INDIRECT("'"&CONFIG!D9&"'!"&CONFIG!E9&$C9&":"&CONFIG!F9&$C9)) -> 3.0526316 | E9: =AVERAGE(INDIRECT("'"&CONFIG!D9&"'!"&CONFIG!G9&$C9&":"&CONFIG!H9&$C9)) -> 3 | F9: =AVERAGE(INDIRECT("'"&CONFIG!D9&"'!"&CONFIG!I9&$C9&":"&CONFIG!J9&$C9)) -> 4 | G9: =D9*0.35+E9*0.35+F9*0.3 -> 3.3184211 | H9: =IF(G9>4.99,"Exceptional",IF(G9>3.99,"Exceed Expectation",IF(G9>=2.99,"Meet Expectation",IF(G9>1.9,"Below Expectation","Unsatisfactory")))) -> Meet Expectation
A10: =CONFIG!A10 -> 9 | B10: =CONFIG!B10 -> Ciptadra Softindo - Pemeliharaan Axits & DMTM | C10: =MATCH($B10,INDIRECT("'"&CONFIG!D10&"'!$F:$F"),0) -> 10 | D10: =AVERAGE(INDIRECT("'"&CONFIG!D10&"'!"&CONFIG!E10&$C10&":"&CONFIG!F10&$C10)) -> 4 | E10: =AVERAGE(INDIRECT("'"&CONFIG!D10&"'!"&CONFIG!G10&$C10&":"&CONFIG!H10&$C10)) -> 4 | F10: =AVERAGE(INDIRECT("'"&CONFIG!D10&"'!"&CONFIG!I10&$C10&":"&CONFIG!J10&$C10)) -> 4 | G10: =D10*0.35+E10*0.35+F10*0.3 -> 4 | H10: =IF(G10>4.99,"Exceptional",IF(G10>3.99,"Exceed Expectation",IF(G10>=2.99,"Meet Expectation",IF(G10>1.9,"Below Expectation","Unsatisfactory")))) -> Exceed Expectation
A11: =CONFIG!A11 -> 10 | B11: =CONFIG!B11 -> Target Sukses Sinergi - Email Marketing Automation | C11: =MATCH($B11,INDIRECT("'"&CONFIG!D11&"'!$F:$F"),0) -> 11 | D11: =AVERAGE(INDIRECT("'"&CONFIG!D11&"'!"&CONFIG!E11&$C11&":"&CONFIG!F11&$C11)) -> 3.7142857 | E11: =AVERAGE(INDIRECT("'"&CONFIG!D11&"'!"&CONFIG!G11&$C11&":"&CONFIG!H11&$C11)) -> 4 | F11: =AVERAGE(INDIRECT("'"&CONFIG!D11&"'!"&CONFIG!I11&$C11&":"&CONFIG!J11&$C11)) -> 4 | G11: =D11*0.35+E11*0.35+F11*0.3 -> 3.9 | H11: =IF(G11>4.99,"Exceptional",IF(G11>3.99,"Exceed Expectation",IF(G11>=2.99,"Meet Expectation",IF(G11>1.9,"Below Expectation","Unsatisfactory")))) -> Meet Expectation
A12: =CONFIG!A12 -> 11 | B12: =CONFIG!B12 -> Inmotion Inovasi Teknologi - Jasa Aplikasi Chatbot dan Live Chat | C12: =MATCH($B12,INDIRECT("'"&CONFIG!D12&"'!$F:$F"),0) -> 12 | D12: =AVERAGE(INDIRECT("'"&CONFIG!D12&"'!"&CONFIG!E12&$C12&":"&CONFIG!F12&$C12)) -> 4 | E12: =AVERAGE(INDIRECT("'"&CONFIG!D12&"'!"&CONFIG!G12&$C12&":"&CONFIG!H12&$C12)) -> 4 | F12: =AVERAGE(INDIRECT("'"&CONFIG!D12&"'!"&CONFIG!I12&$C12&":"&CONFIG!J12&$C12)) -> 4 | G12: =D12*0.35+E12*0.35+F12*0.3 -> 4 | H12: =IF(G12>4.99,"Exceptional",IF(G12>3.99,"Exceed Expectation",IF(G12>=2.99,"Meet Expectation",IF(G12>1.9,"Below Expectation","Unsatisfactory")))) -> Exceed Expectation
A13: =CONFIG!A13 -> 12 | B13: =CONFIG!B13 -> Mitra Integrasi Informatika - SFDC Maintenance | C13: =MATCH($B13,INDIRECT("'"&CONFIG!D13&"'!$F:$F"),0) -> 13 | D13: =AVERAGE(INDIRECT("'"&CONFIG!D13&"'!"&CONFIG!E13&$C13&":"&CONFIG!F13&$C13)) -> 4.8461538 | E13: =AVERAGE(INDIRECT("'"&CONFIG!D13&"'!"&CONFIG!G13&$C13&":"&CONFIG!H13&$C13)) -> 4.6666667 | F13: =AVERAGE(INDIRECT("'"&CONFIG!D13&"'!"&CONFIG!I13&$C13&":"&CONFIG!J13&$C13)) -> 5 | G13: =D13*0.35+E13*0.35+F13*0.3 -> 4.8294872 | H13: =IF(G13>4.99,"Exceptional",IF(G13>3.99,"Exceed Expectation",IF(G13>=2.99,"Meet Expectation",IF(G13>1.9,"Below Expectation","Unsatisfactory")))) -> Exceed Expectation
... A19: =CONFIG!A19 -> 18 | B19: =CONFIG!B19 -> Karya Putra Surya Gemilang - Telemarketing Revamp Project | C19: =MATCH($B19,INDIRECT("'"&CONFIG!D19&"'!$F:$F"),0) -> 7 | D19: =AVERAGE(INDIRECT("'"&CONFIG!D19&"'!"&CONFIG!E19&$C19&":"&CONFIG!F19&$C19)) -> 3.0909091 | E19: =AVERAGE(INDIRECT("'"&CONFIG!D19&"'!"&CONFIG!G19&$C19&":"&CONFIG!H19&$C19)) -> 3 | F19: =AVERAGE(INDIRECT("'"&CONFIG!D19&"'!"&CONFIG!I19&$C19&":"&CONFIG!J19&$C19)) -> 3 | G19: =D19*0.35+E19*0.35+F19*0.3 -> 3.0318182 | H19: =IF(G19>4.99,"Exceptional",IF(G19>3.99,"Exceed Expectation",IF(G19>=2.99,"Meet Expectation",IF(G19>1.9,"Below Expectation","Unsatisfactory")))) -> Meet Expectation

Sheet RESULT
A1: No | B1: Supplier Name | C1: Service | D1: PIC (User) | E1: Total Score | F1: Status | G1: Remarks (dari User) | H1: DD Result (by User) - Auto | I1: Assessment Result (by SRM) - Manual Input | J1: Repetition Below Expectation - Manual Input | K1: Helper: Below Expectation/Unsatisfactory Name
A2: ='SCORE CALC'!A2 -> 1 | B2: =TRIM(LEFT(CONFIG!B2,FIND(" - ",CONFIG!B2)-1)) -> Itsec Asia | C2: =TRIM(MID(CONFIG!B2,FIND(" - ",CONFIG!B2)+3,255)) -> Penetration Testing | D2: =CONFIG!C2 -> fauzi.aryanto@axa-mandiri.co.id | E2: ='SCORE CALC'!G2 -> 3 | F2: ='SCORE CALC'!H2 -> Meet Expectation | G2: =INDIRECT("'"&CONFIG!D2&"'!"&CONFIG!K2&'SCORE CALC'!C2) -> Currently no need improvement | H2: ="Financial Assessment: "&INDIRECT("'"&CONFIG!D2&"'!"&CONFIG!L2&'SCORE CALC'!C2)&CHAR(10)&"Reputational Assessment: "&INDIRECT("'"&CONFIG!D2&"'!"&CONFIG!M2&'SCORE CALC'!C2)&CHAR(10)&"DPIA: "&INDIRECT("'"&CONFIG!D2&"'!"&CONFIG!N2&'SCORE CALC'!C2)&CHAR(10)&"DPSQ: "&INDIRECT("'"&CONFIG!D2&"'!"&CONFIG!O2&'SCORE CALC'!C2)&CHAR(10)&"VSDDT: "&INDIRECT("'"&CONFIG!D2&"'!"&CONFIG!P2&'SCORE CALC'!C2)&CHAR(10)&"Action Plan: "&INDIRECT("'"&CONFIG!D2&"'!"&CONFIG!Q2&'SCORE CALC'!C2) -> Financial Assessment: Yes Reputational Assessment: Yes DPIA: Not required – DPIA is not applicable for this service DPSQ: Not required – DPSQ is not applicable for this service VSDDT: Required – VSDDT completed and approved Action Plan: Yes – All action items have been completed and coordinated with relevant SME | K2: =IF(OR(F2="Below Expectation",F2="Unsatisfactory"),B2&" - "&C2,"")
A3: ='SCORE CALC'!A3 -> 2 | B3: =TRIM(LEFT(CONFIG!B3,FIND(" - ",CONFIG!B3)-1)) -> Iproteksi Telematika | C3: =TRIM(MID(CONFIG!B3,FIND(" - ",CONFIG!B3)+3,255)) -> Penetration Testing | D3: =CONFIG!C3 -> fauzi.aryanto@axa-mandiri.co.id | E3: ='SCORE CALC'!G3 -> 4 | F3: ='SCORE CALC'!H3 -> Exceed Expectation | G3: =INDIRECT("'"&CONFIG!D3&"'!"&CONFIG!K3&'SCORE CALC'!C3) -> no need improvement | H3: ="Financial Assessment: "&INDIRECT("'"&CONFIG!D3&"'!"&CONFIG!L3&'SCORE CALC'!C3)&CHAR(10)&"Reputational Assessment: "&INDIRECT("'"&CONFIG!D3&"'!"&CONFIG!M3&'SCORE CALC'!C3)&CHAR(10)&"DPIA: "&INDIRECT("'"&CONFIG!D3&"'!"&CONFIG!N3&'SCORE CALC'!C3)&CHAR(10)&"DPSQ: "&INDIRECT("'"&CONFIG!D3&"'!"&CONFIG!O3&'SCORE CALC'!C3)&CHAR(10)&"VSDDT: "&INDIRECT("'"&CONFIG!D3&"'!"&CONFIG!P3&'SCORE CALC'!C3)&CHAR(10)&"Action Plan: "&INDIRECT("'"&CONFIG!D3&"'!"&CONFIG!Q3&'SCORE CALC'!C3) -> Financial Assessment: Yes Reputational Assessment: Yes DPIA: Not required – DPIA is not applicable for this service DPSQ: Not required – DPSQ is not applicable for this service VSDDT: Required – VSDDT completed and approved Action Plan: Yes – All action items have been completed and coordinated with relevant SME | K3: =IF(OR(F3="Below Expectation",F3="Unsatisfactory"),B3&" - "&C3,"")
A4: ='SCORE CALC'!A4 -> 3 | B4: =TRIM(LEFT(CONFIG!B4,FIND(" - ",CONFIG!B4)-1)) -> FPT Metrodata | C4: =TRIM(MID(CONFIG!B4,FIND(" - ",CONFIG!B4)+3,255)) -> Penetration Testing | D4: =CONFIG!C4 -> fauzi.aryanto@axa-mandiri.co.id | E4: ='SCORE CALC'!G4 -> 3 | F4: ='SCORE CALC'!H4 -> Meet Expectation | G4: =INDIRECT("'"&CONFIG!D4&"'!"&CONFIG!K4&'SCORE CALC'!C4) -> No need improvement | H4: ="Financial Assessment: "&INDIRECT("'"&CONFIG!D4&"'!"&CONFIG!L4&'SCORE CALC'!C4)&CHAR(10)&"Reputational Assessment: "&INDIRECT("'"&CONFIG!D4&"'!"&CONFIG!M4&'SCORE CALC'!C4)&CHAR(10)&"DPIA: "&INDIRECT("'"&CONFIG!D4&"'!"&CONFIG!N4&'SCORE CALC'!C4)&CHAR(10)&"DPSQ: "&INDIRECT("'"&CONFIG!D4&"'!"&CONFIG!O4&'SCORE CALC'!C4)&CHAR(10)&"VSDDT: "&INDIRECT("'"&CONFIG!D4&"'!"&CONFIG!P4&'SCORE CALC'!C4)&CHAR(10)&"Action Plan: "&INDIRECT("'"&CONFIG!D4&"'!"&CONFIG!Q4&'SCORE CALC'!C4) -> Financial Assessment: Yes Reputational Assessment: Yes DPIA: Not required – DPIA is not applicable for this service DPSQ: Not required – DPSQ is not applicable for this service VSDDT: Required – VSDDT completed and approved Action Plan: Yes – All action items have been completed and coordinated with relevant SME | K4: =IF(OR(F4="Below Expectation",F4="Unsatisfactory"),B4&" - "&C4,"")
A5: ='SCORE CALC'!A5 -> 4 | B5: =TRIM(LEFT(CONFIG!B5,FIND(" - ",CONFIG!B5)-1)) -> Satria Antaran Prima | C5: =TRIM(MID(CONFIG!B5,FIND(" - ",CONFIG!B5)+3,255)) -> Mailing Room | D5: =CONFIG!C5 -> ibnu.kumala@axa-mandiri.co.id | E5: ='SCORE CALC'!G5 -> 3.4041667 | F5: ='SCORE CALC'!H5 -> Meet Expectation | G5: =INDIRECT("'"&CONFIG!D5&"'!"&CONFIG!K5&'SCORE CALC'!C5) -> Over all mailing ok, please improve coordinated with Headoffice team for reduce complain/misscomm (ex case overseas shipment ) | H5: ="Financial Assessment: "&INDIRECT("'"&CONFIG!D5&"'!"&CONFIG!L5&'SCORE CALC'!C5)&CHAR(10)&"Reputational Assessment: "&INDIRECT("'"&CONFIG!D5&"'!"&CONFIG!M5&'SCORE CALC'!C5)&CHAR(10)&"DPIA: "&INDIRECT("'"&CONFIG!D5&"'!"&CONFIG!N5&'SCORE CALC'!C5)&CHAR(10)&"DPSQ: "&INDIRECT("'"&CONFIG!D5&"'!"&CONFIG!O5&'SCORE CALC'!C5)&CHAR(10)&"VSDDT: "&INDIRECT("'"&CONFIG!D5&"'!"&CONFIG!P5&'SCORE CALC'!C5)&CHAR(10)&"Action Plan: "&INDIRECT("'"&CONFIG!D5&"'!"&CONFIG!Q5&'SCORE CALC'!C5) -> Financial Assessment: Yes Reputational Assessment: Yes DPIA: Required – DPIA completed and approved DPSQ: Not required – DPSQ is not applicable for this service VSDDT: Required – VSDDT completed and approved Action Plan: Yes – All action items have been completed and coordinated with relevant SME | K5: =IF(OR(F5="Below Expectation",F5="Unsatisfactory"),B5&" - "&C5,"")
A6: ='SCORE CALC'!A6 -> 5 | B6: =TRIM(LEFT(CONFIG!B6,FIND(" - ",CONFIG!B6)-1)) -> Informasi Teknologi Indonesia | C6: =TRIM(MID(CONFIG!B6,FIND(" - ",CONFIG!B6)+3,255)) -> SMS Broadcast | D6: =CONFIG!C6 -> fifin.sarinurlita@axa-mandiri.co.id | E6: ='SCORE CALC'!G6 -> 3 | F6: ='SCORE CALC'!H6 -> Meet Expectation | G6: =INDIRECT("'"&CONFIG!D6&"'!"&CONFIG!K6&'SCORE CALC'!C6) -> Jatis has provided good service throughout this year | H6: ="Financial Assessment: "&INDIRECT("'"&CONFIG!D6&"'!"&CONFIG!L6&'SCORE CALC'!C6)&CHAR(10)&"Reputational Assessment: "&INDIRECT("'"&CONFIG!D6&"'!"&CONFIG!M6&'SCORE CALC'!C6)&CHAR(10)&"DPIA: "&INDIRECT("'"&CONFIG!D6&"'!"&CONFIG!N6&'SCORE CALC'!C6)&CHAR(10)&"DPSQ: "&INDIRECT("'"&CONFIG!D6&"'!"&CONFIG!O6&'SCORE CALC'!C6)&CHAR(10)&"VSDDT: "&INDIRECT("'"&CONFIG!D6&"'!"&CONFIG!P6&'SCORE CALC'!C6)&CHAR(10)&"Action Plan: "&INDIRECT("'"&CONFIG!D6&"'!"&CONFIG!Q6&'SCORE CALC'!C6) -> Financial Assessment: Yes Reputational Assessment: Yes DPIA: Required – DPIA completed and approved DPSQ: Required – DPSQ completed and approved VSDDT: Required – VSDDT completed and approved Action Plan: No – No action items were required | K6: =IF(OR(F6="Below Expectation",F6="Unsatisfactory"),B6&" - "&C6,"")
A7: ='SCORE CALC'!A7 -> 6 | B7: =TRIM(LEFT(CONFIG!B7,FIND(" - ",CONFIG!B7)-1)) -> Satria Antaran Prima | C7: =TRIM(MID(CONFIG!B7,FIND(" - ",CONFIG!B7)+3,255)) -> Courier Service | D7: =CONFIG!C7 -> fifin.sarinurlita@axa-mandiri.co.id | E7: ='SCORE CALC'!G7 -> 3 | F7: ='SCORE CALC'!H7 -> Meet Expectation | G7: =INDIRECT("'"&CONFIG!D7&"'!"&CONFIG!K7&'SCORE CALC'!C7) -> SAP has provided excellent service throughout this year | H7: ="Financial Assessment: "&INDIRECT("'"&CONFIG!D7&"'!"&CONFIG!L7&'SCORE CALC'!C7)&CHAR(10)&"Reputational Assessment: "&INDIRECT("'"&CONFIG!D7&"'!"&CONFIG!M7&'SCORE CALC'!C7)&CHAR(10)&"DPIA: "&INDIRECT("'"&CONFIG!D7&"'!"&CONFIG!N7&'SCORE CALC'!C7)&CHAR(10)&"DPSQ: "&INDIRECT("'"&CONFIG!D7&"'!"&CONFIG!O7&'SCORE CALC'!C7)&CHAR(10)&"VSDDT: "&INDIRECT("'"&CONFIG!D7&"'!"&CONFIG!P7&'SCORE CALC'!C7)&CHAR(10)&"Action Plan: "&INDIRECT("'"&CONFIG!D7&"'!"&CONFIG!Q7&'SCORE CALC'!C7) -> Financial Assessment: Yes Reputational Assessment: Yes DPIA: Required – DPIA completed and approved DPSQ: Required – DPSQ completed and approved VSDDT: Required – VSDDT completed and approved Action Plan: Yes – Action items identified, but follow‑up and coordination with relevant SME is still required | K7: =IF(OR(F7="Below Expectation",F7="Unsatisfactory"),B7&" - "&C7,"")
A8: ='SCORE CALC'!A8 -> 7 | B8: =TRIM(LEFT(CONFIG!B8,FIND(" - ",CONFIG!B8)-1)) -> Multifiling Mitra Indonesia | C8: =TRIM(MID(CONFIG!B8,FIND(" - ",CONFIG!B8)+3,255)) -> Record Management Service | D8: =CONFIG!C8 -> ibnu.kumala@axa-mandiri.co.id | E8: ='SCORE CALC'!G8 -> 3.0318182 | F8: ='SCORE CALC'!H8 -> Meet Expectation | G8: =INDIRECT("'"&CONFIG!D8&"'!"&CONFIG!K8&'SCORE CALC'!C8) -> impprove innovation dan simplyfy process | H8: ="Financial Assessment: "&INDIRECT("'"&CONFIG!D8&"'!"&CONFIG!L8&'SCORE CALC'!C8)&CHAR(10)&"Reputational Assessment: "&INDIRECT("'"&CONFIG!D8&"'!"&CONFIG!M8&'SCORE CALC'!C8)&CHAR(10)&"DPIA: "&INDIRECT("'"&CONFIG!D8&"'!"&CONFIG!N8&'SCORE CALC'!C8)&CHAR(10)&"DPSQ: "&INDIRECT("'"&CONFIG!D8&"'!"&CONFIG!O8&'SCORE CALC'!C8)&CHAR(10)&"VSDDT: "&INDIRECT("'"&CONFIG!D8&"'!"&CONFIG!P8&'SCORE CALC'!C8)&CHAR(10)&"Action Plan: "&INDIRECT("'"&CONFIG!D8&"'!"&CONFIG!Q8&'SCORE CALC'!C8) -> Financial Assessment: Yes Reputational Assessment: Yes DPIA: Required – DPIA completed and approved DPSQ: Required – DPSQ completed and approved VSDDT: Required – VSDDT completed and approved Action Plan: Yes – All action items have been completed and coordinated with relevant SME | K8: =IF(OR(F8="Below Expectation",F8="Unsatisfactory"),B8&" - "&C8,"")
A9: ='SCORE CALC'!A9 -> 8 | B9: =TRIM(LEFT(CONFIG!B9,FIND(" - ",CONFIG!B9)-1)) -> Indosat | C9: =TRIM(MID(CONFIG!B9,FIND(" - ",CONFIG!B9)+3,255)) -> Layanan PBX berbasiskan cloud dengan Teknologi SIP Trunk | D9: =CONFIG!C9 -> nuril.hudha@axa-mandiri.co.id | E9: ='SCORE CALC'!G9 -> 3.3184211 | F9: ='SCORE CALC'!H9 -> Meet Expectation | G9: =INDIRECT("'"&CONFIG!D9&"'!"&CONFIG!K9&'SCORE CALC'!C9) -> The performance is getting better, please keep improve the performance. | H9: ="Financial Assessment: "&INDIRECT("'"&CONFIG!D9&"'!"&CONFIG!L9&'SCORE CALC'!C9)&CHAR(10)&"Reputational Assessment: "&INDIRECT("'"&CONFIG!D9&"'!"&CONFIG!M9&'SCORE CALC'!C9)&CHAR(10)&"DPIA: "&INDIRECT("'"&CONFIG!D9&"'!"&CONFIG!N9&'SCORE CALC'!C9)&CHAR(10)&"DPSQ: "&INDIRECT("'"&CONFIG!D9&"'!"&CONFIG!O9&'SCORE CALC'!C9)&CHAR(10)&"VSDDT: "&INDIRECT("'"&CONFIG!D9&"'!"&CONFIG!P9&'SCORE CALC'!C9)&CHAR(10)&"Action Plan: "&INDIRECT("'"&CONFIG!D9&"'!"&CONFIG!Q9&'SCORE CALC'!C9) -> Financial Assessment: No Reputational Assessment: Yes DPIA: Required – DPIA completed and approved DPSQ: Not required – DPSQ is not applicable for this service VSDDT: Required – VSDDT completed and approved Action Plan: Yes – Action items identified, but follow‑up and coordination with relevant SME is still required | K9: =IF(OR(F9="Below Expectation",F9="Unsatisfactory"),B9&" - "&C9,"")
A10: ='SCORE CALC'!A10 -> 9 | B10: =TRIM(LEFT(CONFIG!B10,FIND(" - ",CONFIG!B10)-1)) -> Ciptadra Softindo | C10: =TRIM(MID(CONFIG!B10,FIND(" - ",CONFIG!B10)+3,255)) -> Pemeliharaan Axits & DMTM | D10: =CONFIG!C10 -> raninta.mahardi@axa-mandiri.co.id | E10: ='SCORE CALC'!G10 -> 4 | F10: ='SCORE CALC'!H10 -> Exceed Expectation | G10: =INDIRECT("'"&CONFIG!D10&"'!"&CONFIG!K10&'SCORE CALC'!C10) -> Performance is Good | H10: ="Financial Assessment: "&INDIRECT("'"&CONFIG!D10&"'!"&CONFIG!L10&'SCORE CALC'!C10)&CHAR(10)&"Reputational Assessment: "&INDIRECT("'"&CONFIG!D10&"'!"&CONFIG!M10&'SCORE CALC'!C10)&CHAR(10)&"DPIA: "&INDIRECT("'"&CONFIG!D10&"'!"&CONFIG!N10&'SCORE CALC'!C10)&CHAR(10)&"DPSQ: "&INDIRECT("'"&CONFIG!D10&"'!"&CONFIG!O10&'SCORE CALC'!C10)&CHAR(10)&"VSDDT: "&INDIRECT("'"&CONFIG!D10&"'!"&CONFIG!P10&'SCORE CALC'!C10)&CHAR(10)&"Action Plan: "&INDIRECT("'"&CONFIG!D10&"'!"&CONFIG!Q10&'SCORE CALC'!C10) -> Financial Assessment: Yes Reputational Assessment: Yes DPIA: Required – DPIA completed and approved DPSQ: Required – DPSQ completed and approved VSDDT: Required – VSDDT completed and approved Action Plan: Yes – All action items have been completed and coordinated with relevant SME | K10: =IF(OR(F10="Below Expectation",F10="Unsatisfactory"),B10&" - "&C10,"")
A11: ='SCORE CALC'!A11 -> 10 | B11: =TRIM(LEFT(CONFIG!B11,FIND(" - ",CONFIG!B11)-1)) -> Target Sukses Sinergi | C11: =TRIM(MID(CONFIG!B11,FIND(" - ",CONFIG!B11)+3,255)) -> Email Marketing Automation | D11: =CONFIG!C11 -> bella.depari@axa-mandiri.co.id | E11: ='SCORE CALC'!G11 -> 3.9 | F11: ='SCORE CALC'!H11 -> Meet Expectation | G11: =INDIRECT("'"&CONFIG!D11&"'!"&CONFIG!K11&'SCORE CALC'!C11) -> Harganya buat next contrac please murahin ya | H11: ="Financial Assessment: "&INDIRECT("'"&CONFIG!D11&"'!"&CONFIG!L11&'SCORE CALC'!C11)&CHAR(10)&"Reputational Assessment: "&INDIRECT("'"&CONFIG!D11&"'!"&CONFIG!M11&'SCORE CALC'!C11)&CHAR(10)&"DPIA: "&INDIRECT("'"&CONFIG!D11&"'!"&CONFIG!N11&'SCORE CALC'!C11)&CHAR(10)&"DPSQ: "&INDIRECT("'"&CONFIG!D11&"'!"&CONFIG!O11&'SCORE CALC'!C11)&CHAR(10)&"VSDDT: "&INDIRECT("'"&CONFIG!D11&"'!"&CONFIG!P11&'SCORE CALC'!C11)&CHAR(10)&"Action Plan: "&INDIRECT("'"&CONFIG!D11&"'!"&CONFIG!Q11&'SCORE CALC'!C11) -> Financial Assessment: Yes Reputational Assessment: Yes DPIA: Required – DPIA completed and approved DPSQ: Required – DPSQ completed and approved VSDDT: Required – VSDDT completed and approved Action Plan: Yes – All action items have been completed and coordinated with relevant SME | K11: =IF(OR(F11="Below Expectation",F11="Unsatisfactory"),B11&" - "&C11,"")
A12: ='SCORE CALC'!A12 -> 11 | B12: =TRIM(LEFT(CONFIG!B12,FIND(" - ",CONFIG!B12)-1)) -> Inmotion Inovasi Teknologi | C12: =TRIM(MID(CONFIG!B12,FIND(" - ",CONFIG!B12)+3,255)) -> Jasa Aplikasi Chatbot dan Live Chat | D12: =CONFIG!C12 -> djoko.djoko@axa-mandiri.co.id | E12: ='SCORE CALC'!G12 -> 4 | F12: ='SCORE CALC'!H12 -> Exceed Expectation | G12: =INDIRECT("'"&CONFIG!D12&"'!"&CONFIG!K12&'SCORE CALC'!C12) -> continue performing thorough and frequent periodic checks to ensure that during service hours, there are no issues that could disrupt operations and resolve the remaining unresolved 401 issue Berikan umpan balik Anda tentang BizChat | H12: ="Financial Assessment: "&INDIRECT("'"&CONFIG!D12&"'!"&CONFIG!L12&'SCORE CALC'!C12)&CHAR(10)&"Reputational Assessment: "&INDIRECT("'"&CONFIG!D12&"'!"&CONFIG!M12&'SCORE CALC'!C12)&CHAR(10)&"DPIA: "&INDIRECT("'"&CONFIG!D12&"'!"&CONFIG!N12&'SCORE CALC'!C12)&CHAR(10)&"DPSQ: "&INDIRECT("'"&CONFIG!D12&"'!"&CONFIG!O12&'SCORE CALC'!C12)&CHAR(10)&"VSDDT: "&INDIRECT("'"&CONFIG!D12&"'!"&CONFIG!P12&'SCORE CALC'!C12)&CHAR(10)&"Action Plan: "&INDIRECT("'"&CONFIG!D12&"'!"&CONFIG!Q12&'SCORE CALC'!C12) -> Financial Assessment: Yes Reputational Assessment: Yes DPIA: Required – DPIA completed and approved DPSQ: Required – DPSQ not yet completed or approved VSDDT: Required – VSDDT completed and approved Action Plan: Yes – All action items have been completed and coordinated with relevant SME | K12: =IF(OR(F12="Below Expectation",F12="Unsatisfactory"),B12&" - "&C12,"")
A13: ='SCORE CALC'!A13 -> 12 | B13: =TRIM(LEFT(CONFIG!B13,FIND(" - ",CONFIG!B13)-1)) -> Mitra Integrasi Informatika | C13: =TRIM(MID(CONFIG!B13,FIND(" - ",CONFIG!B13)+3,255)) -> SFDC Maintenance | D13: =CONFIG!C13 -> chandra.putra@axa-mandiri.co.id | E13: ='SCORE CALC'!G13 -> 4.8294872 | F13: ='SCORE CALC'!H13 -> Exceed Expectation | G13: =INDIRECT("'"&CONFIG!D13&"'!"&CONFIG!K13&'SCORE CALC'!C13) -> verall, the level of support has been satisfactory. The improvements carried out were highly effective, and several demands were consistent with the initial assessment and expectations. | H13: ="Financial Assessment: "&INDIRECT("'"&CONFIG!D13&"'!"&CONFIG!L13&'SCORE CALC'!C13)&CHAR(10)&"Reputational Assessment: "&INDIRECT("'"&CONFIG!D13&"'!"&CONFIG!M13&'SCORE CALC'!C13)&CHAR(10)&"DPIA: "&INDIRECT("'"&CONFIG!D13&"'!"&CONFIG!N13&'SCORE CALC'!C13)&CHAR(10)&"DPSQ: "&INDIRECT("'"&CONFIG!D13&"'!"&CONFIG!O13&'SCORE CALC'!C13)&CHAR(10)&"VSDDT: "&INDIRECT("'"&CONFIG!D13&"'!"&CONFIG!P13&'SCORE CALC'!C13)&CHAR(10)&"Action Plan: "&INDIRECT("'"&CONFIG!D13&"'!"&CONFIG!Q13&'SCORE CALC'!C13) -> Financial Assessment: No Reputational Assessment: No DPIA: Not required – DPIA is not applicable for this service DPSQ: Not required – DPSQ is not applicable for this service VSDDT: Required – VSDDT not yet completed or approved Action Plan: No – No action items were required | K13: =IF(OR(F13="Below Expectation",F13="Unsatisfactory"),B13&" - "&C13,"")
... A19: ='SCORE CALC'!A19 -> 18 | B19: =TRIM(LEFT(CONFIG!B19,FIND(" - ",CONFIG!B19)-1)) -> Karya Putra Surya Gemilang | C19: =TRIM(MID(CONFIG!B19,FIND(" - ",CONFIG!B19)+3,255)) -> Telemarketing Revamp Project | D19: =CONFIG!C19 -> reza.resdilana@axa-mandiri.co.id | E19: ='SCORE CALC'!G19 -> 3.0318182 | F19: ='SCORE CALC'!H19 -> Meet Expectation | G19: =INDIRECT("'"&CONFIG!D19&"'!"&CONFIG!K19&'SCORE CALC'!C19) -> Diharapkan untuk tim project yang diassign apabila CR sudah di signoff agar availibility dari resource ready | H19: ="Financial Assessment: "&INDIRECT("'"&CONFIG!D19&"'!"&CONFIG!L19&'SCORE CALC'!C19)&CHAR(10)&"Reputational Assessment: "&INDIRECT("'"&CONFIG!D19&"'!"&CONFIG!M19&'SCORE CALC'!C19)&CHAR(10)&"DPIA: "&INDIRECT("'"&CONFIG!D19&"'!"&CONFIG!N19&'SCORE CALC'!C19)&CHAR(10)&"DPSQ: "&INDIRECT("'"&CONFIG!D19&"'!"&CONFIG!O19&'SCORE CALC'!C19)&CHAR(10)&"VSDDT: "&INDIRECT("'"&CONFIG!D19&"'!"&CONFIG!P19&'SCORE CALC'!C19)&CHAR(10)&"Action Plan: "&INDIRECT("'"&CONFIG!D19&"'!"&CONFIG!Q19&'SCORE CALC'!C19) -> Financial Assessment: Yes Reputational Assessment: Yes DPIA: Required – DPIA completed and approved DPSQ: Required – DPSQ not yet completed or approved VSDDT: Required – VSDDT completed and approved Action Plan: Yes – All action items have been completed and coordinated with relevant SME | K19: =IF(OR(F19="Below Expectation",F19="Unsatisfactory"),B19&" - "&C19,"")

Sheet RAW DATA Q1 - 1
A1: Start time | B1: Completion time | C1: Email | D1: Name | E1: User Name | F1: Supplier and Service | G1: How would you rate Supplier's ability to understand and meet your needs? | H1: How would you rate the Quality of fulfillment of specifications required by Perfect Assistant? | I1: How would you rate the data model of source of leads on customer level, which contains Existing Customers, Potential Customers, and Hot Leads? | J1: How would you rate the Leads activity evidence and result details, such as Call, Appointment, Visit, and Closing result evidence? | K1: How would you rate the Sales Activity Management process, as tracked by the Sales Leader and sorted by time range? | L1: How would you rate the Notification to Sales Team which consist of: | M1: How would you rate the telephony features which enable to mask either/both Customers’ and Agents’ personal phone number for better customer service and better protection of Customers’ privacy? | N1: How would you rate the assignment features which enable leaders to re-assign the leads to other FA (e.g. FA resigned or move to other branch then the Leads will be assigned to existing FA)? | O1: How would you rate the System Availability, Redundancy, and Overload Protection? | P1: How would you rate the Security Access? | Q1: How would you rate the Audit Trail? | R1: How would you rate the Overall Supplier's reports including Report of Leads activity record and tracking? | S1: How would you rate the Resources / Authorized Personel Commitment and Qualification? | T1: How would you rate supplier initiative to take mitigation/preventive action to prevent recurring problem? | U1: How would you rate supplier compliance with administrative processes, including completion of draft cooperation contract? | V1: How would you rate the Integration with Perfect Assistant? | W1: How would you rate the SIT dan UAT Phase? | X1: How would you rate the use of channels to avoid customer data leaks? | Y1: How would you rate the Access to the recording dashboard? | Z1: How would you rate the Security compare to its standard? | AA1: How would you rate Supplier's ability to understand and meet your needs?1 | AB1: How would you rate the goods/services provided by the Supplier against the agreed standards? | AC1: How would you rate the accuracy of the data in the Supplier's reports? | AD1: How would you rate overall quality of the work reports provided by the Supplier? | AE1: How would you rate the solutions provided when there is trouble? | AF1: How would you rate the resolution to the problem that occurred? | AG1: How would you rate the speed of resolution given to problems that occur? | AH1: How would you rate the supplier initiative to take mitigation/preventive action to prevent the problem from recurring? | AI1: How would you rate supplier compliance with administrative processes, including completion of draft cooperation contract?1 | AJ1: How would you rate the Implementation of UAT? | AK1: How would you rate the maintenance includes bug fixing and support for system problems that occur in the JATIS MOBILE application/service? | AL1: How would you rate Supplier's ability to understand and meet your needs?2 | AM1: How would you rate the The goods/services provided by the Supplier against the agreed standards? | AN1: How would you rate the General support and maintenance requirement? | AO1: How would you rate the Performance Management Requirement which includes to support low latency, documentation, performance monitoring, and any major or minor updates? | AP1: How would you rate the Security Management Requirement? | AQ1: How would you rate the Supporting Model which includes onsite support from dedicated engineers and its service level agreement (SLA)? | AR1: How would you rate the accuracy of the data in the Supplier's reports?1 | AS1: How would you rate overall quality of the work reports provided by the Supplier?1 | AT1: How would you rate the solutions provided when there is trouble?1 | AU1: How would you rate the resolution to the problem that occurred?1 | AV1: How would you rate the speed of resolution given to problems that occur?1 | AW1: How would you rate the supplier initiative to take mitigation/preventive action to prevent the problem from recurring?1 | AX1: How would you rate supplier compliance with administrative processes, including completion of draft cooperation contract?2 | AY1: How would you rate The goods/services provided by the Supplier against the agreed standards | AZ1: How would you rate the supplier's services? | BA1: How would you rate the supplier's service in providing a guarantee of administrative services for archive management, computer data collection for all AXA cartons, and ease of access for AXA to the ar | BB1: How would you rate the supplier's service in providing the required number of empty cartons? | BC1: How would you rate overall quality of the work reports provided by the Supplier?2 | BD1: How would you rate the completeness report containing the number of AXA cartons deposited in the supplier's warehouse, a list of cartons that are being borrowed (retrieval) and have not been returned | BE1: How would you rate the solutions provided when there is trouble?2 | BF1: How would you rate the resolution to the problem that occurred?2 | BG1: How would you rate the speed of resolution given to problems that occur?2 | BH1: How would you rate the supplier initiative to take mitigation/preventive action to prevent the problem from recurring?2 | BI1: How would you rate supplier compliance with administrative processes, including completion of draft cooperation contract?3 | BJ1: How would you rate the goods/services provided by the Supplier against the agreed standards1 | BK1: How would you rate overall quality of the work reports provided by the Supplier?3 | BL1: How would you rate the solutions provided when there is trouble?3 | BM1: How would you rate the resolution to the problem that occurred?3 | BN1: How would you rate the supplier initiative to take mitigation/preventive action to prevent the problem from recurring?3 | BO1: How would you rate the accuracy of the data in the Supplier's reports?2 | BP1: How would you rate the overall quality of the work reports provided by the Supplier? | BQ1: How would you rate the competence of people provided by the supplier to provide support (understand AXITS and/or DMTM software)? | BR1: How would you rate the supplier support in providing the form of consultation, offsite and onsite support if there is a disruption to application operations? | BS1: How would you rate the supplier support in doing periodic checks once every 3 months to maintain application quality, including application performance checks (profiling) and error log checks? | BT1: How would you rate the supplier support for updating versions of components, frameworks and libraries issued by third parties with prior written approval from AXA if this is possible? | BU1: How would you rate the suppliers support in compliance to security? | BV1: How would you rate the supplier initiative to take mitigation/preventive action to prevent the problem from recurring?4 | BW1: How would you rate supplier compliance with administrative processes, including completion of draft cooperation contract?4 | BX1: How would you rate the goods/services provided by the Supplier against the agreed standards2 | BY1: How would you rate the Customer Interaction Requirement which includes: | BZ1: How would you rate the Case Management which includes: | CA1: How would you rate the Integration process which includes: | CB1: How would you rate the Architectural Requirement? | CC1: How would you rate the Security Requirement? | CD1: How would you rate the Backup and Restore, Capacity and Performance Requirements? | CE1: How would you rate the Operational and Configuration Management? | CF1: How would you rate the accuracy of the data in the Supplier's reports?3 | CG1: How would you rate overall quality of the work reports provided by the Supplier?4 | CH1: How would you rate the solutions provided when there is trouble?4 | CI1: How would you rate the resolution to the problem that occurred?4 | CJ1: How would you rate the speed of resolution given to problems that occur?3 | CK1: How would you rate the supplier initiative to take mitigation/preventive action to prevent the problem from recurring?5 | CL1: How would you rate supplier compliance with administrative processes, including completion of draft cooperation contract?5 | CM1: How would you rate the accuracy of the data in the Supplier's reports?4 | CN1: How would you rate the overall quality of the work reports provided by the Supplier?1 | CO1: How would you rate the performing installation, setup and configuration of 3Dolphins? | CP1: How would you rate the integration of 3Dolphins with SalesForce? | CQ1: How would you rate the Chatbot Corpus with data provided by AXA? | CR1: How would you rate the supplier's services in providing 3Dolphins Solutions as stated in the Functional Specification Document (FSD) and Technical Specification Document (TSD)? | CS1: How would you rate the supplier's services in conducting System Integration Test (SIT) with AXA IT testing team and IT Project Team? | CT1: How would you rate the supplier's services in conducting User Acceptance Test (UAT) with AXA Business Team and Project IT Team? | CU1: How would you rate the supplier's services in migrating to production server or Go Live and providing support after Go Live? | CV1: How would you rate the supplier's services in providing the human resources needed in the project and timeline according to the agreed scope? | CW1: How would you rate the supplier's services in assigning a Project Manager to coordinate with the AXA team? | CX1: How would you rate the supplier's project documentation as follows: | CY1: How would you rate the supplier support in providing the perform maintenance on all software related to 3Dolphins, which is installed in the AXA data center? | CZ1: How would you rate the supplier support in providing 3Dolphins application maintenance service time, namely 24 hours x 7 days a week, 365 days/year? | DA1: How would you rate the supplier support in preparing at least 2 people who understand and are experts in chatbots owned by AXA and can also provide support for services that often occur (eg. New custo | DB1: How would you rate the supplier support in providing support center that can be visited during AXA business hours to respond to any questions and issues that arise? | DC1: How would you rate the supplier support in providing SLA reports to AXA? | DD1: How would you rate the supplier support in providing testing and updates the Chatbot Solution if there is a new software version/release/patch according to the required conditions? | DE1: How would you rate the supplier support in reinstall the 3Dolphins application a maximum of 1 time per year if AXA will upgrade the hardware? | DF1: How would you rate the supplier support in providing a checklist to monitor daily activities? | DG1: How would you rate the supplier support in providing a testing configuration and event logging? | DH1: How would you rate the supplier support in providing a backup for short and long term? | DI1: How would you rate the goods/services provided by the Supplier against the agreed standards3 | DJ1: How would you rate the accuracy of the data in the Supplier's reports?5 | DK1: How would you rate overall quality of the work reports provided by the Supplier?5 | DL1: How would you rate the solutions provided when there is trouble?5 | DM1: How would you rate the resolution to the problem that occurred?5 | DN1: How would you rate the speed of resolution given to problems that occur | DO1: How would you rate the supplier initiative to take mitigation/preventive action to prevent the problem from recurring?6 | DP1: How would you rate supplier compliance with administrative processes, including completion of draft cooperation contract?6 | DQ1: How would you rate the shipping target achievement? | DR1: How would you rate the delivery times? Based on SLA, the delivery time are Monday to Saturday, service levels will remain the same from Monday to Friday. | DS1: How would you rate the Receipt retention period? | DT1: How would you rate the Airway Bill Storage: | DU1: How would you rate the Handling of Policies/Documents and/or delivery process? | DV1: How would you rate the response to complaints/investigations of the delivery process? | DW1: How would you rate the response taken when a delivery failure occurs? | DX1: How would you rate the goods/services provided by the Supplier against the agreed standards?1 | DY1: How would you rate the accuracy of the data in the Supplier's reports?6 | DZ1: How would you rate overall quality of the work reports provided by the Supplier?6 | EA1: How would you rate the solutions provided when there is trouble?6 | EB1: How would you rate the resolution to the problem that occurred?6 | EC1: How would you rate the supplier initiative to take mitigation/preventive action to prevent the problem from recurring?7 | ED1: How would you rate the service provided? | EE1: How would you rate the Complaint Handling? | EF1: How would you rate the service provided?1 | EG1: How would you rate the accuracy of the data in the Supplier's reports?7 | EH1: How would you rate overall quality of the work reports provided by the Supplier?7 | EI1: How would you rate the solutions provided when there is trouble?7 | EJ1: How would you rate the resolution to the problem that occurred?7 | EK1: How would you rate the supplier initiative to take mitigation/preventive action to prevent the problem from recurring?8 | EL1: How would you rate supplier compliance with administrative processes, including completion of draft cooperation contract?7 | EM1: How would you rate the goods/services provided by the Supplier against the agreed standards?2 | EN1: How would you rate overall quality of the work reports provided by the Supplier?8 | EO1: How would you rate the solutions provided when there is trouble?8 | EP1: How would you rate the speed of resolution given to problems that occur?4 | EQ1: How would you rate the Vendor initiative to take mitigation/preventive action to prevent the problem from recurring? | ER1: How would you rate supplier compliance with administrative processes, including completion of draft cooperation contract? | ES1: How would you rate supplier ability to provide manpower according to the required position and job description before the project starts? | ET1: How would you rate the Supplier’s Timelines in replacing manpower? | EU1: How would you rate the Supplier’s ability to conduct training for TSO? | EV1: How would you rate the Supplier’s ability to conduct training for Leader? | EW1: How would you rate the Supplier’s ability to conduct training for Manager? | EX1: How would you rate the Supplier’s ability to ensure employees achieve an A rating on the KPI Dashboard for 3 consecutive months to qualify for promotion? | EY1: How would you rate the Supplier’s ability to enforce demotion for employees who receive a D rating for 3 consecutive months? | EZ1: How would you rate the Supplier’s ability to provide accurate and complete data management as per agreed requirements which is providing leads, mapping, until distribute to TSO? | FA1: How would you rate the Supplier’s ability to ensure connectivity between the telemarketing system and our back end (DMTM) system? | FB1: How would you rate the Supplier’s ability to recommend suitable premise locations and provide photos as required? | FC1: How would you rate the Supplier’s ability to develop and execute Sales Activity & Monitoring which include: | FD1: How would you rate the Technical services that is used to penetrate the application which includes: 1. Technical Specification Design. 2. Hardware and capacity sizing for concurrent requests 3. Functi | FE1: How would you rate the after sales support capability and methodology? | FF1: How would you rate the availability of documentation for service (user manual, troubleshoot document, setup document, etc)? | FG1: How would you rate the Technical services that is used to penetrate the application which includes: 1. Technical Specification Design. 2. Hardware and capacity sizing for concurrent requests 3. Functi1 | FH1: How would you rate the after sales support capability and methodology?1 | FI1: How would you rate the availability of documentation for product (user manual, troubleshoot document, setup document, etc)? | FJ1: How would you rate the Technical services that is used to penetrate the application which includes: 1. Technical Specification Design. 2. Hardware and capacity sizing for concurrent requests 3. Functi2 | FK1: How would you rate the after sales support capability and methodology?2 | FL1: How would you rate the availability of documentation for product (user manual, troubleshoot document, setup document, etc)?1 | FM1: How would you rate the Supplier’s ability to implement the backup plan within 3 hours after system downtime occurs? | FN1: How would you rate the supplier's timeliness in delivering goods/services compared to the agreed-upon timeline? | FO1: How would you rate the supplier's timeliness in sending reports to you? | FP1: How would you rate the supplier's speed ​​of administrative completion, including completion of contracts draft? | FQ1: How would you rate the supplier's timeliness in delivering goods/services compared to the agreed-upon timeline?1 | FR1: How would you rate the supplier's timeliness in sending reports to you? | FS1: How would you rate the supplier's Traffic Confirmation SLA Fulfillment? | FT1: How would you rate the supplier's speed ​​of administrative completion, including completion of contracts draft? | FU1: How would you rate the supplier's timeliness in delivering goods/services compared to the agreed-upon timeline?2 | FV1: How would you rate the supplier's timeliness in sending reports to you? Based on SLA, suppliers must provide reports on the 10th of each month. | FW1: How would you rate the supplier's speed ​​of administrative completion, including completion of contracts draft? 1 | FX1: How would you rate the supplier's SLA Fulfillment? | FY1: How would you rate the Supplier's timeliness in delivering goods/services compared to the agreed-upon timeline?3 | FZ1: How would you reat timeliness of the work reports submitted by the Supplier to you? | GA1: How would you rate the supplier's timeliness in sending reports to you? Based on SLA, support reports should be sent every 3 months on the 10th | GB1: How would you rate the supplier's speed ​​of administrative completion, including completion of contracts draft?1 | GC1: How would you rate the supplier's response time? | GD1: How would you rate the supplier's resolution time? | GE1: How would you rate the supplier's timeliness in delivering goods/services compared to the agreed-upon timeline?4 | GF1: How would you rate the supplier's timeliness in sending reports to you?1 | GG1: How would you rate the supplier's speed ​​of administrative completion, including completion of contracts draft?2 | GH1: How would you rate the supplier's communication with you? | GI1: How would you rate the supplier's PIC's availability to be contacted when needed? | GJ1: How would you rate the supplier's response speed to you when there are issues? | GK1: Has the vendor completed the latest Financial Assessment? | GL1: Has the vendor’s Reputational Assessment been performed? | GM1: Does the services require the fulfillment of Data Privacy Impact Assessment (DPIA)? | GN1: Does the services require the fulfillment of Data Privacy Service Provider Questionnaire assessment (DPSQ)? | GO1: Does the services require the fulfillment of Vendor Security Due Diligence Tooling (VSDDT)? | GP1: Has the Vendor Security Due Diligence Tooling (VSDDT) been completed and approved? | GQ1: Based on the the results (financial, reputational, DPIA, VSDDT, DPSQ), do you have an action plan in place? If yes, has it been completed, and have you coordinated with the relevant SMEs? | GR1: Have all required actions been completed by your team? | GS1: Please provide feedback or suggestion for the supplier, including areas for improvement
A2: 46112.432 | B2: 46112.436 | C2: fauzi.aryanto@axa-mandiri.co.id | D2: Fauzi ARYANTO | E2: Fauzi Aryanto | F2: Itsec Asia - Penetration Testing | FJ2: 3 | FK2: 3 | FL2: 3 | FN2: 3 | FO2: 3 | FP2: 3 | GH2: 3 | GI2: 3 | GJ2: 3 | GK2: Yes | GL2: Yes | GM2: Not required – DPIA is not applicable for this service | GN2: Not required – DPSQ is not applicable for this service | GO2: Required – VSDDT completed and approved | GQ2: Yes – All action items have been completed and coordinated with relevant SME | GS2: Currently no need improvement
A3: 46112.436 | B3: 46112.437 | C3: fauzi.aryanto@axa-mandiri.co.id | D3: Fauzi ARYANTO | E3: Fauzi Aryanto | F3: Iproteksi Telematika - Penetration Testing | FG3: 4 | FH3: 4 | FI3: 4 | FN3: 4 | FO3: 4 | FP3: 4 | GH3: 4 | GI3: 4 | GJ3: 4 | GK3: Yes | GL3: Yes | GM3: Not required – DPIA is not applicable for this service | GN3: Not required – DPSQ is not applicable for this service | GO3: Required – VSDDT completed and approved | GQ3: Yes – All action items have been completed and coordinated with relevant SME | GS3: no need improvement
