Workbook

Sheet README
A1: CRITICAL SUPPLIER PERFORMANCE REVIEW — Q2 2026
A2: File khusus Q2 2026 (terpisah dari file Q1 2026)
A5: 1. ISI FILE INI
A6: • RAW DATA Q2 - 1 / Q2 - 2 — data mentah asli dari Microsoft Forms untuk periode Q2 2026 (jangan diedit, sumber data utama).
A7: • 21 sheet per-vendor (prefix 'Q2 ') — satu sheet per vendor, menampilkan SEMUA pertanyaan & jawaban asli (bukan cuma rata-rata), formula live ke RAW DATA.
A8: • RESULT Q2 — konsolidasi ke-21 vendor tsb + 1 baris untuk Arah Sejahtera Abadi (Kuncit) yang tidak mengisi assessment Q2.
A9: • HISTORICAL — tren skor 2024 s.d. Q2 2026, dengan Score + User Comment + Remarks per kuartal (sesuai format yang sudah baku dipakai sebelumnya, hanya dirapikan tampilannya).
A10: • DASHBOARD — cari vendor via dropdown, langsung muncul skor terkini, status, tren, riwayat performance per kuartal LENGKAP dengan comment-nya, grafik tren, dan tabel ringkasan semua vendor.
A11: • SUMMARY Q2 2026 — ringkasan angka: jumlah vendor dievaluasi, % evaluasi, status keseluruhan.
A13: 2. FILE INI TERPISAH DARI Q1 2026
A14: File 'SUPERMAN_Performance_Review_Q1_2026_REVAMPED.xlsx' yang sebelumnya dibuat adalah pegangan Q1 tersendiri dan TIDAK digabung ke file ini. HISTORICAL di file ini tetap menampilkan tren dari 2024 sampai Q1 2026 sebagai data referensi (angka historis, bukan link langsung ke file Q1), lalu kolom Q2 2026 baru yang formula-nya live ke RESULT Q2 di file ini sendiri.
A16: 3. KLARIFIKASI DARI DISKUSI SEBELUMNYA
... A29: Score > 4.99 → Exceptional | Score > 3.99 → Exceed Expectation | Score >= 2.99 → Meet Expectation | Score > 1.9 → Below Expectation | Score <= 1.9 → Unsatisfactory

Sheet DASHBOARD
A1: DASHBOARD — CRITICAL SUPPLIER PERFORMANCE REVIEW (Q2 2026)
A3: 🔍 Cari Vendor: | C3: INDOSAT - LAYANAN PBX BERBASISKAN CLOUD DENGAN TEKNOLOGI SIP TRUNK | J3: MatchRow
A4: (pilih dari dropdown, atau ketik sebagian nama) | J4: =IFERROR(MATCH($C$3,HISTORICAL!$AF$7:$AF$28,0)+6,"") -> 7
A6: Vendor | B6: Service | C6: PIC Saat Ini | D6: Skor Q2 2026 | E6: Status Q2 2026 | F6: Skor Q1 2026 | G6: Tren vs Q1
A7: =IF($J$4="","",INDEX(HISTORICAL!B:B,$J$4)) -> INDOSAT | B7: =IF($J$4="","",INDEX(HISTORICAL!C:C,$J$4)) -> LAYANAN PBX BERBASISKAN CLOUD DENGAN TEKNOLOGI SIP TRUNK | C7: =IF($J$4="","",IFERROR(INDEX(HISTORICAL!AG:AG,$J$4),"-")) -> Nuril HUDHA | D7: =IF($J$4="","",INDEX(HISTORICAL!AC:AC,$J$4)) -> 3.4394737 | E7: =IF($J$4="","",INDEX(HISTORICAL!AE:AE,$J$4)) -> Meet Expectation | F7: =IF($J$4="","",INDEX(HISTORICAL!Z:Z,$J$4)) -> 3.3184211 | G7: =IF($J$4="","",IF(OR(NOT(ISNUMBER(D7)),NOT(ISNUMBER(F7))),"n/a",IF(D7>F7,"▲ Naik "&TEXT(D7-F7,"0.00"),IF(D7<F7,"▼ Turun "&TEXT(F7-D7,"0.00"),"— Stabil")))) -> ▲ Naik 0.12
A10: RIWAYAT PERFORMANCE PER KUARTAL
A11: Periode | B11: Skor | C11: Status | D11: User Comment / Remarks | I11: ChartVal
A12: 2024 Q1 | B12: =IF($J$4="","",IF(OR(INDEX(HISTORICAL!D:D,$J$4)="N/A",INDEX(HISTORICAL!D:D,$J$4)=0),"-",INDEX(HISTORICAL!D:D,$J$4))) -> 3 | C12: =IF($J$4="","",IF(INDEX(HISTORICAL!E:E,$J$4)="","-",INDEX(HISTORICAL!E:E,$J$4))) -> Meet Expectation | D12: ="(tidak ada data comment terpisah untuk periode ini)" -> (tidak ada data comment terpisah untuk periode ini) | I12: =IFERROR(IF(B12="-",NA(),B12),NA()) -> 3
A13: 2024 Q2 | B13: =IF($J$4="","",IF(OR(INDEX(HISTORICAL!F:F,$J$4)="N/A",INDEX(HISTORICAL!F:F,$J$4)=0),"-",INDEX(HISTORICAL!F:F,$J$4))) -> 3 | C13: =IF($J$4="","",IF(INDEX(HISTORICAL!G:G,$J$4)="","-",INDEX(HISTORICAL!G:G,$J$4))) -> Meet Expectation | D13: ="(tidak ada data comment terpisah untuk periode ini)" -> (tidak ada data comment terpisah untuk periode ini) | I13: =IFERROR(IF(B13="-",NA(),B13),NA()) -> 3
A14: 2024 Q3 | B14: =IF($J$4="","",IF(OR(INDEX(HISTORICAL!H:H,$J$4)="N/A",INDEX(HISTORICAL!H:H,$J$4)=0),"-",INDEX(HISTORICAL!H:H,$J$4))) -> 2.95 | C14: =IF($J$4="","",IF(INDEX(HISTORICAL!I:I,$J$4)="","-",INDEX(HISTORICAL!I:I,$J$4))) -> Below Expectation | D14: ="(tidak ada data comment terpisah untuk periode ini)" -> (tidak ada data comment terpisah untuk periode ini) | I14: =IFERROR(IF(B14="-",NA(),B14),NA()) -> 2.95
A15: 2024 Q4 | B15: =IF($J$4="","",IF(OR(INDEX(HISTORICAL!J:J,$J$4)="N/A",INDEX(HISTORICAL!J:J,$J$4)=0),"-",INDEX(HISTORICAL!J:J,$J$4))) -> 3 | C15: =IF($J$4="","",IF(INDEX(HISTORICAL!K:K,$J$4)="","-",INDEX(HISTORICAL!K:K,$J$4))) -> Meet Expectation | D15: ="(tidak ada data comment terpisah untuk periode ini)" -> (tidak ada data comment terpisah untuk periode ini) | I15: =IFERROR(IF(B15="-",NA(),B15),NA()) -> 3
A16: 2025 Q1 | B16: =IF($J$4="","",IF(OR(INDEX(HISTORICAL!L:L,$J$4)="N/A",INDEX(HISTORICAL!L:L,$J$4)=0),"-",INDEX(HISTORICAL!L:L,$J$4))) -> 2.345 | C16: =IF($J$4="","",IF(INDEX(HISTORICAL!N:N,$J$4)="","-",INDEX(HISTORICAL!N:N,$J$4))) -> Below Expectation | D16: =IF($J$4="","",IF(INDEX(HISTORICAL!M:M,$J$4)="","-",INDEX(HISTORICAL!M:M,$J$4))) -> Need improvement for the part of fair and to be more responsive to solve issues. | I16: =IFERROR(IF(B16="-",NA(),B16),NA()) -> 2.345
A17: 2025 Q2 | B17: =IF($J$4="","",IF(OR(INDEX(HISTORICAL!O:O,$J$4)="N/A",INDEX(HISTORICAL!O:O,$J$4)=0),"-",INDEX(HISTORICAL!O:O,$J$4))) -> 1.99 | C17: =IF($J$4="","",IF(INDEX(HISTORICAL!Q:Q,$J$4)="","-",INDEX(HISTORICAL!Q:Q,$J$4))) -> Below Expectation | D17: =IF($J$4="","",IF(INDEX(HISTORICAL!P:P,$J$4)="","-",INDEX(HISTORICAL!P:P,$J$4))) -> 1. Dashboard access to required user 2. Response time to be improved as promised 3. To be more proactive in update the progress 4. To provide regular report (usage, recording, etc) | I17: =IFERROR(IF(B17="-",NA(),B17),NA()) -> 1.99
A18: 2025 Q3 | B18: =IF($J$4="","",IF(OR(INDEX(HISTORICAL!R:R,$J$4)="N/A",INDEX(HISTORICAL!R:R,$J$4)=0),"-",INDEX(HISTORICAL!R:R,$J$4))) -> 2.72 | C18: =IF($J$4="","",IF(INDEX(HISTORICAL!T:T,$J$4)="","-",INDEX(HISTORICAL!T:T,$J$4))) -> Below Expectation | D18: =IF($J$4="","",IF(INDEX(HISTORICAL!S:S,$J$4)="","-",INDEX(HISTORICAL!S:S,$J$4))) -> improve responsiveness when there is problem appear, and more proactive ask client follow up for the re-solution work or not after fixing. have plan maintenance and communicated earlier to client so client can aware about maintenance process. | I18: =IFERROR(IF(B18="-",NA(),B18),NA()) -> 2.72
A19: 2025 Q4 | B19: =IF($J$4="","",IF(OR(INDEX(HISTORICAL!W:W,$J$4)="N/A",INDEX(HISTORICAL!W:W,$J$4)=0),"-",INDEX(HISTORICAL!W:W,$J$4))) -> 2.9825 | C19: =IF($J$4="","",IF(INDEX(HISTORICAL!Y:Y,$J$4)="","-",INDEX(HISTORICAL!Y:Y,$J$4))) -> BELOW EXPECTATION | D19: =IF($J$4="","",IF(INDEX(HISTORICAL!X:X,$J$4)="","-",INDEX(HISTORICAL!X:X,$J$4))) -> PLEASE KINDLY IMPROVE REQUIRED REPORT DELIVERY AS AGREED WITH ANALYZED DATA FOR BUSINESS CONSIDERATION. | I19: =IFERROR(IF(B19="-",NA(),B19),NA()) -> 2.9825
A20: 2026 Q1 | B20: =IF($J$4="","",IF(OR(INDEX(HISTORICAL!Z:Z,$J$4)="N/A",INDEX(HISTORICAL!Z:Z,$J$4)=0),"-",INDEX(HISTORICAL!Z:Z,$J$4))) -> 3.3184211 | C20: =IF($J$4="","",IF(INDEX(HISTORICAL!AB:AB,$J$4)="","-",INDEX(HISTORICAL!AB:AB,$J$4))) -> MEET EXPECTATION | D20: =IF($J$4="","",IF(INDEX(HISTORICAL!AA:AA,$J$4)="","-",INDEX(HISTORICAL!AA:AA,$J$4))) -> The performance is getting better, please keep improve the performance. | I20: =IFERROR(IF(B20="-",NA(),B20),NA()) -> 3.3184211
A21: 2026 Q2 | B21: =IF($J$4="","",IF(OR(INDEX(HISTORICAL!AC:AC,$J$4)="N/A",INDEX(HISTORICAL!AC:AC,$J$4)=0),"-",INDEX(HISTORICAL!AC:AC,$J$4))) -> 3.4394737 | C21: =IF($J$4="","",IF(INDEX(HISTORICAL!AE:AE,$J$4)="","-",INDEX(HISTORICAL!AE:AE,$J$4))) -> Meet Expectation | D21: =IF($J$4="","",IF(INDEX(HISTORICAL!AD:AD,$J$4)="","-",INDEX(HISTORICAL!AD:AD,$J$4))) -> Vendor performance is generally acceptable and aligns with the expected level of service. While the engagement has been positive overall, improvements are needed in feature enhancement, dashboard capabilities, and the regularity of report updates. Better preparation in deployment and timely reporting would help increase the overall value and effectiveness of the service. | I21: =IFERROR(IF(B21="-",NA(),B21),NA()) -> 3.4394737
A24: RINGKASAN SEMUA VENDOR (Q2 2026)
A25: No | B25: Vendor | C25: Service | D25: Skor Q1 2026 | E25: Skor Q2 2026 | F25: Status Terkini | G25: Tren
A26: 1 | B26: =HISTORICAL!B7 -> INDOSAT | C26: =HISTORICAL!C7 -> LAYANAN PBX BERBASISKAN CLOUD DENGAN TEKNOLOGI SIP TRUNK | D26: =IF(OR(HISTORICAL!Z7="N/A",HISTORICAL!Z7=0),"-",HISTORICAL!Z7) -> 3.3184211 | E26: =IF(HISTORICAL!AC7="N/A","-",HISTORICAL!AC7) -> 3.4394737 | F26: =IF(HISTORICAL!AE7<>"N/A",HISTORICAL!AE7,IF(HISTORICAL!AB7<>"N/A",HISTORICAL!AB7,"N/A")) -> Meet Expectation | G26: =IF(OR(NOT(ISNUMBER(D26)),NOT(ISNUMBER(E26))),"-",IF(E26>D26,"▲",IF(E26<D26,"▼","—"))) -> ▲
A27: 2 | B27: =HISTORICAL!B8 -> INFORMASI TEKNOLOGI INDONESIA | C27: =HISTORICAL!C8 -> PENYEDIAAN JASA SMS BROADCAST DAN JASA SMS PULL; CONNECTIVITY PRIMARY LINK | D27: =IF(OR(HISTORICAL!Z8="N/A",HISTORICAL!Z8=0),"-",HISTORICAL!Z8) -> 3 | E27: =IF(HISTORICAL!AC8="N/A","-",HISTORICAL!AC8) -> 3 | F27: =IF(HISTORICAL!AE8<>"N/A",HISTORICAL!AE8,IF(HISTORICAL!AB8<>"N/A",HISTORICAL!AB8,"N/A")) -> Meet Expectation | G27: =IF(OR(NOT(ISNUMBER(D27)),NOT(ISNUMBER(E27))),"-",IF(E27>D27,"▲",IF(E27<D27,"▼","—"))) -> —
A28: 3 | B28: =HISTORICAL!B9 -> MITRA INTEGRASI INFORMATIKA | C28: =HISTORICAL!C9 -> SFDC MAINTENANCE | D28: =IF(OR(HISTORICAL!Z9="N/A",HISTORICAL!Z9=0),"-",HISTORICAL!Z9) -> 4.8294872 | E28: =IF(HISTORICAL!AC9="N/A","-",HISTORICAL!AC9) -> 4.7487179 | F28: =IF(HISTORICAL!AE9<>"N/A",HISTORICAL!AE9,IF(HISTORICAL!AB9<>"N/A",HISTORICAL!AB9,"N/A")) -> Exceed Expectation | G28: =IF(OR(NOT(ISNUMBER(D28)),NOT(ISNUMBER(E28))),"-",IF(E28>D28,"▲",IF(E28<D28,"▼","—"))) -> ▼
A29: 4 | B29: =HISTORICAL!B10 -> MULTIFILING MITRA INDONESIA | C29: =HISTORICAL!C10 -> RECORD MANAGEMENT SERVICE | D29: =IF(OR(HISTORICAL!Z10="N/A",HISTORICAL!Z10=0),"-",HISTORICAL!Z10) -> 3.0318182 | E29: =IF(HISTORICAL!AC10="N/A","-",HISTORICAL!AC10) -> 3 | F29: =IF(HISTORICAL!AE10<>"N/A",HISTORICAL!AE10,IF(HISTORICAL!AB10<>"N/A",HISTORICAL!AB10,"N/A")) -> Meet Expectation | G29: =IF(OR(NOT(ISNUMBER(D29)),NOT(ISNUMBER(E29))),"-",IF(E29>D29,"▲",IF(E29<D29,"▼","—"))) -> ▼
A30: 5 | B30: =HISTORICAL!B11 -> CIPTADRA SOFTINDO | C30: =HISTORICAL!C11 -> PEMELIHARAAN PERANGKAT LUNAK AXITS DAN PERANGKAT LUNAK DMTM | D30: =IF(OR(HISTORICAL!Z11="N/A",HISTORICAL!Z11=0),"-",HISTORICAL!Z11) -> 4 | E30: =IF(HISTORICAL!AC11="N/A","-",HISTORICAL!AC11) -> 4.3 | F30: =IF(HISTORICAL!AE11<>"N/A",HISTORICAL!AE11,IF(HISTORICAL!AB11<>"N/A",HISTORICAL!AB11,"N/A")) -> Exceed Expectation | G30: =IF(OR(NOT(ISNUMBER(D30)),NOT(ISNUMBER(E30))),"-",IF(E30>D30,"▲",IF(E30<D30,"▼","—"))) -> ▲
A31: 6 | B31: =HISTORICAL!B12 -> INMOTION INOVASI TEKNOLOGI | C31: =HISTORICAL!C12 -> JASA APLIKASI CHATBOT DAN LIVE CHAT | D31: =IF(OR(HISTORICAL!Z12="N/A",HISTORICAL!Z12=0),"-",HISTORICAL!Z12) -> 4 | E31: =IF(HISTORICAL!AC12="N/A","-",HISTORICAL!AC12) -> 4 | F31: =IF(HISTORICAL!AE12<>"N/A",HISTORICAL!AE12,IF(HISTORICAL!AB12<>"N/A",HISTORICAL!AB12,"N/A")) -> Exceed Expectation | G31: =IF(OR(NOT(ISNUMBER(D31)),NOT(ISNUMBER(E31))),"-",IF(E31>D31,"▲",IF(E31<D31,"▼","—"))) -> —
A32: 7 | B32: =HISTORICAL!B13 -> SATRIA ANTARAN PRIMA TBK | C32: =HISTORICAL!C13 -> PENGIRIMAN POLIS DOKUMEN DAN PAKET DALAM NEGERI | D32: =IF(OR(HISTORICAL!Z13="N/A",HISTORICAL!Z13=0),"-",HISTORICAL!Z13) -> 3 | E32: =IF(HISTORICAL!AC13="N/A","-",HISTORICAL!AC13) -> 3.2383333 | F32: =IF(HISTORICAL!AE13<>"N/A",HISTORICAL!AE13,IF(HISTORICAL!AB13<>"N/A",HISTORICAL!AB13,"N/A")) -> Meet Expectation | G32: =IF(OR(NOT(ISNUMBER(D32)),NOT(ISNUMBER(E32))),"-",IF(E32>D32,"▲",IF(E32<D32,"▼","—"))) -> ▲
A33: 8 | B33: =HISTORICAL!B14 -> SATRIA ANTARAN PRIMA TBK | C33: =HISTORICAL!C14 -> MAILING ROOM | D33: =IF(OR(HISTORICAL!Z14="N/A",HISTORICAL!Z14=0),"-",HISTORICAL!Z14) -> 3.4041667 | E33: =IF(HISTORICAL!AC14="N/A","-",HISTORICAL!AC14) -> 3.04375 | F33: =IF(HISTORICAL!AE14<>"N/A",HISTORICAL!AE14,IF(HISTORICAL!AB14<>"N/A",HISTORICAL!AB14,"N/A")) -> Meet Expectation | G33: =IF(OR(NOT(ISNUMBER(D33)),NOT(ISNUMBER(E33))),"-",IF(E33>D33,"▲",IF(E33<D33,"▼","—"))) -> ▼
A34: 9 | B34: =HISTORICAL!B15 -> TARGET SUKSES SINERGI | C34: =HISTORICAL!C15 -> PENGIRIMAN EMAIL MARKETING AUTOMATION | D34: =IF(OR(HISTORICAL!Z15="N/A",HISTORICAL!Z15=0),"-",HISTORICAL!Z15) -> 3.9 | E34: =IF(HISTORICAL!AC15="N/A","-",HISTORICAL!AC15) -> 2.9416667 | F34: =IF(HISTORICAL!AE15<>"N/A",HISTORICAL!AE15,IF(HISTORICAL!AB15<>"N/A",HISTORICAL!AB15,"N/A")) -> Below Expectation | G34: =IF(OR(NOT(ISNUMBER(D34)),NOT(ISNUMBER(E34))),"-",IF(E34>D34,"▲",IF(E34<D34,"▼","—"))) -> ▼
A35: 10 | B35: =HISTORICAL!B16 -> WIZ TECHNOLOGY INDONESIA | C35: =HISTORICAL!C16 -> VOICE BOT REMINDER CALL | D35: =IF(OR(HISTORICAL!Z16="N/A",HISTORICAL!Z16=0),"-",HISTORICAL!Z16) -> - | E35: =IF(HISTORICAL!AC16="N/A","-",HISTORICAL!AC16) -> 3.0875 | F35: =IF(HISTORICAL!AE16<>"N/A",HISTORICAL!AE16,IF(HISTORICAL!AB16<>"N/A",HISTORICAL!AB16,"N/A")) -> Meet Expectation | G35: =IF(OR(NOT(ISNUMBER(D35)),NOT(ISNUMBER(E35))),"-",IF(E35>D35,"▲",IF(E35<D35,"▼","—"))) -> -
A36: 11 | B36: =HISTORICAL!B17 -> KARYAPUTRA SURYAGEMILANG | C36: =HISTORICAL!C17 -> TELEMARKETING REVAMP PROJECT | D36: =IF(OR(HISTORICAL!Z17="N/A",HISTORICAL!Z17=0),"-",HISTORICAL!Z17) -> 3.0318182 | E36: =IF(HISTORICAL!AC17="N/A","-",HISTORICAL!AC17) -> 3.5393939 | F36: =IF(HISTORICAL!AE17<>"N/A",HISTORICAL!AE17,IF(HISTORICAL!AB17<>"N/A",HISTORICAL!AB17,"N/A")) -> Meet Expectation | G36: =IF(OR(NOT(ISNUMBER(D36)),NOT(ISNUMBER(E36))),"-",IF(E36>D36,"▲",IF(E36<D36,"▼","—"))) -> ▲
A37: 12 | B37: =HISTORICAL!B18 -> ARAH SEJAHTERA ABADI | C37: =HISTORICAL!C18 -> PERJANJIAN SEWA MENYEWA | D37: =IF(OR(HISTORICAL!Z18="N/A",HISTORICAL!Z18=0),"-",HISTORICAL!Z18) -> 2.9611111 | E37: =IF(HISTORICAL!AC18="N/A","-",HISTORICAL!AC18) -> - | F37: =IF(HISTORICAL!AE18<>"N/A",HISTORICAL!AE18,IF(HISTORICAL!AB18<>"N/A",HISTORICAL!AB18,"N/A")) -> Tidak Dievaluasi Q2 | G37: =IF(OR(NOT(ISNUMBER(D37)),NOT(ISNUMBER(E37))),"-",IF(E37>D37,"▲",IF(E37<D37,"▼","—"))) -> -
... A47: 22 | B47: =HISTORICAL!B28 -> ESHAEL Indonesia | C47: =HISTORICAL!C28 -> Talent Assesment | D47: =IF(OR(HISTORICAL!Z28="N/A",HISTORICAL!Z28=0),"-",HISTORICAL!Z28) -> - | E47: =IF(HISTORICAL!AC28="N/A","-",HISTORICAL!AC28) -> 4.6083333 | F47: =IF(HISTORICAL!AE28<>"N/A",HISTORICAL!AE28,IF(HISTORICAL!AB28<>"N/A",HISTORICAL!AB28,"N/A")) -> Exceed Expectation | G47: =IF(OR(NOT(ISNUMBER(D47)),NOT(ISNUMBER(E47))),"-",IF(E47>D47,"▲",IF(E47<D47,"▼","—"))) -> -

Sheet HISTORICAL
A1: HISTORICAL PERFORMANCE REVIEW — SEMUA VENDOR (2024 s.d. Q2 2026)
A2: Catatan: skor Q1 2026 untuk Satria Antaran Prima (Mailing Room) & Reycom Document Solution sudah DIKOREKSI dari laporan resmi sebelumnya (ditemukan bug formula/copy-paste di file asli Q1) — lihat sheet README untuk detail.
A4: No | B4: Vendor | C4: Service Scope | D4: 2024 | L4: 2025 | U4: Repetition of Below Expectation | V4: Catatan Repetisi | W4: 2025 - 2026 | AC4: 2026 (BARU)
D5: 2024 Q1 | F5: 2024 Q2 | H5: 2024 Q3 | J5: 2024 Q4 | L5: 2025 Q1 | O5: 2025 Q2 | R5: 2025 Q3 | W5: 2025 Q4 | Z5: 2026 Q1 | AC5: 2026 Q2
D6: Score | E6: Remarks | F6: Score | G6: Remarks | H6: Score | I6: Remarks | J6: Score | K6: Remarks | L6: Score | M6: User Comment | N6: Remarks | O6: Score | P6: User Comment | Q6: Remarks | R6: Score | S6: User Comment | T6: Remarks | W6: Score | X6: User Comment | Y6: Remarks | Z6: Score | AA6: User Comment | AB6: Remarks | AC6: Score | AD6: User Comment | AE6: Remarks | AF6: Search Key | AG6: PIC Q2 2026
A7: 1 | B7: INDOSAT | C7: LAYANAN PBX BERBASISKAN CLOUD DENGAN TEKNOLOGI SIP TRUNK | D7: 3 | E7: Meet Expectation | F7: 3 | G7: Meet Expectation | H7: 2.95 | I7: Below Expectation | J7: 3 | K7: Meet Expectation | L7: 2.345 | M7: Need improvement for the part of fair and to be more responsive to solve issues. | N7: Below Expectation | O7: 1.99 | P7: 1. Dashboard access to required user 2. Response time to be improved as promised 3. To be more proactive in update the progress 4. To provide regular report (usage, recording, etc) | Q7: Below Expectation | R7: 2.72 | S7: improve responsiveness when there is problem appear, and more proactive ask client follow up for the re-solution work or not after fixing. have plan maintenance and communicated earlier to client so client can aware about maintenance process. | T7: Below Expectation | U7: 3X | V7: Sudah dilakukan pemanggilan terhadap vendor yang bersangkutan dan pada Q3 terjadi perbaikan performance pada aspek kualitas jasa yang diberikan, dan pemenuhan timeline SLA | W7: 2.9825 | X7: PLEASE KINDLY IMPROVE REQUIRED REPORT DELIVERY AS AGREED WITH ANALYZED DATA FOR BUSINESS CONSIDERATION. | Y7: BELOW EXPECTATION | Z7: 3.3184211 | AA7: The performance is getting better, please keep improve the performance. | AB7: MEET EXPECTATION | AC7: =IFERROR(VALUE('RESULT Q2'!E9),"N/A") -> 3.4394737 | AD7: =IFERROR('RESULT Q2'!G9,"-") -> Vendor performance is generally acceptable and aligns with the expected level of service. While the engagement has been positive overall, improvements are needed in feature enhancement, dashboard capabilities, and the regularity of report updates. Better preparation in deployment and timely reporting would help increase the overall value and effectiveness of the service. | AE7: =IFERROR('RESULT Q2'!F9,"N/A") -> Meet Expectation | AF7: =B7&" - "&C7 -> INDOSAT - LAYANAN PBX BERBASISKAN CLOUD DENGAN TEKNOLOGI SIP TRUNK | AG7: =IFERROR('RESULT Q2'!D9,"-") -> Nuril HUDHA
A8: 2 | B8: INFORMASI TEKNOLOGI INDONESIA | C8: PENYEDIAAN JASA SMS BROADCAST DAN JASA SMS PULL; CONNECTIVITY PRIMARY LINK | D8: 3.78 | E8: Meet Expectation | F8: 4.21 | G8: Exceed Expectation | H8: 3 | I8: Meet Expectation | J8: 3 | K8: Meet Expectation | L8: 3 | M8: Sejauh ini untuk Vendor jaris tidak ada kendala, responsif. | N8: Meet Expectation | O8: 3 | P8: So far Jatis has provided good service | Q8: Meet Expectation | R8: 3 | S8: Secara keseluran service yang diberikan oleh JATIS baik | T8: Meet Expectation | U8: 0x | V8: - | W8: 3.0818182 | X8: STILL MEET REQUIREMENT | Y8: MEET EXPECTATION | Z8: 3 | AA8: Jatis has provided good service throughout this year | AB8: MEET EXPECTATION | AC8: =IFERROR(VALUE('RESULT Q2'!E6),"N/A") -> 3 | AD8: =IFERROR('RESULT Q2'!G6,"-") -> So far, Jatis Vendor has provided good service. Their response time is fast, and they are able to provide effective solutions whenever issues arise | AE8: =IFERROR('RESULT Q2'!F6,"N/A") -> Meet Expectation | AF8: =B8&" - "&C8 -> INFORMASI TEKNOLOGI INDONESIA - PENYEDIAAN JASA SMS BROADCAST DAN JASA SMS PULL; CONNECTIVITY PRIMARY LINK | AG8: =IFERROR('RESULT Q2'!D6,"-") -> Fifin SARINURLITA
A9: 3 | B9: MITRA INTEGRASI INFORMATIKA | C9: SFDC MAINTENANCE | D9: 3 | E9: Meet Expectation | F9: 3 | G9: Meet Expectation | H9: 3.96 | I9: Meet Expectation | J9: 3.65 | K9: Meet Expectation | L9: 3 | M9: 0 | N9: Meet Expectation | O9: 4.4166667 | P9: The response from the MII Team to all the issues and needs we encountered has been quite good. They were able to promptly provide workarounds and broad solutions. The PIC assigned to the project was very communicative and responsible. Please maintain this level of performance, as we truly rely on it. | Q9: Exceed Expectation | R9: 4.3538462 | S9: Good for MII, keep it up. | T9: Exceed Expectation | U9: 0x | V9: - | W9: 4.2730769 | X9: OVERALL, THE SUPPORT FROM MII IS VERY GOOD AND VERY HELPFUL, BOTH IN TERMS OF COMMUNICATION AND TECHNICAL ASPECTS, IT IS VERY EASY TO UNDERSTAND. | Y9: EXCEED EXPECTATION | Z9: 4.8294872 | AA9: verall, the level of support has been satisfactory. The improvements carried out were highly effective, and several demands were consistent with the initial assessment and expectations. | AB9: MEET EXPECTATION | AC9: =IFERROR(VALUE('RESULT Q2'!E13),"N/A") -> 4.7487179 | AD9: =IFERROR('RESULT Q2'!G13,"-") -> Respons terhadap issue maupun kebutuhan sudah cukup baik dan cepat. Support on-site juga sangat membantu dan responsif. Ke depannya, mungkin dapat lebih rutin memberikan update terkait progress kendala atau perbaikan yang sedang dilakukan, sehingga pihak terkait dapat mengetahui status terbaru dan lebih cepat menentukan langkah selanjutnya. | AE9: =IFERROR('RESULT Q2'!F13,"N/A") -> Exceed Expectation | AF9: =B9&" - "&C9 -> MITRA INTEGRASI INFORMATIKA - SFDC MAINTENANCE | AG9: =IFERROR('RESULT Q2'!D13,"-") -> Chandra Nugraha PUTRA
A10: 4 | B10: MULTIFILING MITRA INDONESIA | C10: RECORD MANAGEMENT SERVICE | D10: 3 | E10: Meet Expectation | F10: 4 | G10: Exceed Expectation | H10: 4 | I10: Exceed Expectation | J10: 3.65 | K10: Meet Expectation | L10: 3 | M10: - | N10: Meet Expectation | O10: 3 | P10: overall OK | Q10: Meet Expectation | R10: 3.9125 | S10: Untuk project destroy harga jangan mahal mahal | T10: Exceed Expectation | U10: 0x | V10: - | W10: 3.0693182 | X10: INOVASI FROM MMI FOR SIMPLIFY PROCESS STORAGE | Y10: MEET EXPECTATION | Z10: 3.0318182 | AA10: impprove innovation dan simplyfy process | AB10: MEET EXPECTATION | AC10: =IFERROR(VALUE('RESULT Q2'!E8),"N/A") -> 3 | AD10: =IFERROR('RESULT Q2'!G8,"-") -> .. | AE10: =IFERROR('RESULT Q2'!F8,"N/A") -> Meet Expectation | AF10: =B10&" - "&C10 -> MULTIFILING MITRA INDONESIA - RECORD MANAGEMENT SERVICE | AG10: =IFERROR('RESULT Q2'!D8,"-") -> Ibnu KUMALA
A11: 5 | B11: CIPTADRA SOFTINDO | C11: PEMELIHARAAN PERANGKAT LUNAK AXITS DAN PERANGKAT LUNAK DMTM | D11: 4.9 | E11: Exceed Expectation | F11: 4.73 | G11: Exceed Expectation | H11: 3.38 | I11: Meet Expectation | J11: 3 | K11: Meet Expectation | L11: 3.975 | M11: Ciptadra saat ini sudah sangat membantu IT AMFS apabila ada Issue atau Problem yang terjadi di DMTM dengan cepat. | N11: Exceed Expectation | O11: 3.675 | P11: Ciptadra sudah bekerja dengan baik apabila ada Issue terjadi, sangat fast Response. | Q11: Meet Expectation | R11: 3.75 | S11: - | T11: Meet Expectation | U11: 0x | V11: - | W11: 4.2 | X11: - | Y11: EXCEED EXPECTATION | Z11: 4 | AA11: Performance is Good | AB11: MEET EXPECTATION | AC11: =IFERROR(VALUE('RESULT Q2'!E10),"N/A") -> 4.3 | AD11: =IFERROR('RESULT Q2'!G10,"-") -> Ciptadra selalu fast response ketika ada incident yang terjadi di DMTM | AE11: =IFERROR('RESULT Q2'!F10,"N/A") -> Exceed Expectation | AF11: =B11&" - "&C11 -> CIPTADRA SOFTINDO - PEMELIHARAAN PERANGKAT LUNAK AXITS DAN PERANGKAT LUNAK DMTM | AG11: =IFERROR('RESULT Q2'!D10,"-") -> Raninta MAHARDI
A12: 6 | B12: INMOTION INOVASI TEKNOLOGI | C12: JASA APLIKASI CHATBOT DAN LIVE CHAT | D12: 3 | E12: Meet Expectation | F12: 3 | G12: Meet Expectation | H12: 3.09 | I12: Meet Expectation | J12: 3 | K12: Meet Expectation | L12: 2.121875 | M12: More responsive in solving problems and always providing information on the latest features to support future customer service. | N12: Below Expectation | O12: 2.9890625 | P12: Maintain the consistency and communication that has been established. Always take the initiative to provide the latest information regarding developments in the Live Chat service. | Q12: Below Expectation | R12: 3 | S12: Tetap selalu berikan Service yang Terbaik | T12: Meet Expectation | U12: 0x | V12: Sudah dilakukan pemanggilan terhadap vendor yang bersangkutan dan pada Q3 terjadi perbaikan performance | W12: 3.65 | X12: - | Y12: MEET EXPECTATION | Z12: 4 | AA12: continue performing thorough and frequent periodic checks to ensure that during service hours, there are no issues that could disrupt operations and resolve the remaining unresolved 401 issue Berikan umpan balik Anda tentang BizChat | AB12: MEET EXPECTATION | AC12: =IFERROR(VALUE('RESULT Q2'!E12),"N/A") -> 4 | AD12: =IFERROR('RESULT Q2'!G12,"-") -> Tetap up to date dan helpful | AE12: =IFERROR('RESULT Q2'!F12,"N/A") -> Exceed Expectation | AF12: =B12&" - "&C12 -> INMOTION INOVASI TEKNOLOGI - JASA APLIKASI CHATBOT DAN LIVE CHAT | AG12: =IFERROR('RESULT Q2'!D12,"-") -> Djoko DJOKO
A13: 7 | B13: SATRIA ANTARAN PRIMA TBK | C13: PENGIRIMAN POLIS DOKUMEN DAN PAKET DALAM NEGERI | D13: 3.75 | E13: Meet Expectation | F13: 3.83 | G13: Meet Expectation | H13: 2.74 | I13: Below Expectation | J13: 2.725 | K13: Below Expectation | L13: 2.86 | M13: User 1: ada progress positif dari SAP untuk memperbaiki apa yang kurang di periode sebelumnya. User 2: late respon terhadap keluhan pickup pengiriman dan validasi pengiriman dari PIC Unie. Draft invoice yang dikirimkan blm tertata dengan baik atau sesuai dengan kesamaan data dari User. | N13: Below Expectation | O13: 2.6166667 | P13: - SAP should be improve the quality of its couriers regarding accuracy of delivery status. - komunikasi dgn Unie sangat sulit, slow respons, invoice yg dikirimkan juga tidak ada respon dan updatenya ketika sudah di reminder. pickup dokumen secara manual (tidak menggunakan sistem) masih berjalan dan diterima oleh SAP. | Q13: Below Expectation | R13: 2.5 | S13: User 1: invoice periode maret-juni 2025 tdk ada update. update status informasi pengiriman tidak valid (fake shipment), kendala akun tidak dapat melakukan input, pickup manual masih terus berjalan (no commit). dah laah caapee User 2: sudah ada kemajuan mengenai respon terhadap complain handling oleh SAP | T13: Below Expectation | U13: 5X | V13: Pada periode Q2, Business User memberikan konfirmasi bahwa SAP diberi penilaian positif atas adanya perubahan dari proses pickup dokumen dan pengiriman invoice sebagai tanggapan kepada procurement ketika procurement memberikan masukan untuk melakukan penggantian vendor. Pada periode Q3, User kembali memberikan nilai below expectation dan akan dilakukan pemanggilan kepada vendor terkait. Paralel dengan proses tersebut, procurement melakukan arrangement untuk pemilihan vendor alternatif atas kebutuhan courier services. | W13: 2.9611111 | X13: VEMDOR SAP ADA PENINGKATAN TERUTAMA DI KOMUNIKASI PIC NYA | Y13: BELOW EXPECTATION | Z13: 3 | AA13: SAP has provided excellent service throughout this year | AB13: MEET EXPECTATION | AC13: =IFERROR(VALUE('RESULT Q2'!E7),"N/A") -> 3.2383333 | AD13: =IFERROR('RESULT Q2'!G7,"-") -> SAP has shown improvement in terms of reporting and provides a fast response whenever issues arise. | 1. untuk detail status pengiriman dokumen/barang harus diberikan keterangan penerima dengan lengkap dan jelas; 2. Maks. SLA pengiriman harus memenuhi sesuai dengan yang ditetapkan yaitu <5% not meet SLA; 3. Invoice biaya pengiriman dikirimkan ke user yang sesuai dan dikirimkan tidak melebihi periode yang ditetapkan. 4. Report Stock sesuai dengan real stock di warehouse. | AE13: =IFERROR('RESULT Q2'!F7,"N/A") -> Meet Expectation | AF13: =B13&" - "&C13 -> SATRIA ANTARAN PRIMA TBK - PENGIRIMAN POLIS DOKUMEN DAN PAKET DALAM NEGERI | AG13: =IFERROR('RESULT Q2'!D7,"-") -> Fifin SARINURLITA, Novia Laras SANTI
A14: 8 | B14: SATRIA ANTARAN PRIMA TBK | C14: MAILING ROOM | D14: N/A | E14: N/A | F14: N/A | G14: N/A | H14: N/A | I14: N/A | J14: N/A | K14: N/A | L14: 3 | M14: - | N14: Meet Expectation | O14: N/A | P14: N/A | Q14: N/A | R14: 3.9125 | S14: tingkatkan lebih performancenya | T14: Exceed Expectation | U14: 0x | V14: - | W14: 3.05 | X14: NEED INOVATION FROM SAP FOR SIMPLIFY PROCESS AT AXA MANDIRI MAILING ROOM | Y14: MEET EXPECTATION | Z14: 3.4041667 | AA14: Over all mailing ok, please improve coordinated with Headoffice team for reduce complain/misscomm (ex case overseas shipment ) | AB14: MEET EXPECTATION | AC14: =IFERROR(VALUE('RESULT Q2'!E5),"N/A") -> 3.04375 | AD14: =IFERROR('RESULT Q2'!G5,"-") -> improve inisiatsis | AE14: =IFERROR('RESULT Q2'!F5,"N/A") -> Meet Expectation | AF14: =B14&" - "&C14 -> SATRIA ANTARAN PRIMA TBK - MAILING ROOM | AG14: =IFERROR('RESULT Q2'!D5,"-") -> Ibnu KUMALA
A15: 9 | B15: TARGET SUKSES SINERGI | C15: PENGIRIMAN EMAIL MARKETING AUTOMATION | D15: 2.85 | E15: Below Expectation | F15: 3.28 | G15: Meet Expectation | H15: 4 | I15: Exceed Expectation | J15: 3.3125 | K15: Meet Expectation | L15: 3.7444444 | M15: Overall our partnership going well | N15: Meet Expectation | O15: 4 | P15: Please keep up the good work! | Q15: Exceed Expectation | R15: 3 | S15: Overall Good | T15: Meet Expectation | U15: 0x | V15: - | W15: 3.65 | X15: GOOD | Y15: MEET EXPECTATION | Z15: 3.9 | AA15: Harganya buat next contrac please murahin ya | AB15: MEET EXPECTATION | AC15: =IFERROR(VALUE('RESULT Q2'!E11),"N/A") -> 2.9416667 | AD15: =IFERROR('RESULT Q2'!G11,"-") -> Secara keseluruhan, MTarget telah memberikan dukungan yang baik dalam operasional email campaign dan responsif dalam menangani kebutuhan maupun isu yang muncul. Namun, insiden kesalahan pengiriman email yang terjadi menunjukkan perlunya penguatan pada proses deployment, pengujian, serta validasi sebelum implementasi ke production. Ke depannya, kami berharap MTarget dapat memperkuat proses change management, quality assurance, dan kontrol terhadap segmentasi serta pengiriman email untuk meminimalkan risiko terjadinya insiden serupa. | AE15: =IFERROR('RESULT Q2'!F11,"N/A") -> Below Expectation | AF15: =B15&" - "&C15 -> TARGET SUKSES SINERGI - PENGIRIMAN EMAIL MARKETING AUTOMATION | AG15: =IFERROR('RESULT Q2'!D11,"-") -> Bella Friska DEPARI
A16: 10 | B16: WIZ TECHNOLOGY INDONESIA | C16: VOICE BOT REMINDER CALL | D16: 3 | E16: Meet Expectation | F16: 3.61 | G16: Meet Expectation | H16: 3.4 | I16: Meet Expectation | J16: 3.0875 | K16: Meet Expectation | L16: 3.0388889 | M16: so far wiz.AI sudah memenuhi apa yang menjadi kebutuhan kami | N16: Meet Expectation | O16: 3.5444444 | P16: needs better communication for quicker responses. | Q16: Meet Expectation | R16: 3 | S16: sudah baik | T16: Meet Expectation | U16: 0x | V16: - | W16: 3.46875 | X16: WE EXPECT INITIATIVE TO BE TAKEN IN IMPLEMENTING MITIGATION MEASURES AND IN ACCELERATING THE PROCESS WITHIN COLLABORATION WITH WIZ AI. | Y16: MEET EXPECTATION | Z16: 0 | AA16: 0 | AC16: =IFERROR(VALUE('RESULT Q2'!E19),"N/A") -> 3.0875 | AD16: =IFERROR('RESULT Q2'!G19,"-") -> To ensure a smooth process, we need to move faster and maintain effective communication | AE16: =IFERROR('RESULT Q2'!F19,"N/A") -> Meet Expectation | AF16: =B16&" - "&C16 -> WIZ TECHNOLOGY INDONESIA - VOICE BOT REMINDER CALL | AG16: =IFERROR('RESULT Q2'!D19,"-") -> Ravika OKTAVIANI
A17: 11 | B17: KARYAPUTRA SURYAGEMILANG | C17: TELEMARKETING REVAMP PROJECT | D17: 3.46 | E17: Meet Expectation | F17: 3.46 | G17: Meet Expectation | H17: 3.86 | I17: Meet Expectation | J17: 3 | K17: Meet Expectation | L17: 3.1807692 | M17: Need to speed up the investigation and fixing process when issues arise. | N17: Meet Expectation | O17: 2.9371795 | P17: As we have many projects involved KPSG in AMFS, please do maintain the dedicated team for TM Revamp. Currently activities in other projects may impact in TM Revamp project, i.e. PureCloud Decommissioned impact in TM Revamp activities (huddle meeting) and deliverables (CRs). We believe each project has different urgency and separate budget which need to be considered not impacted each other. | Q17: Below Expectation | R17: 2.4272727 | S17: We concenrn about human resource, somehow we need extra effort time to make Change Request, Assesment Scope and issue. It takes long time to asses new Change Request because availibility human resources. | T17: Below Expectation | U17: 2x | V17: Pada periode Q2 mendapatkan hasil below expectation dan procurement sudah lakukan pemanggilan untuk menyampaikan evaluasi performance tersebut bersama sama dengan business user. Pada periode Q3, business user menyampaikan concern kembali dengan hasil below expectation, dan akan dilakukan pemanggilan kembali kepada KPSG. | W17: 3.5181818 | X17: PLEASE BE MORE PERFORMED BECAUSE OUR NEEDS IS SO FAST FOR STRATEGIC DELIVERY | Y17: MEET EXPECTATION | Z17: 3.0318182 | AA17: Diharapkan untuk tim project yang diassign apabila CR sudah di signoff agar availibility dari resource ready | AB17: MEET EXPECTATION | AC17: =IFERROR(VALUE('RESULT Q2'!E18),"N/A") -> 3.5393939 | AD17: =IFERROR('RESULT Q2'!G18,"-") -> 1. For AI Implementation, KPSG need to improve the delivery time, quality and PIC availability and backup PIC support 2. Another enhancement need to speed up with dedicated team | AE17: =IFERROR('RESULT Q2'!F18,"N/A") -> Meet Expectation | AF17: =B17&" - "&C17 -> KARYAPUTRA SURYAGEMILANG - TELEMARKETING REVAMP PROJECT | AG17: =IFERROR('RESULT Q2'!D18,"-") -> Nuril HUDHA
A18: 12 | B18: ARAH SEJAHTERA ABADI | C18: PERJANJIAN SEWA MENYEWA | D18: N/A | E18: N/A | F18: 3 | G18: Meet Expectation | H18: 3 | I18: Meet Expectation | J18: 3.35 | K18: Meet Expectation | L18: 2.8409091 | M18: Improve Resolution repair, for this year resolution fro problem dusty and project smell CCC impact project from another tenant behind CCC GF ( NOV 2024 until now still not yet solution ) | N18: Below Expectation | O18: 2.7727273 | P18: for improvment is Improve resolusi repair/corective device Building in tenant area | Q18: Below Expectation | R18: 2 | S18: adanya SLA atau KPI utuk review kuncit | T18: Below Expectation | U18: 3x | V18: Pada periode Q1, Q2, dan Q3, hasil penilaian evaluasinya cenderung turun karena dari pihak Kuningan City tidak bersedia dianggap sebagai vendor / supplier, yang bisa diberlakukan penilaian performance atas layanan yang diberikan. Dari sisi operasional, memberikan nilai below expectation karena pihak Kuncit dirasa kurang responsif dalam menanggapi keluhan. | W18: 2.9611111 | X18: KUNCIT SUPPORT FOR SPACE AMFS (GIVE MORE ADVANTAGE FREE CHARGE FOR 12), FOR THE REPAIR /SOLUTION NEED MORE IMPROVE TIME OR QUALITY | Y18: BELOW EXPECTATION | Z18: 2.9611111 | AA18: Improve quality service, specially for leakage, | AB18: BELOW EXPECTATION | AC18: =IFERROR(VALUE('RESULT Q2'!E23),"N/A") -> N/A | AD18: =IFERROR('RESULT Q2'!G23,"-") -> - | AE18: =IFERROR('RESULT Q2'!F23,"N/A") -> Tidak Dievaluasi Q2 | AF18: =B18&" - "&C18 -> ARAH SEJAHTERA ABADI - PERJANJIAN SEWA MENYEWA | AG18: =IFERROR('RESULT Q2'!D23,"-") -> ibnu.kumala@axa-mandiri.co.id
A19: 13 | B19: DELOITTE CONSULTING | C19: DATA PRIVACY TOOLS & PELATIHAN PERSONAL DATA PROTECTION (PDP) | D19: N/A | E19: N/A | F19: N/A | G19: N/A | H19: N/A | I19: N/A | J19: 3.2333333 | K19: Meet Expectation | L19: 2.9708333 | M19: They need to deepen their product knowledge so that they can be right on target in providing solutions. | N19: Below Expectation | O19: 2.8833333 | P19: Understand more about product feature knowledge so that vendors can explain accurately and convincingly when there is trouble or product limitations. | Q19: Below Expectation | R19: 3.1 | S19: More coordination with PIC Principal Product (Securiti.ai) to get information regarding product updates earlier. | T19: Meet Expectation | U19: 0x | V19: - | W19: 3.1166667 | X19: MORE COORDINATION WITH PIC PRINCIPAL PRODUCT (SECURITI.AI) TO GET INFORMATION REGARDING PRODUCT UPDATES EARLIER. | Y19: MEET EXPECTATION | Z19: 3.1636364 | AA19: Need more improvement regarding initiative to take mitigation/preventive action to prevent the problem from recurring/current issue. | AB19: MEET EXPECTATION | AC19: =IFERROR(VALUE('RESULT Q2'!E16),"N/A") -> 4.0636364 | AD19: =IFERROR('RESULT Q2'!G16,"-") -> In dealing with Security AI-related issues, Deloitte is occasionally unable to provide a resolution and therefore redirects the matter to the Security AI team. Furthermore, several system features are restricted, and these limitations were not clearly communicated at the outset. Consequently, this has created challenges in implementing system enhancements and aligning the system with the business requirements of Security AI users. | AE19: =IFERROR('RESULT Q2'!F16,"N/A") -> Exceed Expectation | AF19: =B19&" - "&C19 -> DELOITTE CONSULTING - DATA PRIVACY TOOLS & PELATIHAN PERSONAL DATA PROTECTION (PDP) | AG19: =IFERROR('RESULT Q2'!D16,"-") -> M. Andrian Patria Shaleh RIZAL
A20: 14 | B20: SUTRA MANAGEMENT CONSULTANCIES | C20: IMPLEMENTASI SAS IFRS17 | D20: N/A | E20: N/A | F20: N/A | G20: N/A | H20: N/A | I20: N/A | J20: N/A | K20: N/A | L20: 3.1866667 | M20: Sometimes the vendor must think out-of-the box meaning that they need to be "somehow creative enough" in expediting the problem-solution approaches to any issues being raised by us as customers in the fields of both IT and Finance/Actuary. They seems to play "by the book" instead of proposing the new ideas and thoughts flexibel enough to be implemented as long as not crossing the compliance issues. Those kind ideas that can help us to have more effective and productive outcomes in the very challenging timeline. | N20: Meet Expectation | O20: 3.6733333 | P20: In overall is above the "Good Criteria" except when starting to develop the infrastructure in the beginning because the development team of this vendor is not in Jakarta but instead in India that added extra challenges for us to communicate (in English) and coordinate (long distance) | Q20: Meet Expectation | R20: 3.5166667 | S20: I think we need to be fair that the PSAK117 Methodology is the new thing that even for the vendor to execute in the CSM Engine needs to know some critical particular requirements that business users expect for CSM to deliver. Therefore, CSM Engine needs to be customized, and this takes time from the vendor to adjust/modify. My suggestion for the vendor is to always provide a stand-by expertise in the field of IFRS17 Methodoly, and he/she is able to explain clearly to users how these things work in the CSM System, and how users should provide required items in our existing data input system. Mutual understanding is the key; system modification is easy to implement; and expertise people from the vendor are always stand by | T20: Meet Expectation | U20: 0x | V20: - | W20: 3.8666667 | X20: N/A | Y20: MEET EXPECTATION | Z20: 3.6833333 | AA20: Local vendor Sutra is affiliated with SAS Technology which is known as more expensive system compared to other vendors during the Vendor Bidding Process. However, SAS Technology System has been used in few well-known insurance companies in Indonesia, so it is easier to get the review and information; mostly positive. | AB20: MEET EXPECTATION | AC20: =IFERROR(VALUE('RESULT Q2'!E14),"N/A") -> 3.3333333 | AD20: =IFERROR('RESULT Q2'!G14,"-") -> no feedback | AE20: =IFERROR('RESULT Q2'!F14,"N/A") -> Meet Expectation | AF20: =B20&" - "&C20 -> SUTRA MANAGEMENT CONSULTANCIES - IMPLEMENTASI SAS IFRS17 | AG20: =IFERROR('RESULT Q2'!D14,"-") -> Tatang SUTIAMAN
A21: 15 | B21: TMF INDONESIA | C21: PAYROLL | L21: N/A | M21: N/A | N21: N/A | O21: N/A | P21: N/A | Q21: N/A | R21: N/A | S21: N/A | T21: N/A | U21: 3 | V21: BETTER COORDINATION THAN 2025, REPORTS ARE ALWAYS REVIEWED BY RELATED MANAGER BEFORE SUBMIT TO AMFS PIC. | Z21: 3 | AA21: Always check and recheck the task in internal PIC TMF before send the report to AMFS PIC | AB21: MEET EXPECTATION | AC21: =IFERROR(VALUE('RESULT Q2'!E17),"N/A") -> 3 | AD21: =IFERROR('RESULT Q2'!G17,"-") -> - | AE21: =IFERROR('RESULT Q2'!F17,"N/A") -> Meet Expectation | AF21: =B21&" - "&C21 -> TMF INDONESIA - PAYROLL | AG21: =IFERROR('RESULT Q2'!D17,"-") -> Enung HARYATI
A22: 16 | B22: REYCOM DOCUMENT SOLUTION | C22: PRINTING & DMC | L22: N/A | M22: N/A | N22: N/A | O22: N/A | P22: N/A | Q22: N/A | R22: N/A | S22: N/A | T22: N/A | U22: 3.5416667 | V22: PLEASE BE MORE PERFORMED BECAUSE OUR NEEDS IS SO FAST FOR STRATEGIC DELIVERY | Z22: 4.7666667 | AA22: More inovation for 2026 | AB22: EXCEED EXPECTATION | AC22: =IFERROR(VALUE('RESULT Q2'!E15),"N/A") -> 4.3 | AD22: =IFERROR('RESULT Q2'!G15,"-") -> Improvements to their latest Technology to support process at AXA | AE22: =IFERROR('RESULT Q2'!F15,"N/A") -> Exceed Expectation | AF22: =B22&" - "&C22 -> REYCOM DOCUMENT SOLUTION - PRINTING & DMC | AG22: =IFERROR('RESULT Q2'!D15,"-") -> Yulia KURNIATI
A23: 17 | B23: FPT METRODATA INDONESIA | C23: PENETRATION TEST | Z23: 3 | AA23: No need improvement | AB23: MEET EXPECTATION | AC23: =IFERROR(VALUE('RESULT Q2'!E4),"N/A") -> 4 | AD23: =IFERROR('RESULT Q2'!G4,"-") -> - | AE23: =IFERROR('RESULT Q2'!F4,"N/A") -> Exceed Expectation | AF23: =B23&" - "&C23 -> FPT METRODATA INDONESIA - PENETRATION TEST | AG23: =IFERROR('RESULT Q2'!D4,"-") -> Fauzi ARYANTO
A24: 18 | B24: IPROTEKSI TELEMATIKA | C24: PENETRATION TEST | Z24: 4 | AA24: no need improvement | AB24: MEET EXPECTATION | AC24: =IFERROR(VALUE('RESULT Q2'!E3),"N/A") -> 4 | AD24: =IFERROR('RESULT Q2'!G3,"-") -> - | AE24: =IFERROR('RESULT Q2'!F3,"N/A") -> Exceed Expectation | AF24: =B24&" - "&C24 -> IPROTEKSI TELEMATIKA - PENETRATION TEST | AG24: =IFERROR('RESULT Q2'!D3,"-") -> Fauzi ARYANTO
A25: 19 | B25: ITSEC ASIA | C25: PENETRATION TEST | Z25: 3 | AA25: Currently no need improvement | AB25: MEET EXPECTATION | AC25: =IFERROR(VALUE('RESULT Q2'!E2),"N/A") -> 3 | AD25: =IFERROR('RESULT Q2'!G2,"-") -> - | AE25: =IFERROR('RESULT Q2'!F2,"N/A") -> Meet Expectation | AF25: =B25&" - "&C25 -> ITSEC ASIA - PENETRATION TEST | AG25: =IFERROR('RESULT Q2'!D2,"-") -> Fauzi ARYANTO
A26: 20 | B26: Karyaputra Suryagemilang | C26: Purecloud Decommisioning | D26: N/A | E26: - | F26: N/A | G26: - | H26: N/A | I26: - | J26: N/A | K26: - | L26: N/A | M26: - | N26: N/A | O26: N/A | P26: - | Q26: N/A | R26: N/A | S26: - | T26: N/A | U26: N/A | V26: - | W26: N/A | X26: N/A | Y26: N/A | Z26: N/A | AA26: - | AB26: N/A | AC26: =IFERROR(VALUE('RESULT Q2'!E20),"N/A") -> 3.4458333 | AD26: =IFERROR('RESULT Q2'!G20,"-") -> 1. KPSG-ARSI Perspective (The approach applied is still limited to best practices without considering the scenarios occurring in AMFS). 2. Requirement Gap (There is a significant requirement gap due to missed requirements, caused by insufficient exploration of user needs and requirements) 3. Frequent Manpower (MP) and PIC Changes (Manpower changes occur quite frequently, while the implementation team is no longer on-site. The PIC from KPSG also changes often. It is requested that a dedicated PIC be provided for IT Support as well as a dedicated Project Manager) 4. Deployment Issues (Each deployment consistently results in new issues that impact areas outside the deployment scope. This indicates a lack of proper health checks after deployment). 5. Deployment Communication (Communication regarding deployment plans is still lacking, particularly in obtaining approval from business users. This matter has already been communicated by AMFS to the KPSG team). 6. Contact Center Experience (The team’s experience in contact center operations, especially inbound, remains limited). 7. Change Requests (CR) and Production Issues (Many CRs and production issues are delivered based on targets determined unilaterally by KPSG). 8. User Guide and Feature Socialization. (The User Guide is not well maintained. When new features are introduced, documentation should be updated immediately, socialized to users, and the latest User Guide shared to ensure optimal usage) | AE26: =IFERROR('RESULT Q2'!F20,"N/A") -> Meet Expectation | AF26: =B26&" - "&C26 -> Karyaputra Suryagemilang - Purecloud Decommisioning | AG26: =IFERROR('RESULT Q2'!D20,"-") -> Noviani MARBUN
A27: 21 | B27: Mitra Integrasi Informatika | C27: Purecloud Decommisioning | D27: N/A | E27: - | F27: N/A | G27: - | H27: N/A | I27: - | J27: N/A | K27: - | L27: N/A | M27: - | N27: N/A | O27: N/A | P27: - | Q27: N/A | R27: N/A | S27: - | T27: N/A | U27: N/A | V27: - | W27: N/A | X27: N/A | Y27: N/A | Z27: N/A | AA27: - | AB27: N/A | AC27: =IFERROR(VALUE('RESULT Q2'!E21),"N/A") -> 3.8833333 | AD27: =IFERROR('RESULT Q2'!G21,"-") -> 1) Training Process During the training sessions, it is expected that explanations are delivered in detail and step by step. When participants are conducting hands-on activities, they should be properly provided with guidance and direct support. This is important to avoid unnecessary questions that could otherwise be answered clearly, ensuring that participants can immediately understand the changes and new features introduced. 2) “Baby Sitting” Phase In the “baby sitting” phase, the MII team was expected to be present full day on-site at AMFS for two weeks. However, in practice, the team did not consistently attend and only joined full day after being specifically requested. As a result, the actual presence was only around five days instead of the full two weeks as originally required. | AE27: =IFERROR('RESULT Q2'!F21,"N/A") -> Meet Expectation | AF27: =B27&" - "&C27 -> Mitra Integrasi Informatika - Purecloud Decommisioning | AG27: =IFERROR('RESULT Q2'!D21,"-") -> Noviani MARBUN
A28: 22 | B28: ESHAEL Indonesia | C28: Talent Assesment | D28: N/A | E28: - | F28: N/A | G28: - | H28: N/A | I28: - | J28: N/A | K28: - | L28: N/A | M28: - | N28: N/A | O28: N/A | P28: - | Q28: N/A | R28: N/A | S28: - | T28: N/A | U28: N/A | V28: - | W28: N/A | X28: N/A | Y28: N/A | Z28: N/A | AA28: - | AB28: N/A | AC28: =IFERROR(VALUE('RESULT Q2'!E22),"N/A") -> 4.6083333 | AD28: =IFERROR('RESULT Q2'!G22,"-") -> N/A | AE28: =IFERROR('RESULT Q2'!F22,"N/A") -> Exceed Expectation | AF28: =B28&" - "&C28 -> ESHAEL Indonesia - Talent Assesment | AG28: =IFERROR('RESULT Q2'!D22,"-") -> I Gusti Ayu Mira SETYAWARDHANIE

Sheet SUMMARY Q2 2026
A1: CRITICAL SUPPLIER PERFORMANCE REVIEW — SUMMARY Q2 2026
A2: Periode Review | B2: Q2 2026
A3: Jumlah Vendor Dievaluasi | B3: =COUNTA('RESULT Q2'!B2:B22) -> 21
A4: Total Vendor Kritis (Master List) - Input Manual | B4: 22
A5: % Vendor Dievaluasi | B5: =B3/B4 -> 0.95454545
A6: Jumlah "Meet / Exceed / Exceptional" | B6: =SUMPRODUCT(--(('RESULT Q2'!F2:F23<>"Below Expectation")*('RESULT Q2'!F2:F23<>"Unsatisfactory")*('RESULT Q2'!F2:F23<>"Tidak Dievaluasi Q2"))) -> 20
A7: Jumlah "Under Performance" (Below Expectation/Unsatisfactory) | B7: =COUNTIF('RESULT Q2'!F2:F23,"Below Expectation")+COUNTIF('RESULT Q2'!F2:F23,"Unsatisfactory") -> 1
A8: Jumlah Vendor Tidak Dievaluasi Q2 | B8: =COUNTIF('RESULT Q2'!F2:F23,"Tidak Dievaluasi Q2") -> 1
A9: Vendor Critical Below Expectation | B9: =_xlfn.TEXTJOIN(", ",TRUE(),'RESULT Q2'!I2:I23) -> Target Sukses Sinergi - Email Marketing Automation
A10: Vendor Baru Q2 2026 (belum ada histori) | B10: Karyaputra Suryagemilang - Purecloud Decommisioning; Mitra Integrasi Informatika - Purecloud Decommisioning; ESHAEL Indonesia - Talent Assesment

Sheet RESULT Q2
A1: No | B1: Vendor | C1: Service | D1: PIC (User) | E1: Total Score | F1: Status | G1: Remarks | H1: Catatan Data | I1: Helper: Below/Unsatisfactory Name
A2: 1 | B2: Itsec Asia | C2: Penetration Testing | D2: Fauzi ARYANTO | E2: ='Q2 ITSEC'!B20 -> 3 | F2: ='Q2 ITSEC'!B21 -> Meet Expectation | G2: ='Q2 ITSEC'!B32 -> - | I2: =IF(OR(F2="Below Expectation",F2="Unsatisfactory"),B2&" - "&C2,"")
A3: 2 | B3: Iproteksi Telematika | C3: Penetration Testing | D3: Fauzi ARYANTO | E3: ='Q2 IPROTEKSI'!B20 -> 4 | F3: ='Q2 IPROTEKSI'!B21 -> Exceed Expectation | G3: ='Q2 IPROTEKSI'!B32 -> - | I3: =IF(OR(F3="Below Expectation",F3="Unsatisfactory"),B3&" - "&C3,"")
A4: 3 | B4: FPT Metrodata | C4: Penetration Testing | D4: Fauzi ARYANTO | E4: ='Q2 FPT'!B20 -> 4 | F4: ='Q2 FPT'!B21 -> Exceed Expectation | G4: ='Q2 FPT'!B32 -> - | I4: =IF(OR(F4="Below Expectation",F4="Unsatisfactory"),B4&" - "&C4,"")
A5: 4 | B5: Satria Antaran Prima | C5: Mailing Room | D5: Ibnu KUMALA | E5: ='Q2 SAP-Mailing'!B25 -> 3.04375 | F5: ='Q2 SAP-Mailing'!B26 -> Meet Expectation | G5: ='Q2 SAP-Mailing'!B37 -> improve inisiatsis | I5: =IF(OR(F5="Below Expectation",F5="Unsatisfactory"),B5&" - "&C5,"")
A6: 5 | B6: Informasi Teknologi Indonesia - SMS Broadcast | D6: Fifin SARINURLITA | E6: ='Q2 JATIS'!B29 -> 3 | F6: ='Q2 JATIS'!B30 -> Meet Expectation | G6: ='Q2 JATIS'!B41 -> So far, Jatis Vendor has provided good service. Their response time is fast, and they are able to provide effective solutions whenever issues arise | I6: =IF(OR(F6="Below Expectation",F6="Unsatisfactory"),B6&" - "&C6,"")
A7: 6 | B7: Satria Antaran Prima | C7: Courier Service | D7: Fifin SARINURLITA, Novia Laras SANTI | E7: ='Q2 SAP-Courier'!B33 -> 3.2383333 | F7: ='Q2 SAP-Courier'!B34 -> Meet Expectation | G7: ='Q2 SAP-Courier'!B47&" | "&'Q2 SAP-Courier'!B48 -> SAP has shown improvement in terms of reporting and provides a fast response whenever issues arise. | 1. untuk detail status pengiriman dokumen/barang harus diberikan keterangan penerima dengan lengkap dan jelas; 2. Maks. SLA pengiriman harus memenuhi sesuai dengan yang ditetapkan yaitu <5% not meet SLA; 3. Invoice biaya pengiriman dikirimkan ke user yang sesuai dan dikirimkan tidak melebihi periode yang ditetapkan. 4. Report Stock sesuai dengan real stock di warehouse. | H7: Skor rata-rata 2 business user (kasus normal, multiple raters untuk vendor/service yang sama). | I7: =IF(OR(F7="Below Expectation",F7="Unsatisfactory"),B7&" - "&C7,"")
A8: 7 | B8: Multifiling Mitra Indonesia | C8: Record Management Service | D8: Ibnu KUMALA | E8: ='Q2 MMI'!B29 -> 3 | F8: ='Q2 MMI'!B30 -> Meet Expectation | G8: ='Q2 MMI'!B41 -> .. | I8: =IF(OR(F8="Below Expectation",F8="Unsatisfactory"),B8&" - "&C8,"")
A9: 8 | B9: Indosat | C9: Layanan PBX berbasiskan cloud dengan Teknologi SIP Trunk | D9: Nuril HUDHA | E9: ='Q2 INDOSAT'!B36 -> 3.4394737 | F9: ='Q2 INDOSAT'!B37 -> Meet Expectation | G9: ='Q2 INDOSAT'!B48 -> Vendor performance is generally acceptable and aligns with the expected level of service. While the engagement has been positive overall, improvements are needed in feature enhancement, dashboard capabilities, and the regularity of report updates. Better preparation in deployment and timely reporting would help increase the overall value and effectiveness of the service. | I9: =IF(OR(F9="Below Expectation",F9="Unsatisfactory"),B9&" - "&C9,"")
A10: 9 | B10: Ciptadra Softindo | C10: Pemeliharaan Axits & DMTM | D10: Raninta MAHARDI | E10: ='Q2 CIPTADRA'!B32 -> 4.3 | F10: ='Q2 CIPTADRA'!B33 -> Exceed Expectation | G10: ='Q2 CIPTADRA'!B44 -> Ciptadra selalu fast response ketika ada incident yang terjadi di DMTM | I10: =IF(OR(F10="Below Expectation",F10="Unsatisfactory"),B10&" - "&C10,"")
A11: 10 | B11: Target Sukses Sinergi | C11: Email Marketing Automation | D11: Bella Friska DEPARI | E11: ='Q2 MTARGET'!B23 -> 2.9416667 | F11: ='Q2 MTARGET'!B24 -> Below Expectation | G11: ='Q2 MTARGET'!B35 -> Secara keseluruhan, MTarget telah memberikan dukungan yang baik dalam operasional email campaign dan responsif dalam menangani kebutuhan maupun isu yang muncul. Namun, insiden kesalahan pengiriman email yang terjadi menunjukkan perlunya penguatan pada proses deployment, pengujian, serta validasi sebelum implementasi ke production. Ke depannya, kami berharap MTarget dapat memperkuat proses change management, quality assurance, dan kontrol terhadap segmentasi serta pengiriman email untuk meminimalkan risiko terjadinya insiden serupa. | I11: =IF(OR(F11="Below Expectation",F11="Unsatisfactory"),B11&" - "&C11,"") -> Target Sukses Sinergi - Email Marketing Automation
A12: 11 | B12: Inmotion Inovasi Teknologi | C12: Jasa Aplikasi Chatbot dan Live Chat | D12: Djoko DJOKO | E12: ='Q2 INMOTION'!B54 -> 4 | F12: ='Q2 INMOTION'!B55 -> Exceed Expectation | G12: ='Q2 INMOTION'!B66 -> Tetap up to date dan helpful | I12: =IF(OR(F12="Below Expectation",F12="Unsatisfactory"),B12&" - "&C12,"")
A13: 12 | B13: Mitra Integrasi Informatika | C13: SFDC Maintenance | D13: Chandra Nugraha PUTRA | E13: ='Q2 MII-SFDC'!B30 -> 4.7487179 | F13: ='Q2 MII-SFDC'!B31 -> Exceed Expectation | G13: ='Q2 MII-SFDC'!B42 -> Respons terhadap issue maupun kebutuhan sudah cukup baik dan cepat. Support on-site juga sangat membantu dan responsif. Ke depannya, mungkin dapat lebih rutin memberikan update terkait progress kendala atau perbaikan yang sedang dilakukan, sehingga pihak terkait dapat mengetahui status terbaru dan lebih cepat menentukan langkah selanjutnya. | I13: =IF(OR(F13="Below Expectation",F13="Unsatisfactory"),B13&" - "&C13,"")
A14: 13 | B14: Sutra Management Consultancies | C14: Implementasi SAS IFRS17 | D14: Tatang SUTIAMAN | E14: ='Q2 SUTRA'!B38 -> 3.3333333 | F14: ='Q2 SUTRA'!B39 -> Meet Expectation | G14: ='Q2 SUTRA'!B50 -> no feedback | I14: =IF(OR(F14="Below Expectation",F14="Unsatisfactory"),B14&" - "&C14,"")
A15: 14 | B15: Reycom Document Solution | C15: Printing & Data Management Center | D15: Yulia KURNIATI | E15: ='Q2 RDS-Printing'!B33 -> 4.3 | F15: ='Q2 RDS-Printing'!B34 -> Exceed Expectation | G15: ='Q2 RDS-Printing'!B45 -> Improvements to their latest Technology to support process at AXA | H15: Vendor submit 2x; menggunakan submission terakhir (lebih lengkap). | I15: =IF(OR(F15="Below Expectation",F15="Unsatisfactory"),B15&" - "&C15,"")
A16: 15 | B16: Deloitte Consulting | C16: Data Privacy & Pelatihan Personal Data Protection (PDP) | D16: M. Andrian Patria Shaleh RIZAL | E16: ='Q2 DELOITTE'!B28 -> 4.0636364 | F16: ='Q2 DELOITTE'!B29 -> Exceed Expectation | G16: ='Q2 DELOITTE'!B40 -> In dealing with Security AI-related issues, Deloitte is occasionally unable to provide a resolution and therefore redirects the matter to the Security AI team. Furthermore, several system features are restricted, and these limitations were not clearly communicated at the outset. Consequently, this has created challenges in implementing system enhancements and aligning the system with the business requirements of Security AI users. | I16: =IF(OR(F16="Below Expectation",F16="Unsatisfactory"),B16&" - "&C16,"")
A17: 16 | B17: TMF Indonesia | C17: Payroll | D17: Enung HARYATI | E17: ='Q2 TMF'!B23 -> 3 | F17: ='Q2 TMF'!B24 -> Meet Expectation | G17: ='Q2 TMF'!B35 -> - | I17: =IF(OR(F17="Below Expectation",F17="Unsatisfactory"),B17&" - "&C17,"")
A18: 17 | B18: Karya Putra Surya Gemilang | C18: Telemarketing Revamp Project | D18: Nuril HUDHA | E18: ='Q2 KPSG-TM'!B28 -> 3.5393939 | F18: ='Q2 KPSG-TM'!B29 -> Meet Expectation | G18: ='Q2 KPSG-TM'!B40 -> 1. For AI Implementation, KPSG need to improve the delivery time, quality and PIC availability and backup PIC support 2. Another enhancement need to speed up with dedicated team | I18: =IF(OR(F18="Below Expectation",F18="Unsatisfactory"),B18&" - "&C18,"")
A19: 18 | B19: Wiz Technology | C19: Voice Bot Reminder Call | D19: Ravika OKTAVIANI | E19: ='Q2 WIZ'!B25 -> 3.0875 | F19: ='Q2 WIZ'!B26 -> Meet Expectation | G19: ='Q2 WIZ'!B37 -> To ensure a smooth process, we need to move faster and maintain effective communication | I19: =IF(OR(F19="Below Expectation",F19="Unsatisfactory"),B19&" - "&C19,"")
A20: 19 | B20: Karyaputra Suryagemilang | C20: Purecloud Decommisioning | D20: Noviani MARBUN | E20: ='Q2 KPSG-ARSI'!B34 -> 3.4458333 | F20: ='Q2 KPSG-ARSI'!B35 -> Meet Expectation | G20: ='Q2 KPSG-ARSI'!B46 -> 1. KPSG-ARSI Perspective (The approach applied is still limited to best practices without considering the scenarios occurring in AMFS). 2. Requirement Gap (There is a significant requirement gap due to missed requirements, caused by insufficient exploration of user needs and requirements) 3. Frequent Manpower (MP) and PIC Changes (Manpower changes occur quite frequently, while the implementation team is no longer on-site. The PIC from KPSG also changes often. It is requested that a dedicated PIC be provided for IT Support as well as a dedicated Project Manager) 4. Deployment Issues (Each deployment consistently results in new issues that impact areas outside the deployment scope. This indicates a lack of proper health checks after deployment). 5. Deployment Communication (Communication regarding deployment plans is still lacking, particularly in obtaining approval from business users. This matter has already been communicated by AMFS to the KPSG team). 6. Contact Center Experience (The team’s experience in contact center operations, especially inbound, remains limited). 7. Change Requests (CR) and Production Issues (Many CRs and production issues are delivered based on targets determined unilaterally by KPSG). 8. User Guide and Feature Socialization. (The User Guide is not well maintained. When new features are introduced, documentation should be updated immediately, socialized to users, and the latest User Guide shared to ensure optimal usage) | H20: Vendor/proyek baru; belum ada histori kuartal sebelumnya. Klasifikasi Quality/Timeline pada pertanyaan custom memakai heuristik kata kunci — mohon di-review SRM. | I20: =IF(OR(F20="Below Expectation",F20="Unsatisfactory"),B20&" - "&C20,"")
A21: 20 | B21: Mitra Integrasi Informatika | C21: Purecloud Decommisioning | D21: Noviani MARBUN | E21: ='Q2 MII-Purecloud'!B30 -> 3.8833333 | F21: ='Q2 MII-Purecloud'!B31 -> Meet Expectation | G21: ='Q2 MII-Purecloud'!B42 -> 1) Training Process During the training sessions, it is expected that explanations are delivered in detail and step by step. When participants are conducting hands-on activities, they should be properly provided with guidance and direct support. This is important to avoid unnecessary questions that could otherwise be answered clearly, ensuring that participants can immediately understand the changes and new features introduced. 2) “Baby Sitting” Phase In the “baby sitting” phase, the MII team was expected to be present full day on-site at AMFS for two weeks. However, in practice, the team did not consistently attend and only joined full day after being specifically requested. As a result, the actual presence was only around five days instead of the full two weeks as originally required. | H21: Vendor/proyek baru; belum ada histori kuartal sebelumnya. Klasifikasi Quality/Timeline pada pertanyaan custom memakai heuristik kata kunci — mohon di-review SRM. | I21: =IF(OR(F21="Below Expectation",F21="Unsatisfactory"),B21&" - "&C21,"")
A22: 21 | B22: ESHAEL Indonesia | C22: Talent Assesment | D22: I Gusti Ayu Mira SETYAWARDHANIE | E22: ='Q2 ESHAEL'!B29 -> 4.6083333 | F22: ='Q2 ESHAEL'!B30 -> Exceed Expectation | G22: ='Q2 ESHAEL'!B41 -> N/A | H22: Vendor/proyek baru; belum ada histori kuartal sebelumnya. Klasifikasi Quality/Timeline pada pertanyaan custom memakai heuristik kata kunci — mohon di-review SRM. | I22: =IF(OR(F22="Below Expectation",F22="Unsatisfactory"),B22&" - "&C22,"")
A23: 22 | B23: Arah Sejahtera Abadi | C23: Perjanjian Sewa Menyewa | D23: ibnu.kumala@axa-mandiri.co.id | E23: N/A | F23: Tidak Dievaluasi Q2 | G23: - | H23: Vendor tidak mengisi assessment pada periode Q2 2026. | I23: =IF(OR(F23="Below Expectation",F23="Unsatisfactory"),B23&" - "&C23,"")

Sheet Q2 ITSEC
A1: HASIL REVIEW VENDOR — Q2 2026
A2: Vendor | B2: Itsec Asia
A3: Service | B3: Penetration Testing
A4: PIC (Business User) | B4: Fauzi ARYANTO
A6: No | B6: Dimensi | C6: Pertanyaan | D6: Skor
A7: 1 | B7: Quality | C7: ='RAW DATA Q2 - 1'!ER$1 -> How would you rate the Technical services that is used to penetrate the application which includes: 1. Technical Specification Design. 2. Hardware and capacity sizing for concurrent requests 3. Functi2 | D7: ='RAW DATA Q2 - 1'!ER10 -> 3
A8: 2 | B8: Quality | C8: ='RAW DATA Q2 - 1'!ES$1 -> How would you rate the after sales support capability and methodology?2 | D8: ='RAW DATA Q2 - 1'!ES10 -> 3
A9: 3 | B9: Quality | C9: ='RAW DATA Q2 - 1'!ET$1 -> How would you rate the availability of documentation for product (user manual, troubleshoot document, setup document, etc)?1 | D9: ='RAW DATA Q2 - 1'!ET10 -> 3
A10: 4 | B10: Timeline | C10: ='RAW DATA Q2 - 1'!EU$1 -> How would you rate the supplier's timeliness in delivering goods/services compared to the agreed-upon timeline? | D10: ='RAW DATA Q2 - 1'!EU10 -> 3
A11: 5 | B11: Timeline | C11: ='RAW DATA Q2 - 1'!EV$1 -> How would you rate the supplier's timeliness in sending reports to you? | D11: ='RAW DATA Q2 - 1'!EV10 -> 3
A12: 6 | B12: Timeline | C12: ='RAW DATA Q2 - 1'!EW$1 -> How would you rate the supplier's speed ​​of administrative completion, including completion of contracts draft? | D12: ='RAW DATA Q2 - 1'!EW10 -> 3
A13: 7 | B13: Relationship | C13: ='RAW DATA Q2 - 1'!FM$1 -> How would you rate the supplier's communication with you? | D13: ='RAW DATA Q2 - 1'!FM10 -> 3
A14: 8 | B14: Relationship | C14: ='RAW DATA Q2 - 1'!FN$1 -> How would you rate the supplier's PIC's availability to be contacted when needed? | D14: ='RAW DATA Q2 - 1'!FN10 -> 3
A15: 9 | B15: Relationship | C15: ='RAW DATA Q2 - 1'!FO$1 -> How would you rate the supplier's response speed to you when there are issues? | D15: ='RAW DATA Q2 - 1'!FO10 -> 3
A17: Quality Avg (35%) | B17: =AVERAGEIF(B7:B15,"Quality",D7:D15) -> 3
A18: Timeline Avg (35%) | B18: =AVERAGEIF(B7:B15,"Timeline",D7:D15) -> 3
A19: Relationship Avg (30%) | B19: =AVERAGEIF(B7:B15,"Relationship",D7:D15) -> 3
A20: TOTAL SCORE | B20: =B17*0.35+B18*0.35+B19*0.3 -> 3
A21: STATUS | B21: =IF(B20>4.99,"Exceptional",IF(B20>3.99,"Exceed Expectation",IF(B20>=2.99,"Meet Expectation",IF(B20>1.9,"Below Expectation","Unsatisfactory")))) -> Meet Expectation
A23: DUE DILIGENCE / COMPLIANCE
A24: Financial Assessment | B24: ='RAW DATA Q2 - 1'!FP10 -> Yes
A25: Reputational Assessment | B25: ='RAW DATA Q2 - 1'!FQ10 -> Yes
A26: DPIA | B26: ='RAW DATA Q2 - 1'!FR10 -> Yes, DPIA completed and there are actions to be done by Project Owner
A27: DPSQ | B27: ='RAW DATA Q2 - 1'!FS10 -> No Implementation
A28: VSDDT | B28: ='RAW DATA Q2 - 1'!FT10 -> Yes, VSDDT completed and there are actions to be done by supplier
A29: Action Plan
A31: REMARKS / FEEDBACK
B32: ='RAW DATA Q2 - 1'!FU10 -> -

Sheet Q2 IPROTEKSI
A1: HASIL REVIEW VENDOR — Q2 2026
A2: Vendor | B2: Iproteksi Telematika
A3: Service | B3: Penetration Testing
A4: PIC (Business User) | B4: Fauzi ARYANTO
A6: No | B6: Dimensi | C6: Pertanyaan | D6: Skor
A7: 1 | B7: Quality | C7: ='RAW DATA Q2 - 1'!EO$1 -> How would you rate the Technical services that is used to penetrate the application which includes: 1. Technical Specification Design. 2. Hardware and capacity sizing for concurrent requests 3. Functi1 | D7: ='RAW DATA Q2 - 1'!EO9 -> 4
A8: 2 | B8: Quality | C8: ='RAW DATA Q2 - 1'!EP$1 -> How would you rate the after sales support capability and methodology?1 | D8: ='RAW DATA Q2 - 1'!EP9 -> 4
A9: 3 | B9: Quality | C9: ='RAW DATA Q2 - 1'!EQ$1 -> How would you rate the availability of documentation for product (user manual, troubleshoot document, setup document, etc)? | D9: ='RAW DATA Q2 - 1'!EQ9 -> 4
A10: 4 | B10: Timeline | C10: ='RAW DATA Q2 - 1'!EU$1 -> How would you rate the supplier's timeliness in delivering goods/services compared to the agreed-upon timeline? | D10: ='RAW DATA Q2 - 1'!EU9 -> 4
A11: 5 | B11: Timeline | C11: ='RAW DATA Q2 - 1'!EV$1 -> How would you rate the supplier's timeliness in sending reports to you? | D11: ='RAW DATA Q2 - 1'!EV9 -> 4
A12: 6 | B12: Timeline | C12: ='RAW DATA Q2 - 1'!EW$1 -> How would you rate the supplier's speed ​​of administrative completion, including completion of contracts draft? | D12: ='RAW DATA Q2 - 1'!EW9 -> 4
A13: 7 | B13: Relationship | C13: ='RAW DATA Q2 - 1'!FM$1 -> How would you rate the supplier's communication with you? | D13: ='RAW DATA Q2 - 1'!FM9 -> 4
A14: 8 | B14: Relationship | C14: ='RAW DATA Q2 - 1'!FN$1 -> How would you rate the supplier's PIC's availability to be contacted when needed? | D14: ='RAW DATA Q2 - 1'!FN9 -> 4
A15: 9 | B15: Relationship | C15: ='RAW DATA Q2 - 1'!FO$1 -> How would you rate the supplier's response speed to you when there are issues? | D15: ='RAW DATA Q2 - 1'!FO9 -> 4
A17: Quality Avg (35%) | B17: =AVERAGEIF(B7:B15,"Quality",D7:D15) -> 4
A18: Timeline Avg (35%) | B18: =AVERAGEIF(B7:B15,"Timeline",D7:D15) -> 4
A19: Relationship Avg (30%) | B19: =AVERAGEIF(B7:B15,"Relationship",D7:D15) -> 4
A20: TOTAL SCORE | B20: =B17*0.35+B18*0.35+B19*0.3 -> 4
A21: STATUS | B21: =IF(B20>4.99,"Exceptional",IF(B20>3.99,"Exceed Expectation",IF(B20>=2.99,"Meet Expectation",IF(B20>1.9,"Below Expectation","Unsatisfactory")))) -> Exceed Expectation
A23: DUE DILIGENCE / COMPLIANCE
A24: Financial Assessment | B24: ='RAW DATA Q2 - 1'!FP9 -> Yes
A25: Reputational Assessment | B25: ='RAW DATA Q2 - 1'!FQ9 -> Yes
A26: DPIA | B26: ='RAW DATA Q2 - 1'!FR9 -> Yes, DPIA completed and there are actions to be done by Project Owner
A27: DPSQ | B27: ='RAW DATA Q2 - 1'!FS9 -> No Implementation
A28: VSDDT | B28: ='RAW DATA Q2 - 1'!FT9 -> Yes, VSDDT completed and there are actions to be done by supplier
A29: Action Plan
A31: REMARKS / FEEDBACK
B32: ='RAW DATA Q2 - 1'!FU9 -> -

Sheet Q2 FPT
A1: HASIL REVIEW VENDOR — Q2 2026
A2: Vendor | B2: FPT Metrodata
A3: Service | B3: Penetration Testing
A4: PIC (Business User) | B4: Fauzi ARYANTO
A6: No | B6: Dimensi | C6: Pertanyaan | D6: Skor
A7: 1 | B7: Quality | C7: ='RAW DATA Q2 - 1'!EL$1 -> How would you rate the Technical services that is used to penetrate the application which includes: 1. Technical Specification Design. 2. Hardware and capacity sizing for concurrent requests 3. Functi | D7: ='RAW DATA Q2 - 1'!EL8 -> 4
A8: 2 | B8: Quality | C8: ='RAW DATA Q2 - 1'!EM$1 -> How would you rate the after sales support capability and methodology? | D8: ='RAW DATA Q2 - 1'!EM8 -> 4
A9: 3 | B9: Quality | C9: ='RAW DATA Q2 - 1'!EN$1 -> How would you rate the availability of documentation for service (user manual, troubleshoot document, setup document, etc)? | D9: ='RAW DATA Q2 - 1'!EN8 -> 4
A10: 4 | B10: Timeline | C10: ='RAW DATA Q2 - 1'!EU$1 -> How would you rate the supplier's timeliness in delivering goods/services compared to the agreed-upon timeline? | D10: ='RAW DATA Q2 - 1'!EU8 -> 4
A11: 5 | B11: Timeline | C11: ='RAW DATA Q2 - 1'!EV$1 -> How would you rate the supplier's timeliness in sending reports to you? | D11: ='RAW DATA Q2 - 1'!EV8 -> 4
A12: 6 | B12: Timeline | C12: ='RAW DATA Q2 - 1'!EW$1 -> How would you rate the supplier's speed ​​of administrative completion, including completion of contracts draft? | D12: ='RAW DATA Q2 - 1'!EW8 -> 4
A13: 7 | B13: Relationship | C13: ='RAW DATA Q2 - 1'!FM$1 -> How would you rate the supplier's communication with you? | D13: ='RAW DATA Q2 - 1'!FM8 -> 4
A14: 8 | B14: Relationship | C14: ='RAW DATA Q2 - 1'!FN$1 -> How would you rate the supplier's PIC's availability to be contacted when needed? | D14: ='RAW DATA Q2 - 1'!FN8 -> 4
A15: 9 | B15: Relationship | C15: ='RAW DATA Q2 - 1'!FO$1 -> How would you rate the supplier's response speed to you when there are issues? | D15: ='RAW DATA Q2 - 1'!FO8 -> 4
A17: Quality Avg (35%) | B17: =AVERAGEIF(B7:B15,"Quality",D7:D15) -> 4
A18: Timeline Avg (35%) | B18: =AVERAGEIF(B7:B15,"Timeline",D7:D15) -> 4
A19: Relationship Avg (30%) | B19: =AVERAGEIF(B7:B15,"Relationship",D7:D15) -> 4
A20: TOTAL SCORE | B20: =B17*0.35+B18*0.35+B19*0.3 -> 4
A21: STATUS | B21: =IF(B20>4.99,"Exceptional",IF(B20>3.99,"Exceed Expectation",IF(B20>=2.99,"Meet Expectation",IF(B20>1.9,"Below Expectation","Unsatisfactory")))) -> Exceed Expectation
A23: DUE DILIGENCE / COMPLIANCE
A24: Financial Assessment | B24: ='RAW DATA Q2 - 1'!FP8 -> Yes
A25: Reputational Assessment | B25: ='RAW DATA Q2 - 1'!FQ8 -> Yes
A26: DPIA | B26: ='RAW DATA Q2 - 1'!FR8 -> Yes, DPIA completed and there are actions to be done by Project Owner
A27: DPSQ | B27: ='RAW DATA Q2 - 1'!FS8 -> No Implementation
A28: VSDDT | B28: ='RAW DATA Q2 - 1'!FT8 -> Yes, VSDDT completed and there are actions to be done by supplier
A29: Action Plan
A31: REMARKS / FEEDBACK
B32: ='RAW DATA Q2 - 1'!FU8 -> -

Sheet Q2 SAP-Mailing
A1: HASIL REVIEW VENDOR — Q2 2026
A2: Vendor | B2: Satria Antaran Prima
A3: Service | B3: Mailing Room
A4: PIC (Business User) | B4: Ibnu KUMALA
A6: No | B6: Dimensi | C6: Pertanyaan | D6: Skor
A7: 1 | B7: Quality | C7: ='RAW DATA Q2 - 1'!DX$1 -> How would you rate the goods/services provided by the Supplier against the agreed standards?1 | D7: ='RAW DATA Q2 - 1'!DX11 -> 3
A8: 2 | B8: Quality | C8: ='RAW DATA Q2 - 1'!DY$1 -> How would you rate the accuracy of the data in the Supplier's reports?6 | D8: ='RAW DATA Q2 - 1'!DY11 -> 4
A9: 3 | B9: Quality | C9: ='RAW DATA Q2 - 1'!DZ$1 -> How would you rate overall quality of the work reports provided by the Supplier?6 | D9: ='RAW DATA Q2 - 1'!DZ11 -> 3
A10: 4 | B10: Quality | C10: ='RAW DATA Q2 - 1'!EA$1 -> How would you rate the solutions provided when there is trouble?6 | D10: ='RAW DATA Q2 - 1'!EA11 -> 3
A11: 5 | B11: Quality | C11: ='RAW DATA Q2 - 1'!EB$1 -> How would you rate the resolution to the problem that occurred?6 | D11: ='RAW DATA Q2 - 1'!EB11 -> 3
A12: 6 | B12: Quality | C12: ='RAW DATA Q2 - 1'!EC$1 -> How would you rate the supplier initiative to take mitigation/preventive action to prevent the problem from recurring?7 | D12: ='RAW DATA Q2 - 1'!EC11 -> 3
A13: 7 | B13: Quality | C13: ='RAW DATA Q2 - 1'!ED$1 -> How would you rate the service provided? | D13: ='RAW DATA Q2 - 1'!ED11 -> 3
A14: 8 | B14: Quality | C14: ='RAW DATA Q2 - 1'!EE$1 -> How would you rate the Complaint Handling? | D14: ='RAW DATA Q2 - 1'!EE11 -> 3
A15: 9 | B15: Timeline | C15: ='RAW DATA Q2 - 1'!EU$1 -> How would you rate the supplier's timeliness in delivering goods/services compared to the agreed-upon timeline? | D15: ='RAW DATA Q2 - 1'!EU11 -> 3
A16: 10 | B16: Timeline | C16: ='RAW DATA Q2 - 1'!EV$1 -> How would you rate the supplier's timeliness in sending reports to you? | D16: ='RAW DATA Q2 - 1'!EV11 -> 3
A17: 11 | B17: Timeline | C17: ='RAW DATA Q2 - 1'!EW$1 -> How would you rate the supplier's speed ​​of administrative completion, including completion of contracts draft? | D17: ='RAW DATA Q2 - 1'!EW11 -> 3
A18: 12 | B18: Relationship | C18: ='RAW DATA Q2 - 1'!FM$1 -> How would you rate the supplier's communication with you? | D18: ='RAW DATA Q2 - 1'!FM11 -> 3
A19: 13 | B19: Relationship | C19: ='RAW DATA Q2 - 1'!FN$1 -> How would you rate the supplier's PIC's availability to be contacted when needed? | D19: ='RAW DATA Q2 - 1'!FN11 -> 3
A20: 14 | B20: Relationship | C20: ='RAW DATA Q2 - 1'!FO$1 -> How would you rate the supplier's response speed to you when there are issues? | D20: ='RAW DATA Q2 - 1'!FO11 -> 3
A22: Quality Avg (35%) | B22: =AVERAGEIF(B7:B20,"Quality",D7:D20) -> 3.125
A23: Timeline Avg (35%) | B23: =AVERAGEIF(B7:B20,"Timeline",D7:D20) -> 3
A24: Relationship Avg (30%) | B24: =AVERAGEIF(B7:B20,"Relationship",D7:D20) -> 3
A25: TOTAL SCORE | B25: =B22*0.35+B23*0.35+B24*0.3 -> 3.04375
A26: STATUS | B26: =IF(B25>4.99,"Exceptional",IF(B25>3.99,"Exceed Expectation",IF(B25>=2.99,"Meet Expectation",IF(B25>1.9,"Below Expectation","Unsatisfactory")))) -> Meet Expectation
A28: DUE DILIGENCE / COMPLIANCE
A29: Financial Assessment | B29: ='RAW DATA Q2 - 1'!FP11 -> Yes
A30: Reputational Assessment | B30: ='RAW DATA Q2 - 1'!FQ11 -> Yes
A31: DPIA | B31: ='RAW DATA Q2 - 1'!FR11 -> Yes, DPIA completed and there are actions to be done by Project Owner
A32: DPSQ | B32: ='RAW DATA Q2 - 1'!FS11 -> No Implementation
A33: VSDDT | B33: ='RAW DATA Q2 - 1'!FT11 -> Yes, VSDDT completed and there are actions to be done by supplier
A34: Action Plan
A36: REMARKS / FEEDBACK
B37: ='RAW DATA Q2 - 1'!FU11 -> improve inisiatsis

Sheet Q2 JATIS
A1: HASIL REVIEW VENDOR — Q2 2026
A2: Vendor | B2: Informasi Teknologi Indonesia - SMS Broadcast
A3: Service
A4: PIC (Business User) | B4: Fifin SARINURLITA
A6: No | B6: Dimensi | C6: Pertanyaan | D6: Skor
A7: 1 | B7: Quality | C7: ='RAW DATA Q2 - 1'!AA$1 -> How would you rate Supplier's ability to understand and meet your needs?1 | D7: ='RAW DATA Q2 - 1'!AA5 -> 3
A8: 2 | B8: Quality | C8: ='RAW DATA Q2 - 1'!AB$1 -> How would you rate the goods/services provided by the Supplier against the agreed standards? | D8: ='RAW DATA Q2 - 1'!AB5 -> 3
A9: 3 | B9: Quality | C9: ='RAW DATA Q2 - 1'!AC$1 -> How would you rate the accuracy of the data in the Supplier's reports? | D9: ='RAW DATA Q2 - 1'!AC5 -> 3
A10: 4 | B10: Quality | C10: ='RAW DATA Q2 - 1'!AD$1 -> How would you rate overall quality of the work reports provided by the Supplier? | D10: ='RAW DATA Q2 - 1'!AD5 -> 3
A11: 5 | B11: Quality | C11: ='RAW DATA Q2 - 1'!AE$1 -> How would you rate the solutions provided when there is trouble? | D11: ='RAW DATA Q2 - 1'!AE5 -> 3
A12: 6 | B12: Quality | C12: ='RAW DATA Q2 - 1'!AF$1 -> How would you rate the resolution to the problem that occurred? | D12: ='RAW DATA Q2 - 1'!AF5 -> 3
A13: 7 | B13: Quality | C13: ='RAW DATA Q2 - 1'!AG$1 -> How would you rate the speed of resolution given to problems that occur? | D13: ='RAW DATA Q2 - 1'!AG5 -> 3
A14: 8 | B14: Quality | C14: ='RAW DATA Q2 - 1'!AH$1 -> How would you rate the supplier initiative to take mitigation/preventive action to prevent the problem from recurring? | D14: ='RAW DATA Q2 - 1'!AH5 -> 3
A15: 9 | B15: Quality | C15: ='RAW DATA Q2 - 1'!AI$1 -> How would you rate supplier compliance with administrative processes, including completion of draft cooperation contract?1 | D15: ='RAW DATA Q2 - 1'!AI5 -> 3
A16: 10 | B16: Quality | C16: ='RAW DATA Q2 - 1'!AJ$1 -> How would you rate the Implementation of UAT? | D16: ='RAW DATA Q2 - 1'!AJ5 -> 3
A17: 11 | B17: Quality | C17: ='RAW DATA Q2 - 1'!AK$1 -> How would you rate the maintenance includes bug fixing and support for system problems that occur in the JATIS MOBILE application/service? | D17: ='RAW DATA Q2 - 1'!AK5 -> 3
A18: 12 | B18: Timeline | C18: ='RAW DATA Q2 - 1'!EX$1 -> How would you rate the supplier's timeliness in delivering goods/services compared to the agreed-upon timeline?1 | D18: ='RAW DATA Q2 - 1'!EX5 -> 3
A19: 13 | B19: Timeline | C19: ='RAW DATA Q2 - 1'!EY$1 -> How would you rate the supplier's timeliness in sending reports to you? | D19: ='RAW DATA Q2 - 1'!EY5 -> 3
A20: 14 | B20: Timeline | C20: ='RAW DATA Q2 - 1'!EZ$1 -> How would you rate the supplier's Traffic Confirmation SLA Fulfillment? | D20: ='RAW DATA Q2 - 1'!EZ5 -> 3
A21: 15 | B21: Timeline | C21: ='RAW DATA Q2 - 1'!FA$1 -> How would you rate the supplier's speed ​​of administrative completion, including completion of contracts draft? | D21: ='RAW DATA Q2 - 1'!FA5 -> 3
A22: 16 | B22: Relationship | C22: ='RAW DATA Q2 - 1'!FM$1 -> How would you rate the supplier's communication with you? | D22: ='RAW DATA Q2 - 1'!FM5 -> 3
A23: 17 | B23: Relationship | C23: ='RAW DATA Q2 - 1'!FN$1 -> How would you rate the supplier's PIC's availability to be contacted when needed? | D23: ='RAW DATA Q2 - 1'!FN5 -> 3
A24: 18 | B24: Relationship | C24: ='RAW DATA Q2 - 1'!FO$1 -> How would you rate the supplier's response speed to you when there are issues? | D24: ='RAW DATA Q2 - 1'!FO5 -> 3
A26: Quality Avg (35%) | B26: =AVERAGEIF(B7:B24,"Quality",D7:D24) -> 3
A27: Timeline Avg (35%) | B27: =AVERAGEIF(B7:B24,"Timeline",D7:D24) -> 3
A28: Relationship Avg (30%) | B28: =AVERAGEIF(B7:B24,"Relationship",D7:D24) -> 3
A29: TOTAL SCORE | B29: =B26*0.35+B27*0.35+B28*0.3 -> 3
A30: STATUS | B30: =IF(B29>4.99,"Exceptional",IF(B29>3.99,"Exceed Expectation",IF(B29>=2.99,"Meet Expectation",IF(B29>1.9,"Below Expectation","Unsatisfactory")))) -> Meet Expectation
A32: DUE DILIGENCE / COMPLIANCE
A33: Financial Assessment | B33: ='RAW DATA Q2 - 1'!FP5 -> Yes
A34: Reputational Assessment | B34: ='RAW DATA Q2 - 1'!FQ5 -> Yes
A35: DPIA | B35: ='RAW DATA Q2 - 1'!FR5 -> Yes, DPIA completed and there are actions to be done by Project Owner
A36: DPSQ | B36: ='RAW DATA Q2 - 1'!FS5 -> Yes, DPSQ completed
A37: VSDDT | B37: ='RAW DATA Q2 - 1'!FT5 -> Yes, VSDDT completed and there are actions to be done by supplier
A38: Action Plan
A40: REMARKS / FEEDBACK
B41: ='RAW DATA Q2 - 1'!FU5 -> So far, Jatis Vendor has provided good service. Their response time is fast, and they are able to provide effective solutions whenever issues arise

Sheet Q2 SAP-Courier
A1: HASIL REVIEW VENDOR — Q2 2026
A2: Vendor | B2: Satria Antaran Prima
A3: Service | B3: Courier Service
A4: PIC (Business User) | B4: Fifin SARINURLITA, Novia Laras SANTI
A5: Catatan | B5: Skor merupakan RATA-RATA dari 2 business user yang menilai vendor/service yang sama pada periode ini (kasus normal: multiple raters).
A7: No | B7: Dimensi | C7: Pertanyaan | D7: Skor
A8: 1 | B8: Quality | C8: ='RAW DATA Q2 - 1'!DI$1 -> How would you rate the goods/services provided by the Supplier against the agreed standards3 | D8: =AVERAGE('RAW DATA Q2 - 1'!DI6,'RAW DATA Q2 - 1'!DI7) -> 3.5
A9: 2 | B9: Quality | C9: ='RAW DATA Q2 - 1'!DJ$1 -> How would you rate the accuracy of the data in the Supplier's reports?5 | D9: =AVERAGE('RAW DATA Q2 - 1'!DJ6,'RAW DATA Q2 - 1'!DJ7) -> 2.5
A10: 3 | B10: Quality | C10: ='RAW DATA Q2 - 1'!DK$1 -> How would you rate overall quality of the work reports provided by the Supplier?5 | D10: =AVERAGE('RAW DATA Q2 - 1'!DK6,'RAW DATA Q2 - 1'!DK7) -> 3
A11: 4 | B11: Quality | C11: ='RAW DATA Q2 - 1'!DL$1 -> How would you rate the solutions provided when there is trouble?5 | D11: =AVERAGE('RAW DATA Q2 - 1'!DL6,'RAW DATA Q2 - 1'!DL7) -> 3
A12: 5 | B12: Quality | C12: ='RAW DATA Q2 - 1'!DM$1 -> How would you rate the resolution to the problem that occurred?5 | D12: =AVERAGE('RAW DATA Q2 - 1'!DM6,'RAW DATA Q2 - 1'!DM7) -> 2.5
A13: 6 | B13: Quality | C13: ='RAW DATA Q2 - 1'!DN$1 -> How would you rate the speed of resolution given to problems that occur | D13: =AVERAGE('RAW DATA Q2 - 1'!DN6,'RAW DATA Q2 - 1'!DN7) -> 3.5
A14: 7 | B14: Quality | C14: ='RAW DATA Q2 - 1'!DO$1 -> How would you rate the supplier initiative to take mitigation/preventive action to prevent the problem from recurring?6 | D14: =AVERAGE('RAW DATA Q2 - 1'!DO6,'RAW DATA Q2 - 1'!DO7) -> 3
A15: 8 | B15: Quality | C15: ='RAW DATA Q2 - 1'!DP$1 -> How would you rate supplier compliance with administrative processes, including completion of draft cooperation contract?6 | D15: =AVERAGE('RAW DATA Q2 - 1'!DP6,'RAW DATA Q2 - 1'!DP7) -> 3
A16: 9 | B16: Quality | C16: ='RAW DATA Q2 - 1'!DQ$1 -> How would you rate the shipping target achievement? | D16: =AVERAGE('RAW DATA Q2 - 1'!DQ6,'RAW DATA Q2 - 1'!DQ7) -> 2.5
A17: 10 | B17: Quality | C17: ='RAW DATA Q2 - 1'!DR$1 -> How would you rate the delivery times? Based on SLA, the delivery time are Monday to Saturday, service levels will remain the same from Monday to Friday. | D17: =AVERAGE('RAW DATA Q2 - 1'!DR6,'RAW DATA Q2 - 1'!DR7) -> 2.5
A18: 11 | B18: Quality | C18: ='RAW DATA Q2 - 1'!DS$1 -> How would you rate the Receipt retention period? | D18: =AVERAGE('RAW DATA Q2 - 1'!DS6,'RAW DATA Q2 - 1'!DS7) -> 2.5
A19: 12 | B19: Quality | C19: ='RAW DATA Q2 - 1'!DT$1 -> How would you rate the Airway Bill Storage: | D19: =AVERAGE('RAW DATA Q2 - 1'!DT6,'RAW DATA Q2 - 1'!DT7) -> 3.5
A20: 13 | B20: Quality | C20: ='RAW DATA Q2 - 1'!DU$1 -> How would you rate the Handling of Policies/Documents and/or delivery process? | D20: =AVERAGE('RAW DATA Q2 - 1'!DU6,'RAW DATA Q2 - 1'!DU7) -> 3
A21: 14 | B21: Quality | C21: ='RAW DATA Q2 - 1'!DV$1 -> How would you rate the response to complaints/investigations of the delivery process? | D21: =AVERAGE('RAW DATA Q2 - 1'!DV6,'RAW DATA Q2 - 1'!DV7) -> 3.5
A22: 15 | B22: Quality | C22: ='RAW DATA Q2 - 1'!DW$1 -> How would you rate the response taken when a delivery failure occurs? | D22: =AVERAGE('RAW DATA Q2 - 1'!DW6,'RAW DATA Q2 - 1'!DW7) -> 3
A23: 16 | B23: Timeline | C23: ='RAW DATA Q2 - 1'!FJ$1 -> How would you rate the supplier's timeliness in delivering goods/services compared to the agreed-upon timeline?4 | D23: =AVERAGE('RAW DATA Q2 - 1'!FJ6,'RAW DATA Q2 - 1'!FJ7) -> 2.5
A24: 17 | B24: Timeline | C24: ='RAW DATA Q2 - 1'!FK$1 -> How would you rate the supplier's timeliness in sending reports to you?1 | D24: =AVERAGE('RAW DATA Q2 - 1'!FK6,'RAW DATA Q2 - 1'!FK7) -> 3.5
A25: 18 | B25: Timeline | C25: ='RAW DATA Q2 - 1'!FL$1 -> How would you rate the supplier's speed ​​of administrative completion, including completion of contracts draft?2 | D25: =AVERAGE('RAW DATA Q2 - 1'!FL6,'RAW DATA Q2 - 1'!FL7) -> 3
A26: 19 | B26: Relationship | C26: ='RAW DATA Q2 - 1'!FM$1 -> How would you rate the supplier's communication with you? | D26: =AVERAGE('RAW DATA Q2 - 1'!FM6,'RAW DATA Q2 - 1'!FM7) -> 4
A27: 20 | B27: Relationship | C27: ='RAW DATA Q2 - 1'!FN$1 -> How would you rate the supplier's PIC's availability to be contacted when needed? | D27: =AVERAGE('RAW DATA Q2 - 1'!FN6,'RAW DATA Q2 - 1'!FN7) -> 4
A28: 21 | B28: Relationship | C28: ='RAW DATA Q2 - 1'!FO$1 -> How would you rate the supplier's response speed to you when there are issues? | D28: =AVERAGE('RAW DATA Q2 - 1'!FO6,'RAW DATA Q2 - 1'!FO7) -> 3.5
A30: Quality Avg (35%) | B30: =AVERAGEIF(B8:B28,"Quality",D8:D28) -> 2.9666667
A31: Timeline Avg (35%) | B31: =AVERAGEIF(B8:B28,"Timeline",D8:D28) -> 3
A32: Relationship Avg (30%) | B32: =AVERAGEIF(B8:B28,"Relationship",D8:D28) -> 3.8333333
A33: TOTAL SCORE | B33: =B30*0.35+B31*0.35+B32*0.3 -> 3.2383333
A34: STATUS | B34: =IF(B33>4.99,"Exceptional",IF(B33>3.99,"Exceed Expectation",IF(B33>=2.99,"Meet Expectation",IF(B33>1.9,"Below Expectation","Unsatisfactory")))) -> Meet Expectation
A36: DUE DILIGENCE / COMPLIANCE
B37: Fifin SARINURLITA | C37: Novia Laras SANTI
A38: Financial Assessment | B38: ='RAW DATA Q2 - 1'!FP6 -> Yes | C38: ='RAW DATA Q2 - 1'!FP7 -> No
A39: Reputational Assessment | B39: ='RAW DATA Q2 - 1'!FQ6 -> Yes | C39: ='RAW DATA Q2 - 1'!FQ7 -> Yes
A40: DPIA | B40: ='RAW DATA Q2 - 1'!FR6 -> Yes, DPIA completed and there are actions to be done by Project Owner | C40: ='RAW DATA Q2 - 1'!FR7 -> No Implementation
A41: DPSQ | B41: ='RAW DATA Q2 - 1'!FS6 -> Yes, DPSQ completed | C41: ='RAW DATA Q2 - 1'!FS7 -> No Implementation
A42: VSDDT | B42: ='RAW DATA Q2 - 1'!FT6 -> Yes, VSDDT completed and there are actions to be done by supplier | C42: ='RAW DATA Q2 - 1'!FT7 -> No Implementation
A43: Action Plan
A44: ⚠ Catatan | B44: Jawaban compliance dari 2 user BERBEDA — mohon konfirmasi dengan SRM/PIC terkait mana yang valid.
A46: REMARKS / FEEDBACK
A47: Fifin SARINURLITA: | B47: ='RAW DATA Q2 - 1'!FU6 -> SAP has shown improvement in terms of reporting and provides a fast response whenever issues arise.
A48: Novia Laras SANTI: | B48: ='RAW DATA Q2 - 1'!FU7 -> 1. untuk detail status pengiriman dokumen/barang harus diberikan keterangan penerima dengan lengkap dan jelas; 2. Maks. SLA pengiriman harus memenuhi sesuai dengan yang ditetapkan yaitu <5% not meet SLA; 3. Invoice biaya pengiriman dikirimkan ke user yang sesuai dan dikirimkan tidak melebihi periode yang ditetapkan. 4. Report Stock sesuai dengan real stock di warehouse.

Sheet Q2 MMI
A1: HASIL REVIEW VENDOR — Q2 2026
A2: Vendor | B2: Multifiling Mitra Indonesia
A3: Service | B3: Record Management Service
A4: PIC (Business User) | B4: Ibnu KUMALA
A6: No | B6: Dimensi | C6: Pertanyaan | D6: Skor
A7: 1 | B7: Quality | C7: ='RAW DATA Q2 - 1'!AY$1 -> How would you rate The goods/services provided by the Supplier against the agreed standards | D7: ='RAW DATA Q2 - 1'!AY12 -> 3
A8: 2 | B8: Quality | C8: ='RAW DATA Q2 - 1'!AZ$1 -> How would you rate the supplier's services? | D8: ='RAW DATA Q2 - 1'!AZ12 -> 3
A9: 3 | B9: Quality | C9: ='RAW DATA Q2 - 1'!BA$1 -> How would you rate the supplier's service in providing a guarantee of administrative services for archive management, computer data collection for all AXA cartons, and ease of access for AXA to the ar | D9: ='RAW DATA Q2 - 1'!BA12 -> 3
A10: 4 | B10: Quality | C10: ='RAW DATA Q2 - 1'!BB$1 -> How would you rate the supplier's service in providing the required number of empty cartons? | D10: ='RAW DATA Q2 - 1'!BB12 -> 3
A11: 5 | B11: Quality | C11: ='RAW DATA Q2 - 1'!BC$1 -> How would you rate overall quality of the work reports provided by the Supplier?2 | D11: ='RAW DATA Q2 - 1'!BC12 -> 3
A12: 6 | B12: Quality | C12: ='RAW DATA Q2 - 1'!BD$1 -> How would you rate the completeness report containing the number of AXA cartons deposited in the supplier's warehouse, a list of cartons that are being borrowed (retrieval) and have not been returned | D12: ='RAW DATA Q2 - 1'!BD12 -> 3
A13: 7 | B13: Quality | C13: ='RAW DATA Q2 - 1'!BE$1 -> How would you rate the solutions provided when there is trouble?2 | D13: ='RAW DATA Q2 - 1'!BE12 -> 3
A14: 8 | B14: Quality | C14: ='RAW DATA Q2 - 1'!BF$1 -> How would you rate the resolution to the problem that occurred?2 | D14: ='RAW DATA Q2 - 1'!BF12 -> 3
A15: 9 | B15: Quality | C15: ='RAW DATA Q2 - 1'!BG$1 -> How would you rate the speed of resolution given to problems that occur?2 | D15: ='RAW DATA Q2 - 1'!BG12 -> 3
A16: 10 | B16: Quality | C16: ='RAW DATA Q2 - 1'!BH$1 -> How would you rate the supplier initiative to take mitigation/preventive action to prevent the problem from recurring?2 | D16: ='RAW DATA Q2 - 1'!BH12 -> 3
A17: 11 | B17: Quality | C17: ='RAW DATA Q2 - 1'!BI$1 -> How would you rate supplier compliance with administrative processes, including completion of draft cooperation contract?3 | D17: ='RAW DATA Q2 - 1'!BI12 -> 3
A18: 12 | B18: Timeline | C18: ='RAW DATA Q2 - 1'!FB$1 -> How would you rate the supplier's timeliness in delivering goods/services compared to the agreed-upon timeline?2 | D18: ='RAW DATA Q2 - 1'!FB12 -> 3
A19: 13 | B19: Timeline | C19: ='RAW DATA Q2 - 1'!FC$1 -> How would you rate the supplier's timeliness in sending reports to you? Based on SLA, suppliers must provide reports on the 10th of each month. | D19: ='RAW DATA Q2 - 1'!FC12 -> 3
A20: 14 | B20: Timeline | C20: ='RAW DATA Q2 - 1'!FD$1 -> How would you rate the supplier's speed ​​of administrative completion, including completion of contracts draft? 1 | D20: ='RAW DATA Q2 - 1'!FD12 -> 3
A21: 15 | B21: Timeline | C21: ='RAW DATA Q2 - 1'!FE$1 -> How would you rate the supplier's SLA Fulfillment? | D21: ='RAW DATA Q2 - 1'!FE12 -> 3
A22: 16 | B22: Relationship | C22: ='RAW DATA Q2 - 1'!FM$1 -> How would you rate the supplier's communication with you? | D22: ='RAW DATA Q2 - 1'!FM12 -> 3
A23: 17 | B23: Relationship | C23: ='RAW DATA Q2 - 1'!FN$1 -> How would you rate the supplier's PIC's availability to be contacted when needed? | D23: ='RAW DATA Q2 - 1'!FN12 -> 3
A24: 18 | B24: Relationship | C24: ='RAW DATA Q2 - 1'!FO$1 -> How would you rate the supplier's response speed to you when there are issues? | D24: ='RAW DATA Q2 - 1'!FO12 -> 3
A26: Quality Avg (35%) | B26: =AVERAGEIF(B7:B24,"Quality",D7:D24) -> 3
A27: Timeline Avg (35%) | B27: =AVERAGEIF(B7:B24,"Timeline",D7:D24) -> 3
A28: Relationship Avg (30%) | B28: =AVERAGEIF(B7:B24,"Relationship",D7:D24) -> 3
A29: TOTAL SCORE | B29: =B26*0.35+B27*0.35+B28*0.3 -> 3
A30: STATUS | B30: =IF(B29>4.99,"Exceptional",IF(B29>3.99,"Exceed Expectation",IF(B29>=2.99,"Meet Expectation",IF(B29>1.9,"Below Expectation","Unsatisfactory")))) -> Meet Expectation
A32: DUE DILIGENCE / COMPLIANCE
A33: Financial Assessment | B33: ='RAW DATA Q2 - 1'!FP12 -> Yes
A34: Reputational Assessment | B34: ='RAW DATA Q2 - 1'!FQ12 -> Yes
A35: DPIA | B35: ='RAW DATA Q2 - 1'!FR12 -> Yes, DPIA completed and there are actions to be done by Project Owner
A36: DPSQ | B36: ='RAW DATA Q2 - 1'!FS12 -> Yes, DPSQ completed
A37: VSDDT | B37: ='RAW DATA Q2 - 1'!FT12 -> Yes, VSDDT completed and there are actions to be done by supplier
A38: Action Plan
A40: REMARKS / FEEDBACK
B41: ='RAW DATA Q2 - 1'!FU12 -> ..

Sheet Q2 INDOSAT
A1: HASIL REVIEW VENDOR — Q2 2026
A2: Vendor | B2: Indosat
A3: Service | B3: Layanan PBX berbasiskan cloud dengan Teknologi SIP Trunk
A4: PIC (Business User) | B4: Nuril HUDHA
A6: No | B6: Dimensi | C6: Pertanyaan | D6: Skor
A7: 1 | B7: Quality | C7: ='RAW DATA Q2 - 1'!H$1 -> How would you rate Supplier's ability to understand and meet your needs? | D7: ='RAW DATA Q2 - 1'!H3 -> 3
A8: 2 | B8: Quality | C8: ='RAW DATA Q2 - 1'!I$1 -> How would you rate the Quality of fulfillment of specifications required by Perfect Assistant? | D8: ='RAW DATA Q2 - 1'!I3 -> 3
A9: 3 | B9: Quality | C9: ='RAW DATA Q2 - 1'!J$1 -> How would you rate the data model of source of leads on customer level, which contains Existing Customers, Potential Customers, and Hot Leads? | D9: ='RAW DATA Q2 - 1'!J3 -> 4
A10: 4 | B10: Quality | C10: ='RAW DATA Q2 - 1'!K$1 -> How would you rate the Leads activity evidence and result details, such as Call, Appointment, Visit, and Closing result evidence? | D10: ='RAW DATA Q2 - 1'!K3 -> 4
A11: 5 | B11: Quality | C11: ='RAW DATA Q2 - 1'!L$1 -> How would you rate the Sales Activity Management process, as tracked by the Sales Leader and sorted by time range? | D11: ='RAW DATA Q2 - 1'!L3 -> 4
A12: 6 | B12: Quality | C12: ='RAW DATA Q2 - 1'!M$1 -> How would you rate the Notification to Sales Team which consist of: | D12: ='RAW DATA Q2 - 1'!M3 -> 4
A13: 7 | B13: Quality | C13: ='RAW DATA Q2 - 1'!N$1 -> How would you rate the telephony features which enable to mask either/both Customers’ and Agents’ personal phone number for better customer service and better protection of Customers’ privacy? | D13: ='RAW DATA Q2 - 1'!N3 -> 4
A14: 8 | B14: Quality | C14: ='RAW DATA Q2 - 1'!O$1 -> How would you rate the assignment features which enable leaders to re-assign the leads to other FA (e.g. FA resigned or move to other branch then the Leads will be assigned to existing FA)? | D14: ='RAW DATA Q2 - 1'!O3 -> 3
A15: 9 | B15: Quality | C15: ='RAW DATA Q2 - 1'!P$1 -> How would you rate the System Availability, Redundancy, and Overload Protection? | D15: ='RAW DATA Q2 - 1'!P3 -> 3
A16: 10 | B16: Quality | C16: ='RAW DATA Q2 - 1'!Q$1 -> How would you rate the Security Access? | D16: ='RAW DATA Q2 - 1'!Q3 -> 4
A17: 11 | B17: Quality | C17: ='RAW DATA Q2 - 1'!R$1 -> How would you rate the Audit Trail? | D17: ='RAW DATA Q2 - 1'!R3 -> 4
A18: 12 | B18: Quality | C18: ='RAW DATA Q2 - 1'!S$1 -> How would you rate the Overall Supplier's reports including Report of Leads activity record and tracking? | D18: ='RAW DATA Q2 - 1'!S3 -> 4
A19: 13 | B19: Quality | C19: ='RAW DATA Q2 - 1'!T$1 -> How would you rate the Resources / Authorized Personel Commitment and Qualification? | D19: ='RAW DATA Q2 - 1'!T3 -> 4
A20: 14 | B20: Quality | C20: ='RAW DATA Q2 - 1'!U$1 -> How would you rate supplier initiative to take mitigation/preventive action to prevent recurring problem? | D20: ='RAW DATA Q2 - 1'!U3 -> 4
A21: 15 | B21: Quality | C21: ='RAW DATA Q2 - 1'!V$1 -> How would you rate supplier compliance with administrative processes, including completion of draft cooperation contract? | D21: ='RAW DATA Q2 - 1'!V3 -> 4
A22: 16 | B22: Quality | C22: ='RAW DATA Q2 - 1'!W$1 -> How would you rate the Integration with Perfect Assistant? | D22: ='RAW DATA Q2 - 1'!W3 -> 4
A23: 17 | B23: Quality | C23: ='RAW DATA Q2 - 1'!X$1 -> How would you rate the use of channels to avoid customer data leaks? | D23: ='RAW DATA Q2 - 1'!X3 -> 4
A24: 18 | B24: Quality | C24: ='RAW DATA Q2 - 1'!Y$1 -> How would you rate the Access to the recording dashboard? | D24: ='RAW DATA Q2 - 1'!Y3 -> 3
A25: 19 | B25: Quality | C25: ='RAW DATA Q2 - 1'!Z$1 -> How would you rate the Security compare to its standard? | D25: ='RAW DATA Q2 - 1'!Z3 -> 3
A26: 20 | B26: Timeline | C26: ='RAW DATA Q2 - 1'!EU$1 -> How would you rate the supplier's timeliness in delivering goods/services compared to the agreed-upon timeline? | D26: ='RAW DATA Q2 - 1'!EU3 -> 3
A27: 21 | B27: Timeline | C27: ='RAW DATA Q2 - 1'!EV$1 -> How would you rate the supplier's timeliness in sending reports to you? | D27: ='RAW DATA Q2 - 1'!EV3 -> 3
A28: 22 | B28: Timeline | C28: ='RAW DATA Q2 - 1'!EW$1 -> How would you rate the supplier's speed ​​of administrative completion, including completion of contracts draft? | D28: ='RAW DATA Q2 - 1'!EW3 -> 3
A29: 23 | B29: Relationship | C29: ='RAW DATA Q2 - 1'!FM$1 -> How would you rate the supplier's communication with you? | D29: ='RAW DATA Q2 - 1'!FM3 -> 4
A30: 24 | B30: Relationship | C30: ='RAW DATA Q2 - 1'!FN$1 -> How would you rate the supplier's PIC's availability to be contacted when needed? | D30: ='RAW DATA Q2 - 1'!FN3 -> 4
A31: 25 | B31: Relationship | C31: ='RAW DATA Q2 - 1'!FO$1 -> How would you rate the supplier's response speed to you when there are issues? | D31: ='RAW DATA Q2 - 1'!FO3 -> 3
A33: Quality Avg (35%) | B33: =AVERAGEIF(B7:B31,"Quality",D7:D31) -> 3.6842105
A34: Timeline Avg (35%) | B34: =AVERAGEIF(B7:B31,"Timeline",D7:D31) -> 3
A35: Relationship Avg (30%) | B35: =AVERAGEIF(B7:B31,"Relationship",D7:D31) -> 3.6666667
A36: TOTAL SCORE | B36: =B33*0.35+B34*0.35+B35*0.3 -> 3.4394737
A37: STATUS | B37: =IF(B36>4.99,"Exceptional",IF(B36>3.99,"Exceed Expectation",IF(B36>=2.99,"Meet Expectation",IF(B36>1.9,"Below Expectation","Unsatisfactory")))) -> Meet Expectation
A39: DUE DILIGENCE / COMPLIANCE
A40: Financial Assessment | B40: ='RAW DATA Q2 - 1'!FP3 -> Yes
A41: Reputational Assessment | B41: ='RAW DATA Q2 - 1'!FQ3 -> Yes
A42: DPIA | B42: ='RAW DATA Q2 - 1'!FR3 -> No Implementation
A43: DPSQ | B43: ='RAW DATA Q2 - 1'!FS3 -> DPSQ not completed yet
A44: VSDDT | B44: ='RAW DATA Q2 - 1'!FT3 -> No Implementation
A45: Action Plan
A47: REMARKS / FEEDBACK
B48: ='RAW DATA Q2 - 1'!FU3 -> Vendor performance is generally acceptable and aligns with the expected level of service. While the engagement has been positive overall, improvements are needed in feature enhancement, dashboard capabilities, and the regularity of report updates. Better preparation in deployment and timely reporting would help increase the overall value and effectiveness of the service.

Sheet Q2 CIPTADRA
A1: HASIL REVIEW VENDOR — Q2 2026
A2: Vendor | B2: Ciptadra Softindo
A3: Service | B3: Pemeliharaan Axits & DMTM
A4: PIC (Business User) | B4: Raninta MAHARDI
A6: No | B6: Dimensi | C6: Pertanyaan | D6: Skor
A7: 1 | B7: Quality | C7: ='RAW DATA Q2 - 1'!BJ$1 -> How would you rate the goods/services provided by the Supplier against the agreed standards1 | D7: ='RAW DATA Q2 - 1'!BJ13 -> 4
A8: 2 | B8: Quality | C8: ='RAW DATA Q2 - 1'!BK$1 -> How would you rate overall quality of the work reports provided by the Supplier?3 | D8: ='RAW DATA Q2 - 1'!BK13 -> 4
A9: 3 | B9: Quality | C9: ='RAW DATA Q2 - 1'!BL$1 -> How would you rate the solutions provided when there is trouble?3 | D9: ='RAW DATA Q2 - 1'!BL13 -> 4
A10: 4 | B10: Quality | C10: ='RAW DATA Q2 - 1'!BM$1 -> How would you rate the resolution to the problem that occurred?3 | D10: ='RAW DATA Q2 - 1'!BM13 -> 4
A11: 5 | B11: Quality | C11: ='RAW DATA Q2 - 1'!BN$1 -> How would you rate the supplier initiative to take mitigation/preventive action to prevent the problem from recurring?3 | D11: ='RAW DATA Q2 - 1'!BN13 -> 4
A12: 6 | B12: Quality | C12: ='RAW DATA Q2 - 1'!BO$1 -> How would you rate the accuracy of the data in the Supplier's reports?2 | D12: ='RAW DATA Q2 - 1'!BO13 -> 4
A13: 7 | B13: Quality | C13: ='RAW DATA Q2 - 1'!BP$1 -> How would you rate the overall quality of the work reports provided by the Supplier? | D13: ='RAW DATA Q2 - 1'!BP13 -> 4
A14: 8 | B14: Quality | C14: ='RAW DATA Q2 - 1'!BQ$1 -> How would you rate the competence of people provided by the supplier to provide support (understand AXITS and/or DMTM software)? | D14: ='RAW DATA Q2 - 1'!BQ13 -> 4
A15: 9 | B15: Quality | C15: ='RAW DATA Q2 - 1'!BR$1 -> How would you rate the supplier support in providing the form of consultation, offsite and onsite support if there is a disruption to application operations? | D15: ='RAW DATA Q2 - 1'!BR13 -> 4
A16: 10 | B16: Quality | C16: ='RAW DATA Q2 - 1'!BS$1 -> How would you rate the supplier support in doing periodic checks once every 3 months to maintain application quality, including application performance checks (profiling) and error log checks? | D16: ='RAW DATA Q2 - 1'!BS13 -> 4
A17: 11 | B17: Quality | C17: ='RAW DATA Q2 - 1'!BT$1 -> How would you rate the supplier support for updating versions of components, frameworks and libraries issued by third parties with prior written approval from AXA if this is possible? | D17: ='RAW DATA Q2 - 1'!BT13 -> 4
A18: 12 | B18: Quality | C18: ='RAW DATA Q2 - 1'!BU$1 -> How would you rate the suppliers support in compliance to security? | D18: ='RAW DATA Q2 - 1'!BU13 -> 4
A19: 13 | B19: Quality | C19: ='RAW DATA Q2 - 1'!BV$1 -> How would you rate the supplier initiative to take mitigation/preventive action to prevent the problem from recurring?4 | D19: ='RAW DATA Q2 - 1'!BV13 -> 4
A20: 14 | B20: Quality | C20: ='RAW DATA Q2 - 1'!BW$1 -> How would you rate supplier compliance with administrative processes, including completion of draft cooperation contract?4 | D20: ='RAW DATA Q2 - 1'!BW13 -> 4
A21: 15 | B21: Timeline | C21: ='RAW DATA Q2 - 1'!FF$1 -> How would you rate the Supplier's timeliness in delivering goods/services compared to the agreed-upon timeline?3 | D21: ='RAW DATA Q2 - 1'!FF13 -> 4
A22: 16 | B22: Timeline | C22: ='RAW DATA Q2 - 1'!FG$1 -> How would you rate the supplier's timeliness in sending reports to you? Based on SLA, support reports should be sent every 3 months on the 10th | D22: ='RAW DATA Q2 - 1'!FG13 -> 4
A23: 17 | B23: Timeline | C23: ='RAW DATA Q2 - 1'!FH$1 -> How would you rate the supplier's speed ​​of administrative completion, including completion of contracts draft?1 | D23: ='RAW DATA Q2 - 1'!FH13 -> 4
A24: 18 | B24: Timeline | C24: ='RAW DATA Q2 - 1'!FI$1 -> How would you rate the supplier's resolution time? | D24: ='RAW DATA Q2 - 1'!FI13 -> 4
A25: 19 | B25: Relationship | C25: ='RAW DATA Q2 - 1'!FM$1 -> How would you rate the supplier's communication with you? | D25: ='RAW DATA Q2 - 1'!FM13 -> 5
A26: 20 | B26: Relationship | C26: ='RAW DATA Q2 - 1'!FN$1 -> How would you rate the supplier's PIC's availability to be contacted when needed? | D26: ='RAW DATA Q2 - 1'!FN13 -> 5
A27: 21 | B27: Relationship | C27: ='RAW DATA Q2 - 1'!FO$1 -> How would you rate the supplier's response speed to you when there are issues? | D27: ='RAW DATA Q2 - 1'!FO13 -> 5
A29: Quality Avg (35%) | B29: =AVERAGEIF(B7:B27,"Quality",D7:D27) -> 4
A30: Timeline Avg (35%) | B30: =AVERAGEIF(B7:B27,"Timeline",D7:D27) -> 4
A31: Relationship Avg (30%) | B31: =AVERAGEIF(B7:B27,"Relationship",D7:D27) -> 5
A32: TOTAL SCORE | B32: =B29*0.35+B30*0.35+B31*0.3 -> 4.3
A33: STATUS | B33: =IF(B32>4.99,"Exceptional",IF(B32>3.99,"Exceed Expectation",IF(B32>=2.99,"Meet Expectation",IF(B32>1.9,"Below Expectation","Unsatisfactory")))) -> Exceed Expectation
A35: DUE DILIGENCE / COMPLIANCE
A36: Financial Assessment | B36: ='RAW DATA Q2 - 1'!FP13 -> Yes
A37: Reputational Assessment | B37: ='RAW DATA Q2 - 1'!FQ13 -> Yes
A38: DPIA | B38: ='RAW DATA Q2 - 1'!FR13 -> Yes, DPIA completed and there are actions to be done by Project Owner
A39: DPSQ | B39: ='RAW DATA Q2 - 1'!FS13 -> No Implementation
A40: VSDDT | B40: ='RAW DATA Q2 - 1'!FT13 -> Yes, VSDDT completed and there are actions to be done by supplier
A41: Action Plan
A43: REMARKS / FEEDBACK
B44: ='RAW DATA Q2 - 1'!FU13 -> Ciptadra selalu fast response ketika ada incident yang terjadi di DMTM

Sheet Q2 MTARGET
A1: HASIL REVIEW VENDOR — Q2 2026
A2: Vendor | B2: Target Sukses Sinergi
A3: Service | B3: Email Marketing Automation
A4: PIC (Business User) | B4: Bella Friska DEPARI
A6: No | B6: Dimensi | C6: Pertanyaan | D6: Skor
A7: 1 | B7: Quality | C7: ='RAW DATA Q2 - 1'!EF$1 -> How would you rate the service provided?1 | D7: ='RAW DATA Q2 - 1'!EF4 -> 3
A8: 2 | B8: Quality | C8: ='RAW DATA Q2 - 1'!EG$1 -> How would you rate the accuracy of the data in the Supplier's reports?7 | D8: ='RAW DATA Q2 - 1'!EG4 -> 3
A9: 3 | B9: Quality | C9: ='RAW DATA Q2 - 1'!EH$1 -> How would you rate overall quality of the work reports provided by the Supplier?7 | D9: ='RAW DATA Q2 - 1'!EH4 -> 3
A10: 4 | B10: Quality | C10: ='RAW DATA Q2 - 1'!EI$1 -> How would you rate the resolution to the problem that occurred?7 | D10: ='RAW DATA Q2 - 1'!EI4 -> 3
A11: 5 | B11: Quality | C11: ='RAW DATA Q2 - 1'!EJ$1 -> How would you rate the supplier initiative to take mitigation/preventive action to prevent the problem from recurring?8 | D11: ='RAW DATA Q2 - 1'!EJ4 -> 2
A12: 6 | B12: Quality | C12: ='RAW DATA Q2 - 1'!EK$1 -> How would you rate supplier compliance with administrative processes, including completion of draft cooperation contract?7 | D12: ='RAW DATA Q2 - 1'!EK4 -> 3
A13: 7 | B13: Timeline | C13: ='RAW DATA Q2 - 1'!EU$1 -> How would you rate the supplier's timeliness in delivering goods/services compared to the agreed-upon timeline? | D13: ='RAW DATA Q2 - 1'!EU4 -> 3
A14: 8 | B14: Timeline | C14: ='RAW DATA Q2 - 1'!EV$1 -> How would you rate the supplier's timeliness in sending reports to you? | D14: ='RAW DATA Q2 - 1'!EV4 -> 3
A15: 9 | B15: Timeline | C15: ='RAW DATA Q2 - 1'!EW$1 -> How would you rate the supplier's speed ​​of administrative completion, including completion of contracts draft? | D15: ='RAW DATA Q2 - 1'!EW4 -> 3
A16: 10 | B16: Relationship | C16: ='RAW DATA Q2 - 1'!FM$1 -> How would you rate the supplier's communication with you? | D16: ='RAW DATA Q2 - 1'!FM4 -> 3
A17: 11 | B17: Relationship | C17: ='RAW DATA Q2 - 1'!FN$1 -> How would you rate the supplier's PIC's availability to be contacted when needed? | D17: ='RAW DATA Q2 - 1'!FN4 -> 3
A18: 12 | B18: Relationship | C18: ='RAW DATA Q2 - 1'!FO$1 -> How would you rate the supplier's response speed to you when there are issues? | D18: ='RAW DATA Q2 - 1'!FO4 -> 3
A20: Quality Avg (35%) | B20: =AVERAGEIF(B7:B18,"Quality",D7:D18) -> 2.8333333
A21: Timeline Avg (35%) | B21: =AVERAGEIF(B7:B18,"Timeline",D7:D18) -> 3
A22: Relationship Avg (30%) | B22: =AVERAGEIF(B7:B18,"Relationship",D7:D18) -> 3
A23: TOTAL SCORE | B23: =B20*0.35+B21*0.35+B22*0.3 -> 2.9416667
A24: STATUS | B24: =IF(B23>4.99,"Exceptional",IF(B23>3.99,"Exceed Expectation",IF(B23>=2.99,"Meet Expectation",IF(B23>1.9,"Below Expectation","Unsatisfactory")))) -> Below Expectation
A26: DUE DILIGENCE / COMPLIANCE
A27: Financial Assessment | B27: ='RAW DATA Q2 - 1'!FP4 -> Yes
A28: Reputational Assessment | B28: ='RAW DATA Q2 - 1'!FQ4 -> Yes
A29: DPIA | B29: ='RAW DATA Q2 - 1'!FR4 -> Yes, DPIA completed and there are actions to be done by Project Owner
A30: DPSQ | B30: ='RAW DATA Q2 - 1'!FS4 -> No Implementation
A31: VSDDT | B31: ='RAW DATA Q2 - 1'!FT4 -> Yes, VSDDT completed and there are actions to be done by supplier
A32: Action Plan
A34: REMARKS / FEEDBACK
B35: ='RAW DATA Q2 - 1'!FU4 -> Secara keseluruhan, MTarget telah memberikan dukungan yang baik dalam operasional email campaign dan responsif dalam menangani kebutuhan maupun isu yang muncul. Namun, insiden kesalahan pengiriman email yang terjadi menunjukkan perlunya penguatan pada proses deployment, pengujian, serta validasi sebelum implementasi ke production. Ke depannya, kami berharap MTarget dapat memperkuat proses change management, quality assurance, dan kontrol terhadap segmentasi serta pengiriman email untuk meminimalkan risiko terjadinya insiden serupa.

Sheet Q2 INMOTION
A1: HASIL REVIEW VENDOR — Q2 2026
A2: Vendor | B2: Inmotion Inovasi Teknologi
A3: Service | B3: Jasa Aplikasi Chatbot dan Live Chat
A4: PIC (Business User) | B4: Djoko DJOKO
A6: No | B6: Dimensi | C6: Pertanyaan | D6: Skor
A7: 1 | B7: Quality | C7: ='RAW DATA Q2 - 1'!BX$1 -> How would you rate the goods/services provided by the Supplier against the agreed standards2 | D7: ='RAW DATA Q2 - 1'!BX2 -> 4
A8: 2 | B8: Quality | C8: ='RAW DATA Q2 - 1'!BY$1 -> How would you rate the Customer Interaction Requirement which includes: | D8: ='RAW DATA Q2 - 1'!BY2 -> 4
A9: 3 | B9: Quality | C9: ='RAW DATA Q2 - 1'!BZ$1 -> How would you rate the Case Management which includes: | D9: ='RAW DATA Q2 - 1'!BZ2 -> 4
A10: 4 | B10: Quality | C10: ='RAW DATA Q2 - 1'!CA$1 -> How would you rate the Integration process which includes: | D10: ='RAW DATA Q2 - 1'!CA2 -> 4
A11: 5 | B11: Quality | C11: ='RAW DATA Q2 - 1'!CB$1 -> How would you rate the Architectural Requirement? | D11: ='RAW DATA Q2 - 1'!CB2 -> 4
A12: 6 | B12: Quality | C12: ='RAW DATA Q2 - 1'!CC$1 -> How would you rate the Security Requirement? | D12: ='RAW DATA Q2 - 1'!CC2 -> 4
A13: 7 | B13: Quality | C13: ='RAW DATA Q2 - 1'!CD$1 -> How would you rate the Backup and Restore, Capacity and Performance Requirements? | D13: ='RAW DATA Q2 - 1'!CD2 -> 4
A14: 8 | B14: Quality | C14: ='RAW DATA Q2 - 1'!CE$1 -> How would you rate the Operational and Configuration Management? | D14: ='RAW DATA Q2 - 1'!CE2 -> 4
A15: 9 | B15: Quality | C15: ='RAW DATA Q2 - 1'!CF$1 -> How would you rate the accuracy of the data in the Supplier's reports?3 | D15: ='RAW DATA Q2 - 1'!CF2 -> 4
A16: 10 | B16: Quality | C16: ='RAW DATA Q2 - 1'!CG$1 -> How would you rate overall quality of the work reports provided by the Supplier?4 | D16: ='RAW DATA Q2 - 1'!CG2 -> 4
A17: 11 | B17: Quality | C17: ='RAW DATA Q2 - 1'!CH$1 -> How would you rate the solutions provided when there is trouble?4 | D17: ='RAW DATA Q2 - 1'!CH2 -> 4
A18: 12 | B18: Quality | C18: ='RAW DATA Q2 - 1'!CI$1 -> How would you rate the resolution to the problem that occurred?4 | D18: ='RAW DATA Q2 - 1'!CI2 -> 4
A19: 13 | B19: Quality | C19: ='RAW DATA Q2 - 1'!CJ$1 -> How would you rate the speed of resolution given to problems that occur?3 | D19: ='RAW DATA Q2 - 1'!CJ2 -> 4
A20: 14 | B20: Quality | C20: ='RAW DATA Q2 - 1'!CK$1 -> How would you rate the supplier initiative to take mitigation/preventive action to prevent the problem from recurring?5 | D20: ='RAW DATA Q2 - 1'!CK2 -> 4
A21: 15 | B21: Quality | C21: ='RAW DATA Q2 - 1'!CL$1 -> How would you rate supplier compliance with administrative processes, including completion of draft cooperation contract?5 | D21: ='RAW DATA Q2 - 1'!CL2 -> 4
A22: 16 | B22: Quality | C22: ='RAW DATA Q2 - 1'!CM$1 -> How would you rate the accuracy of the data in the Supplier's reports?4 | D22: ='RAW DATA Q2 - 1'!CM2 -> 4
A23: 17 | B23: Quality | C23: ='RAW DATA Q2 - 1'!CN$1 -> How would you rate the overall quality of the work reports provided by the Supplier?1 | D23: ='RAW DATA Q2 - 1'!CN2 -> 4
A24: 18 | B24: Quality | C24: ='RAW DATA Q2 - 1'!CO$1 -> How would you rate the performing installation, setup and configuration of 3Dolphins? | D24: ='RAW DATA Q2 - 1'!CO2 -> 4
A25: 19 | B25: Quality | C25: ='RAW DATA Q2 - 1'!CP$1 -> How would you rate the integration of 3Dolphins with SalesForce? | D25: ='RAW DATA Q2 - 1'!CP2 -> 4
A26: 20 | B26: Quality | C26: ='RAW DATA Q2 - 1'!CQ$1 -> How would you rate the Chatbot Corpus with data provided by AXA? | D26: ='RAW DATA Q2 - 1'!CQ2 -> 4
A27: 21 | B27: Quality | C27: ='RAW DATA Q2 - 1'!CR$1 -> How would you rate the supplier's services in providing 3Dolphins Solutions as stated in the Functional Specification Document (FSD) and Technical Specification Document (TSD)? | D27: ='RAW DATA Q2 - 1'!CR2 -> 4
A28: 22 | B28: Quality | C28: ='RAW DATA Q2 - 1'!CS$1 -> How would you rate the supplier's services in conducting System Integration Test (SIT) with AXA IT testing team and IT Project Team? | D28: ='RAW DATA Q2 - 1'!CS2 -> 4
A29: 23 | B29: Quality | C29: ='RAW DATA Q2 - 1'!CT$1 -> How would you rate the supplier's services in conducting User Acceptance Test (UAT) with AXA Business Team and Project IT Team? | D29: ='RAW DATA Q2 - 1'!CT2 -> 4
A30: 24 | B30: Quality | C30: ='RAW DATA Q2 - 1'!CU$1 -> How would you rate the supplier's services in migrating to production server or Go Live and providing support after Go Live? | D30: ='RAW DATA Q2 - 1'!CU2 -> 4
A31: 25 | B31: Quality | C31: ='RAW DATA Q2 - 1'!CV$1 -> How would you rate the supplier's services in providing the human resources needed in the project and timeline according to the agreed scope? | D31: ='RAW DATA Q2 - 1'!CV2 -> 4
A32: 26 | B32: Quality | C32: ='RAW DATA Q2 - 1'!CW$1 -> How would you rate the supplier's services in assigning a Project Manager to coordinate with the AXA team? | D32: ='RAW DATA Q2 - 1'!CW2 -> 4
A33: 27 | B33: Quality | C33: ='RAW DATA Q2 - 1'!CX$1 -> How would you rate the supplier's project documentation as follows: | D33: ='RAW DATA Q2 - 1'!CX2 -> 4
A34: 28 | B34: Quality | C34: ='RAW DATA Q2 - 1'!CY$1 -> How would you rate the supplier support in providing the perform maintenance on all software related to 3Dolphins, which is installed in the AXA data center? | D34: ='RAW DATA Q2 - 1'!CY2 -> 4
A35: 29 | B35: Quality | C35: ='RAW DATA Q2 - 1'!CZ$1 -> How would you rate the supplier support in providing 3Dolphins application maintenance service time, namely 24 hours x 7 days a week, 365 days/year? | D35: ='RAW DATA Q2 - 1'!CZ2 -> 4
A36: 30 | B36: Quality | C36: ='RAW DATA Q2 - 1'!DA$1 -> How would you rate the supplier support in preparing at least 2 people who understand and are experts in chatbots owned by AXA and can also provide support for services that often occur (eg. New custo | D36: ='RAW DATA Q2 - 1'!DA2 -> 4
A37: 31 | B37: Quality | C37: ='RAW DATA Q2 - 1'!DB$1 -> How would you rate the supplier support in providing support center that can be visited during AXA business hours to respond to any questions and issues that arise? | D37: ='RAW DATA Q2 - 1'!DB2 -> 4
A38: 32 | B38: Quality | C38: ='RAW DATA Q2 - 1'!DC$1 -> How would you rate the supplier support in providing SLA reports to AXA? | D38: ='RAW DATA Q2 - 1'!DC2 -> 4
A39: 33 | B39: Quality | C39: ='RAW DATA Q2 - 1'!DD$1 -> How would you rate the supplier support in providing testing and updates the Chatbot Solution if there is a new software version/release/patch according to the required conditions? | D39: ='RAW DATA Q2 - 1'!DD2 -> 4
A40: 34 | B40: Quality | C40: ='RAW DATA Q2 - 1'!DE$1 -> How would you rate the supplier support in reinstall the 3Dolphins application a maximum of 1 time per year if AXA will upgrade the hardware? | D40: ='RAW DATA Q2 - 1'!DE2 -> 4
A41: 35 | B41: Quality | C41: ='RAW DATA Q2 - 1'!DF$1 -> How would you rate the supplier support in providing a checklist to monitor daily activities? | D41: ='RAW DATA Q2 - 1'!DF2 -> 4
A42: 36 | B42: Quality | C42: ='RAW DATA Q2 - 1'!DG$1 -> How would you rate the supplier support in providing a testing configuration and event logging? | D42: ='RAW DATA Q2 - 1'!DG2 -> 4
A43: 37 | B43: Quality | C43: ='RAW DATA Q2 - 1'!DH$1 -> How would you rate the supplier support in providing a backup for short and long term? | D43: ='RAW DATA Q2 - 1'!DH2 -> 4
A44: 38 | B44: Timeline | C44: ='RAW DATA Q2 - 1'!EU$1 -> How would you rate the supplier's timeliness in delivering goods/services compared to the agreed-upon timeline? | D44: ='RAW DATA Q2 - 1'!EU2 -> 4
A45: 39 | B45: Timeline | C45: ='RAW DATA Q2 - 1'!EV$1 -> How would you rate the supplier's timeliness in sending reports to you? | D45: ='RAW DATA Q2 - 1'!EV2 -> 4
A46: 40 | B46: Timeline | C46: ='RAW DATA Q2 - 1'!EW$1 -> How would you rate the supplier's speed ​​of administrative completion, including completion of contracts draft? | D46: ='RAW DATA Q2 - 1'!EW2 -> 4
A47: 41 | B47: Relationship | C47: ='RAW DATA Q2 - 1'!FM$1 -> How would you rate the supplier's communication with you? | D47: ='RAW DATA Q2 - 1'!FM2 -> 4
A48: 42 | B48: Relationship | C48: ='RAW DATA Q2 - 1'!FN$1 -> How would you rate the supplier's PIC's availability to be contacted when needed? | D48: ='RAW DATA Q2 - 1'!FN2 -> 4
A49: 43 | B49: Relationship | C49: ='RAW DATA Q2 - 1'!FO$1 -> How would you rate the supplier's response speed to you when there are issues? | D49: ='RAW DATA Q2 - 1'!FO2 -> 4
A51: Quality Avg (35%) | B51: =AVERAGEIF(B7:B49,"Quality",D7:D49) -> 4
A52: Timeline Avg (35%) | B52: =AVERAGEIF(B7:B49,"Timeline",D7:D49) -> 4
A53: Relationship Avg (30%) | B53: =AVERAGEIF(B7:B49,"Relationship",D7:D49) -> 4
A54: TOTAL SCORE | B54: =B51*0.35+B52*0.35+B53*0.3 -> 4
A55: STATUS | B55: =IF(B54>4.99,"Exceptional",IF(B54>3.99,"Exceed Expectation",IF(B54>=2.99,"Meet Expectation",IF(B54>1.9,"Below Expectation","Unsatisfactory")))) -> Exceed Expectation
A57: DUE DILIGENCE / COMPLIANCE
A58: Financial Assessment | B58: ='RAW DATA Q2 - 1'!FP2 -> Yes
A59: Reputational Assessment | B59: ='RAW DATA Q2 - 1'!FQ2 -> Yes
A60: DPIA | B60: ='RAW DATA Q2 - 1'!FR2 -> Yes, DPIA completed and there are actions to be done by Project Owner
A61: DPSQ | B61: ='RAW DATA Q2 - 1'!FS2 -> DPSQ not completed yet
A62: VSDDT | B62: ='RAW DATA Q2 - 1'!FT2 -> Yes, VSDDT completed and there are actions to be done by supplier
A63: Action Plan
A65: REMARKS / FEEDBACK
B66: ='RAW DATA Q2 - 1'!FU2 -> Tetap up to date dan helpful

Sheet Q2 MII-SFDC
A1: HASIL REVIEW VENDOR — Q2 2026
A2: Vendor | B2: Mitra Integrasi Informatika
A3: Service | B3: SFDC Maintenance
A4: PIC (Business User) | B4: Chandra Nugraha PUTRA
A6: No | B6: Dimensi | C6: Pertanyaan | D6: Skor
A7: 1 | B7: Quality | C7: ='RAW DATA Q2 - 1'!AL$1 -> How would you rate Supplier's ability to understand and meet your needs?2 | D7: ='RAW DATA Q2 - 1'!AL14 -> 4
A8: 2 | B8: Quality | C8: ='RAW DATA Q2 - 1'!AM$1 -> How would you rate the The goods/services provided by the Supplier against the agreed standards? | D8: ='RAW DATA Q2 - 1'!AM14 -> 5
A9: 3 | B9: Quality | C9: ='RAW DATA Q2 - 1'!AN$1 -> How would you rate the General support and maintenance requirement? | D9: ='RAW DATA Q2 - 1'!AN14 -> 5
A10: 4 | B10: Quality | C10: ='RAW DATA Q2 - 1'!AO$1 -> How would you rate the Performance Management Requirement which includes to support low latency, documentation, performance monitoring, and any major or minor updates? | D10: ='RAW DATA Q2 - 1'!AO14 -> 5
A11: 5 | B11: Quality | C11: ='RAW DATA Q2 - 1'!AP$1 -> How would you rate the Security Management Requirement? | D11: ='RAW DATA Q2 - 1'!AP14 -> 5
A12: 6 | B12: Quality | C12: ='RAW DATA Q2 - 1'!AQ$1 -> How would you rate the Supporting Model which includes onsite support from dedicated engineers and its service level agreement (SLA)? | D12: ='RAW DATA Q2 - 1'!AQ14 -> 4
A13: 7 | B13: Quality | C13: ='RAW DATA Q2 - 1'!AR$1 -> How would you rate the accuracy of the data in the Supplier's reports?1 | D13: ='RAW DATA Q2 - 1'!AR14 -> 5
A14: 8 | B14: Quality | C14: ='RAW DATA Q2 - 1'!AS$1 -> How would you rate overall quality of the work reports provided by the Supplier?1 | D14: ='RAW DATA Q2 - 1'!AS14 -> 4
A15: 9 | B15: Quality | C15: ='RAW DATA Q2 - 1'!AT$1 -> How would you rate the solutions provided when there is trouble?1 | D15: ='RAW DATA Q2 - 1'!AT14 -> 5
A16: 10 | B16: Quality | C16: ='RAW DATA Q2 - 1'!AU$1 -> How would you rate the resolution to the problem that occurred?1 | D16: ='RAW DATA Q2 - 1'!AU14 -> 4
A17: 11 | B17: Quality | C17: ='RAW DATA Q2 - 1'!AV$1 -> How would you rate the speed of resolution given to problems that occur?1 | D17: ='RAW DATA Q2 - 1'!AV14 -> 5
A18: 12 | B18: Quality | C18: ='RAW DATA Q2 - 1'!AW$1 -> How would you rate the supplier initiative to take mitigation/preventive action to prevent the problem from recurring?1 | D18: ='RAW DATA Q2 - 1'!AW14 -> 4
A19: 13 | B19: Quality | C19: ='RAW DATA Q2 - 1'!AX$1 -> How would you rate supplier compliance with administrative processes, including completion of draft cooperation contract?2 | D19: ='RAW DATA Q2 - 1'!AX14 -> 5
A20: 14 | B20: Timeline | C20: ='RAW DATA Q2 - 1'!EU$1 -> How would you rate the supplier's timeliness in delivering goods/services compared to the agreed-upon timeline? | D20: ='RAW DATA Q2 - 1'!EU14 -> 4
A21: 15 | B21: Timeline | C21: ='RAW DATA Q2 - 1'!EV$1 -> How would you rate the supplier's timeliness in sending reports to you? | D21: ='RAW DATA Q2 - 1'!EV14 -> 5
A22: 16 | B22: Timeline | C22: ='RAW DATA Q2 - 1'!EW$1 -> How would you rate the supplier's speed ​​of administrative completion, including completion of contracts draft? | D22: ='RAW DATA Q2 - 1'!EW14 -> 5
A23: 17 | B23: Relationship | C23: ='RAW DATA Q2 - 1'!FM$1 -> How would you rate the supplier's communication with you? | D23: ='RAW DATA Q2 - 1'!FM14 -> 5
A24: 18 | B24: Relationship | C24: ='RAW DATA Q2 - 1'!FN$1 -> How would you rate the supplier's PIC's availability to be contacted when needed? | D24: ='RAW DATA Q2 - 1'!FN14 -> 5
A25: 19 | B25: Relationship | C25: ='RAW DATA Q2 - 1'!FO$1 -> How would you rate the supplier's response speed to you when there are issues? | D25: ='RAW DATA Q2 - 1'!FO14 -> 5
A27: Quality Avg (35%) | B27: =AVERAGEIF(B7:B25,"Quality",D7:D25) -> 4.6153846
A28: Timeline Avg (35%) | B28: =AVERAGEIF(B7:B25,"Timeline",D7:D25) -> 4.6666667
A29: Relationship Avg (30%) | B29: =AVERAGEIF(B7:B25,"Relationship",D7:D25) -> 5
A30: TOTAL SCORE | B30: =B27*0.35+B28*0.35+B29*0.3 -> 4.7487179
A31: STATUS | B31: =IF(B30>4.99,"Exceptional",IF(B30>3.99,"Exceed Expectation",IF(B30>=2.99,"Meet Expectation",IF(B30>1.9,"Below Expectation","Unsatisfactory")))) -> Exceed Expectation
A33: DUE DILIGENCE / COMPLIANCE
A34: Financial Assessment | B34: ='RAW DATA Q2 - 1'!FP14 -> Yes
A35: Reputational Assessment | B35: ='RAW DATA Q2 - 1'!FQ14 -> Yes
A36: DPIA | B36: ='RAW DATA Q2 - 1'!FR14 -> Yes, DPIA completed and there are actions to be done by Project Owner
A37: DPSQ | B37: ='RAW DATA Q2 - 1'!FS14 -> No Implementation
A38: VSDDT | B38: ='RAW DATA Q2 - 1'!FT14 -> Yes, VSDDT completed and there are actions to be done by supplier
A39: Action Plan
A41: REMARKS / FEEDBACK
B42: ='RAW DATA Q2 - 1'!FU14 -> Respons terhadap issue maupun kebutuhan sudah cukup baik dan cepat. Support on-site juga sangat membantu dan responsif. Ke depannya, mungkin dapat lebih rutin memberikan update terkait progress kendala atau perbaikan yang sedang dilakukan, sehingga pihak terkait dapat mengetahui status terbaru dan lebih cepat menentukan langkah selanjutnya.

Sheet Q2 SUTRA
A1: HASIL REVIEW VENDOR — Q2 2026
A2: Vendor | B2: Sutra Management Consultancies
A3: Service | B3: Implementasi SAS IFRS17
A4: PIC (Business User) | B4: Tatang SUTIAMAN
A6: No | B6: Dimensi | C6: Pertanyaan | D6: Skor
A7: 1 | B7: Quality | C7: ='RAW DATA Q2 - 2'!AU$1 -> How would you rate the goods/services provided by the Supplier against the agreed standards1 | D7: ='RAW DATA Q2 - 2'!AU10 -> 4
A8: 2 | B8: Quality | C8: ='RAW DATA Q2 - 2'!AV$1 -> How would you rate the accuracy of the data in the Supplier's reports?2 | D8: ='RAW DATA Q2 - 2'!AV10 -> 3
A9: 3 | B9: Quality | C9: ='RAW DATA Q2 - 2'!AW$1 -> How would you rate the Vendor initiative to take mitigation/preventive action to prevent the problem from recurring?3 | D9: ='RAW DATA Q2 - 2'!AW10 -> 4
A10: 4 | B10: Quality | C10: ='RAW DATA Q2 - 2'!AX$1 -> How would you rate supplier compliance with administrative processes, including completion of draft cooperation contract?4 | D10: ='RAW DATA Q2 - 2'!AX10 -> 3
A11: 5 | B11: Quality | C11: ='RAW DATA Q2 - 2'!AY$1 -> How would you rate the Installation of SAS IFRS17 solution on AXA infrastructure? | D11: ='RAW DATA Q2 - 2'!AY10 -> 3
A12: 6 | B12: Quality | C12: ='RAW DATA Q2 - 2'!AZ$1 -> How would you rate the workshops and finalize functional specification documents that summarize requirements which conducted by the supplier? | D12: ='RAW DATA Q2 - 2'!AZ10 -> 3
A13: 7 | B13: Quality | C13: ='RAW DATA Q2 - 2'!BA$1 -> How would you rate the implementation of an end-to-end solution flow design for SAS IFRS17? | D13: ='RAW DATA Q2 - 2'!BA10 -> 3
A14: 8 | B14: Quality | C14: ='RAW DATA Q2 - 2'!BB$1 -> How would you rate the Implementation of SAS IFRS17solution? | D14: ='RAW DATA Q2 - 2'!BB10 -> 3
A15: 9 | B15: Quality | C15: ='RAW DATA Q2 - 2'!BC$1 -> How would you rate the End-to-End Calculation Functions which includes: | D15: ='RAW DATA Q2 - 2'!BC10 -> 3
A16: 10 | B16: Quality | C16: ='RAW DATA Q2 - 2'!BD$1 -> How would you rate the PSAK74 Contract Grouping using Data Input and Predefine Rule which generates: | D16: ='RAW DATA Q2 - 2'!BD10 -> 3
A17: 11 | B17: Quality | C17: ='RAW DATA Q2 - 2'!BE$1 -> How would you rate PSAK74 System implementation on its standard and configurable rule which includes: | D17: ='RAW DATA Q2 - 2'!BE10 -> 3
A18: 12 | B18: Quality | C18: ='RAW DATA Q2 - 2'!BF$1 -> How would you rate the currencies and interest rate facilitation? | D18: ='RAW DATA Q2 - 2'!BF10 -> 3
A19: 13 | B19: Quality | C19: ='RAW DATA Q2 - 2'!BG$1 -> How would you rate the capability to estimate the Initial Recognition? | D19: ='RAW DATA Q2 - 2'!BG10 -> 3
A20: 14 | B20: Quality | C20: ='RAW DATA Q2 - 2'!BH$1 -> How would you rate the capability to estimate GMM/PAA/VFA Approach both direct and reinsurance: | D20: ='RAW DATA Q2 - 2'!BH10 -> 3
A21: 15 | B21: Quality | C21: ='RAW DATA Q2 - 2'!BI$1 -> How would you rate the capability to do the Allocation on Actual Cash Flow (CF): | D21: ='RAW DATA Q2 - 2'!BI10 -> 3
A22: 16 | B22: Quality | C22: ='RAW DATA Q2 - 2'!BJ$1 -> How would you rate the capability to generate PSAK74 Disclosure in monthly base: | D22: ='RAW DATA Q2 - 2'!BJ10 -> 3
A23: 17 | B23: Quality | C23: ='RAW DATA Q2 - 2'!BK$1 -> How would you rate the System Availability, Redundancy, and Overload Protection? | D23: ='RAW DATA Q2 - 2'!BK10 -> 3
A24: 18 | B24: Quality | C24: ='RAW DATA Q2 - 2'!BL$1 -> How would you rate the Common Security Access? | D24: ='RAW DATA Q2 - 2'!BL10 -> 3
A25: 19 | B25: Quality | C25: ='RAW DATA Q2 - 2'!BM$1 -> How would you rate the Audit Trail? | D25: ='RAW DATA Q2 - 2'!BM10 -> 3
A26: 20 | B26: Quality | C26: ='RAW DATA Q2 - 2'!BN$1 -> How would you rate the supplier's service in providing one month warranty support after go-live? | D26: ='RAW DATA Q2 - 2'!BN10 -> 3
A27: 21 | B27: Quality | C27: ='RAW DATA Q2 - 2'!BO$1 -> How would you rate the supplier's services in conducting three-day user training for SAS IFRS17 solution and conducted one-day system administration training for users? | D27: ='RAW DATA Q2 - 2'!BO10 -> 3
A28: 22 | B28: Timeline | C28: ='RAW DATA Q2 - 2'!DO$1 -> How would you rate the supplier's timeliness in delivering goods/services compared to the agreed-upon timeline? | D28: ='RAW DATA Q2 - 2'!DO10 -> 3
A29: 23 | B29: Timeline | C29: ='RAW DATA Q2 - 2'!DP$1 -> How would you rate the supplier's timeliness in sending reports to you? | D29: ='RAW DATA Q2 - 2'!DP10 -> 3
A30: 24 | B30: Timeline | C30: ='RAW DATA Q2 - 2'!DQ$1 -> How would you rate the supplier's speed ​​of administrative completion, including completion of contracts draft? | D30: ='RAW DATA Q2 - 2'!DQ10 -> 3
A31: 25 | B31: Relationship | C31: ='RAW DATA Q2 - 2'!FM$1 -> How would you rate the supplier's communication with you? | D31: ='RAW DATA Q2 - 2'!FM10 -> 4
A32: 26 | B32: Relationship | C32: ='RAW DATA Q2 - 2'!FN$1 -> How would you rate the supplier's PIC's availability to be contacted when needed? | D32: ='RAW DATA Q2 - 2'!FN10 -> 4
A33: 27 | B33: Relationship | C33: ='RAW DATA Q2 - 2'!FO$1 -> How would you rate the supplier's response speed to you when there are issues? | D33: ='RAW DATA Q2 - 2'!FO10 -> 4
A35: Quality Avg (35%) | B35: =AVERAGEIF(B7:B33,"Quality",D7:D33) -> 3.0952381
A36: Timeline Avg (35%) | B36: =AVERAGEIF(B7:B33,"Timeline",D7:D33) -> 3
A37: Relationship Avg (30%) | B37: =AVERAGEIF(B7:B33,"Relationship",D7:D33) -> 4
A38: TOTAL SCORE | B38: =B35*0.35+B36*0.35+B37*0.3 -> 3.3333333
A39: STATUS | B39: =IF(B38>4.99,"Exceptional",IF(B38>3.99,"Exceed Expectation",IF(B38>=2.99,"Meet Expectation",IF(B38>1.9,"Below Expectation","Unsatisfactory")))) -> Meet Expectation
A41: DUE DILIGENCE / COMPLIANCE
A42: Financial Assessment | B42: ='RAW DATA Q2 - 2'!FP10 -> Yes
A43: Reputational Assessment | B43: ='RAW DATA Q2 - 2'!FQ10 -> Yes
A44: DPIA | B44: ='RAW DATA Q2 - 2'!FR10 -> No Implementation
A45: DPSQ | B45: ='RAW DATA Q2 - 2'!FS10 -> No Implementation
A46: VSDDT | B46: ='RAW DATA Q2 - 2'!FT10 -> No Implementation
A47: Action Plan | B47: ='RAW DATA Q2 - 2'!FU10 -> No – No action items were required
A49: REMARKS / FEEDBACK
B50: ='RAW DATA Q2 - 2'!FV10 -> no feedback

Sheet Q2 RDS-Printing
A1: HASIL REVIEW VENDOR — Q2 2026
A2: Vendor | B2: Reycom Document Solution
A3: Service | B3: Printing & Data Management Center
A4: PIC (Business User) | B4: Yulia KURNIATI
A5: Catatan | B5: Vendor submit assessment 2x pada periode ini; sheet ini menggunakan submission TERAKHIR (paling lengkap).
A7: No | B7: Dimensi | C7: Pertanyaan | D7: Skor
A8: 1 | B8: Quality | C8: ='RAW DATA Q2 - 2'!BV$1 -> How would you rate the Supplier’s ability to deliver Policy Printing Services SLA? | D8: ='RAW DATA Q2 - 2'!BV9 -> 4
A9: 2 | B9: Quality | C9: ='RAW DATA Q2 - 2'!BW$1 -> Printed policy documents met the agreed material specifications for each policy type? | D9: ='RAW DATA Q2 - 2'!BW9 -> 4
A10: 3 | B10: Quality | C10: ='RAW DATA Q2 - 2'!BX$1 -> How would you rate overall quality of Letter Printing services which includes: | D10: ='RAW DATA Q2 - 2'!BX9 -> 4
A11: 4 | B11: Quality | C11: ='RAW DATA Q2 - 2'!BY$1 -> How would you rate the overall quality of Training Material Printing service which includes: | D11: ='RAW DATA Q2 - 2'!BY9 -> 4
A12: 5 | B12: Quality | C12: ='RAW DATA Q2 - 2'!BZ$1 -> How would you rate the Data Capture quality control which should be performed at 100% volume (not random/sample check) for all required QC fields | D12: ='RAW DATA Q2 - 2'!BZ9 -> 4
A13: 6 | B13: Quality | C13: ='RAW DATA Q2 - 2'!CA$1 -> How would you rate the Data Capture quality control which should be performed at 100% volume (not random/sample check) for all required QC fields? | D13: ='RAW DATA Q2 - 2'!CA9 -> 4
A14: 7 | B14: Timeline | C14: ='RAW DATA Q2 - 2'!CB$1 -> Daily and monthly operational reports were submitted completely, accurately, and on time. | D14: ='RAW DATA Q2 - 2'!CB9 -> 4
A15: 8 | B15: Quality | C15: ='RAW DATA Q2 - 2'!CC$1 -> How would you rate the Data Maintenance, Data Security, and Access Control which includes: | D15: ='RAW DATA Q2 - 2'!CC9 -> 4
A16: 9 | B16: Quality | C16: ='RAW DATA Q2 - 2'!CD$1 -> How would you rate the Recovery Process in the Event of Hardware/Software Failure which includes: | D16: ='RAW DATA Q2 - 2'!CD9 -> 4
A17: 10 | B17: Quality | C17: ='RAW DATA Q2 - 2'!CE$1 -> How would you rate overall Document Management Center service? | D17: ='RAW DATA Q2 - 2'!CE9 -> 4
A18: 11 | B18: Timeline | C18: ='RAW DATA Q2 - 2'!DR$1 -> Policy printing was completed within the agreed H0 → H1 → H3 delivery timeline | D18: ='RAW DATA Q2 - 2'!DR9 -> 4
A19: 12 | B19: Timeline | C19: ='RAW DATA Q2 - 2'!DS$1 -> Letter printing (Cetak Surat) was completed within H+2 from AMFS approval of the print data file. | D19: ='RAW DATA Q2 - 2'!DS9 -> 4
A20: 13 | B20: Timeline | C20: ='RAW DATA Q2 - 2'!DT$1 -> Training material printing (Cetak Dokumen Materi Training) was completed within all three agreed SLA phases | D20: ='RAW DATA Q2 - 2'!DT9 -> 4
A21: 14 | B21: Timeline | C21: ='RAW DATA Q2 - 2'!DU$1 -> New Business data was uploaded to RLS within the agreed daily cut-off schedule | D21: ='RAW DATA Q2 - 2'!DU9 -> 4
A22: 15 | B22: Timeline | C22: ='RAW DATA Q2 - 2'!DV$1 -> POS and Claim documents were scanned, indexed, and uploaded on the same day within the agreed scanning SLA window | D22: ='RAW DATA Q2 - 2'!DV9 -> 4
A23: 16 | B23: Timeline | C23: ='RAW DATA Q2 - 2'!DW$1 -> Physical document retrieval requests from AMFS were fulfilled within 2 working days | D23: ='RAW DATA Q2 - 2'!DW9 -> 4
A24: 17 | B24: Timeline | C24: ='RAW DATA Q2 - 2'!DX$1 -> The supplier consistently met late delivery penalty thresholds and did not trigger the escalated penalty clause for policy printing | D24: ='RAW DATA Q2 - 2'!DX9 -> 4
A25: 18 | B25: Timeline | C25: ='RAW DATA Q2 - 2'!DY$1 -> The supplier proactively communicated whenever daily SLA targets or processing volumes were at risk of not being met. | D25: ='RAW DATA Q2 - 2'!DY9 -> 4
A26: 19 | B26: Relationship | C26: ='RAW DATA Q2 - 2'!FM$1 -> How would you rate the supplier's communication with you? | D26: ='RAW DATA Q2 - 2'!FM9 -> 5
A27: 20 | B27: Relationship | C27: ='RAW DATA Q2 - 2'!FN$1 -> How would you rate the supplier's PIC's availability to be contacted when needed? | D27: ='RAW DATA Q2 - 2'!FN9 -> 5
A28: 21 | B28: Relationship | C28: ='RAW DATA Q2 - 2'!FO$1 -> How would you rate the supplier's response speed to you when there are issues? | D28: ='RAW DATA Q2 - 2'!FO9 -> 5
A30: Quality Avg (35%) | B30: =AVERAGEIF(B8:B28,"Quality",D8:D28) -> 4
A31: Timeline Avg (35%) | B31: =AVERAGEIF(B8:B28,"Timeline",D8:D28) -> 4
A32: Relationship Avg (30%) | B32: =AVERAGEIF(B8:B28,"Relationship",D8:D28) -> 5
A33: TOTAL SCORE | B33: =B30*0.35+B31*0.35+B32*0.3 -> 4.3
A34: STATUS | B34: =IF(B33>4.99,"Exceptional",IF(B33>3.99,"Exceed Expectation",IF(B33>=2.99,"Meet Expectation",IF(B33>1.9,"Below Expectation","Unsatisfactory")))) -> Exceed Expectation
A36: DUE DILIGENCE / COMPLIANCE
A37: Financial Assessment | B37: ='RAW DATA Q2 - 2'!FP9 -> Yes
A38: Reputational Assessment | B38: ='RAW DATA Q2 - 2'!FQ9 -> Yes
A39: DPIA | B39: ='RAW DATA Q2 - 2'!FR9 -> Yes, DPIA completed and there are actions to be done by Project Owner
A40: DPSQ | B40: ='RAW DATA Q2 - 2'!FS9 -> Yes, DPSQ completed
A41: VSDDT | B41: ='RAW DATA Q2 - 2'!FT9 -> Yes, VSDDT completed and there are actions to be done by supplier
A42: Action Plan | B42: ='RAW DATA Q2 - 2'!FU9 -> Yes – All action items have been completed and coordinated with relevant SME
A44: REMARKS / FEEDBACK
B45: ='RAW DATA Q2 - 2'!FV9 -> Improvements to their latest Technology to support process at AXA

Sheet Q2 DELOITTE
A1: HASIL REVIEW VENDOR — Q2 2026
A2: Vendor | B2: Deloitte Consulting
A3: Service | B3: Data Privacy & Pelatihan Personal Data Protection (PDP)
A4: PIC (Business User) | B4: M. Andrian Patria Shaleh RIZAL
A6: No | B6: Dimensi | C6: Pertanyaan | D6: Skor
A7: 1 | B7: Quality | C7: ='RAW DATA Q2 - 2'!AJ$1 -> How would you rate the services provided by the Supplier against the agreed standards | D7: ='RAW DATA Q2 - 2'!AJ11 -> 5
A8: 2 | B8: Quality | C8: ='RAW DATA Q2 - 2'!AK$1 -> How would you rate the accuracy of the data in the Supplier's reports?1 | D8: ='RAW DATA Q2 - 2'!AK11 -> 5
A9: 3 | B9: Quality | C9: ='RAW DATA Q2 - 2'!AL$1 -> How would you rate overall quality of the work reports provided by the Supplier?1 | D9: ='RAW DATA Q2 - 2'!AL11 -> 4
A10: 4 | B10: Quality | C10: ='RAW DATA Q2 - 2'!AM$1 -> How would you rate the solutions provided when there is trouble?2 | D10: ='RAW DATA Q2 - 2'!AM11 -> 3
A11: 5 | B11: Quality | C11: ='RAW DATA Q2 - 2'!AN$1 -> How would you rate the vendor initiative to take mitigation/preventive action to prevent the problem from recurring?2 | D11: ='RAW DATA Q2 - 2'!AN11 -> 3
A12: 6 | B12: Quality | C12: ='RAW DATA Q2 - 2'!AO$1 -> How would you rate supplier compliance with administrative processes, including completion of draft cooperation contract?3 | D12: ='RAW DATA Q2 - 2'!AO11 -> 5
A13: 7 | B13: Quality | C13: ='RAW DATA Q2 - 2'!AP$1 -> How would you rate the supplier's service in providing training materials in accordance with: | D13: ='RAW DATA Q2 - 2'!AP11 -> 5
A14: 8 | B14: Quality | C14: ='RAW DATA Q2 - 2'!AQ$1 -> How would you rate the supplier's service in creating a discussion session that covers current conditions, understanding objectives, and discussions using specific cases from the training material wit | D14: ='RAW DATA Q2 - 2'!AQ11 -> 3
A15: 9 | B15: Quality | C15: ='RAW DATA Q2 - 2'!AR$1 -> How would you rate the supplier's service in conducting 1 (one) session of Data Privacy and Protection awareness training sessions for AXA and its related business units, along with a post-test. | D15: ='RAW DATA Q2 - 2'!AR11 -> 5
A16: 10 | B16: Quality | C16: ='RAW DATA Q2 - 2'!AS$1 -> How would you rate the supplier's response time for service issues? | D16: ='RAW DATA Q2 - 2'!AS11 -> 4
A17: 11 | B17: Quality | C17: ='RAW DATA Q2 - 2'!AT$1 -> How would you rate the supplier's project management & management report? | D17: ='RAW DATA Q2 - 2'!AT11 -> 4
A18: 12 | B18: Timeline | C18: ='RAW DATA Q2 - 2'!DO$1 -> How would you rate the supplier's timeliness in delivering goods/services compared to the agreed-upon timeline? | D18: ='RAW DATA Q2 - 2'!DO11 -> 4
A19: 13 | B19: Timeline | C19: ='RAW DATA Q2 - 2'!DP$1 -> How would you rate the supplier's timeliness in sending reports to you? | D19: ='RAW DATA Q2 - 2'!DP11 -> 4
A20: 14 | B20: Timeline | C20: ='RAW DATA Q2 - 2'!DQ$1 -> How would you rate the supplier's speed ​​of administrative completion, including completion of contracts draft? | D20: ='RAW DATA Q2 - 2'!DQ11 -> 4
A21: 15 | B21: Relationship | C21: ='RAW DATA Q2 - 2'!FM$1 -> How would you rate the supplier's communication with you? | D21: ='RAW DATA Q2 - 2'!FM11 -> 4
A22: 16 | B22: Relationship | C22: ='RAW DATA Q2 - 2'!FN$1 -> How would you rate the supplier's PIC's availability to be contacted when needed? | D22: ='RAW DATA Q2 - 2'!FN11 -> 4
A23: 17 | B23: Relationship | C23: ='RAW DATA Q2 - 2'!FO$1 -> How would you rate the supplier's response speed to you when there are issues? | D23: ='RAW DATA Q2 - 2'!FO11 -> 4
A25: Quality Avg (35%) | B25: =AVERAGEIF(B7:B23,"Quality",D7:D23) -> 4.1818182
A26: Timeline Avg (35%) | B26: =AVERAGEIF(B7:B23,"Timeline",D7:D23) -> 4
A27: Relationship Avg (30%) | B27: =AVERAGEIF(B7:B23,"Relationship",D7:D23) -> 4
A28: TOTAL SCORE | B28: =B25*0.35+B26*0.35+B27*0.3 -> 4.0636364
A29: STATUS | B29: =IF(B28>4.99,"Exceptional",IF(B28>3.99,"Exceed Expectation",IF(B28>=2.99,"Meet Expectation",IF(B28>1.9,"Below Expectation","Unsatisfactory")))) -> Exceed Expectation
A31: DUE DILIGENCE / COMPLIANCE
A32: Financial Assessment | B32: ='RAW DATA Q2 - 2'!FP11 -> Yes
A33: Reputational Assessment | B33: ='RAW DATA Q2 - 2'!FQ11 -> Yes
A34: DPIA | B34: ='RAW DATA Q2 - 2'!FR11 -> Yes, DPIA completed and there are actions to be done by Project Owner
A35: DPSQ | B35: ='RAW DATA Q2 - 2'!FS11 -> No Implementation
A36: VSDDT | B36: ='RAW DATA Q2 - 2'!FT11 -> Yes, VSDDT completed and there are actions to be done by supplier
A37: Action Plan | B37: ='RAW DATA Q2 - 2'!FU11 -> Yes – Action items identified, but follow‑up and coordination with relevant SME is still required
A39: REMARKS / FEEDBACK
B40: ='RAW DATA Q2 - 2'!FV11 -> In dealing with Security AI-related issues, Deloitte is occasionally unable to provide a resolution and therefore redirects the matter to the Security AI team. Furthermore, several system features are restricted, and these limitations were not clearly communicated at the outset. Consequently, this has created challenges in implementing system enhancements and aligning the system with the business requirements of Security AI users.

Sheet Q2 TMF
A1: HASIL REVIEW VENDOR — Q2 2026
A2: Vendor | B2: TMF Indonesia
A3: Service | B3: Payroll
A4: PIC (Business User) | B4: Enung HARYATI
A6: No | B6: Dimensi | C6: Pertanyaan | D6: Skor
A7: 1 | B7: Quality | C7: ='RAW DATA Q2 - 2'!BP$1 -> How would you rate the Supplier’s ability to deliver monthly Payroll Services? | D7: ='RAW DATA Q2 - 2'!BP2 -> 3
A8: 2 | B8: Quality | C8: ='RAW DATA Q2 - 2'!BQ$1 -> How would you rate the Supplier’s ability to deliver Cash Management Services, including the following aspects: | D8: ='RAW DATA Q2 - 2'!BQ2 -> 3
A9: 3 | B9: Quality | C9: ='RAW DATA Q2 - 2'!BR$1 -> How would you rate the Supplier’s ability to deliver Compliance Services, including the following aspects: | D9: ='RAW DATA Q2 - 2'!BR2 -> 3
A10: 4 | B10: Quality | C10: ='RAW DATA Q2 - 2'!BS$1 -> How would you rate the Supplier’s ability to deliver BPJS Kesehatan Services? | D10: ='RAW DATA Q2 - 2'!BS2 -> 3
A11: 5 | B11: Quality | C11: ='RAW DATA Q2 - 2'!BT$1 -> How would you rate the Supplier’s ability to comply with penalty provisions for payroll processing? | D11: ='RAW DATA Q2 - 2'!BT2 -> 3
A12: 6 | B12: Quality | C12: ='RAW DATA Q2 - 2'!BU$1 -> How would you rate the Supplier’s ability to execute the Special Project for BPJS Kesehatan? | D12: ='RAW DATA Q2 - 2'!BU2 -> 3
A13: 7 | B13: Timeline | C13: ='RAW DATA Q2 - 2'!DZ$1 -> How would you rate the Supplier’s ability to meet payroll disbursement timelines? | D13: ='RAW DATA Q2 - 2'!DZ2 -> 3
A14: 8 | B14: Timeline | C14: ='RAW DATA Q2 - 2'!EA$1 -> How would you rate the Supplier’s ability to meet the timelines for report and form submissions, including the following aspects: | D14: ='RAW DATA Q2 - 2'!EA2 -> 3
A15: 9 | B15: Timeline | C15: ='RAW DATA Q2 - 2'!EB$1 -> How would you rate the Supplier’s ability to meet the required timelines for payment processing? | D15: ='RAW DATA Q2 - 2'!EB2 -> 3
A16: 10 | B16: Relationship | C16: ='RAW DATA Q2 - 2'!FM$1 -> How would you rate the supplier's communication with you? | D16: ='RAW DATA Q2 - 2'!FM2 -> 3
A17: 11 | B17: Relationship | C17: ='RAW DATA Q2 - 2'!FN$1 -> How would you rate the supplier's PIC's availability to be contacted when needed? | D17: ='RAW DATA Q2 - 2'!FN2 -> 3
A18: 12 | B18: Relationship | C18: ='RAW DATA Q2 - 2'!FO$1 -> How would you rate the supplier's response speed to you when there are issues? | D18: ='RAW DATA Q2 - 2'!FO2 -> 3
A20: Quality Avg (35%) | B20: =AVERAGEIF(B7:B18,"Quality",D7:D18) -> 3
A21: Timeline Avg (35%) | B21: =AVERAGEIF(B7:B18,"Timeline",D7:D18) -> 3
A22: Relationship Avg (30%) | B22: =AVERAGEIF(B7:B18,"Relationship",D7:D18) -> 3
A23: TOTAL SCORE | B23: =B20*0.35+B21*0.35+B22*0.3 -> 3
A24: STATUS | B24: =IF(B23>4.99,"Exceptional",IF(B23>3.99,"Exceed Expectation",IF(B23>=2.99,"Meet Expectation",IF(B23>1.9,"Below Expectation","Unsatisfactory")))) -> Meet Expectation
A26: DUE DILIGENCE / COMPLIANCE
A27: Financial Assessment | B27: ='RAW DATA Q2 - 2'!FP2 -> Yes
A28: Reputational Assessment | B28: ='RAW DATA Q2 - 2'!FQ2 -> Yes
A29: DPIA | B29: ='RAW DATA Q2 - 2'!FR2 -> Yes, DPIA completed and there are actions to be done by Project Owner
A30: DPSQ | B30: ='RAW DATA Q2 - 2'!FS2 -> Yes, DPSQ completed
A31: VSDDT | B31: ='RAW DATA Q2 - 2'!FT2 -> Yes, VSDDT completed and there are actions to be done by supplier
A32: Action Plan | B32: ='RAW DATA Q2 - 2'!FU2 -> Yes – All action items have been completed and coordinated with relevant SME
A34: REMARKS / FEEDBACK
B35: ='RAW DATA Q2 - 2'!FV2 -> -

Sheet Q2 KPSG-TM
A1: HASIL REVIEW VENDOR — Q2 2026
A2: Vendor | B2: Karya Putra Surya Gemilang
A3: Service | B3: Telemarketing Revamp Project
A4: PIC (Business User) | B4: Nuril HUDHA
A6: No | B6: Dimensi | C6: Pertanyaan | D6: Skor
A7: 1 | B7: Quality | C7: ='RAW DATA Q2 - 2'!P$1 -> How would you rate the goods/services provided by the Supplier against the agreed standards | D7: ='RAW DATA Q2 - 2'!P5 -> 3
A8: 2 | B8: Quality | C8: ='RAW DATA Q2 - 2'!Q$1 -> How would you rate the accuracy of the data in the Supplier's reports? | D8: ='RAW DATA Q2 - 2'!Q5 -> 4
A9: 3 | B9: Quality | C9: ='RAW DATA Q2 - 2'!R$1 -> How would you rate overall quality of the work reports provided by the Supplier? | D9: ='RAW DATA Q2 - 2'!R5 -> 4
A10: 4 | B10: Quality | C10: ='RAW DATA Q2 - 2'!S$1 -> How would you rate the solutions provided when there is trouble? | D10: ='RAW DATA Q2 - 2'!S5 -> 3
A11: 5 | B11: Quality | C11: ='RAW DATA Q2 - 2'!T$1 -> How would you rate the Vendor initiative to take mitigation/preventive action to prevent the problem from recurring? | D11: ='RAW DATA Q2 - 2'!T5 -> 3
A12: 6 | B12: Quality | C12: ='RAW DATA Q2 - 2'!U$1 -> How would you rate supplier compliance with administrative processes, including completion of draft cooperation contract?1 | D12: ='RAW DATA Q2 - 2'!U5 -> 4
A13: 7 | B13: Quality | C13: ='RAW DATA Q2 - 2'!V$1 -> How would you rate the supplier implementation on a Project Management Approach, which includes: | D13: ='RAW DATA Q2 - 2'!V5 -> 3
A14: 8 | B14: Quality | C14: ='RAW DATA Q2 - 2'!W$1 -> How would you rate the supplier support in providing 1 (one) Technical Support personnel who is specifically assigned? Based on SLA, this technical support will be assigned at Menara Global and Graha | D14: ='RAW DATA Q2 - 2'!W5 -> 4
A15: 9 | B15: Quality | C15: ='RAW DATA Q2 - 2'!X$1 -> How would you rate the supplier support in providing technical support personnel who will perform several activities such as: | D15: ='RAW DATA Q2 - 2'!X5 -> 4
A16: 10 | B16: Quality | C16: ='RAW DATA Q2 - 2'!Y$1 -> How would you rate the supplier support in maintaining 99% SLA for System Availability in providing the Services to AMFS (SLA calculation does not include service downtime triggered by deliverables no | D16: ='RAW DATA Q2 - 2'!Y5 -> 4
A17: 11 | B17: Quality | C17: ='RAW DATA Q2 - 2'!Z$1 -> How would you rate the supplier support in providing Annual Support such as: | D17: ='RAW DATA Q2 - 2'!Z5 -> 4
A18: 12 | B18: Timeline | C18: ='RAW DATA Q2 - 2'!DO$1 -> How would you rate the supplier's timeliness in delivering goods/services compared to the agreed-upon timeline? | D18: ='RAW DATA Q2 - 2'!DO5 -> 3
A19: 13 | B19: Timeline | C19: ='RAW DATA Q2 - 2'!DP$1 -> How would you rate the supplier's timeliness in sending reports to you? | D19: ='RAW DATA Q2 - 2'!DP5 -> 4
A20: 14 | B20: Timeline | C20: ='RAW DATA Q2 - 2'!DQ$1 -> How would you rate the supplier's speed ​​of administrative completion, including completion of contracts draft? | D20: ='RAW DATA Q2 - 2'!DQ5 -> 3
A21: 15 | B21: Relationship | C21: ='RAW DATA Q2 - 2'!FM$1 -> How would you rate the supplier's communication with you? | D21: ='RAW DATA Q2 - 2'!FM5 -> 4
A22: 16 | B22: Relationship | C22: ='RAW DATA Q2 - 2'!FN$1 -> How would you rate the supplier's PIC's availability to be contacted when needed? | D22: ='RAW DATA Q2 - 2'!FN5 -> 3
A23: 17 | B23: Relationship | C23: ='RAW DATA Q2 - 2'!FO$1 -> How would you rate the supplier's response speed to you when there are issues? | D23: ='RAW DATA Q2 - 2'!FO5 -> 4
A25: Quality Avg (35%) | B25: =AVERAGEIF(B7:B23,"Quality",D7:D23) -> 3.6363636
A26: Timeline Avg (35%) | B26: =AVERAGEIF(B7:B23,"Timeline",D7:D23) -> 3.3333333
A27: Relationship Avg (30%) | B27: =AVERAGEIF(B7:B23,"Relationship",D7:D23) -> 3.6666667
A28: TOTAL SCORE | B28: =B25*0.35+B26*0.35+B27*0.3 -> 3.5393939
A29: STATUS | B29: =IF(B28>4.99,"Exceptional",IF(B28>3.99,"Exceed Expectation",IF(B28>=2.99,"Meet Expectation",IF(B28>1.9,"Below Expectation","Unsatisfactory")))) -> Meet Expectation
A31: DUE DILIGENCE / COMPLIANCE
A32: Financial Assessment | B32: ='RAW DATA Q2 - 2'!FP5 -> Yes
A33: Reputational Assessment | B33: ='RAW DATA Q2 - 2'!FQ5 -> Yes
A34: DPIA | B34: ='RAW DATA Q2 - 2'!FR5 -> Yes, DPIA completed and there are actions to be done by Project Owner
A35: DPSQ | B35: ='RAW DATA Q2 - 2'!FS5 -> Yes, DPSQ not completed yet
A36: VSDDT | B36: ='RAW DATA Q2 - 2'!FT5 -> Yes, VSDDT completed and there are actions to be done by supplier
A37: Action Plan | B37: ='RAW DATA Q2 - 2'!FU5 -> Yes – Action items identified, but follow‑up and coordination with relevant SME is still required
A39: REMARKS / FEEDBACK
B40: ='RAW DATA Q2 - 2'!FV5 -> 1. For AI Implementation, KPSG need to improve the delivery time, quality and PIC availability and backup PIC support 2. Another enhancement need to speed up with dedicated team

Sheet Q2 WIZ
A1: HASIL REVIEW VENDOR — Q2 2026
A2: Vendor | B2: Wiz Technology
A3: Service | B3: Voice Bot Reminder Call
A4: PIC (Business User) | B4: Ravika OKTAVIANI
A6: No | B6: Dimensi | C6: Pertanyaan | D6: Skor
A7: 1 | B7: Quality | C7: ='RAW DATA Q2 - 2'!H$1 -> How would you rate the services provided by the supplier? | D7: ='RAW DATA Q2 - 2'!H7 -> 4
A8: 2 | B8: Quality | C8: ='RAW DATA Q2 - 2'!I$1 -> How would you rate the accuracy of the data in the Supplier's reports? | D8: ='RAW DATA Q2 - 2'!I7 -> 4
A9: 3 | B9: Quality | C9: ='RAW DATA Q2 - 2'!J$1 -> How would you rate overall quality of the work reports provided by the Supplier | D9: ='RAW DATA Q2 - 2'!J7 -> 3
A10: 4 | B10: Quality | C10: ='RAW DATA Q2 - 2'!K$1 -> How would you rate the solutions provided by the supplier when there is trouble? | D10: ='RAW DATA Q2 - 2'!K7 -> 3
A11: 5 | B11: Quality | C11: ='RAW DATA Q2 - 2'!L$1 -> How would you rate the resolution to the problem that occurred? | D11: ='RAW DATA Q2 - 2'!L7 -> 3
A12: 6 | B12: Quality | C12: ='RAW DATA Q2 - 2'!M$1 -> How would you rate the speed of resolution given to problems that occur? | D12: ='RAW DATA Q2 - 2'!M7 -> 3
A13: 7 | B13: Quality | C13: ='RAW DATA Q2 - 2'!N$1 -> How would you rate supplier initiative to take mitigation/preventive action to prevent recurring problem? | D13: ='RAW DATA Q2 - 2'!N7 -> 3
A14: 8 | B14: Quality | C14: ='RAW DATA Q2 - 2'!O$1 -> How would you rate supplier compliance with administrative processes, including completion of draft cooperation contract? | D14: ='RAW DATA Q2 - 2'!O7 -> 3
A15: 9 | B15: Timeline | C15: ='RAW DATA Q2 - 2'!DO$1 -> How would you rate the supplier's timeliness in delivering goods/services compared to the agreed-upon timeline? | D15: ='RAW DATA Q2 - 2'!DO7 -> 3
A16: 10 | B16: Timeline | C16: ='RAW DATA Q2 - 2'!DP$1 -> How would you rate the supplier's timeliness in sending reports to you? | D16: ='RAW DATA Q2 - 2'!DP7 -> 3
A17: 11 | B17: Timeline | C17: ='RAW DATA Q2 - 2'!DQ$1 -> How would you rate the supplier's speed ​​of administrative completion, including completion of contracts draft? | D17: ='RAW DATA Q2 - 2'!DQ7 -> 3
A18: 12 | B18: Relationship | C18: ='RAW DATA Q2 - 2'!FM$1 -> How would you rate the supplier's communication with you? | D18: ='RAW DATA Q2 - 2'!FM7 -> 3
A19: 13 | B19: Relationship | C19: ='RAW DATA Q2 - 2'!FN$1 -> How would you rate the supplier's PIC's availability to be contacted when needed? | D19: ='RAW DATA Q2 - 2'!FN7 -> 3
A20: 14 | B20: Relationship | C20: ='RAW DATA Q2 - 2'!FO$1 -> How would you rate the supplier's response speed to you when there are issues? | D20: ='RAW DATA Q2 - 2'!FO7 -> 3
A22: Quality Avg (35%) | B22: =AVERAGEIF(B7:B20,"Quality",D7:D20) -> 3.25
A23: Timeline Avg (35%) | B23: =AVERAGEIF(B7:B20,"Timeline",D7:D20) -> 3
A24: Relationship Avg (30%) | B24: =AVERAGEIF(B7:B20,"Relationship",D7:D20) -> 3
A25: TOTAL SCORE | B25: =B22*0.35+B23*0.35+B24*0.3 -> 3.0875
A26: STATUS | B26: =IF(B25>4.99,"Exceptional",IF(B25>3.99,"Exceed Expectation",IF(B25>=2.99,"Meet Expectation",IF(B25>1.9,"Below Expectation","Unsatisfactory")))) -> Meet Expectation
A28: DUE DILIGENCE / COMPLIANCE
A29: Financial Assessment | B29: ='RAW DATA Q2 - 2'!FP7 -> Yes
A30: Reputational Assessment | B30: ='RAW DATA Q2 - 2'!FQ7 -> Yes
A31: DPIA | B31: ='RAW DATA Q2 - 2'!FR7 -> Yes, DPIA completed and there are actions to be done by Project Owner
A32: DPSQ | B32: ='RAW DATA Q2 - 2'!FS7 -> Yes, DPSQ completed
A33: VSDDT | B33: ='RAW DATA Q2 - 2'!FT7 -> Yes, VSDDT completed and there are actions to be done by supplier
A34: Action Plan | B34: ='RAW DATA Q2 - 2'!FU7 -> No – No action items were required
A36: REMARKS / FEEDBACK
B37: ='RAW DATA Q2 - 2'!FV7 -> To ensure a smooth process, we need to move faster and maintain effective communication

Sheet Q2 KPSG-ARSI
A1: HASIL REVIEW VENDOR — Q2 2026
A2: Vendor | B2: Karyaputra Suryagemilang
A3: Service | B3: Purecloud Decommisioning
A4: PIC (Business User) | B4: Noviani MARBUN
A6: No | B6: Dimensi | C6: Pertanyaan | D6: Skor
A7: 1 | B7: Quality | C7: ='RAW DATA Q2 - 2'!CF$1 -> The ARSI system (Inbound & Outbound) works properly and is ready to use as promised | D7: ='RAW DATA Q2 - 2'!CF3 -> 4
A8: 2 | B8: Quality | C8: ='RAW DATA Q2 - 2'!CG$1 -> The work delivered by KPSG reflects a high level of professionalism and expertise | D8: ='RAW DATA Q2 - 2'!CG3 -> 3
A9: 3 | B9: Quality | C9: ='RAW DATA Q2 - 2'!CH$1 -> The integration with our other systems runs smoothly | D9: ='RAW DATA Q2 - 2'!CH3 -> 2
A10: 4 | B10: Quality | C10: ='RAW DATA Q2 - 2'!CI$1 -> The features provided work as expected | D10: ='RAW DATA Q2 - 2'!CI3 -> 3
A11: 5 | B11: Quality | C11: ='RAW DATA Q2 - 2'!CJ$1 -> Bugs or errors in the system are rare, and when they occur, they are fixed properly | D11: ='RAW DATA Q2 - 2'!CJ3 -> 3
A12: 6 | B12: Quality | C12: ='RAW DATA Q2 - 2'!CK$1 -> Project documents are complete and clear | D12: ='RAW DATA Q2 - 2'!CK3 -> 3
A13: 7 | B13: Quality | C13: ='RAW DATA Q2 - 2'!CL$1 -> Regular reports provided by KPSG are accurate and easy to understand | D13: ='RAW DATA Q2 - 2'!CL3 -> 4
A14: 8 | B14: Quality | C14: ='RAW DATA Q2 - 2'!CM$1 -> KPSG responds well and cooperatively when we raise complaints or request improvements | D14: ='RAW DATA Q2 - 2'!CM3 -> 4
A15: 9 | B15: Quality | C15: ='RAW DATA Q2 - 2'!CN$1 -> Our data and information are kept secure while using KPSG's system | D15: ='RAW DATA Q2 - 2'!CN3 -> 4
A16: 10 | B16: Quality | C16: ='RAW DATA Q2 - 2'!CO$1 -> Overall, the quality of KPSG's service meets our expectations | D16: ='RAW DATA Q2 - 2'!CO3 -> 3
A17: 11 | B17: Timeline | C17: ='RAW DATA Q2 - 2'!EC$1 -> KPSG's support team is available during agreed service hours (Mon–Fri, 09:00–18:00), with on-call support outside these hours when needed | D17: ='RAW DATA Q2 - 2'!EC3 -> 4
A18: 12 | B18: Quality | C18: ='RAW DATA Q2 - 2'!ED$1 -> The system is available at least 99% of the time, with minimal downtime | D18: ='RAW DATA Q2 - 2'!ED3 -> 4
A19: 13 | B19: Timeline | C19: ='RAW DATA Q2 - 2'!EE$1 -> KPSG responds to our service requests within 1 hour during normal working hours | D19: ='RAW DATA Q2 - 2'!EE3 -> 3
A20: 14 | B20: Timeline | C20: ='RAW DATA Q2 - 2'!EF$1 -> Issues are resolved within the agreed timeframe based on impact level | D20: ='RAW DATA Q2 - 2'!EF3 -> 2
A21: 15 | B21: Quality | C21: ='RAW DATA Q2 - 2'!EG$1 -> How would you rate the Data Back Up processing | D21: ='RAW DATA Q2 - 2'!EG3 -> 4
A22: 16 | B22: Timeline | C22: ='RAW DATA Q2 - 2'!EH$1 -> Project milestones are completed on the agreed dates | D22: ='RAW DATA Q2 - 2'!EH3 -> 2
A23: 17 | B23: Timeline | C23: ='RAW DATA Q2 - 2'!EI$1 -> KPSG gives us early warning if there's a risk of delay in any deliverable | D23: ='RAW DATA Q2 - 2'!EI3 -> 3
A24: 18 | B24: Timeline | C24: ='RAW DATA Q2 - 2'!EJ$1 -> Monthly and weekly reports are submitted on time | D24: ='RAW DATA Q2 - 2'!EJ3 -> 4
A25: 19 | B25: Timeline | C25: ='RAW DATA Q2 - 2'!EK$1 -> Any cybersecurity incidents are reported to us within 4 hours of detection | D25: ='RAW DATA Q2 - 2'!EK3 -> 3
A26: 20 | B26: Timeline | C26: ='RAW DATA Q2 - 2'!EL$1 -> Requests for system changes are followed up and completed within the agreed timeline | D26: ='RAW DATA Q2 - 2'!EL3 -> 3
A27: 21 | B27: Relationship | C27: ='RAW DATA Q2 - 2'!FM$1 -> How would you rate the supplier's communication with you? | D27: ='RAW DATA Q2 - 2'!FM3 -> 4
A28: 22 | B28: Relationship | C28: ='RAW DATA Q2 - 2'!FN$1 -> How would you rate the supplier's PIC's availability to be contacted when needed? | D28: ='RAW DATA Q2 - 2'!FN3 -> 4
A29: 23 | B29: Relationship | C29: ='RAW DATA Q2 - 2'!FO$1 -> How would you rate the supplier's response speed to you when there are issues? | D29: ='RAW DATA Q2 - 2'!FO3 -> 4
A31: Quality Avg (35%) | B31: =AVERAGEIF(B7:B29,"Quality",D7:D29) -> 3.4166667
A32: Timeline Avg (35%) | B32: =AVERAGEIF(B7:B29,"Timeline",D7:D29) -> 3
A33: Relationship Avg (30%) | B33: =AVERAGEIF(B7:B29,"Relationship",D7:D29) -> 4
A34: TOTAL SCORE | B34: =B31*0.35+B32*0.35+B33*0.3 -> 3.4458333
A35: STATUS | B35: =IF(B34>4.99,"Exceptional",IF(B34>3.99,"Exceed Expectation",IF(B34>=2.99,"Meet Expectation",IF(B34>1.9,"Below Expectation","Unsatisfactory")))) -> Meet Expectation
A37: DUE DILIGENCE / COMPLIANCE
A38: Financial Assessment | B38: ='RAW DATA Q2 - 2'!FP3 -> Yes
A39: Reputational Assessment | B39: ='RAW DATA Q2 - 2'!FQ3 -> Yes
A40: DPIA | B40: ='RAW DATA Q2 - 2'!FR3 -> Yes, DPIA completed and there are actions to be done by Project Owner
A41: DPSQ | B41: ='RAW DATA Q2 - 2'!FS3 -> Yes, DPSQ not completed yet
A42: VSDDT | B42: ='RAW DATA Q2 - 2'!FT3 -> Yes, VSDDT completed and there are actions to be done by supplier
A43: Action Plan | B43: ='RAW DATA Q2 - 2'!FU3 -> Yes – Action items identified, but follow‑up and coordination with relevant SME is still required
A45: REMARKS / FEEDBACK
B46: ='RAW DATA Q2 - 2'!FV3 -> 1. KPSG-ARSI Perspective (The approach applied is still limited to best practices without considering the scenarios occurring in AMFS). 2. Requirement Gap (There is a significant requirement gap due to missed requirements, caused by insufficient exploration of user needs and requirements) 3. Frequent Manpower (MP) and PIC Changes (Manpower changes occur quite frequently, while the implementation team is no longer on-site. The PIC from KPSG also changes often. It is requested that a dedicated PIC be provided for IT Support as well as a dedicated Project Manager) 4. Deployment Issues (Each deployment consistently results in new issues that impact areas outside the deployment scope. This indicates a lack of proper health checks after deployment). 5. Deployment Communication (Communication regarding deployment plans is still lacking, particularly in obtaining approval from business users. This matter has already been communicated by AMFS to the KPSG team). 6. Contact Center Experience (The team’s experience in contact center operations, especially inbound, remains limited). 7. Change Requests (CR) and Production Issues (Many CRs and production issues are delivered based on targets determined unilaterally by KPSG). 8. User Guide and Feature Socialization. (The User Guide is not well maintained. When new features are introduced, documentation should be updated immediately, socialized to users, and the latest User Guide shared to ensure optimal usage)

Sheet Q2 MII-Purecloud
A1: HASIL REVIEW VENDOR — Q2 2026
A2: Vendor | B2: Mitra Integrasi Informatika
A3: Service | B3: Purecloud Decommisioning
A4: PIC (Business User) | B4: Noviani MARBUN
A6: No | B6: Dimensi | C6: Pertanyaan | D6: Skor
A7: 1 | B7: Quality | C7: ='RAW DATA Q2 - 2'!CZ$1 -> The delivered solution met all agreed functional requirements | D7: ='RAW DATA Q2 - 2'!CZ4 -> 4
A8: 2 | B8: Quality | C8: ='RAW DATA Q2 - 2'!DA$1 -> The system passed User Acceptance Testing (UAT) with minimal critical issues or rework needed | D8: ='RAW DATA Q2 - 2'!DA4 -> 4
A9: 3 | B9: Timeline | C9: ='RAW DATA Q2 - 2'!DB$1 -> Call recordings were accessible and properly linked within the agreed retention period | D9: ='RAW DATA Q2 - 2'!DB4 -> 4
A10: 4 | B10: Quality | C10: ='RAW DATA Q2 - 2'!DC$1 -> Reports and dashboards were accurate and matched AXA’s required format | D10: ='RAW DATA Q2 - 2'!DC4 -> 4
A11: 5 | B11: Quality | C11: ='RAW DATA Q2 - 2'!DD$1 -> Defects or bugs found during the warranty period were minimal and resolved promptly at no extra cost | D11: ='RAW DATA Q2 - 2'!DD4 -> 4
A12: 6 | B12: Timeline | C12: ='RAW DATA Q2 - 2'!DE$1 -> Project documentation was complete, accurate, and submitted on time | D12: ='RAW DATA Q2 - 2'!DE4 -> 4
A13: 7 | B13: Quality | C13: ='RAW DATA Q2 - 2'!DF$1 -> Training provided was clear and sufficient for AXA’s team to operate independently | D13: ='RAW DATA Q2 - 2'!DF4 -> 2
A14: 8 | B14: Quality | C14: ='RAW DATA Q2 - 2'!DG$1 -> Overall, the quality of supplier work on the purecloud decommisioning project meets our expectations | D14: ='RAW DATA Q2 - 2'!DG4 -> 4
A15: 9 | B15: Timeline | C15: ='RAW DATA Q2 - 2'!EW$1 -> The Planning & Architecture phase was completed on schedule | D15: ='RAW DATA Q2 - 2'!EW4 -> 4
A16: 10 | B16: Timeline | C16: ='RAW DATA Q2 - 2'!EX$1 -> The Build/Construction phase was completed on schedule | D16: ='RAW DATA Q2 - 2'!EX4 -> 4
A17: 11 | B17: Timeline | C17: ='RAW DATA Q2 - 2'!EY$1 -> The Validation/UAT phase was completed on schedule | D17: ='RAW DATA Q2 - 2'!EY4 -> 4
A18: 12 | B18: Timeline | C18: ='RAW DATA Q2 - 2'!EZ$1 -> The Deployment & Go-Live phase was completed on schedule | D18: ='RAW DATA Q2 - 2'!EZ4 -> 4
A19: 13 | B19: Timeline | C19: ='RAW DATA Q2 - 2'!FA$1 -> The supplier responded to reported issues within the agreed response time | D19: ='RAW DATA Q2 - 2'!FA4 -> 4
A20: 14 | B20: Timeline | C20: ='RAW DATA Q2 - 2'!FB$1 -> The supplier resolved reported issues within the agreed resolution time | D20: ='RAW DATA Q2 - 2'!FB4 -> 4
A21: 15 | B21: Timeline | C21: ='RAW DATA Q2 - 2'!FC$1 -> The project was completed without delays requiring AXA to invoke late penalties | D21: ='RAW DATA Q2 - 2'!FC4 -> 4
A22: 16 | B22: Timeline | C22: ='RAW DATA Q2 - 2'!FD$1 -> The supplier proactively communicated whenever a milestone was at risk of delay | D22: ='RAW DATA Q2 - 2'!FD4 -> 4
A23: 17 | B23: Relationship | C23: ='RAW DATA Q2 - 2'!FM$1 -> How would you rate the supplier's communication with you? | D23: ='RAW DATA Q2 - 2'!FM4 -> 4
A24: 18 | B24: Relationship | C24: ='RAW DATA Q2 - 2'!FN$1 -> How would you rate the supplier's PIC's availability to be contacted when needed? | D24: ='RAW DATA Q2 - 2'!FN4 -> 4
A25: 19 | B25: Relationship | C25: ='RAW DATA Q2 - 2'!FO$1 -> How would you rate the supplier's response speed to you when there are issues? | D25: ='RAW DATA Q2 - 2'!FO4 -> 4
A27: Quality Avg (35%) | B27: =AVERAGEIF(B7:B25,"Quality",D7:D25) -> 3.6666667
A28: Timeline Avg (35%) | B28: =AVERAGEIF(B7:B25,"Timeline",D7:D25) -> 4
A29: Relationship Avg (30%) | B29: =AVERAGEIF(B7:B25,"Relationship",D7:D25) -> 4
A30: TOTAL SCORE | B30: =B27*0.35+B28*0.35+B29*0.3 -> 3.8833333
A31: STATUS | B31: =IF(B30>4.99,"Exceptional",IF(B30>3.99,"Exceed Expectation",IF(B30>=2.99,"Meet Expectation",IF(B30>1.9,"Below Expectation","Unsatisfactory")))) -> Meet Expectation
A33: DUE DILIGENCE / COMPLIANCE
A34: Financial Assessment | B34: ='RAW DATA Q2 - 2'!FP4 -> Yes
A35: Reputational Assessment | B35: ='RAW DATA Q2 - 2'!FQ4 -> Yes
A36: DPIA | B36: ='RAW DATA Q2 - 2'!FR4 -> Yes, DPIA completed and there are actions to be done by Project Owner
A37: DPSQ | B37: ='RAW DATA Q2 - 2'!FS4 -> No Implementation
A38: VSDDT | B38: ='RAW DATA Q2 - 2'!FT4 -> Yes, VSDDT completed and there are actions to be done by supplier
A39: Action Plan | B39: ='RAW DATA Q2 - 2'!FU4 -> Yes – Action items identified, but follow‑up and coordination with relevant SME is still required
A41: REMARKS / FEEDBACK
B42: ='RAW DATA Q2 - 2'!FV4 -> 1) Training Process During the training sessions, it is expected that explanations are delivered in detail and step by step. When participants are conducting hands-on activities, they should be properly provided with guidance and direct support. This is important to avoid unnecessary questions that could otherwise be answered clearly, ensuring that participants can immediately understand the changes and new features introduced. 2) “Baby Sitting” Phase In the “baby sitting” phase, the MII team was expected to be present full day on-site at AMFS for two weeks. However, in practice, the team did not consistently attend and only joined full day after being specifically requested. As a result, the actual presence was only around five days instead of the full two weeks as originally required.

Sheet Q2 ESHAEL
A1: HASIL REVIEW VENDOR — Q2 2026
A2: Vendor | B2: ESHAEL Indonesia
A3: Service | B3: Talent Assesment
A4: PIC (Business User) | B4: I Gusti Ayu Mira SETYAWARDHANIE
A6: No | B6: Dimensi | C6: Pertanyaan | D6: Skor
A7: 1 | B7: Quality | C7: ='RAW DATA Q2 - 2'!DH$1 -> How would you rate the assessment tools & results (Group Report & Individual Report) for Talent Acquisition/Talent Management needs | D7: ='RAW DATA Q2 - 2'!DH6 -> 4
A8: 2 | B8: Quality | C8: ='RAW DATA Q2 - 2'!DI$1 -> Assessment tools (Psychometric Test, Verbal/Numerical/Abstract Reasoning, Personality Questionnaire, Competency Based Interview, etc.) are relevant and appropriate to participants’ level/grade | D8: ='RAW DATA Q2 - 2'!DI6 -> 4
A9: 3 | B9: Timeline | C9: ='RAW DATA Q2 - 2'!DJ$1 -> Assessment sessions (online and offline) are conducted in an orderly, professional manner and according to the agreed schedule | D9: ='RAW DATA Q2 - 2'!DJ6 -> 5
A10: 4 | B10: Quality | C10: ='RAW DATA Q2 - 2'!DK$1 -> SHL maintains the confidentiality and security of assessment participants’ Personal Data in accordance with the privacy provisions in the Agreement | D10: ='RAW DATA Q2 - 2'!DK6 -> 5
A11: 5 | B11: Quality | C11: ='RAW DATA Q2 - 2'!DL$1 -> There are no administrative errors (participant data, grade, test type) throughout the process from Booking Form submission to report delivery | D11: ='RAW DATA Q2 - 2'!DL6 -> 4
A12: 6 | B12: Quality | C12: ='RAW DATA Q2 - 2'!DM$1 -> SHL proactively coordinates when there is a potential dispute or issue before it impacts participants/AXA | D12: ='RAW DATA Q2 - 2'!DM6 -> 4
A13: 7 | B13: Quality | C13: ='RAW DATA Q2 - 2'!DN$1 -> Overall, the quality of supplier work on the talent assesment project meets our expectations | D13: ='RAW DATA Q2 - 2'!DN6 -> 4
A14: 8 | B14: Timeline | C14: ='RAW DATA Q2 - 2'!FE$1 -> Booking Forms for Talent Acquisition assessments are processed on the same Business Day if received before 16.30 WIB | D14: ='RAW DATA Q2 - 2'!FE6 -> 5
A15: 9 | B15: Timeline | C15: ='RAW DATA Q2 - 2'!FF$1 -> Booking Forms for Talent Management assessments are responded to on the same Business Day for further scheduling | D15: ='RAW DATA Q2 - 2'!FF6 -> 5
A16: 10 | B16: Timeline | C16: ='RAW DATA Q2 - 2'!FG$1 -> Individual Reports for Talent Acquisition assessments are delivered within H+1 Business Day after the assessment is completed | D16: ='RAW DATA Q2 - 2'!FG6 -> 5
A17: 11 | B17: Timeline | C17: ='RAW DATA Q2 - 2'!FH$1 -> Recap Reports for Talent Acquisition assessments are delivered within H+3 Business Days after the assessment is completed | D17: ='RAW DATA Q2 - 2'!FH6 -> 5
A18: 12 | B18: Timeline | C18: ='RAW DATA Q2 - 2'!FI$1 -> Recap Reports for Talent Management assessments are delivered within H+5 Business Days after the assessment is completed | D18: ='RAW DATA Q2 - 2'!FI6 -> 5
A19: 13 | B19: Timeline | C19: ='RAW DATA Q2 - 2'!FJ$1 -> Individual Reports for Talent Management assessments are delivered within H+10 Business Days after the assessment is completed | D19: ='RAW DATA Q2 - 2'!FJ6 -> 5
A20: 14 | B20: Timeline | C20: ='RAW DATA Q2 - 2'!FK$1 -> SHL's helpdesk operates and is reachable within the committed service hours (Monday–Friday, 08.00–17.00 WIB). | D20: ='RAW DATA Q2 - 2'!FK6 -> 5
A21: 15 | B21: Timeline | C21: ='RAW DATA Q2 - 2'!FL$1 -> Overall, SHL is consistent in meeting all the time commitments agreed under this Agreement | D21: ='RAW DATA Q2 - 2'!FL6 -> 5
A22: 16 | B22: Relationship | C22: ='RAW DATA Q2 - 2'!FM$1 -> How would you rate the supplier's communication with you? | D22: ='RAW DATA Q2 - 2'!FM6 -> 5
A23: 17 | B23: Relationship | C23: ='RAW DATA Q2 - 2'!FN$1 -> How would you rate the supplier's PIC's availability to be contacted when needed? | D23: ='RAW DATA Q2 - 2'!FN6 -> 5
A24: 18 | B24: Relationship | C24: ='RAW DATA Q2 - 2'!FO$1 -> How would you rate the supplier's response speed to you when there are issues? | D24: ='RAW DATA Q2 - 2'!FO6 -> 4
A26: Quality Avg (35%) | B26: =AVERAGEIF(B7:B24,"Quality",D7:D24) -> 4.1666667
A27: Timeline Avg (35%) | B27: =AVERAGEIF(B7:B24,"Timeline",D7:D24) -> 5
A28: Relationship Avg (30%) | B28: =AVERAGEIF(B7:B24,"Relationship",D7:D24) -> 4.6666667
A29: TOTAL SCORE | B29: =B26*0.35+B27*0.35+B28*0.3 -> 4.6083333
A30: STATUS | B30: =IF(B29>4.99,"Exceptional",IF(B29>3.99,"Exceed Expectation",IF(B29>=2.99,"Meet Expectation",IF(B29>1.9,"Below Expectation","Unsatisfactory")))) -> Exceed Expectation
A32: DUE DILIGENCE / COMPLIANCE
A33: Financial Assessment | B33: ='RAW DATA Q2 - 2'!FP6 -> Yes
A34: Reputational Assessment | B34: ='RAW DATA Q2 - 2'!FQ6 -> Yes
A35: DPIA | B35: ='RAW DATA Q2 - 2'!FR6 -> Yes, DPIA completed and there are actions to be done by Project Owner
A36: DPSQ | B36: ='RAW DATA Q2 - 2'!FS6 -> No Implementation
A37: VSDDT | B37: ='RAW DATA Q2 - 2'!FT6 -> No Implementation
A38: Action Plan | B38: ='RAW DATA Q2 - 2'!FU6 -> No – No action items were required
A40: REMARKS / FEEDBACK
B41: ='RAW DATA Q2 - 2'!FV6 -> N/A

Sheet RAW DATA Q2 - 1
A1: Id | B1: Waktu mulai | C1: Waktu selesai | D1: Email | E1: Nama | F1: Business User Full Name | G1: Supplier and Service | H1: How would you rate Supplier's ability to understand and meet your needs? | I1: How would you rate the Quality of fulfillment of specifications required by Perfect Assistant? | J1: How would you rate the data model of source of leads on customer level, which contains Existing Customers, Potential Customers, and Hot Leads? | K1: How would you rate the Leads activity evidence and result details, such as Call, Appointment, Visit, and Closing result evidence? | L1: How would you rate the Sales Activity Management process, as tracked by the Sales Leader and sorted by time range? | M1: How would you rate the Notification to Sales Team which consist of: | N1: How would you rate the telephony features which enable to mask either/both Customers’ and Agents’ personal phone number for better customer service and better protection of Customers’ privacy? | O1: How would you rate the assignment features which enable leaders to re-assign the leads to other FA (e.g. FA resigned or move to other branch then the Leads will be assigned to existing FA)? | P1: How would you rate the System Availability, Redundancy, and Overload Protection? | Q1: How would you rate the Security Access? | R1: How would you rate the Audit Trail? | S1: How would you rate the Overall Supplier's reports including Report of Leads activity record and tracking? | T1: How would you rate the Resources / Authorized Personel Commitment and Qualification? | U1: How would you rate supplier initiative to take mitigation/preventive action to prevent recurring problem? | V1: How would you rate supplier compliance with administrative processes, including completion of draft cooperation contract? | W1: How would you rate the Integration with Perfect Assistant? | X1: How would you rate the use of channels to avoid customer data leaks? | Y1: How would you rate the Access to the recording dashboard? | Z1: How would you rate the Security compare to its standard? | AA1: How would you rate Supplier's ability to understand and meet your needs?1 | AB1: How would you rate the goods/services provided by the Supplier against the agreed standards? | AC1: How would you rate the accuracy of the data in the Supplier's reports? | AD1: How would you rate overall quality of the work reports provided by the Supplier? | AE1: How would you rate the solutions provided when there is trouble? | AF1: How would you rate the resolution to the problem that occurred? | AG1: How would you rate the speed of resolution given to problems that occur? | AH1: How would you rate the supplier initiative to take mitigation/preventive action to prevent the problem from recurring? | AI1: How would you rate supplier compliance with administrative processes, including completion of draft cooperation contract?1 | AJ1: How would you rate the Implementation of UAT? | AK1: How would you rate the maintenance includes bug fixing and support for system problems that occur in the JATIS MOBILE application/service? | AL1: How would you rate Supplier's ability to understand and meet your needs?2 | AM1: How would you rate the The goods/services provided by the Supplier against the agreed standards? | AN1: How would you rate the General support and maintenance requirement? | AO1: How would you rate the Performance Management Requirement which includes to support low latency, documentation, performance monitoring, and any major or minor updates? | AP1: How would you rate the Security Management Requirement? | AQ1: How would you rate the Supporting Model which includes onsite support from dedicated engineers and its service level agreement (SLA)? | AR1: How would you rate the accuracy of the data in the Supplier's reports?1 | AS1: How would you rate overall quality of the work reports provided by the Supplier?1 | AT1: How would you rate the solutions provided when there is trouble?1 | AU1: How would you rate the resolution to the problem that occurred?1 | AV1: How would you rate the speed of resolution given to problems that occur?1 | AW1: How would you rate the supplier initiative to take mitigation/preventive action to prevent the problem from recurring?1 | AX1: How would you rate supplier compliance with administrative processes, including completion of draft cooperation contract?2 | AY1: How would you rate The goods/services provided by the Supplier against the agreed standards | AZ1: How would you rate the supplier's services? | BA1: How would you rate the supplier's service in providing a guarantee of administrative services for archive management, computer data collection for all AXA cartons, and ease of access for AXA to the ar | BB1: How would you rate the supplier's service in providing the required number of empty cartons? | BC1: How would you rate overall quality of the work reports provided by the Supplier?2 | BD1: How would you rate the completeness report containing the number of AXA cartons deposited in the supplier's warehouse, a list of cartons that are being borrowed (retrieval) and have not been returned | BE1: How would you rate the solutions provided when there is trouble?2 | BF1: How would you rate the resolution to the problem that occurred?2 | BG1: How would you rate the speed of resolution given to problems that occur?2 | BH1: How would you rate the supplier initiative to take mitigation/preventive action to prevent the problem from recurring?2 | BI1: How would you rate supplier compliance with administrative processes, including completion of draft cooperation contract?3 | BJ1: How would you rate the goods/services provided by the Supplier against the agreed standards1 | BK1: How would you rate overall quality of the work reports provided by the Supplier?3 | BL1: How would you rate the solutions provided when there is trouble?3 | BM1: How would you rate the resolution to the problem that occurred?3 | BN1: How would you rate the supplier initiative to take mitigation/preventive action to prevent the problem from recurring?3 | BO1: How would you rate the accuracy of the data in the Supplier's reports?2 | BP1: How would you rate the overall quality of the work reports provided by the Supplier? | BQ1: How would you rate the competence of people provided by the supplier to provide support (understand AXITS and/or DMTM software)? | BR1: How would you rate the supplier support in providing the form of consultation, offsite and onsite support if there is a disruption to application operations? | BS1: How would you rate the supplier support in doing periodic checks once every 3 months to maintain application quality, including application performance checks (profiling) and error log checks? | BT1: How would you rate the supplier support for updating versions of components, frameworks and libraries issued by third parties with prior written approval from AXA if this is possible? | BU1: How would you rate the suppliers support in compliance to security? | BV1: How would you rate the supplier initiative to take mitigation/preventive action to prevent the problem from recurring?4 | BW1: How would you rate supplier compliance with administrative processes, including completion of draft cooperation contract?4 | BX1: How would you rate the goods/services provided by the Supplier against the agreed standards2 | BY1: How would you rate the Customer Interaction Requirement which includes: | BZ1: How would you rate the Case Management which includes: | CA1: How would you rate the Integration process which includes: | CB1: How would you rate the Architectural Requirement? | CC1: How would you rate the Security Requirement? | CD1: How would you rate the Backup and Restore, Capacity and Performance Requirements? | CE1: How would you rate the Operational and Configuration Management? | CF1: How would you rate the accuracy of the data in the Supplier's reports?3 | CG1: How would you rate overall quality of the work reports provided by the Supplier?4 | CH1: How would you rate the solutions provided when there is trouble?4 | CI1: How would you rate the resolution to the problem that occurred?4 | CJ1: How would you rate the speed of resolution given to problems that occur?3 | CK1: How would you rate the supplier initiative to take mitigation/preventive action to prevent the problem from recurring?5 | CL1: How would you rate supplier compliance with administrative processes, including completion of draft cooperation contract?5 | CM1: How would you rate the accuracy of the data in the Supplier's reports?4 | CN1: How would you rate the overall quality of the work reports provided by the Supplier?1 | CO1: How would you rate the performing installation, setup and configuration of 3Dolphins? | CP1: How would you rate the integration of 3Dolphins with SalesForce? | CQ1: How would you rate the Chatbot Corpus with data provided by AXA? | CR1: How would you rate the supplier's services in providing 3Dolphins Solutions as stated in the Functional Specification Document (FSD) and Technical Specification Document (TSD)? | CS1: How would you rate the supplier's services in conducting System Integration Test (SIT) with AXA IT testing team and IT Project Team? | CT1: How would you rate the supplier's services in conducting User Acceptance Test (UAT) with AXA Business Team and Project IT Team? | CU1: How would you rate the supplier's services in migrating to production server or Go Live and providing support after Go Live? | CV1: How would you rate the supplier's services in providing the human resources needed in the project and timeline according to the agreed scope? | CW1: How would you rate the supplier's services in assigning a Project Manager to coordinate with the AXA team? | CX1: How would you rate the supplier's project documentation as follows: | CY1: How would you rate the supplier support in providing the perform maintenance on all software related to 3Dolphins, which is installed in the AXA data center? | CZ1: How would you rate the supplier support in providing 3Dolphins application maintenance service time, namely 24 hours x 7 days a week, 365 days/year? | DA1: How would you rate the supplier support in preparing at least 2 people who understand and are experts in chatbots owned by AXA and can also provide support for services that often occur (eg. New custo | DB1: How would you rate the supplier support in providing support center that can be visited during AXA business hours to respond to any questions and issues that arise? | DC1: How would you rate the supplier support in providing SLA reports to AXA? | DD1: How would you rate the supplier support in providing testing and updates the Chatbot Solution if there is a new software version/release/patch according to the required conditions? | DE1: How would you rate the supplier support in reinstall the 3Dolphins application a maximum of 1 time per year if AXA will upgrade the hardware? | DF1: How would you rate the supplier support in providing a checklist to monitor daily activities? | DG1: How would you rate the supplier support in providing a testing configuration and event logging? | DH1: How would you rate the supplier support in providing a backup for short and long term? | DI1: How would you rate the goods/services provided by the Supplier against the agreed standards3 | DJ1: How would you rate the accuracy of the data in the Supplier's reports?5 | DK1: How would you rate overall quality of the work reports provided by the Supplier?5 | DL1: How would you rate the solutions provided when there is trouble?5 | DM1: How would you rate the resolution to the problem that occurred?5 | DN1: How would you rate the speed of resolution given to problems that occur | DO1: How would you rate the supplier initiative to take mitigation/preventive action to prevent the problem from recurring?6 | DP1: How would you rate supplier compliance with administrative processes, including completion of draft cooperation contract?6 | DQ1: How would you rate the shipping target achievement? | DR1: How would you rate the delivery times? Based on SLA, the delivery time are Monday to Saturday, service levels will remain the same from Monday to Friday. | DS1: How would you rate the Receipt retention period? | DT1: How would you rate the Airway Bill Storage: | DU1: How would you rate the Handling of Policies/Documents and/or delivery process? | DV1: How would you rate the response to complaints/investigations of the delivery process? | DW1: How would you rate the response taken when a delivery failure occurs? | DX1: How would you rate the goods/services provided by the Supplier against the agreed standards?1 | DY1: How would you rate the accuracy of the data in the Supplier's reports?6 | DZ1: How would you rate overall quality of the work reports provided by the Supplier?6 | EA1: How would you rate the solutions provided when there is trouble?6 | EB1: How would you rate the resolution to the problem that occurred?6 | EC1: How would you rate the supplier initiative to take mitigation/preventive action to prevent the problem from recurring?7 | ED1: How would you rate the service provided? | EE1: How would you rate the Complaint Handling? | EF1: How would you rate the service provided?1 | EG1: How would you rate the accuracy of the data in the Supplier's reports?7 | EH1: How would you rate overall quality of the work reports provided by the Supplier?7 | EI1: How would you rate the resolution to the problem that occurred?7 | EJ1: How would you rate the supplier initiative to take mitigation/preventive action to prevent the problem from recurring?8 | EK1: How would you rate supplier compliance with administrative processes, including completion of draft cooperation contract?7 | EL1: How would you rate the Technical services that is used to penetrate the application which includes: 1. Technical Specification Design. 2. Hardware and capacity sizing for concurrent requests 3. Functi | EM1: How would you rate the after sales support capability and methodology? | EN1: How would you rate the availability of documentation for service (user manual, troubleshoot document, setup document, etc)? | EO1: How would you rate the Technical services that is used to penetrate the application which includes: 1. Technical Specification Design. 2. Hardware and capacity sizing for concurrent requests 3. Functi1 | EP1: How would you rate the after sales support capability and methodology?1 | EQ1: How would you rate the availability of documentation for product (user manual, troubleshoot document, setup document, etc)? | ER1: How would you rate the Technical services that is used to penetrate the application which includes: 1. Technical Specification Design. 2. Hardware and capacity sizing for concurrent requests 3. Functi2 | ES1: How would you rate the after sales support capability and methodology?2 | ET1: How would you rate the availability of documentation for product (user manual, troubleshoot document, setup document, etc)?1 | EU1: How would you rate the supplier's timeliness in delivering goods/services compared to the agreed-upon timeline? | EV1: How would you rate the supplier's timeliness in sending reports to you? | EW1: How would you rate the supplier's speed ​​of administrative completion, including completion of contracts draft? | EX1: How would you rate the supplier's timeliness in delivering goods/services compared to the agreed-upon timeline?1 | EY1: How would you rate the supplier's timeliness in sending reports to you? | EZ1: How would you rate the supplier's Traffic Confirmation SLA Fulfillment? | FA1: How would you rate the supplier's speed ​​of administrative completion, including completion of contracts draft? | FB1: How would you rate the supplier's timeliness in delivering goods/services compared to the agreed-upon timeline?2 | FC1: How would you rate the supplier's timeliness in sending reports to you? Based on SLA, suppliers must provide reports on the 10th of each month. | FD1: How would you rate the supplier's speed ​​of administrative completion, including completion of contracts draft? 1 | FE1: How would you rate the supplier's SLA Fulfillment? | FF1: How would you rate the Supplier's timeliness in delivering goods/services compared to the agreed-upon timeline?3 | FG1: How would you rate the supplier's timeliness in sending reports to you? Based on SLA, support reports should be sent every 3 months on the 10th | FH1: How would you rate the supplier's speed ​​of administrative completion, including completion of contracts draft?1 | FI1: How would you rate the supplier's resolution time? | FJ1: How would you rate the supplier's timeliness in delivering goods/services compared to the agreed-upon timeline?4 | FK1: How would you rate the supplier's timeliness in sending reports to you?1 | FL1: How would you rate the supplier's speed ​​of administrative completion, including completion of contracts draft?2 | FM1: How would you rate the supplier's communication with you? | FN1: How would you rate the supplier's PIC's availability to be contacted when needed? | FO1: How would you rate the supplier's response speed to you when there are issues? | FP1: Has the vendor completed the latest Financial Assessment? | FQ1: Has the vendor’s Reputational Assessment been performed? | FR1: Does the services require the fulfillment of Data Privacy Impact Assessment (DPIA)? | FS1: Does the services require the fulfillment of Data Privacy Service Provider Questionnaire assessment (DPSQ)? | FT1: Does the services require the fulfillment of Vendor Security Due Diligence Tooling (VSDDT)? | FU1: Please provide feedback or suggestion for the supplier, including areas for improvement
A2: 1 | B2: 46204.406 | C2: 46204.555 | D2: djoko.djoko@axa-mandiri.co.id | E2: Djoko DJOKO | F2: DJOKO | G2: Inmotion Inovasi Teknologi - Jasa Aplikasi Chatbot dan Live Chat | BX2: 4 | BY2: 4 | BZ2: 4 | CA2: 4 | CB2: 4 | CC2: 4 | CD2: 4 | CE2: 4 | CF2: 4 | CG2: 4 | CH2: 4 | CI2: 4 | CJ2: 4 | CK2: 4 | CL2: 4 | CM2: 4 | CN2: 4 | CO2: 4 | CP2: 4 | CQ2: 4 | CR2: 4 | CS2: 4 | CT2: 4 | CU2: 4 | CV2: 4 | CW2: 4 | CX2: 4 | CY2: 4 | CZ2: 4 | DA2: 4 | DB2: 4 | DC2: 4 | DD2: 4 | DE2: 4 | DF2: 4 | DG2: 4 | DH2: 4 | EU2: 4 | EV2: 4 | EW2: 4 | FM2: 4 | FN2: 4 | FO2: 4 | FP2: Yes | FQ2: Yes | FR2: Yes, DPIA completed and there are actions to be done by Project Owner | FS2: DPSQ not completed yet | FT2: Yes, VSDDT completed and there are actions to be done by supplier | FU2: Tetap up to date dan helpful
A3: 2 | B3: 46204.702 | C3: 46204.88 | D3: nuril.hudha@axa-mandiri.co.id | E3: Nuril HUDHA | F3: Nuril Hudha | G3: Indosat - Layanan PBX berbasiskan cloud dengan Teknologi SIP Trunk | H3: 3 | I3: 3 | J3: 4 | K3: 4 | L3: 4 | M3: 4 | N3: 4 | O3: 3 | P3: 3 | Q3: 4 | R3: 4 | S3: 4 | T3: 4 | U3: 4 | V3: 4 | W3: 4 | X3: 4 | Y3: 3 | Z3: 3 | EU3: 3 | EV3: 3 | EW3: 3 | FM3: 4 | FN3: 4 | FO3: 3 | FP3: Yes | FQ3: Yes | FR3: No Implementation | FS3: DPSQ not completed yet | FT3: No Implementation | FU3: Vendor performance is generally acceptable and aligns with the expected level of service. While the engagement has been positive overall, improvements are needed in feature enhancement, dashboard capabilities, and the regularity of report updates. Better preparation in deployment and timely reporting would help increase the overall value and effectiveness of the service.
A4: 3 | B4: 46205.621 | C4: 46205.63 | D4: bella.depari@axa-mandiri.co.id | E4: Bella Friska DEPARI | F4: Bella Friska Depari | G4: Target Sukses Sinergi - Email Marketing Automation | EF4: 3 | EG4: 3 | EH4: 3 | EI4: 3 | EJ4: 2 | EK4: 3 | EU4: 3 | EV4: 3 | EW4: 3 | FM4: 3 | FN4: 3 | FO4: 3 | FP4: Yes | FQ4: Yes | FR4: Yes, DPIA completed and there are actions to be done by Project Owner | FS4: No Implementation | FT4: Yes, VSDDT completed and there are actions to be done by supplier | FU4: Secara keseluruhan, MTarget telah memberikan dukungan yang baik dalam operasional email campaign dan responsif dalam menangani kebutuhan maupun isu yang muncul. Namun, insiden kesalahan pengiriman email yang terjadi menunjukkan perlunya penguatan pada proses deployment, pengujian, serta validasi sebelum implementasi ke production. Ke depannya, kami berharap MTarget dapat memperkuat proses change management, quality assurance, dan kontrol terhadap segmentasi serta pengiriman email untuk meminimalkan risiko terjadinya insiden serupa.
A5: 4 | B5: 46205.647 | C5: 46205.651 | D5: fifin.sarinurlita@axa-mandiri.co.id | E5: Fifin SARINURLITA | F5: Fifin Sarinurlita | G5: Informasi Teknologi Indonesia - SMS Broadcast | AA5: 3 | AB5: 3 | AC5: 3 | AD5: 3 | AE5: 3 | AF5: 3 | AG5: 3 | AH5: 3 | AI5: 3 | AJ5: 3 | AK5: 3 | EX5: 3 | EY5: 3 | EZ5: 3 | FA5: 3 | FM5: 3 | FN5: 3 | FO5: 3 | FP5: Yes | FQ5: Yes | FR5: Yes, DPIA completed and there are actions to be done by Project Owner | FS5: Yes, DPSQ completed | FT5: Yes, VSDDT completed and there are actions to be done by supplier | FU5: So far, Jatis Vendor has provided good service. Their response time is fast, and they are able to provide effective solutions whenever issues arise
A6: 5 | B6: 46205.652 | C6: 46205.656 | D6: fifin.sarinurlita@axa-mandiri.co.id | E6: Fifin SARINURLITA | F6: Fifin Sarinurlita | G6: Satria Antaran Prima - Courier Service | DI6: 3 | DJ6: 3 | DK6: 3 | DL6: 3 | DM6: 3 | DN6: 3 | DO6: 3 | DP6: 3 | DQ6: 3 | DR6: 3 | DS6: 3 | DT6: 3 | DU6: 3 | DV6: 3 | DW6: 3 | FJ6: 3 | FK6: 3 | FL6: 3 | FM6: 3 | FN6: 3 | FO6: 3 | FP6: Yes | FQ6: Yes | FR6: Yes, DPIA completed and there are actions to be done by Project Owner | FS6: Yes, DPSQ completed | FT6: Yes, VSDDT completed and there are actions to be done by supplier | FU6: SAP has shown improvement in terms of reporting and provides a fast response whenever issues arise.
A7: 6 | B7: 46206.353 | C7: 46206.504 | D7: novia.santi@axa-mandiri.co.id | E7: Novia Laras SANTI | F7: Novia Laras Santi | G7: Satria Antaran Prima - Courier Service | DI7: 4 | DJ7: 2 | DK7: 3 | DL7: 3 | DM7: 2 | DN7: 4 | DO7: 3 | DP7: 3 | DQ7: 2 | DR7: 2 | DS7: 2 | DT7: 4 | DU7: 3 | DV7: 4 | DW7: 3 | FJ7: 2 | FK7: 4 | FL7: 3 | FM7: 5 | FN7: 5 | FO7: 4 | FP7: No | FQ7: Yes | FR7: No Implementation | FS7: No Implementation | FT7: No Implementation | FU7: 1. untuk detail status pengiriman dokumen/barang harus diberikan keterangan penerima dengan lengkap dan jelas; 2. Maks. SLA pengiriman harus memenuhi sesuai dengan yang ditetapkan yaitu <5% not meet SLA; 3. Invoice biaya pengiriman dikirimkan ke user yang sesuai dan dikirimkan tidak melebihi periode yang ditetapkan. 4. Report Stock sesuai dengan real stock di warehouse.
A8: 7 | B8: 46209.558 | C8: 46209.585 | D8: B619GA@login.axa | E8: Fauzi ARYANTO | F8: Fauzi Aryanto | G8: FPT Metrodata - Penetration Testing | EL8: 4 | EM8: 4 | EN8: 4 | EU8: 4 | EV8: 4 | EW8: 4 | FM8: 4 | FN8: 4 | FO8: 4 | FP8: Yes | FQ8: Yes | FR8: Yes, DPIA completed and there are actions to be done by Project Owner | FS8: No Implementation | FT8: Yes, VSDDT completed and there are actions to be done by supplier | FU8: -
A9: 8 | B9: 46209.585 | C9: 46209.586 | D9: B619GA@login.axa | E9: Fauzi ARYANTO | F9: Fauzi Aryanto | G9: Iproteksi Telematika - Penetration Testing | EO9: 4 | EP9: 4 | EQ9: 4 | EU9: 4 | EV9: 4 | EW9: 4 | FM9: 4 | FN9: 4 | FO9: 4 | FP9: Yes | FQ9: Yes | FR9: Yes, DPIA completed and there are actions to be done by Project Owner | FS9: No Implementation | FT9: Yes, VSDDT completed and there are actions to be done by supplier | FU9: -
A10: 9 | B10: 46209.586 | C10: 46209.586 | D10: B619GA@login.axa | E10: Fauzi ARYANTO | F10: Fauzi Aryanto | G10: Itsec Asia - Penetration Testing | ER10: 3 | ES10: 3 | ET10: 3 | EU10: 3 | EV10: 3 | EW10: 3 | FM10: 3 | FN10: 3 | FO10: 3 | FP10: Yes | FQ10: Yes | FR10: Yes, DPIA completed and there are actions to be done by Project Owner | FS10: No Implementation | FT10: Yes, VSDDT completed and there are actions to be done by supplier | FU10: -
A11: 10 | B11: 46209.584 | C11: 46209.588 | D11: ibnu.kumala@axa-mandiri.co.id | E11: Ibnu KUMALA | F11: Ibnu kumala | G11: Satria Antaran Prima - Mailing Room | DX11: 3 | DY11: 4 | DZ11: 3 | EA11: 3 | EB11: 3 | EC11: 3 | ED11: 3 | EE11: 3 | EU11: 3 | EV11: 3 | EW11: 3 | FM11: 3 | FN11: 3 | FO11: 3 | FP11: Yes | FQ11: Yes | FR11: Yes, DPIA completed and there are actions to be done by Project Owner | FS11: No Implementation | FT11: Yes, VSDDT completed and there are actions to be done by supplier | FU11: improve inisiatsis
A12: 11 | B12: 46209.588 | C12: 46209.591 | D12: ibnu.kumala@axa-mandiri.co.id | E12: Ibnu KUMALA | F12: Ibnu kumala | G12: Multifiling Mitra Indonesia - Record Management Service | AY12: 3 | AZ12: 3 | BA12: 3 | BB12: 3 | BC12: 3 | BD12: 3 | BE12: 3 | BF12: 3 | BG12: 3 | BH12: 3 | BI12: 3 | FB12: 3 | FC12: 3 | FD12: 3 | FE12: 3 | FM12: 3 | FN12: 3 | FO12: 3 | FP12: Yes | FQ12: Yes | FR12: Yes, DPIA completed and there are actions to be done by Project Owner | FS12: Yes, DPSQ completed | FT12: Yes, VSDDT completed and there are actions to be done by supplier | FU12: ..
A13: 12 | B13: 46209.603 | C13: 46209.609 | D13: A591KD@login.axa | E13: Raninta MAHARDI | F13: Raninta Mahardi | G13: Ciptadra Softindo - Pemeliharaan Axits & DMTM | BJ13: 4 | BK13: 4 | BL13: 4 | BM13: 4 | BN13: 4 | BO13: 4 | BP13: 4 | BQ13: 4 | BR13: 4 | BS13: 4 | BT13: 4 | BU13: 4 | BV13: 4 | BW13: 4 | FF13: 4 | FG13: 4 | FH13: 4 | FI13: 4 | FM13: 5 | FN13: 5 | FO13: 5 | FP13: Yes | FQ13: Yes | FR13: Yes, DPIA completed and there are actions to be done by Project Owner | FS13: No Implementation | FT13: Yes, VSDDT completed and there are actions to be done by supplier | FU13: Ciptadra selalu fast response ketika ada incident yang terjadi di DMTM
A14: 13 | B14: 46211.599 | C14: 46211.622 | D14: B545KY@login.axa | E14: Chandra Nugraha PUTRA | F14: Chandra Nugraha Putra | G14: Mitra Integrasi Informatika - SFDC Maintenance | AL14: 4 | AM14: 5 | AN14: 5 | AO14: 5 | AP14: 5 | AQ14: 4 | AR14: 5 | AS14: 4 | AT14: 5 | AU14: 4 | AV14: 5 | AW14: 4 | AX14: 5 | EU14: 4 | EV14: 5 | EW14: 5 | FM14: 5 | FN14: 5 | FO14: 5 | FP14: Yes | FQ14: Yes | FR14: Yes, DPIA completed and there are actions to be done by Project Owner | FS14: No Implementation | FT14: Yes, VSDDT completed and there are actions to be done by supplier | FU14: Respons terhadap issue maupun kebutuhan sudah cukup baik dan cepat. Support on-site juga sangat membantu dan responsif. Ke depannya, mungkin dapat lebih rutin memberikan update terkait progress kendala atau perbaikan yang sedang dilakukan, sehingga pihak terkait dapat mengetahui status terbaru dan lebih cepat menentukan langkah selanjutnya.

Sheet RAW DATA Q2 - 2
